Workbook

Sheet Cover
B3: GOLDBERG FAMILY OFFICE
B9: 17 Castlereagh Street
B16: Asset Summary — Tenancy Schedule
B18: As at 30 June 2026
B27: — | C27: Prepared by jake goldberg

Sheet Last Updated
A1: 17 CASTLEREAGH STREET, SYDNEY — TRACKER VERSION CONTROL
A2: Record each monthly update below. Update the 'Current Version' fields whenever Input Data is refreshed from the DJ Wear Tenancy Schedule.
B4: CURRENT TRACKER STATUS
B5: Property | D5: 17 Castlereagh Street, Sydney
B6: Current As At | D6: 46234
B7: Total NLA | D7: =SUM('Input Data'!F3:F27) -> 4704.5
B8: Occupancy | D8: =(SUM('Input Data'!F3:F27)-'Input Data'!F27)/SUM('Input Data'!F3:F27) -> 0.96592624
B9: WALE by NLA | D9: =IFERROR(SUMPRODUCT(('Input Data'!K3:K27>0)*'Input Data'!F3:F27*MAX(('Input Data'!H3:H27-TODAY())/365.25,0))/SUMIF('Input Data'!K3:K27,">0",'Input Data'!F3:F27),0) -> 0
B10: WALE by Income | D10: =IFERROR(SUMPRODUCT(('Input Data'!N3:N27>0)*'Input Data'!N3:N27*MAX(('Input Data'!H3:H27-TODAY())/365.25,0))/SUMIF('Input Data'!N3:N27,">0"),0) -> 0
B11: Gross Income PA | D11: =SUMIF('Input Data'!K3:K27,">0") -> 4907584.1
B12: Net Income PA | D12: =SUM('Input Data'!N3:N27) -> 4033664.6
B13: No. of Leases | D13: 23 active | 1 vacant | 1 owner-occupied
B14: Car Parks | D14: 2 garages, 1 tandem space each (74 bay licences to tenants)
B15: Last Updated By
B16: Next Update Due
B17: Notes / Changes
B19: UPDATE LOG — add a row each time you refresh the data
B20: Date Updated | C20: Updated By | D20: As At Date (Schedule) | E20: Occupancy | F20: WALE (NLA) | G20: Key Changes / Notes
B21: 46142 | D21: 30/04/2026 | E21: =(SUM('Input Data'!F3:F27)-'Input Data'!F27)/SUM('Input Data'!F3:F27) -> 0.96592624 | F21: =IFERROR(SUMPRODUCT(('Input Data'!K3:K27>0)*'Input Data'!F3:F27*MAX(('Input Data'!H3:H27-TODAY())/365.25,0))/SUMIF('Input Data'!K3:K27,">0",'Input Data'!F3:F27),0) -> 0 | G21: Initial setup — data loaded from DJ Wear Tenancy Schedule Apr 2026
B22: 46204 | C22: Jake | D22: 01/07/2026 | E22: =(SUM('Input Data'!F3:F27)-'Input Data'!F27)/SUM('Input Data'!F3:F27) -> 0.96592624 | F22: =IFERROR(SUMPRODUCT(('Input Data'!K3:K27>0)*'Input Data'!F3:F27*MAX(('Input Data'!H3:H27-TODAY())/365.25,0))/SUMIF('Input Data'!K3:K27,">0",'Input Data'!F3:F27),0) -> 0 | G22: Refreshed from DJ Wear Tenancy Schedule as at 1.7.2026: PU Prime, IPM Residential, Threat Defence, Satellite Office rent reviews applied; Aitken Investment Mgmt lease dates/PSM corrected; TJC#1 trading name updated to Balance Insolvency. Suite 101&2 (Blitzem) expires 30/6/2026 — will show vacant from next update.
B23: 46234 | C23: Jake | D23: 31/07/2026 | E23: =(SUM('Input Data'!F3:F27)-'Input Data'!F27)/SUM('Input Data'!F3:F27) -> 0.96592624 | F23: =IFERROR(SUMPRODUCT(('Input Data'!K3:K27>0)*'Input Data'!F3:F27*MAX(('Input Data'!H3:H27-TODAY())/365.25,0))/SUMIF('Input Data'!K3:K27,">0",'Input Data'!F3:F27),0) -> 0 | G23: Refreshed from DJ Wear Tenancy Schedule as at 31.7.2026: corrected rent review dates/types for TJC#1 (Balance Insolvency), Pinpoint Talent, Hilliard & Berry, and Aitken Investment Mgmt to match latest TS; renamed suite 1103 tenant from "Inferni Systems" to correct name "Interfi Systems" and confirmed nil Outgoings/Car Parks for that suite. Lewis Woolcott (1102, new lease from 15/8/26) still pending TS confirmation of rent — no financial detail issued yet.
B41: MONTHLY UPDATE CHECKLIST
B42: 1 | C42: Download DJ Wear Tenancy Schedule PDF from property management system
B43: 2 | C43: Update Input Data tab — check each row for rent, dates, PSM, incentive changes
B44: 3 | C44: Update Market Rents 26-27 tab if any market adjustments since last review
B45: 4 | C45: Review Dashboard — confirm KPIs reconcile with schedule totals
B46: 5 | C46: Update Expiry Profile — check any new leases or surrenders
B47: 6 | C47: Update Leasing Activity tab with any new deals, HOAs or renewals
B48: 7 | C48: Update Make Good Obligations — check notice periods and estimated costs
B49: 8 | C49: Update Spec Fitouts tab with any new capex approvals or completions
B50: 9 | C50: Fill in Update Log above with date, occupancy, WALE and key changes
B51: 10 | C51: Save file with month-year in filename (e.g. 17Castlereagh_May26.xlsx)

Sheet Input Data
A1: 17 CASTLEREAGH ST, SYDNEY — TENANCY SCHEDULE INPUT | As at 31.7.2026
A2: Suite ID | B2: Floor | C2: Suite # | D2: Tenant Name | E2: Trading Name | F2: NLA (sqm) | G2: Lease Start | H2: Lease Expiry | I2: Term (Yrs) | J2: PSM (Face) | K2: Office Rent PA ($) | L2: Incentive Rent PA ($) | M2: Outgoings PA ($) | N2: Net Rent PA ($) | O2: Car Parks | P2: Review Type | Q2: Next Review Date | R2: Outgoings Type | S2: Market Rent PSM ($) | T2: Variance to Mkt ($) | U2: Variance to Mkt (%) | V2: WALE (yrs) | W2: Weighted NLA | X2: Notes | Y2: Status | Z2: Expiry Date (Source — Enter Here) | AA2: PSM Src | AB2: Display Name
A3: 00001 | B3: BSMT | C3: LWR GROUND | D3: =IF(Y3="EXPIRED","VACANT","OPULENT TWO ENTERPRISES") -> OPULENT TWO ENTERPRISES | E3: =IF(Y3="EXPIRED","","OPULENT TWO ENTERPRISES") -> OPULENT TWO ENTERPRISES | F3: 151.2 | G3: =IF(Y3="EXPIRED","",DATE(2016,2,1)) -> 42401 | H3: =IF(Z3="","",IF(Z3<TODAY(),"",Z3)) -> 47149 | I3: =IF(Y3="EXPIRED","",13) -> 13 | J3: =IF(Y3="EXPIRED",0,1002.01) -> 1002.01 | K3: =IF(Y3="EXPIRED",0,J3*F3) -> 151503.91 | L3: -28014.84 | M3: 15000 | N3: =K3+L3 -> 123489.07 | O3: 0 | P3: FIXED 4% | Q3: 46419 | R3: Net | S3: =IFERROR(INDEX('Market Rents 26-27'!E:E,MATCH(C3,'Market Rents 26-27'!$A:$A,0)),0) -> 930 | T3: =IF(J3>0,J3-S3,"") -> 72.01 | U3: =IF(AND(J3>0,S3>0),(J3-S3)/S3,"") -> 0.077430108 | V3: =IF(H3="",0,IFERROR(MAX((H3-TODAY())/365.25,0),0)) -> 2.294319 | W3: =F3*V3 -> 346.90103 | Y3: =IF(Z3="","VACANT",IF(Z3<TODAY(),"EXPIRED","ACTIVE")) -> ACTIVE | Z3: 47149 | AA3: 1002.01 | AB3: Opulent Two Enterprises
A4: 00002 | B4: GF | C4: GROUND | D4: =IF(Y4="EXPIRED","VACANT","RCVRI MARTIN PLACE PTY LTD") -> RCVRI MARTIN PLACE PTY LTD | E4: =IF(Y4="EXPIRED","","RECOVERIE") -> RECOVERIE | F4: 298.3 | G4: =IF(Y4="EXPIRED","",DATE(2025,1,21)) -> 45678 | H4: =IF(Z4="","",IF(Z4<TODAY(),"",Z4)) -> 48233 | I4: =IF(Y4="EXPIRED","",7) -> 7 | J4: =IF(Y4="EXPIRED",0,1150.52) -> 1150.52 | K4: =IF(Y4="EXPIRED",0,J4*F4) -> 343200.12 | L4: -70714.32 | M4: 10408.32 | N4: =K4+L4 -> 272485.8 | O4: 0 | P4: FIXED 4% | Q4: 46408 | R4: Gross | S4: =IFERROR(INDEX('Market Rents 26-27'!E:E,MATCH(C4,'Market Rents 26-27'!$A:$A,0)),0) -> 1100 | T4: =IF(J4>0,J4-S4,"") -> 50.52 | U4: =IF(AND(J4>0,S4>0),(J4-S4)/S4,"") -> 0.045927273 | V4: =IF(H4="",0,IFERROR(MAX((H4-TODAY())/365.25,0),0)) -> 5.2621492 | W4: =F4*V4 -> 1569.6991 | Y4: =IF(Z4="","VACANT",IF(Z4<TODAY(),"EXPIRED","ACTIVE")) -> ACTIVE | Z4: 48233 | AA4: 1150.52 | AB4: Recoverie
A5: 00005 | B5: L01 | C5: 101&2 | D5: VACANT | F5: 162.4 | H5: =IF(Z5="","",IF(Z5<TODAY(),"",Z5)) | I5: =IF(Y5="EXPIRED","",3) -> 3 | K5: =IF(Y5="EXPIRED",0,J5*F5) -> 0 | L5: 0 | N5: =K5+L5 -> 0 | O5: 0 | S5: =IFERROR(INDEX('Market Rents 26-27'!E:E,MATCH(C5,'Market Rents 26-27'!$A:$A,0)),0) -> 1115 | T5: =IF(J5>0,J5-S5,"") | V5: =IF(H5="",0,IFERROR(MAX((H5-TODAY())/365.25,0),0)) -> 0 | W5: =F5*V5 -> 0 | Y5: =IF(Z5="","VACANT",IF(Z5<TODAY(),"EXPIRED","ACTIVE")) -> VACANT
A6: 00008 | B6: L01 | C6: 103 | D6: =IF(Y6="EXPIRED","VACANT","PU PRIME TRADING PTY LTD") -> PU PRIME TRADING PTY LTD | E6: =IF(Y6="EXPIRED","","PU PRIME TRADING PTY LTD") -> PU PRIME TRADING PTY LTD | F6: 96.3 | G6: =IF(Y6="EXPIRED","",DATE(2021,7,1)) -> 44378 | H6: =IF(Z6="","",IF(Z6<TODAY(),"",Z6)) -> 46918 | I6: =IF(Y6="EXPIRED","",7) -> 7 | J6: 1021.99 | K6: =IF(Y6="EXPIRED",0,J6*F6) -> 98417.637 | L6: -9021.6 | M6: 6780 | N6: =K6+L6 -> 89396.037 | O6: 0 | P6: FIXED 4% | Q6: 46461 | R6: Net | S6: =IFERROR(INDEX('Market Rents 26-27'!E:E,MATCH(C6,'Market Rents 26-27'!$A:$A,0)),0) -> 960 | T6: =IF(J6>0,J6-S6,"") -> 61.99 | U6: =IF(AND(J6>0,S6>0),(J6-S6)/S6,"") -> 0.064572917 | V6: =IF(H6="",0,IFERROR(MAX((H6-TODAY())/365.25,0),0)) -> 1.6618754 | W6: =F6*V6 -> 160.0386 | Y6: =IF(Z6="","VACANT",IF(Z6<TODAY(),"EXPIRED","ACTIVE")) -> ACTIVE | Z6: 46918 | AA6: 1021.99 | AB6: PU Prime Trading
A7: 00009 | B7: L01 | C7: 104 | D7: =IF(Y7="EXPIRED","VACANT","TJC#1 PTY LTD") -> TJC#1 PTY LTD | E7: =IF(Y7="EXPIRED","","BALANCE INSOLVENCY") -> BALANCE INSOLVENCY | F7: 98.1 | G7: =IF(Y7="EXPIRED","",DATE(2023,8,1)) -> 45139 | H7: =IF(Z7="","",IF(Z7<TODAY(),"",Z7)) -> 47330 | I7: =IF(Y7="EXPIRED","",3) -> 3 | J7: =IF(Y7="EXPIRED",0,973.44) -> 973.44 | K7: =IF(Y7="EXPIRED",0,J7*F7) -> 95494.464 | L7: -19423.8 | M7: 4500 | N7: =K7+L7 -> 76070.664 | O7: 0 | P7: FIXED 4% | Q7: 46600 | R7: Net | S7: =IFERROR(INDEX('Market Rents 26-27'!E:E,MATCH(C7,'Market Rents 26-27'!$A:$A,0)),0) -> 960 | T7: =IF(J7>0,J7-S7,"") -> 13.44 | U7: =IF(AND(J7>0,S7>0),(J7-S7)/S7,"") -> 0.014 | V7: =IF(H7="",0,IFERROR(MAX((H7-TODAY())/365.25,0),0)) -> 2.78987 | W7: =F7*V7 -> 273.68624 | Y7: =IF(Z7="","VACANT",IF(Z7<TODAY(),"EXPIRED","ACTIVE")) -> ACTIVE | Z7: 47330 | AA7: 973.44 | AB7: TJC#1
A8: 00012 | B8: L02 | C8: WHOLE | D8: =IF(Y8="EXPIRED","VACANT","PRINCETON FINANCIAL SERVICES") -> PRINCETON FINANCIAL SERVICES | E8: =IF(Y8="EXPIRED","","PRINCETON FINANCIAL SERVICES") -> PRINCETON FINANCIAL SERVICES | F8: 393.2 | G8: =IF(Y8="EXPIRED","",DATE(2024,1,1)) -> 45292 | H8: =IF(Z8="","",IF(Z8<TODAY(),"",Z8)) -> 47118 | I8: =IF(Y8="EXPIRED","",5) -> 5 | J8: =IF(Y8="EXPIRED",0,1081.6) -> 1081.6 | K8: =IF(Y8="EXPIRED",0,J8*F8) -> 425285.12 | L8: -23581.8 | M8: 16200 | N8: =K8+L8 -> 401703.32 | O8: 0 | P8: FIXED 4% | Q8: 46388 | R8: Net | S8: =IFERROR(INDEX('Market Rents 26-27'!E:E,MATCH(C8,'Market Rents 26-27'!$A:$A,0)),0) -> 1095 | T8: =IF(J8>0,J8-S8,"") -> -13.4 | U8: =IF(AND(J8>0,S8>0),(J8-S8)/S8,"") -> -0.012237443 | V8: =IF(H8="",0,IFERROR(MAX((H8-TODAY())/365.25,0),0)) -> 2.2094456 | W8: =F8*V8 -> 868.754 | Y8: =IF(Z8="","VACANT",IF(Z8<TODAY(),"EXPIRED","ACTIVE")) -> ACTIVE | Z8: 47118 | AA8: 1081.6 | AB8: Princeton Financial Services
A9: 00015 | B9: L03 | C9: 301&2 | D9: =IF(Y9="EXPIRED","VACANT","IPM RESIDENTIAL PTY LTD") -> IPM RESIDENTIAL PTY LTD | E9: =IF(Y9="EXPIRED","","IPM RESIDENTIAL PTY LTD") -> IPM RESIDENTIAL PTY LTD | F9: 164.2 | G9: =IF(Y9="EXPIRED","",DATE(2022,6,1)) -> 44713 | H9: =IF(Z9="","",IF(Z9<TODAY(),"",Z9)) -> 46538 | I9: =IF(Y9="EXPIRED","",5) -> 5 | J9: 1216.58 | K9: =IF(Y9="EXPIRED",0,J9*F9) -> 199762.44 | L9: -15516.96 | M9: 9900 | N9: =K9+L9 -> 184245.48 | O9: 2 | P9: LEASE RENEWAL | Q9: 46539 | R9: Net | S9: =IFERROR(INDEX('Market Rents 26-27'!E:E,MATCH(C9,'Market Rents 26-27'!$A:$A,0)),0) -> 1135 | T9: =IF(J9>0,J9-S9,"") -> 81.58 | U9: =IF(AND(J9>0,S9>0),(J9-S9)/S9,"") -> 0.071876652 | V9: =IF(H9="",0,IFERROR(MAX((H9-TODAY())/365.25,0),0)) -> 0.62149213 | W9: =F9*V9 -> 102.04901 | Y9: =IF(Z9="","VACANT",IF(Z9<TODAY(),"EXPIRED","ACTIVE")) -> ACTIVE | Z9: 46538 | AA9: 1216.58 | AB9: IPM Residential
A10: 00018 | B10: L03 | C10: 303&4 | D10: =IF(Y10="EXPIRED","VACANT","BROADRIDGE (AUSTRALIA) PTY LTD") -> BROADRIDGE (AUSTRALIA) PTY LTD | E10: =IF(Y10="EXPIRED","","BROADRIDGE (AUSTRALI) PTY LTD") -> BROADRIDGE (AUSTRALI) PTY LTD | F10: 193.4 | G10: =IF(Y10="EXPIRED","",DATE(2024,10,1)) -> 45566 | H10: =IF(Z10="","",IF(Z10<TODAY(),"",Z10)) -> 47026 | I10: =IF(Y10="EXPIRED","",4) -> 4 | J10: =IF(Y10="EXPIRED",0,933.75) -> 933.75 | K10: =IF(Y10="EXPIRED",0,J10*F10) -> 180587.25 | L10: -20962.2 | M10: 6300 | N10: =K10+L10 -> 159625.05 | O10: 0 | P10: FIXED 3.75% | Q10: 46296 | R10: Net | S10: =IFERROR(INDEX('Market Rents 26-27'!E:E,MATCH(C10,'Market Rents 26-27'!$A:$A,0)),0) -> 920 | T10: =IF(J10>0,J10-S10,"") -> 13.75 | U10: =IF(AND(J10>0,S10>0),(J10-S10)/S10,"") -> 0.014945652 | V10: =IF(H10="",0,IFERROR(MAX((H10-TODAY())/365.25,0),0)) -> 1.9575633 | W10: =F10*V10 -> 378.59274 | Y10: =IF(Z10="","VACANT",IF(Z10<TODAY(),"EXPIRED","ACTIVE")) -> ACTIVE | Z10: 47026 | AA10: 933.75 | AB10: Broadridge
A11: 00021 | B11: L04 | C11: 401 | D11: =IF(Y11="EXPIRED","VACANT","B-W INTERNATIONAL AUSTRALIA PTY LTD") -> B-W INTERNATIONAL AUSTRALIA PTY LTD | E11: =IF(Y11="EXPIRED","","B-W INTERNATIONAL AUSTRALIA PTY LTD") -> B-W INTERNATIONAL AUSTRALIA PTY LTD | F11: 214.1 | G11: =IF(Y11="EXPIRED","",DATE(2024,3,1)) -> 45352 | H11: =IF(Z11="","",IF(Z11<TODAY(),"",Z11)) -> 47177 | I11: =IF(Y11="EXPIRED","",5) -> 5 | J11: =IF(Y11="EXPIRED",0,1135.61) -> 1135.61 | K11: =IF(Y11="EXPIRED",0,J11*F11) -> 243134.1 | L11: -54203.76 | M11: 8700 | N11: =K11+L11 -> 188930.34 | O11: 0 | P11: FIXED 3.75% | Q11: 46447 | R11: Net | S11: =IFERROR(INDEX('Market Rents 26-27'!E:E,MATCH(C11,'Market Rents 26-27'!$A:$A,0)),0) -> 1145 | T11: =IF(J11>0,J11-S11,"") -> -9.39 | U11: =IF(AND(J11>0,S11>0),(J11-S11)/S11,"") -> -0.0082008734 | V11: =IF(H11="",0,IFERROR(MAX((H11-TODAY())/365.25,0),0)) -> 2.3709788 | W11: =F11*V11 -> 507.62656 | Y11: =IF(Z11="","VACANT",IF(Z11<TODAY(),"EXPIRED","ACTIVE")) -> ACTIVE | Z11: 47177 | AA11: 1135.61 | AB11: B-W International
A12: 00022 | B12: L04 | C12: 402 | D12: =IF(Y12="EXPIRED","VACANT","MP TRAVEL PTY LTD") -> MP TRAVEL PTY LTD | E12: =IF(Y12="EXPIRED","","GRAY DAWES TRAVEL") -> GRAY DAWES TRAVEL | F12: 145.6 | G12: =IF(Y12="EXPIRED","",DATE(2025,1,1)) -> 45658 | H12: =IF(Z12="","",IF(Z12<TODAY(),"",Z12)) -> 47483 | I12: =IF(Y12="EXPIRED","",5) -> 5 | J12: =IF(Y12="EXPIRED",0,1037.5) -> 1037.5 | K12: =IF(Y12="EXPIRED",0,J12*F12) -> 151060 | L12: -17675.88 | M12: 6000 | N12: =K12+L12 -> 133384.12 | O12: 0 | P12: FIXED 3.75% | Q12: 46388 | R12: Net | S12: =IFERROR(INDEX('Market Rents 26-27'!E:E,MATCH(C12,'Market Rents 26-27'!$A:$A,0)),0) -> 1000 | T12: =IF(J12>0,J12-S12,"") -> 37.5 | U12: =IF(AND(J12>0,S12>0),(J12-S12)/S12,"") -> 0.0375 | V12: =IF(H12="",0,IFERROR(MAX((H12-TODAY())/365.25,0),0)) -> 3.2087611 | W12: =F12*V12 -> 467.19562 | Y12: =IF(Z12="","VACANT",IF(Z12<TODAY(),"EXPIRED","ACTIVE")) -> ACTIVE | Z12: 47483 | AA12: 1037.5 | AB12: Gray Dawes Travel
A13: 00025 | B13: L05 | C13: 501 | D13: =IF(Y13="EXPIRED","VACANT","MONTGOMERY INVESTMENT") -> MONTGOMERY INVESTMENT | E13: =IF(Y13="EXPIRED","","MONTGOMERY INVESTMENT") -> MONTGOMERY INVESTMENT | F13: 212.3 | G13: =IF(Y13="EXPIRED","",DATE(2019,11,1)) -> 43770 | H13: =IF(Z13="","",IF(Z13<TODAY(),"",Z13)) -> 46691 | I13: =IF(Y13="EXPIRED","",8) -> 8 | J13: =IF(Y13="EXPIRED",0,1341.24) -> 1341.24 | K13: =IF(Y13="EXPIRED",0,J13*F13) -> 284745.25 | L13: -49361.76 | M13: 9900 | N13: =K13+L13 -> 235383.49 | O13: 0 | P13: FIXED 4% | Q13: 46327 | R13: Net | S13: =IFERROR(INDEX('Market Rents 26-27'!E:E,MATCH(C13,'Market Rents 26-27'!$A:$A,0)),0) -> 1155 | T13: =IF(J13>0,J13-S13,"") -> 186.24 | U13: =IF(AND(J13>0,S13>0),(J13-S13)/S13,"") -> 0.16124675 | V13: =IF(H13="",0,IFERROR(MAX((H13-TODAY())/365.25,0),0)) -> 1.0403833 | W13: =F13*V13 -> 220.87337 | Y13: =IF(Z13="","VACANT",IF(Z13<TODAY(),"EXPIRED","ACTIVE")) -> ACTIVE | Z13: 46691 | AA13: 1341.24 | AB13: Montgomery Investment
A14: 00026 | B14: L05 | C14: 502 | D14: =IF(Y14="EXPIRED","VACANT","THREAT DEFENCE") -> THREAT DEFENCE | E14: =IF(Y14="EXPIRED","","THREAT DEFENCE PTY LTD") -> THREAT DEFENCE PTY LTD | F14: 163.8 | G14: =IF(Y14="EXPIRED","",DATE(2024,7,1)) -> 45474 | H14: =IF(Z14="","",IF(Z14<TODAY(),"",Z14)) -> 46568 | I14: =IF(Y14="EXPIRED","",3) -> 3 | J14: 1054.88 | K14: =IF(Y14="EXPIRED",0,J14*F14) -> 172789.34 | L14: -41736.24 | M14: 7140 | N14: =K14+L14 -> 131053.1 | O14: 0 | P14: LEASE RENEWAL | Q14: 46569 | R14: Net | S14: =IFERROR(INDEX('Market Rents 26-27'!E:E,MATCH(C14,'Market Rents 26-27'!$A:$A,0)),0) -> 1020 | T14: =IF(J14>0,J14-S14,"") -> 34.88 | U14: =IF(AND(J14>0,S14>0),(J14-S14)/S14,"") -> 0.034196078 | V14: =IF(H14="",0,IFERROR(MAX((H14-TODAY())/365.25,0),0)) -> 0.70362765 | W14: =F14*V14 -> 115.25421 | Y14: =IF(Z14="","VACANT",IF(Z14<TODAY(),"EXPIRED","ACTIVE")) -> ACTIVE | Z14: 46568 | AA14: 1054.88 | AB14: Threat Defence
A15: 00029 | B15: L06 | C15: 601 | D15: =IF(Y15="EXPIRED","VACANT","FULLCRM PTY LTD") -> FULLCRM PTY LTD | E15: =IF(Y15="EXPIRED","","FULLCRM PTY LTD") -> FULLCRM PTY LTD | F15: 226.1 | G15: =IF(Y15="EXPIRED","",DATE(2021,12,1)) -> 44531 | H15: =IF(Z15="","",IF(Z15<TODAY(),"",Z15)) -> 46418 | I15: =IF(Y15="EXPIRED","",5.2) -> 5.2 | J15: =IF(Y15="EXPIRED",0,1251.34) -> 1251.34 | K15: =IF(Y15="EXPIRED",0,J15*F15) -> 282927.97 | L15: -31744.44 | M15: 13800 | N15: =K15+L15 -> 251183.53 | O15: 0 | P15: LEASE RENEWAL | Q15: 46419 | R15: Net | S15: =IFERROR(INDEX('Market Rents 26-27'!E:E,MATCH(C15,'Market Rents 26-27'!$A:$A,0)),0) -> 1165 | T15: =IF(J15>0,J15-S15,"") -> 86.34 | U15: =IF(AND(J15>0,S15>0),(J15-S15)/S15,"") -> 0.074111588 | V15: =IF(H15="",0,IFERROR(MAX((H15-TODAY())/365.25,0),0)) -> 0.29295003 | W15: =F15*V15 -> 66.236003 | Y15: =IF(Z15="","VACANT",IF(Z15<TODAY(),"EXPIRED","ACTIVE")) -> ACTIVE | Z15: 46418 | AA15: 1251.34 | AB15: Fullcrm
A16: 00030 | B16: L06 | C16: 602 | D16: INNOVIS | E16: INNOVIS | F16: 152.1 | G16: 46327 | H16: =IF(Z16="","",IF(Z16<TODAY(),"",Z16)) -> 47421 | I16: 3 | J16: 1090 | K16: =IF(Y16="EXPIRED",0,J16*F16) -> 165789 | L16: -29842.02 | N16: =K16+L16 -> 135946.98 | O16: 0 | P16: FIXED 3.75% | Q16: 46692 | R16: Net | S16: =IFERROR(INDEX('Market Rents 26-27'!E:E,MATCH(C16,'Market Rents 26-27'!$A:$A,0)),0) -> 1030 | T16: =IF(J16>0,J16-S16,"") -> 60 | U16: =IF(AND(J16>0,S16>0),(J16-S16)/S16,"") -> 0.058252427 | V16: =IF(H16="",0,IFERROR(MAX((H16-TODAY())/365.25,0),0)) -> 3.0390144 | W16: =F16*V16 -> 462.23409 | Y16: =IF(Z16="","VACANT",IF(Z16<TODAY(),"EXPIRED","ACTIVE")) -> ACTIVE | Z16: 47421 | AA16: 756.36 | AB16: INNOVIS
A17: 00033 | B17: L07 | C17: 701 | D17: =IF(Y17="EXPIRED","VACANT","PINPOINT TALENT PTY LTD") -> PINPOINT TALENT PTY LTD | E17: =IF(Y17="EXPIRED","","PINPOINT TALENT PTY LTD") -> PINPOINT TALENT PTY LTD | F17: 210.5 | G17: =IF(Y17="EXPIRED","",DATE(2023,8,7)) -> 45145 | H17: =IF(Z17="","",IF(Z17<TODAY(),"",Z17)) -> 46605 | I17: =IF(Y17="EXPIRED","",4) -> 4 | J17: =IF(Y17="EXPIRED",0,1173.54) -> 1173.54 | K17: =IF(Y17="EXPIRED",0,J17*F17) -> 247030.17 | L17: -68517.72 | M17: 13800 | N17: =K17+L17 -> 178512.45 | O17: 0 | P17: LEASE RENEWAL | Q17: 46606 | R17: Net | S17: =IFERROR(INDEX('Market Rents 26-27'!E:E,MATCH(C17,'Market Rents 26-27'!$A:$A,0)),0) -> 1175 | T17: =IF(J17>0,J17-S17,"") -> -1.46 | U17: =IF(AND(J17>0,S17>0),(J17-S17)/S17,"") -> -0.0012425532 | V17: =IF(H17="",0,IFERROR(MAX((H17-TODAY())/365.25,0),0)) -> 0.80492813 | W17: =F17*V17 -> 169.43737 | Y17: =IF(Z17="","VACANT",IF(Z17<TODAY(),"EXPIRED","ACTIVE")) -> ACTIVE | Z17: 46605 | AA17: 1173.54 | AB17: Pinpoint Talent
A18: 00034 | B18: L07 | C18: 702 | D18: =IF(Y18="EXPIRED","VACANT","SATELLITE OFFICE PTY LTD") -> SATELLITE OFFICE PTY LTD | E18: =IF(Y18="EXPIRED","","SATELLITE OFFICE PTY LTD") -> SATELLITE OFFICE PTY LTD | F18: 163.9 | G18: =IF(Y18="EXPIRED","",DATE(2024,6,1)) -> 45444 | H18: =IF(Z18="","",IF(Z18<TODAY(),"",Z18)) -> 46904 | I18: =IF(Y18="EXPIRED","",4) -> 4 | J18: 1054.88 | K18: =IF(Y18="EXPIRED",0,J18*F18) -> 172894.83 | L18: -40261.56 | M18: 7020 | N18: =K18+L18 -> 132633.27 | O18: 0 | P18: FIXED 3.75% | Q18: 46539 | R18: Net | S18: =IFERROR(INDEX('Market Rents 26-27'!E:E,MATCH(C18,'Market Rents 26-27'!$A:$A,0)),0) -> 1040 | T18: =IF(J18>0,J18-S18,"") -> 14.88 | U18: =IF(AND(J18>0,S18>0),(J18-S18)/S18,"") -> 0.014307692 | V18: =IF(H18="",0,IFERROR(MAX((H18-TODAY())/365.25,0),0)) -> 1.6235455 | W18: =F18*V18 -> 266.09911 | Y18: =IF(Z18="","VACANT",IF(Z18<TODAY(),"EXPIRED","ACTIVE")) -> ACTIVE | Z18: 46904 | AA18: 1054.88 | AB18: Satellite Office
A19: 00037 | B19: L08 | C19: 801 | D19: =IF(Y19="EXPIRED","VACANT","ARKANCE AUSTRALIA PTY LTD") -> ARKANCE AUSTRALIA PTY LTD | E19: =IF(Y19="EXPIRED","","ARKANCE AUSTRALIA PTY LTD") -> ARKANCE AUSTRALIA PTY LTD | F19: 222 | G19: =IF(Y19="EXPIRED","",DATE(2025,10,1)) -> 45931 | H19: =IF(Z19="","",IF(Z19<TODAY(),"",Z19)) -> 47756 | I19: =IF(Y19="EXPIRED","",5) -> 5 | J19: =IF(Y19="EXPIRED",0,1300) -> 1300 | K19: =IF(Y19="EXPIRED",0,J19*F19) -> 288600 | L19: -46176 | M19: 1500 | N19: =K19+L19 -> 242424 | O19: 0 | P19: FIXED 3.75% | Q19: 46296 | R19: Net | S19: =IFERROR(INDEX('Market Rents 26-27'!E:E,MATCH(C19,'Market Rents 26-27'!$A:$A,0)),0) -> 1300 | T19: =IF(J19>0,J19-S19,"") -> 0 | U19: =IF(AND(J19>0,S19>0),(J19-S19)/S19,"") -> 0 | V19: =IF(H19="",0,IFERROR(MAX((H19-TODAY())/365.25,0),0)) -> 3.9561944 | W19: =F19*V19 -> 878.27515 | Y19: =IF(Z19="","VACANT",IF(Z19<TODAY(),"EXPIRED","ACTIVE")) -> ACTIVE | Z19: 47756 | AA19: 1300 | AB19: Arkance Australia
A20: 00038 | B20: L08 | C20: 802 | D20: =IF(Y20="EXPIRED","VACANT","HILLIARD & BERRY") -> HILLIARD & BERRY | E20: =IF(Y20="EXPIRED","","HILLIARD & BERRY") -> HILLIARD & BERRY | F20: 138.5 | G20: =IF(Y20="EXPIRED","",DATE(2014,1,15)) -> 41654 | H20: =IF(Z20="","",IF(Z20<TODAY(),"",Z20)) -> 46965 | I20: =IF(Y20="EXPIRED","",14.6) -> 14.6 | J20: =IF(Y20="EXPIRED",0,843.65) -> 843.65 | K20: =IF(Y20="EXPIRED",0,J20*F20) -> 116845.52 | L20: 0 | M20: 12240 | N20: =K20+L20 -> 116845.52 | O20: 0 | P20: FIXED 4% | Q20: 46600 | R20: Net | S20: =IFERROR(INDEX('Market Rents 26-27'!E:E,MATCH(C20,'Market Rents 26-27'!$A:$A,0)),0) -> 1030 | T20: =IF(J20>0,J20-S20,"") -> -186.35 | U20: =IF(AND(J20>0,S20>0),(J20-S20)/S20,"") -> -0.18092233 | V20: =IF(H20="",0,IFERROR(MAX((H20-TODAY())/365.25,0),0)) -> 1.7905544 | W20: =F20*V20 -> 247.99179 | Y20: =IF(Z20="","VACANT",IF(Z20<TODAY(),"EXPIRED","ACTIVE")) -> ACTIVE | Z20: 46965 | AA20: 843.65 | AB20: Hilliard & Berry
A21: 00041 | B21: L09 | C21: 901 | D21: =IF(Y21="EXPIRED","VACANT","AITKEN INVESTMENT MANAGEMENT PTY LTD") -> AITKEN INVESTMENT MANAGEMENT PTY LTD | E21: =IF(Y21="EXPIRED","","AITKEN INVESTMENT MANAGEMENT") -> AITKEN INVESTMENT MANAGEMENT | F21: 52.8 | G21: =IF(Y21="EXPIRED","",DATE(2025,6,15)) -> 45823 | H21: =IF(Z21="","",IF(Z21<TODAY(),"",Z21)) -> 46918 | I21: =IF(Y21="EXPIRED","",3) -> 3 | J21: 1338.88 | K21: =IF(Y21="EXPIRED",0,J21*F21) -> 70692.864 | L21: -16394.4 | M21: 3780 | N21: =K21+L21 -> 54298.464 | O21: 0 | P21: FIXED 4% | Q21: 46918 | R21: Net | S21: =IFERROR(INDEX('Market Rents 26-27'!E:E,MATCH(C21,'Market Rents 26-27'!$A:$A,0)),0) -> 1350 | T21: =IF(J21>0,J21-S21,"") -> -11.12 | U21: =IF(AND(J21>0,S21>0),(J21-S21)/S21,"") -> -0.008237037 | V21: =IF(H21="",0,IFERROR(MAX((H21-TODAY())/365.25,0),0)) -> 1.6618754 | W21: =F21*V21 -> 87.747023 | Y21: =IF(Z21="","VACANT",IF(Z21<TODAY(),"EXPIRED","ACTIVE")) -> ACTIVE | Z21: 46918 | AA21: 1338.88 | AB21: Aitken Investment Mgmt
A22: 00044 | B22: L09 | C22: 902&3 | D22: =IF(Y22="EXPIRED","VACANT","CAPITAL E MARKETING AND EVENTS PTY LTD") -> CAPITAL E MARKETING AND EVENTS PTY LTD | E22: =IF(Y22="EXPIRED","","CAPITAL E MARKETING AND EVENTS") -> CAPITAL E MARKETING AND EVENTS | F22: 303 | G22: =IF(Y22="EXPIRED","",DATE(2022,1,1)) -> 44562 | H22: =IF(Z22="","",IF(Z22<TODAY(),"",Z22)) -> 47573 | I22: =IF(Y22="EXPIRED","",8.2) -> 8.2 | J22: =IF(Y22="EXPIRED",0,1141.25) -> 1141.25 | K22: =IF(Y22="EXPIRED",0,J22*F22) -> 345798.75 | L22: -90475.68 | M22: 9300 | N22: =K22+L22 -> 255323.07 | O22: 0 | P22: FIXED 3.75% | Q22: 46478 | R22: Net | S22: =IFERROR(INDEX('Market Rents 26-27'!E:E,MATCH(C22,'Market Rents 26-27'!$A:$A,0)),0) -> 1125 | T22: =IF(J22>0,J22-S22,"") -> 16.25 | U22: =IF(AND(J22>0,S22>0),(J22-S22)/S22,"") -> 0.014444444 | V22: =IF(H22="",0,IFERROR(MAX((H22-TODAY())/365.25,0),0)) -> 3.4551677 | W22: =F22*V22 -> 1046.9158 | Y22: =IF(Z22="","VACANT",IF(Z22<TODAY(),"EXPIRED","ACTIVE")) -> ACTIVE | Z22: 47573 | AA22: 1141.25 | AB22: Capital E Marketing
A23: 00048 | B23: L10 | C23: 1001&2 | D23: =IF(Y23="EXPIRED","VACANT","CONNECTUS SERVICES PTY LTD") -> CONNECTUS SERVICES PTY LTD | E23: =IF(Y23="EXPIRED","","CONNECTUS") -> CONNECTUS | F23: 363.2 | G23: =IF(Y23="EXPIRED","",DATE(2023,12,1)) -> 45261 | H23: =IF(Z23="","",IF(Z23<TODAY(),"",Z23)) -> 47452 | I23: =IF(Y23="EXPIRED","",6) -> 6 | J23: =IF(Y23="EXPIRED",0,1189.67) -> 1189.67 | K23: =IF(Y23="EXPIRED",0,J23*F23) -> 432088.14 | L23: -114537.96 | M23: 15000 | N23: =K23+L23 -> 317550.18 | O23: 0 | P23: FIXED | Q23: 46357 | R23: Net | S23: =IFERROR(INDEX('Market Rents 26-27'!E:E,MATCH(C23,'Market Rents 26-27'!$A:$A,0)),0) -> 1200 | T23: =IF(J23>0,J23-S23,"") -> -10.33 | U23: =IF(AND(J23>0,S23>0),(J23-S23)/S23,"") -> -0.0086083333 | V23: =IF(H23="",0,IFERROR(MAX((H23-TODAY())/365.25,0),0)) -> 3.1238877 | W23: =F23*V23 -> 1134.596 | Y23: =IF(Z23="","VACANT",IF(Z23<TODAY(),"EXPIRED","ACTIVE")) -> ACTIVE | Z23: 47452 | AA23: 1189.67 | AB23: Connectus Services
A24: 00050 | B24: L11 | C24: 1101 | D24: =IF(Y24="EXPIRED","VACANT","MICHAEL FLEGG PTY LTD") -> MICHAEL FLEGG PTY LTD | E24: =IF(Y24="EXPIRED","","MICHAEL FLEGG PTY LTD") -> MICHAEL FLEGG PTY LTD | F24: 62.4 | G24: =IF(Y24="EXPIRED","",DATE(2021,12,1)) -> 44531 | H24: =IF(Z24="","",IF(Z24<TODAY(),"",Z24)) -> 46356 | I24: =IF(Y24="EXPIRED","",5) -> 5 | J24: =IF(Y24="EXPIRED",0,1368.73) -> 1368.73 | K24: =IF(Y24="EXPIRED",0,J24*F24) -> 85408.752 | L24: 0 | M24: 4200 | N24: =K24+L24 -> 85408.752 | O24: 0 | P24: LEASE RENEWAL | Q24: 46357 | R24: Net | S24: =IFERROR(INDEX('Market Rents 26-27'!E:E,MATCH(C24,'Market Rents 26-27'!$A:$A,0)),0) -> 1405 | T24: =IF(J24>0,J24-S24,"") -> -36.27 | U24: =IF(AND(J24>0,S24>0),(J24-S24)/S24,"") -> -0.025814947 | V24: =IF(H24="",0,IFERROR(MAX((H24-TODAY())/365.25,0),0)) -> 0.12320329 | W24: =F24*V24 -> 7.687885 | Y24: =IF(Z24="","VACANT",IF(Z24<TODAY(),"EXPIRED","ACTIVE")) -> ACTIVE | Z24: 46356 | AA24: 1368.73 | AB24: Michael Flegg
A25: 00051 | B25: L11 | C25: 1102 | D25: =IF(Y25="EXPIRED","VACANT","LEWIS WOOLCOTT") -> LEWIS WOOLCOTT | E25: =IF(Y25="EXPIRED","","LEWIS WOOLCOTT") -> LEWIS WOOLCOTT | F25: 133.1 | G25: =IF(Y25="EXPIRED","",DATE(2026,8,15)) -> 46249 | H25: =IF(Z25="","",IF(Z25<TODAY(),"",Z25)) -> 46979 | I25: =IF(Y25="EXPIRED","",2) -> 2 | J25: =IF(Y25="EXPIRED",0,1271.1) -> 1271.1 | K25: =IF(Y25="EXPIRED",0,J25*F25) -> 169183.41 | L25: -30453.01 | M25: 5820 | N25: =K25+L25 -> 138730.4 | O25: 0 | P25: FIXED 4.0% | Q25: 46614 | R25: Net | S25: =IFERROR(INDEX('Market Rents 26-27'!E:E,MATCH(C25,'Market Rents 26-27'!$A:$A,0)),0) -> 1250 | T25: =IF(J25>0,J25-S25,"") -> 21.1 | U25: =IF(AND(J25>0,S25>0),(J25-S25)/S25,"") -> 0.01688 | V25: =IF(H25="",0,IFERROR(MAX((H25-TODAY())/365.25,0),0)) -> 1.8288843 | W25: =F25*V25 -> 243.4245 | X25: Lewis Woolcott new lease commences 15/8/26 (day after PharmX's lease ends), 2 yr term to 14/8/28, $1,271.10 psm. Outgoings carried forward at PharmX's existing rate pending TS confirmation. | Y25: =IF(Z25="","VACANT",IF(Z25<TODAY(),"EXPIRED","ACTIVE")) -> ACTIVE | Z25: 46979 | AA25: 1271.1 | AB25: Lewis Woolcott
A26: 00055 | B26: L12 | C26: L12 | D26: =IF(Y26="EXPIRED","VACANT","DAKOTA CORPORATION") -> DAKOTA CORPORATION | E26: =IF(Y26="EXPIRED","","OWNER OCCUPIED") -> OWNER OCCUPIED | F26: 223.7 | G26: =IF(Y26="EXPIRED","",DATE(2017,1,1)) -> 42736 | H26: =IF(Z26="","",IF(Z26<TODAY(),"",Z26)) -> 47118 | I26: =IF(Y26="EXPIRED","",7) -> 7 | J26: 0 | K26: =IF(Y26="EXPIRED",0,J26*F26) -> 0 | L26: 0 | M26: 0 | N26: =K26+L26 -> 0 | O26: 2 | P26: MONTHLY TENANT | Q26: 45291 | R26: N/A | S26: =IFERROR(INDEX('Market Rents 26-27'!E:E,MATCH(C26,'Market Rents 26-27'!$A:$A,0)),0) -> 384 | T26: =IF(J26>0,J26-S26,"") | U26: =IF(AND(J26>0,S26>0),(J26-S26)/S26,"") | V26: =IF(H26="",0,IFERROR(MAX((H26-TODAY())/365.25,0),0)) -> 2.2094456 | W26: =F26*V26 -> 494.25298 | Y26: =IF(Z26="","VACANT",IF(Z26<TODAY(),"EXPIRED","ACTIVE")) -> ACTIVE | Z26: 47118 | AA26: 0 | AB26: Dakota Corporation
A27: 00052 | B27: L11 | C27: 1103 | D27: =IF(Y27="EXPIRED","VACANT","INTERFI SYSTEMS PTY LTD") -> INTERFI SYSTEMS PTY LTD | E27: =IF(Y27="EXPIRED","","INTERFI SYSTEMS") -> INTERFI SYSTEMS | F27: 160.3 | G27: =IF(Y27="EXPIRED","",DATE(2026,7,15)) -> 46218 | H27: =IF(Z27="","",IF(Z27<TODAY(),"",Z27)) -> 47313 | I27: =IF(Y27="EXPIRED","",3) -> 3 | J27: =IF(Y27="EXPIRED",0,1150) -> 1150 | K27: =IF(Y27="EXPIRED",0,J27*F27) -> 184345 | L27: -55303.5 | M27: 0 | N27: =K27+L27 -> 129041.5 | O27: 0 | P27: FIXED 4.0% | Q27: 46583 | R27: Net | S27: =IFERROR(INDEX('Market Rents 26-27'!E:E,MATCH(C27,'Market Rents 26-27'!$A:$A,0)),0) -> 1060 | T27: =IF(J27>0,J27-S27,"") -> 90 | U27: =IF(AND(J27>0,S27>0),(J27-S27)/S27,"") -> 0.08490566 | V27: =IF(H27="",0,IFERROR(MAX((H27-TODAY())/365.25,0),0)) -> 2.7433265 | W27: =F27*V27 -> 439.75524 | X27: Interfi Systems (correct spelling per Jul26 TS, previously recorded as "Inferni Systems") — 3 yr term from 15/7/26 to 14/7/29, $1,150 psm. Jul26 TS confirms no Outgoings Cont or car parks for this suite (cleaning charged separately, not tracked in Outgoings PA column). | Y27: =IF(Z27="","VACANT",IF(Z27<TODAY(),"EXPIRED","ACTIVE")) -> ACTIVE | Z27: 47313 | AA27: 1150 | AB27: Interfi Systems
A28: TOTALS / BUILDING SUMMARY | F28: =SUM(F3:F27) -> 4704.5 | K28: =SUM(K3:K27) -> 4907584.1 | L28: =SUM(L3:L27) -> -873919.45 | M28: =SUM(M3:M27) -> 187288.32 | N28: =SUM(N3:N27) -> 4033664.6 | V28: =IFERROR(SUMPRODUCT(('Input Data'!K3:K27>0)*'Input Data'!F3:F27*MAX(('Input Data'!H3:H27-TODAY())/365.25,0))/SUMPRODUCT(('Input Data'!K3:K27>0)*'Input Data'!F3:F27),0) -> 0 | W28: =SUM(W3:W27) -> 10555.323
A30: LEGEND: | C30: Expired / Vacant | E30: Expiring in 2026 | G30: Active (odd rows)
A31: Note: Blue text = hardcoded input | Black text = formula | Update monthly from DJ Wear Tenancy Schedule PDF

Sheet Dashboard
A1: 17 CASTLEREAGH STREET, SYDNEY — ASSET MANAGEMENT DASHBOARD
A2: As at 31 July 2026 | Data sourced from Input Data tab
B4: TOTAL NLA | D4: OCCUPIED NLA | F4: VACANT NLA | H4: OCCUPANCY | J4: VACANCY RATE | L4: CAR PARKS
B5: =SUM('Input Data'!F3:F27) -> 4704.5 | D5: =SUMPRODUCT(('Input Data'!D3:D27<>"VACANT")*'Input Data'!F3:F27) -> 4542.1 | F5: {=SUMPRODUCT(('Input Data'!D3:D27="VACANT")*'Input Data'!F3:F27)} -> 162.4 | H5: {=SUMPRODUCT(('Input Data'!D3:D27<>"VACANT")*'Input Data'!F3:F27)/SUM('Input Data'!F3:F27)} -> 0.96547986 | J5: =SUMPRODUCT(('Input Data'!D3:D27="VACANT")*'Input Data'!F3:F27)/SUM('Input Data'!F3:F27) -> 0.03452014 | L5: 4 bays
B8: GROSS INCOME PA | D8: NET INCOME PA | F8: INCENTIVE RENT PA | H8: WALE BY NLA | J8: WALE BY INCOME | L8: TOTAL OUTGOINGS %
B9: =SUMPRODUCT(('Input Data'!AA3:AA27>0)*'Input Data'!AA3:AA27*'Input Data'!F3:F27) -> 4856837.4 | D9: =SUM('Input Data'!N3:N27) -> 4033664.6 | F9: =SUM('Input Data'!L3:L27) -> -873919.45 | H9: =IFERROR(SUMPRODUCT(('Input Data'!Z3:Z27>TODAY())*('Input Data'!AA3:AA27>0)*'Input Data'!F3:F27*('Input Data'!Z3:Z27-TODAY())/365.25)/SUMPRODUCT(('Input Data'!Z3:Z27>TODAY())*('Input Data'!AA3:AA27>0)*'Input Data'!F3:F27),0) -> 2.3298144 | J9: =IFERROR(SUMPRODUCT(('Input Data'!Z3:Z27>TODAY())*('Input Data'!AA3:AA27>0)*'Input Data'!AA3:AA27*'Input Data'!F3:F27*('Input Data'!Z3:Z27-TODAY())/365.25)/SUMPRODUCT(('Input Data'!Z3:Z27>TODAY())*('Input Data'!AA3:AA27>0)*'Input Data'!AA3:AA27*'Input Data'!F3:F27),0) -> 2.3123282 | L9: 92.32%
B12: WEIGHTED AVERAGE LEASE EXPIRY (WALE)
B13: Measure | D13: WALE | E13: Basis
B14: WALE by NLA | D14: =IFERROR(SUMPRODUCT(('Input Data'!Z3:Z27>TODAY())*('Input Data'!AA3:AA27>0)*'Input Data'!F3:F27*('Input Data'!Z3:Z27-TODAY())/365.25)/SUMPRODUCT(('Input Data'!Z3:Z27>TODAY())*('Input Data'!AA3:AA27>0)*'Input Data'!F3:F27),0) -> 2.3298144 | E14: Area-weighted avg of remaining lease terms
B15: WALE by Income | D15: =IFERROR(SUMPRODUCT(('Input Data'!Z3:Z27>TODAY())*('Input Data'!AA3:AA27>0)*'Input Data'!AA3:AA27*'Input Data'!F3:F27*('Input Data'!Z3:Z27-TODAY())/365.25)/SUMPRODUCT(('Input Data'!Z3:Z27>TODAY())*('Input Data'!AA3:AA27>0)*'Input Data'!AA3:AA27*'Input Data'!F3:F27),0) -> 2.3123282 | E15: Income-weighted avg of remaining lease terms
B17: LEASE EXPIRY PROFILE — BY INCOME & AREA (5 YEAR FORWARD VIEW)
B18: Expiry Year | C18: Net Income ($) | D18: Income % | E18: NLA (sqm) | F18: Area % | G18: # Leases | H18: Tenants Expiring
B19: 2026 | C19: =SUMPRODUCT(('Input Data'!Z3:Z27<>"")*('Input Data'!Z3:Z27<=DATE(2026,12,31))*('Input Data'!AA3:AA27>0)*'Input Data'!AA3:AA27*'Input Data'!F3:F27) -> 85408.752 | D19: =IFERROR(C19/(SUMPRODUCT(('Input Data'!Z3:Z27>TODAY())*('Input Data'!AA3:AA27>0)*'Input Data'!AA3:AA27*'Input Data'!F3:F27)),0) -> 0.017585261 | E19: =SUMPRODUCT(('Input Data'!Z3:Z27<>"")*('Input Data'!Z3:Z27<=DATE(2026,12,31))*('Input Data'!AA3:AA27>0)*'Input Data'!F3:F27) -> 62.4 | F19: =IFERROR(E19/(SUMPRODUCT(('Input Data'!Z3:Z27>TODAY())*('Input Data'!AA3:AA27>0)*'Input Data'!F3:F27)),0) -> 0.014449796 | G19: =SUMPRODUCT(('Input Data'!Z3:Z27<>"")*('Input Data'!Z3:Z27<=DATE(2026,12,31))*('Input Data'!AA3:AA27>0)*1) -> 1 | H19: =IFERROR(MID(IF(('Input Data'!Z3<>"")*('Input Data'!Z3<=DATE(2026,12,31)),", "&'Input Data'!AB3&" ("&'Input Data'!C3&")","")&IF(('Input Data'!Z4<>"")*('Input Data'!Z4<=DATE(2026,12,31)),", "&'Input Data'!AB4&" ("&'Input Data'!C4&")","")&IF(('Input Data'!Z5<>"")*('Input Data'!Z5<=DATE(2026,12,31)),", "&'Input Data'!AB5&" ("&'Input Data'!C5&")","")&IF(('Input Data'!Z6<>"")*('Input Data'!Z6<=DATE(2026,12,31)),", "&'Input Data'!AB6&" ("&'Input Data'!C6&")","")&IF(('Input Data'!Z7<>"")*('Input Data'!Z7<=DATE(2026,12,31)),", "&'Input Data'!AB7&" ("&'Input Data'!C7&")","")&IF(('Input Data'!Z8<>"")*('Input Data'!Z8<=DATE(2026,12,31)),", "&'Input Data'!AB8&" ("&'Input Data'!C8&")","")&IF(('Input Data'!Z9<>"")*('Input Data'!Z9<=DATE(2026,12,31)),", "&'Input Data'!AB9&" ("&'Input Data'!C9&")","")&IF(('Input Data'!Z10<>"")*('Input Data'!Z10<=DATE(2026,12,31)),", "&'Input Data'!AB10&" ("&'Input Data'!C10&")","")&IF(('Input Data'!Z11<>"")*('Input Data'!Z11<=DATE(2026,12,31)),", "&'Input Data'!AB11&" ("&'Input Data'!C11&")","")&IF(('Input Data'!Z12<>"")*('Input Data'!Z12<=DATE(2026,12,31)),", "&'Input Data'!AB12&" ("&'Input Data'!C12&")","")&IF(('Input Data'!Z13<>"")*('Input Data'!Z13<=DATE(2026,12,31)),", "&'Input Data'!AB13&" ("&'Input Data'!C13&")","")&IF(('Input Data'!Z14<>"")*('Input Data'!Z14<=DATE(2026,12,31)),", "&'Input Data'!AB14&" ("&'Input Data'!C14&")","")&IF(('Input Data'!Z15<>"")*('Input Data'!Z15<=DATE(2026,12,31)),", "&'Input Data'!AB15&" ("&'Input Data'!C15&")","")&IF(('Input Data'!Z16<>"")*('Input Data'!Z16<=DATE(2026,12,31)),", "&'Input Data'!AB16&" ("&'Input Data'!C16&")","")&IF(('Input Data'!Z17<>"")*('Input Data'!Z17<=DATE(2026,12,31)),", "&'Input Data'!AB17&" ("&'Input Data'!C17&")","")&IF(('Input Data'!Z18<>"")*('Input Data'!Z18<=DATE(2026,12,31)),", "&'Input Data'!AB18&" ("&'Input Data'!C18&")","")&IF(('Input Data'!Z19<>"")*('Input Data'!Z19<=DATE(2026,12,31)),", "&'Input Data'!AB19&" ("&'Input Data'!C19&")","")&IF(('Input Data'!Z20<>"")*('Input Data'!Z20<=DATE(2026,12,31)),", "&'Input Data'!AB20&" ("&'Input Data'!C20&")","")&IF(('Input Data'!Z21<>"")*('Input Data'!Z21<=DATE(2026,12,31)),", "&'Input Data'!AB21&" ("&'Input Data'!C21&")","")&IF(('Input Data'!Z22<>"")*('Input Data'!Z22<=DATE(2026,12,31)),", "&'Input Data'!AB22&" ("&'Input Data'!C22&")","")&IF(('Input Data'!Z23<>"")*('Input Data'!Z23<=DATE(2026,12,31)),", "&'Input Data'!AB23&" ("&'Input Data'!C23&")","")&IF(('Input Data'!Z24<>"")*('Input Data'!Z24<=DATE(2026,12,31)),", "&'Input Data'!AB24&" ("&'Input Data'!C24&")","")&IF(('Input Data'!Z25<>"")*('Input Data'!Z25<=DATE(2026,12,31)),", "&'Input Data'!AB25&" ("&'Input Data'!C25&")","")&IF(('Input Data'!Z26<>"")*('Input Data'!Z26<=DATE(2026,12,31)),", "&'Input Data'!AB26&" ("&'Input Data'!C26&")","")&IF(('Input Data'!Z27<>"")*('Input Data'!Z27<=DATE(2026,12,31)),", "&'Input Data'!AB27&" ("&'Input Data'!C27&")",""),3,999),"—") -> Michael Flegg (1101)
B20: 2027 | C20: =SUMPRODUCT(('Input Data'!Z3:Z27>TODAY())*(YEAR('Input Data'!Z3:Z27)=2027)*('Input Data'!AA3:AA27>0)*'Input Data'!AA3:AA27*'Input Data'!F3:F27) -> 1187255.2 | D20: =IFERROR(C20/(SUMPRODUCT(('Input Data'!Z3:Z27>TODAY())*('Input Data'!AA3:AA27>0)*'Input Data'!AA3:AA27*'Input Data'!F3:F27)),0) -> 0.24445026 | E20: =SUMPRODUCT(('Input Data'!Z3:Z27>TODAY())*(YEAR('Input Data'!Z3:Z27)=2027)*('Input Data'!AA3:AA27>0)*'Input Data'!F3:F27) -> 976.9 | F20: =IFERROR(E20/(SUMPRODUCT(('Input Data'!Z3:Z27>TODAY())*('Input Data'!AA3:AA27>0)*'Input Data'!F3:F27)),0) -> 0.22621804 | G20: =SUMPRODUCT(('Input Data'!Z3:Z27>TODAY())*(YEAR('Input Data'!Z3:Z27)=2027)*('Input Data'!AA3:AA27>0)*1) -> 5 | H20: =IFERROR(MID(IF(('Input Data'!Z3>TODAY())*('Input Data'!AA3>0)*(YEAR('Input Data'!Z3)=2027),", "&'Input Data'!AB3&" ("&'Input Data'!C3&")","")&IF(('Input Data'!Z4>TODAY())*('Input Data'!AA4>0)*(YEAR('Input Data'!Z4)=2027),", "&'Input Data'!AB4&" ("&'Input Data'!C4&")","")&IF(('Input Data'!Z5>TODAY())*('Input Data'!AA5>0)*(YEAR('Input Data'!Z5)=2027),", "&'Input Data'!AB5&" ("&'Input Data'!C5&")","")&IF(('Input Data'!Z6>TODAY())*('Input Data'!AA6>0)*(YEAR('Input Data'!Z6)=2027),", "&'Input Data'!AB6&" ("&'Input Data'!C6&")","")&IF(('Input Data'!Z7>TODAY())*('Input Data'!AA7>0)*(YEAR('Input Data'!Z7)=2027),", "&'Input Data'!AB7&" ("&'Input Data'!C7&")","")&IF(('Input Data'!Z8>TODAY())*('Input Data'!AA8>0)*(YEAR('Input Data'!Z8)=2027),", "&'Input Data'!AB8&" ("&'Input Data'!C8&")","")&IF(('Input Data'!Z9>TODAY())*('Input Data'!AA9>0)*(YEAR('Input Data'!Z9)=2027),", "&'Input Data'!AB9&" ("&'Input Data'!C9&")","")&IF(('Input Data'!Z10>TODAY())*('Input Data'!AA10>0)*(YEAR('Input Data'!Z10)=2027),", "&'Input Data'!AB10&" ("&'Input Data'!C10&")","")&IF(('Input Data'!Z11>TODAY())*('Input Data'!AA11>0)*(YEAR('Input Data'!Z11)=2027),", "&'Input Data'!AB11&" ("&'Input Data'!C11&")","")&IF(('Input Data'!Z12>TODAY())*('Input Data'!AA12>0)*(YEAR('Input Data'!Z12)=2027),", "&'Input Data'!AB12&" ("&'Input Data'!C12&")","")&IF(('Input Data'!Z13>TODAY())*('Input Data'!AA13>0)*(YEAR('Input Data'!Z13)=2027),", "&'Input Data'!AB13&" ("&'Input Data'!C13&")","")&IF(('Input Data'!Z14>TODAY())*('Input Data'!AA14>0)*(YEAR('Input Data'!Z14)=2027),", "&'Input Data'!AB14&" ("&'Input Data'!C14&")","")&IF(('Input Data'!Z15>TODAY())*('Input Data'!AA15>0)*(YEAR('Input Data'!Z15)=2027),", "&'Input Data'!AB15&" ("&'Input Data'!C15&")","")&IF(('Input Data'!Z16>TODAY())*('Input Data'!AA16>0)*(YEAR('Input Data'!Z16)=2027),", "&'Input Data'!AB16&" ("&'Input Data'!C16&")","")&IF(('Input Data'!Z17>TODAY())*('Input Data'!AA17>0)*(YEAR('Input Data'!Z17)=2027),", "&'Input Data'!AB17&" ("&'Input Data'!C17&")","")&IF(('Input Data'!Z18>TODAY())*('Input Data'!AA18>0)*(YEAR('Input Data'!Z18)=2027),", "&'Input Data'!AB18&" ("&'Input Data'!C18&")","")&IF(('Input Data'!Z19>TODAY())*('Input Data'!AA19>0)*(YEAR('Input Data'!Z19)=2027),", "&'Input Data'!AB19&" ("&'Input Data'!C19&")","")&IF(('Input Data'!Z20>TODAY())*('Input Data'!AA20>0)*(YEAR('Input Data'!Z20)=2027),", "&'Input Data'!AB20&" ("&'Input Data'!C20&")","")&IF(('Input Data'!Z21>TODAY())*('Input Data'!AA21>0)*(YEAR('Input Data'!Z21)=2027),", "&'Input Data'!AB21&" ("&'Input Data'!C21&")","")&IF(('Input Data'!Z22>TODAY())*('Input Data'!AA22>0)*(YEAR('Input Data'!Z22)=2027),", "&'Input Data'!AB22&" ("&'Input Data'!C22&")","")&IF(('Input Data'!Z23>TODAY())*('Input Data'!AA23>0)*(YEAR('Input Data'!Z23)=2027),", "&'Input Data'!AB23&" ("&'Input Data'!C23&")","")&IF(('Input Data'!Z24>TODAY())*('Input Data'!AA24>0)*(YEAR('Input Data'!Z24)=2027),", "&'Input Data'!AB24&" ("&'Input Data'!C24&")","")&IF(('Input Data'!Z25>TODAY())*('Input Data'!AA25>0)*(YEAR('Input Data'!Z25)=2027),", "&'Input Data'!AB25&" ("&'Input Data'!C25&")","")&IF(('Input Data'!Z26>TODAY())*('Input Data'!AA26>0)*(YEAR('Input Data'!Z26)=2027),", "&'Input Data'!AB26&" ("&'Input Data'!C26&")","")&IF(('Input Data'!Z27>TODAY())*('Input Data'!AA27>0)*(YEAR('Input Data'!Z27)=2027),", "&'Input Data'!AB27&" ("&'Input Data'!C27&")",""),3,999),"—") -> IPM Residential (301&2), Montgomery Investment (501), Threat Defence (502), Fullcrm (601), Pinpoint Talent (701)
B21: 2028 | C21: =SUMPRODUCT(('Input Data'!Z3:Z27>TODAY())*(YEAR('Input Data'!Z3:Z27)=2028)*('Input Data'!AA3:AA27>0)*'Input Data'!AA3:AA27*'Input Data'!F3:F27) -> 1233906.6 | D21: =IFERROR(C21/(SUMPRODUCT(('Input Data'!Z3:Z27>TODAY())*('Input Data'!AA3:AA27>0)*'Input Data'!AA3:AA27*'Input Data'!F3:F27)),0) -> 0.25405558 | E21: =SUMPRODUCT(('Input Data'!Z3:Z27>TODAY())*(YEAR('Input Data'!Z3:Z27)=2028)*('Input Data'!AA3:AA27>0)*'Input Data'!F3:F27) -> 1171.2 | F21: =IFERROR(E21/(SUMPRODUCT(('Input Data'!Z3:Z27>TODAY())*('Input Data'!AA3:AA27>0)*'Input Data'!F3:F27)),0) -> 0.27121156 | G21: =SUMPRODUCT(('Input Data'!Z3:Z27>TODAY())*(YEAR('Input Data'!Z3:Z27)=2028)*('Input Data'!AA3:AA27>0)*1) -> 7 | H21: =IFERROR(MID(IF(('Input Data'!Z3>TODAY())*('Input Data'!AA3>0)*(YEAR('Input Data'!Z3)=2028),", "&'Input Data'!AB3&" ("&'Input Data'!C3&")","")&IF(('Input Data'!Z4>TODAY())*('Input Data'!AA4>0)*(YEAR('Input Data'!Z4)=2028),", "&'Input Data'!AB4&" ("&'Input Data'!C4&")","")&IF(('Input Data'!Z5>TODAY())*('Input Data'!AA5>0)*(YEAR('Input Data'!Z5)=2028),", "&'Input Data'!AB5&" ("&'Input Data'!C5&")","")&IF(('Input Data'!Z6>TODAY())*('Input Data'!AA6>0)*(YEAR('Input Data'!Z6)=2028),", "&'Input Data'!AB6&" ("&'Input Data'!C6&")","")&IF(('Input Data'!Z7>TODAY())*('Input Data'!AA7>0)*(YEAR('Input Data'!Z7)=2028),", "&'Input Data'!AB7&" ("&'Input Data'!C7&")","")&IF(('Input Data'!Z8>TODAY())*('Input Data'!AA8>0)*(YEAR('Input Data'!Z8)=2028),", "&'Input Data'!AB8&" ("&'Input Data'!C8&")","")&IF(('Input Data'!Z9>TODAY())*('Input Data'!AA9>0)*(YEAR('Input Data'!Z9)=2028),", "&'Input Data'!AB9&" ("&'Input Data'!C9&")","")&IF(('Input Data'!Z10>TODAY())*('Input Data'!AA10>0)*(YEAR('Input Data'!Z10)=2028),", "&'Input Data'!AB10&" ("&'Input Data'!C10&")","")&IF(('Input Data'!Z11>TODAY())*('Input Data'!AA11>0)*(YEAR('Input Data'!Z11)=2028),", "&'Input Data'!AB11&" ("&'Input Data'!C11&")","")&IF(('Input Data'!Z12>TODAY())*('Input Data'!AA12>0)*(YEAR('Input Data'!Z12)=2028),", "&'Input Data'!AB12&" ("&'Input Data'!C12&")","")&IF(('Input Data'!Z13>TODAY())*('Input Data'!AA13>0)*(YEAR('Input Data'!Z13)=2028),", "&'Input Data'!AB13&" ("&'Input Data'!C13&")","")&IF(('Input Data'!Z14>TODAY())*('Input Data'!AA14>0)*(YEAR('Input Data'!Z14)=2028),", "&'Input Data'!AB14&" ("&'Input Data'!C14&")","")&IF(('Input Data'!Z15>TODAY())*('Input Data'!AA15>0)*(YEAR('Input Data'!Z15)=2028),", "&'Input Data'!AB15&" ("&'Input Data'!C15&")","")&IF(('Input Data'!Z16>TODAY())*('Input Data'!AA16>0)*(YEAR('Input Data'!Z16)=2028),", "&'Input Data'!AB16&" ("&'Input Data'!C16&")","")&IF(('Input Data'!Z17>TODAY())*('Input Data'!AA17>0)*(YEAR('Input Data'!Z17)=2028),", "&'Input Data'!AB17&" ("&'Input Data'!C17&")","")&IF(('Input Data'!Z18>TODAY())*('Input Data'!AA18>0)*(YEAR('Input Data'!Z18)=2028),", "&'Input Data'!AB18&" ("&'Input Data'!C18&")","")&IF(('Input Data'!Z19>TODAY())*('Input Data'!AA19>0)*(YEAR('Input Data'!Z19)=2028),", "&'Input Data'!AB19&" ("&'Input Data'!C19&")","")&IF(('Input Data'!Z20>TODAY())*('Input Data'!AA20>0)*(YEAR('Input Data'!Z20)=2028),", "&'Input Data'!AB20&" ("&'Input Data'!C20&")","")&IF(('Input Data'!Z21>TODAY())*('Input Data'!AA21>0)*(YEAR('Input Data'!Z21)=2028),", "&'Input Data'!AB21&" ("&'Input Data'!C21&")","")&IF(('Input Data'!Z22>TODAY())*('Input Data'!AA22>0)*(YEAR('Input Data'!Z22)=2028),", "&'Input Data'!AB22&" ("&'Input Data'!C22&")","")&IF(('Input Data'!Z23>TODAY())*('Input Data'!AA23>0)*(YEAR('Input Data'!Z23)=2028),", "&'Input Data'!AB23&" ("&'Input Data'!C23&")","")&IF(('Input Data'!Z24>TODAY())*('Input Data'!AA24>0)*(YEAR('Input Data'!Z24)=2028),", "&'Input Data'!AB24&" ("&'Input Data'!C24&")","")&IF(('Input Data'!Z25>TODAY())*('Input Data'!AA25>0)*(YEAR('Input Data'!Z25)=2028),", "&'Input Data'!AB25&" ("&'Input Data'!C25&")","")&IF(('Input Data'!Z26>TODAY())*('Input Data'!AA26>0)*(YEAR('Input Data'!Z26)=2028),", "&'Input Data'!AB26&" ("&'Input Data'!C26&")","")&IF(('Input Data'!Z27>TODAY())*('Input Data'!AA27>0)*(YEAR('Input Data'!Z27)=2028),", "&'Input Data'!AB27&" ("&'Input Data'!C27&")",""),3,999),"—") -> PU Prime Trading (103), Princeton Financial Services (WHOLE), Broadridge (303&4), Satellite Office (702), Hilliard & Berry (802), Aitken Investment Mgmt (901), Lewis Woolcott (1102)
B22: 2029 | C22: =SUMPRODUCT(('Input Data'!Z3:Z27>TODAY())*(YEAR('Input Data'!Z3:Z27)=2029)*('Input Data'!AA3:AA27>0)*'Input Data'!AA3:AA27*'Input Data'!F3:F27) -> 1372668 | D22: =IFERROR(C22/(SUMPRODUCT(('Input Data'!Z3:Z27>TODAY())*('Input Data'!AA3:AA27>0)*'Input Data'!AA3:AA27*'Input Data'!F3:F27)),0) -> 0.28262589 | E22: =SUMPRODUCT(('Input Data'!Z3:Z27>TODAY())*(YEAR('Input Data'!Z3:Z27)=2029)*('Input Data'!AA3:AA27>0)*'Input Data'!F3:F27) -> 1284.6 | F22: =IFERROR(E22/(SUMPRODUCT(('Input Data'!Z3:Z27>TODAY())*('Input Data'!AA3:AA27>0)*'Input Data'!F3:F27)),0) -> 0.29747129 | G22: =SUMPRODUCT(('Input Data'!Z3:Z27>TODAY())*(YEAR('Input Data'!Z3:Z27)=2029)*('Input Data'!AA3:AA27>0)*1) -> 7 | H22: =IFERROR(MID(IF(('Input Data'!Z3>TODAY())*('Input Data'!AA3>0)*(YEAR('Input Data'!Z3)=2029),", "&'Input Data'!AB3&" ("&'Input Data'!C3&")","")&IF(('Input Data'!Z4>TODAY())*('Input Data'!AA4>0)*(YEAR('Input Data'!Z4)=2029),", "&'Input Data'!AB4&" ("&'Input Data'!C4&")","")&IF(('Input Data'!Z5>TODAY())*('Input Data'!AA5>0)*(YEAR('Input Data'!Z5)=2029),", "&'Input Data'!AB5&" ("&'Input Data'!C5&")","")&IF(('Input Data'!Z6>TODAY())*('Input Data'!AA6>0)*(YEAR('Input Data'!Z6)=2029),", "&'Input Data'!AB6&" ("&'Input Data'!C6&")","")&IF(('Input Data'!Z7>TODAY())*('Input Data'!AA7>0)*(YEAR('Input Data'!Z7)=2029),", "&'Input Data'!AB7&" ("&'Input Data'!C7&")","")&IF(('Input Data'!Z8>TODAY())*('Input Data'!AA8>0)*(YEAR('Input Data'!Z8)=2029),", "&'Input Data'!AB8&" ("&'Input Data'!C8&")","")&IF(('Input Data'!Z9>TODAY())*('Input Data'!AA9>0)*(YEAR('Input Data'!Z9)=2029),", "&'Input Data'!AB9&" ("&'Input Data'!C9&")","")&IF(('Input Data'!Z10>TODAY())*('Input Data'!AA10>0)*(YEAR('Input Data'!Z10)=2029),", "&'Input Data'!AB10&" ("&'Input Data'!C10&")","")&IF(('Input Data'!Z11>TODAY())*('Input Data'!AA11>0)*(YEAR('Input Data'!Z11)=2029),", "&'Input Data'!AB11&" ("&'Input Data'!C11&")","")&IF(('Input Data'!Z12>TODAY())*('Input Data'!AA12>0)*(YEAR('Input Data'!Z12)=2029),", "&'Input Data'!AB12&" ("&'Input Data'!C12&")","")&IF(('Input Data'!Z13>TODAY())*('Input Data'!AA13>0)*(YEAR('Input Data'!Z13)=2029),", "&'Input Data'!AB13&" ("&'Input Data'!C13&")","")&IF(('Input Data'!Z14>TODAY())*('Input Data'!AA14>0)*(YEAR('Input Data'!Z14)=2029),", "&'Input Data'!AB14&" ("&'Input Data'!C14&")","")&IF(('Input Data'!Z15>TODAY())*('Input Data'!AA15>0)*(YEAR('Input Data'!Z15)=2029),", "&'Input Data'!AB15&" ("&'Input Data'!C15&")","")&IF(('Input Data'!Z16>TODAY())*('Input Data'!AA16>0)*(YEAR('Input Data'!Z16)=2029),", "&'Input Data'!AB16&" ("&'Input Data'!C16&")","")&IF(('Input Data'!Z17>TODAY())*('Input Data'!AA17>0)*(YEAR('Input Data'!Z17)=2029),", "&'Input Data'!AB17&" ("&'Input Data'!C17&")","")&IF(('Input Data'!Z18>TODAY())*('Input Data'!AA18>0)*(YEAR('Input Data'!Z18)=2029),", "&'Input Data'!AB18&" ("&'Input Data'!C18&")","")&IF(('Input Data'!Z19>TODAY())*('Input Data'!AA19>0)*(YEAR('Input Data'!Z19)=2029),", "&'Input Data'!AB19&" ("&'Input Data'!C19&")","")&IF(('Input Data'!Z20>TODAY())*('Input Data'!AA20>0)*(YEAR('Input Data'!Z20)=2029),", "&'Input Data'!AB20&" ("&'Input Data'!C20&")","")&IF(('Input Data'!Z21>TODAY())*('Input Data'!AA21>0)*(YEAR('Input Data'!Z21)=2029),", "&'Input Data'!AB21&" ("&'Input Data'!C21&")","")&IF(('Input Data'!Z22>TODAY())*('Input Data'!AA22>0)*(YEAR('Input Data'!Z22)=2029),", "&'Input Data'!AB22&" ("&'Input Data'!C22&")","")&IF(('Input Data'!Z23>TODAY())*('Input Data'!AA23>0)*(YEAR('Input Data'!Z23)=2029),", "&'Input Data'!AB23&" ("&'Input Data'!C23&")","")&IF(('Input Data'!Z24>TODAY())*('Input Data'!AA24>0)*(YEAR('Input Data'!Z24)=2029),", "&'Input Data'!AB24&" ("&'Input Data'!C24&")","")&IF(('Input Data'!Z25>TODAY())*('Input Data'!AA25>0)*(YEAR('Input Data'!Z25)=2029),", "&'Input Data'!AB25&" ("&'Input Data'!C25&")","")&IF(('Input Data'!Z26>TODAY())*('Input Data'!AA26>0)*(YEAR('Input Data'!Z26)=2029),", "&'Input Data'!AB26&" ("&'Input Data'!C26&")","")&IF(('Input Data'!Z27>TODAY())*('Input Data'!AA27>0)*(YEAR('Input Data'!Z27)=2029),", "&'Input Data'!AB27&" ("&'Input Data'!C27&")",""),3,999),"—") -> Opulent Two Enterprises (LWR GROUND), TJC#1 (104), B-W International (401), Gray Dawes Travel (402), INNOVIS (602), Connectus Services (1001&2), Interfi Systems (1103)
B23: 2030 | C23: =SUMPRODUCT(('Input Data'!Z3:Z27>TODAY())*(YEAR('Input Data'!Z3:Z27)=2030)*('Input Data'!AA3:AA27>0)*'Input Data'!AA3:AA27*'Input Data'!F3:F27) -> 634398.75 | D23: =IFERROR(C23/(SUMPRODUCT(('Input Data'!Z3:Z27>TODAY())*('Input Data'!AA3:AA27>0)*'Input Data'!AA3:AA27*'Input Data'!F3:F27)),0) -> 0.13061972 | E23: =SUMPRODUCT(('Input Data'!Z3:Z27>TODAY())*(YEAR('Input Data'!Z3:Z27)=2030)*('Input Data'!AA3:AA27>0)*'Input Data'!F3:F27) -> 525 | F23: =IFERROR(E23/(SUMPRODUCT(('Input Data'!Z3:Z27>TODAY())*('Input Data'!AA3:AA27>0)*'Input Data'!F3:F27)),0) -> 0.1215728 | G23: =SUMPRODUCT(('Input Data'!Z3:Z27>TODAY())*(YEAR('Input Data'!Z3:Z27)=2030)*('Input Data'!AA3:AA27>0)*1) -> 2 | H23: =IFERROR(MID(IF(('Input Data'!Z3>TODAY())*('Input Data'!AA3>0)*(YEAR('Input Data'!Z3)=2030),", "&'Input Data'!AB3&" ("&'Input Data'!C3&")","")&IF(('Input Data'!Z4>TODAY())*('Input Data'!AA4>0)*(YEAR('Input Data'!Z4)=2030),", "&'Input Data'!AB4&" ("&'Input Data'!C4&")","")&IF(('Input Data'!Z5>TODAY())*('Input Data'!AA5>0)*(YEAR('Input Data'!Z5)=2030),", "&'Input Data'!AB5&" ("&'Input Data'!C5&")","")&IF(('Input Data'!Z6>TODAY())*('Input Data'!AA6>0)*(YEAR('Input Data'!Z6)=2030),", "&'Input Data'!AB6&" ("&'Input Data'!C6&")","")&IF(('Input Data'!Z7>TODAY())*('Input Data'!AA7>0)*(YEAR('Input Data'!Z7)=2030),", "&'Input Data'!AB7&" ("&'Input Data'!C7&")","")&IF(('Input Data'!Z8>TODAY())*('Input Data'!AA8>0)*(YEAR('Input Data'!Z8)=2030),", "&'Input Data'!AB8&" ("&'Input Data'!C8&")","")&IF(('Input Data'!Z9>TODAY())*('Input Data'!AA9>0)*(YEAR('Input Data'!Z9)=2030),", "&'Input Data'!AB9&" ("&'Input Data'!C9&")","")&IF(('Input Data'!Z10>TODAY())*('Input Data'!AA10>0)*(YEAR('Input Data'!Z10)=2030),", "&'Input Data'!AB10&" ("&'Input Data'!C10&")","")&IF(('Input Data'!Z11>TODAY())*('Input Data'!AA11>0)*(YEAR('Input Data'!Z11)=2030),", "&'Input Data'!AB11&" ("&'Input Data'!C11&")","")&IF(('Input Data'!Z12>TODAY())*('Input Data'!AA12>0)*(YEAR('Input Data'!Z12)=2030),", "&'Input Data'!AB12&" ("&'Input Data'!C12&")","")&IF(('Input Data'!Z13>TODAY())*('Input Data'!AA13>0)*(YEAR('Input Data'!Z13)=2030),", "&'Input Data'!AB13&" ("&'Input Data'!C13&")","")&IF(('Input Data'!Z14>TODAY())*('Input Data'!AA14>0)*(YEAR('Input Data'!Z14)=2030),", "&'Input Data'!AB14&" ("&'Input Data'!C14&")","")&IF(('Input Data'!Z15>TODAY())*('Input Data'!AA15>0)*(YEAR('Input Data'!Z15)=2030),", "&'Input Data'!AB15&" ("&'Input Data'!C15&")","")&IF(('Input Data'!Z16>TODAY())*('Input Data'!AA16>0)*(YEAR('Input Data'!Z16)=2030),", "&'Input Data'!AB16&" ("&'Input Data'!C16&")","")&IF(('Input Data'!Z17>TODAY())*('Input Data'!AA17>0)*(YEAR('Input Data'!Z17)=2030),", "&'Input Data'!AB17&" ("&'Input Data'!C17&")","")&IF(('Input Data'!Z18>TODAY())*('Input Data'!AA18>0)*(YEAR('Input Data'!Z18)=2030),", "&'Input Data'!AB18&" ("&'Input Data'!C18&")","")&IF(('Input Data'!Z19>TODAY())*('Input Data'!AA19>0)*(YEAR('Input Data'!Z19)=2030),", "&'Input Data'!AB19&" ("&'Input Data'!C19&")","")&IF(('Input Data'!Z20>TODAY())*('Input Data'!AA20>0)*(YEAR('Input Data'!Z20)=2030),", "&'Input Data'!AB20&" ("&'Input Data'!C20&")","")&IF(('Input Data'!Z21>TODAY())*('Input Data'!AA21>0)*(YEAR('Input Data'!Z21)=2030),", "&'Input Data'!AB21&" ("&'Input Data'!C21&")","")&IF(('Input Data'!Z22>TODAY())*('Input Data'!AA22>0)*(YEAR('Input Data'!Z22)=2030),", "&'Input Data'!AB22&" ("&'Input Data'!C22&")","")&IF(('Input Data'!Z23>TODAY())*('Input Data'!AA23>0)*(YEAR('Input Data'!Z23)=2030),", "&'Input Data'!AB23&" ("&'Input Data'!C23&")","")&IF(('Input Data'!Z24>TODAY())*('Input Data'!AA24>0)*(YEAR('Input Data'!Z24)=2030),", "&'Input Data'!AB24&" ("&'Input Data'!C24&")","")&IF(('Input Data'!Z25>TODAY())*('Input Data'!AA25>0)*(YEAR('Input Data'!Z25)=2030),", "&'Input Data'!AB25&" ("&'Input Data'!C25&")","")&IF(('Input Data'!Z26>TODAY())*('Input Data'!AA26>0)*(YEAR('Input Data'!Z26)=2030),", "&'Input Data'!AB26&" ("&'Input Data'!C26&")","")&IF(('Input Data'!Z27>TODAY())*('Input Data'!AA27>0)*(YEAR('Input Data'!Z27)=2030),", "&'Input Data'!AB27&" ("&'Input Data'!C27&")",""),3,999),"—") -> Arkance Australia (801), Capital E Marketing (902&3)
B24: 2031+ | C24: =SUMPRODUCT(('Input Data'!Z3:Z27>TODAY())*(YEAR('Input Data'!Z3:Z27)>=2031)*('Input Data'!AA3:AA27>0)*'Input Data'!AA3:AA27*'Input Data'!F3:F27) -> 343200.12 | D24: =IFERROR(C24/(SUMPRODUCT(('Input Data'!Z3:Z27>TODAY())*('Input Data'!AA3:AA27>0)*'Input Data'!AA3:AA27*'Input Data'!F3:F27)),0) -> 0.070663291 | E24: =SUMPRODUCT(('Input Data'!Z3:Z27>TODAY())*(YEAR('Input Data'!Z3:Z27)>=2031)*('Input Data'!AA3:AA27>0)*'Input Data'!F3:F27) -> 298.3 | F24: =IFERROR(E24/(SUMPRODUCT(('Input Data'!Z3:Z27>TODAY())*('Input Data'!AA3:AA27>0)*'Input Data'!F3:F27)),0) -> 0.06907651 | G24: =SUMPRODUCT(('Input Data'!Z3:Z27>TODAY())*(YEAR('Input Data'!Z3:Z27)>=2031)*('Input Data'!AA3:AA27>0)*1) -> 1 | H24: =IFERROR(MID(IF(('Input Data'!Z3>TODAY())*('Input Data'!AA3>0)*(YEAR('Input Data'!Z3)>=2031),", "&'Input Data'!AB3&" ("&'Input Data'!C3&")","")&IF(('Input Data'!Z4>TODAY())*('Input Data'!AA4>0)*(YEAR('Input Data'!Z4)>=2031),", "&'Input Data'!AB4&" ("&'Input Data'!C4&")","")&IF(('Input Data'!Z5>TODAY())*('Input Data'!AA5>0)*(YEAR('Input Data'!Z5)>=2031),", "&'Input Data'!AB5&" ("&'Input Data'!C5&")","")&IF(('Input Data'!Z6>TODAY())*('Input Data'!AA6>0)*(YEAR('Input Data'!Z6)>=2031),", "&'Input Data'!AB6&" ("&'Input Data'!C6&")","")&IF(('Input Data'!Z7>TODAY())*('Input Data'!AA7>0)*(YEAR('Input Data'!Z7)>=2031),", "&'Input Data'!AB7&" ("&'Input Data'!C7&")","")&IF(('Input Data'!Z8>TODAY())*('Input Data'!AA8>0)*(YEAR('Input Data'!Z8)>=2031),", "&'Input Data'!AB8&" ("&'Input Data'!C8&")","")&IF(('Input Data'!Z9>TODAY())*('Input Data'!AA9>0)*(YEAR('Input Data'!Z9)>=2031),", "&'Input Data'!AB9&" ("&'Input Data'!C9&")","")&IF(('Input Data'!Z10>TODAY())*('Input Data'!AA10>0)*(YEAR('Input Data'!Z10)>=2031),", "&'Input Data'!AB10&" ("&'Input Data'!C10&")","")&IF(('Input Data'!Z11>TODAY())*('Input Data'!AA11>0)*(YEAR('Input Data'!Z11)>=2031),", "&'Input Data'!AB11&" ("&'Input Data'!C11&")","")&IF(('Input Data'!Z12>TODAY())*('Input Data'!AA12>0)*(YEAR('Input Data'!Z12)>=2031),", "&'Input Data'!AB12&" ("&'Input Data'!C12&")","")&IF(('Input Data'!Z13>TODAY())*('Input Data'!AA13>0)*(YEAR('Input Data'!Z13)>=2031),", "&'Input Data'!AB13&" ("&'Input Data'!C13&")","")&IF(('Input Data'!Z14>TODAY())*('Input Data'!AA14>0)*(YEAR('Input Data'!Z14)>=2031),", "&'Input Data'!AB14&" ("&'Input Data'!C14&")","")&IF(('Input Data'!Z15>TODAY())*('Input Data'!AA15>0)*(YEAR('Input Data'!Z15)>=2031),", "&'Input Data'!AB15&" ("&'Input Data'!C15&")","")&IF(('Input Data'!Z16>TODAY())*('Input Data'!AA16>0)*(YEAR('Input Data'!Z16)>=2031),", "&'Input Data'!AB16&" ("&'Input Data'!C16&")","")&IF(('Input Data'!Z17>TODAY())*('Input Data'!AA17>0)*(YEAR('Input Data'!Z17)>=2031),", "&'Input Data'!AB17&" ("&'Input Data'!C17&")","")&IF(('Input Data'!Z18>TODAY())*('Input Data'!AA18>0)*(YEAR('Input Data'!Z18)>=2031),", "&'Input Data'!AB18&" ("&'Input Data'!C18&")","")&IF(('Input Data'!Z19>TODAY())*('Input Data'!AA19>0)*(YEAR('Input Data'!Z19)>=2031),", "&'Input Data'!AB19&" ("&'Input Data'!C19&")","")&IF(('Input Data'!Z20>TODAY())*('Input Data'!AA20>0)*(YEAR('Input Data'!Z20)>=2031),", "&'Input Data'!AB20&" ("&'Input Data'!C20&")","")&IF(('Input Data'!Z21>TODAY())*('Input Data'!AA21>0)*(YEAR('Input Data'!Z21)>=2031),", "&'Input Data'!AB21&" ("&'Input Data'!C21&")","")&IF(('Input Data'!Z22>TODAY())*('Input Data'!AA22>0)*(YEAR('Input Data'!Z22)>=2031),", "&'Input Data'!AB22&" ("&'Input Data'!C22&")","")&IF(('Input Data'!Z23>TODAY())*('Input Data'!AA23>0)*(YEAR('Input Data'!Z23)>=2031),", "&'Input Data'!AB23&" ("&'Input Data'!C23&")","")&IF(('Input Data'!Z24>TODAY())*('Input Data'!AA24>0)*(YEAR('Input Data'!Z24)>=2031),", "&'Input Data'!AB24&" ("&'Input Data'!C24&")","")&IF(('Input Data'!Z25>TODAY())*('Input Data'!AA25>0)*(YEAR('Input Data'!Z25)>=2031),", "&'Input Data'!AB25&" ("&'Input Data'!C25&")","")&IF(('Input Data'!Z26>TODAY())*('Input Data'!AA26>0)*(YEAR('Input Data'!Z26)>=2031),", "&'Input Data'!AB26&" ("&'Input Data'!C26&")","")&IF(('Input Data'!Z27>TODAY())*('Input Data'!AA27>0)*(YEAR('Input Data'!Z27)>=2031),", "&'Input Data'!AB27&" ("&'Input Data'!C27&")",""),3,999),"—") -> Recoverie (GROUND)
B25: TOTAL (Occupied) | C25: =SUMPRODUCT(('Input Data'!Z3:Z27>TODAY())*('Input Data'!AA3:AA27>0)*'Input Data'!AA3:AA27*'Input Data'!F3:F27) -> 4856837.4 | D25: =SUM(C19:C24) -> 4856837.4 | E25: =SUMPRODUCT(('Input Data'!Z3:Z27>TODAY())*('Input Data'!AA3:AA27>0)*'Input Data'!F3:F27) -> 4318.4 | F25: =SUM(E19:E24) -> 4318.4 | G25: =100% -> 1 | H25: 23 | I25: =SUM(G19:G24) -> 23
B27: PASSING RENT vs MARKET RENT ANALYSIS — 'Market Rents 26-27'
B28: Suite | C28: Tenant | E28: NLA | F28: Passing PSM | G28: Market PSM | H28: Var ($) | I28: Var (%) | J28: Position
B29: ='Input Data'!C3 -> LWR GROUND | C29: ='Input Data'!D3 -> OPULENT TWO ENTERPRISES | E29: ='Input Data'!F3 -> 151.2 | F29: ='Input Data'!J3 -> 1002.01 | G29: ='Input Data'!S3 -> 930 | H29: =F29-G29 -> 72.01 | I29: =IFERROR((F29-G29)/G29,0) -> 0.077430108 | J29: =IF(I29>0.05,"▲ Above Market",IF(I29<-0.05,"▼ Below Market","≈ At Market")) -> ▲ Above Market
B30: ='Input Data'!C4 -> GROUND | C30: ='Input Data'!D4 -> RCVRI MARTIN PLACE PTY LTD | E30: ='Input Data'!F4 -> 298.3 | F30: ='Input Data'!J4 -> 1150.52 | G30: ='Input Data'!S4 -> 1100 | H30: =F30-G30 -> 50.52 | I30: =IFERROR((F30-G30)/G30,0) -> 0.045927273 | J30: =IF(I30>0.05,"▲ Above Market",IF(I30<-0.05,"▼ Below Market","≈ At Market")) -> ≈ At Market
B31: ='Input Data'!C5 -> 101&2 | C31: ='Input Data'!D5 -> VACANT | E31: ='Input Data'!F5 -> 162.4 | F31: ='Input Data'!J5 -> 0 | G31: ='Input Data'!S5 -> 1115 | H31: =F31-G31 -> -1115 | I31: =IFERROR((F31-G31)/G31,0) -> -1 | J31: =IF(I31>0.05,"▲ Above Market",IF(I31<-0.05,"▼ Below Market","≈ At Market")) -> ▼ Below Market
B32: ='Input Data'!C6 -> 103 | C32: ='Input Data'!D6 -> PU PRIME TRADING PTY LTD | E32: ='Input Data'!F6 -> 96.3 | F32: ='Input Data'!J6 -> 1021.99 | G32: ='Input Data'!S6 -> 960 | H32: =F32-G32 -> 61.99 | I32: =IFERROR((F32-G32)/G32,0) -> 0.064572917 | J32: =IF(I32>0.05,"▲ Above Market",IF(I32<-0.05,"▼ Below Market","≈ At Market")) -> ▲ Above Market
B33: ='Input Data'!C7 -> 104 | C33: ='Input Data'!D7 -> TJC#1 PTY LTD | E33: ='Input Data'!F7 -> 98.1 | F33: ='Input Data'!J7 -> 973.44 | G33: ='Input Data'!S7 -> 960 | H33: =F33-G33 -> 13.44 | I33: =IFERROR((F33-G33)/G33,0) -> 0.014 | J33: =IF(I33>0.05,"▲ Above Market",IF(I33<-0.05,"▼ Below Market","≈ At Market")) -> ≈ At Market
B34: ='Input Data'!C8 -> WHOLE | C34: ='Input Data'!D8 -> PRINCETON FINANCIAL SERVICES | E34: ='Input Data'!F8 -> 393.2 | F34: ='Input Data'!J8 -> 1081.6 | G34: ='Input Data'!S8 -> 1095 | H34: =F34-G34 -> -13.4 | I34: =IFERROR((F34-G34)/G34,0) -> -0.012237443 | J34: =IF(I34>0.05,"▲ Above Market",IF(I34<-0.05,"▼ Below Market","≈ At Market")) -> ≈ At Market
B35: ='Input Data'!C9 -> 301&2 | C35: ='Input Data'!D9 -> IPM RESIDENTIAL PTY LTD | E35: ='Input Data'!F9 -> 164.2 | F35: ='Input Data'!J9 -> 1216.58 | G35: ='Input Data'!S9 -> 1135 | H35: =F35-G35 -> 81.58 | I35: =IFERROR((F35-G35)/G35,0) -> 0.071876652 | J35: =IF(I35>0.05,"▲ Above Market",IF(I35<-0.05,"▼ Below Market","≈ At Market")) -> ▲ Above Market
B36: ='Input Data'!C10 -> 303&4 | C36: ='Input Data'!D10 -> BROADRIDGE (AUSTRALIA) PTY LTD | E36: ='Input Data'!F10 -> 193.4 | F36: ='Input Data'!J10 -> 933.75 | G36: ='Input Data'!S10 -> 920 | H36: =F36-G36 -> 13.75 | I36: =IFERROR((F36-G36)/G36,0) -> 0.014945652 | J36: =IF(I36>0.05,"▲ Above Market",IF(I36<-0.05,"▼ Below Market","≈ At Market")) -> ≈ At Market
B37: ='Input Data'!C11 -> 401 | C37: ='Input Data'!D11 -> B-W INTERNATIONAL AUSTRALIA PTY LTD | E37: ='Input Data'!F11 -> 214.1 | F37: ='Input Data'!J11 -> 1135.61 | G37: ='Input Data'!S11 -> 1145 | H37: =F37-G37 -> -9.39 | I37: =IFERROR((F37-G37)/G37,0) -> -0.0082008734 | J37: =IF(I37>0.05,"▲ Above Market",IF(I37<-0.05,"▼ Below Market","≈ At Market")) -> ≈ At Market
B38: ='Input Data'!C12 -> 402 | C38: ='Input Data'!D12 -> MP TRAVEL PTY LTD | E38: ='Input Data'!F12 -> 145.6 | F38: ='Input Data'!J12 -> 1037.5 | G38: ='Input Data'!S12 -> 1000 | H38: =F38-G38 -> 37.5 | I38: =IFERROR((F38-G38)/G38,0) -> 0.0375 | J38: =IF(I38>0.05,"▲ Above Market",IF(I38<-0.05,"▼ Below Market","≈ At Market")) -> ≈ At Market
B39: ='Input Data'!C13 -> 501 | C39: ='Input Data'!D13 -> MONTGOMERY INVESTMENT | E39: ='Input Data'!F13 -> 212.3 | F39: ='Input Data'!J13 -> 1341.24 | G39: ='Input Data'!S13 -> 1155 | H39: =F39-G39 -> 186.24 | I39: =IFERROR((F39-G39)/G39,0) -> 0.16124675 | J39: =IF(I39>0.05,"▲ Above Market",IF(I39<-0.05,"▼ Below Market","≈ At Market")) -> ▲ Above Market
B40: ='Input Data'!C14 -> 502 | C40: ='Input Data'!D14 -> THREAT DEFENCE | E40: ='Input Data'!F14 -> 163.8 | F40: ='Input Data'!J14 -> 1054.88 | G40: ='Input Data'!S14 -> 1020 | H40: =F40-G40 -> 34.88 | I40: =IFERROR((F40-G40)/G40,0) -> 0.034196078 | J40: =IF(I40>0.05,"▲ Above Market",IF(I40<-0.05,"▼ Below Market","≈ At Market")) -> ≈ At Market
... B51: ='Input Data'!C25 -> 1102 | C51: ='Input Data'!D25 -> LEWIS WOOLCOTT | E51: ='Input Data'!F25 -> 133.1 | F51: ='Input Data'!J25 -> 1271.1 | G51: ='Input Data'!S25 -> 1250 | H51: =F51-G51 -> 21.1 | I51: =IFERROR((F51-G51)/G51,0) -> 0.01688 | J51: =IF(I51>0.05,"▲ Above Market",IF(I51<-0.05,"▼ Below Market","≈ At Market")) -> ≈ At Market
B52: Portfolio Avg Passing PSM | F52: =IFERROR(SUMPRODUCT(('Input Data'!K3:K27>0)*'Input Data'!J3:J27)/SUMPRODUCT(('Input Data'!K3:K27>0)*1),0) -> 1135.7461 | G52: =IFERROR(SUMPRODUCT(('Input Data'!K3:K27>0)*'Input Data'!S3:S27)/SUMPRODUCT(('Input Data'!K3:K27>0)*1),0) -> 1110.8696 | H52: =F52-G52 -> 24.876522 | I52: =IFERROR(H52/G52,0) -> 0.022393738
B65: UPCOMING CRITICAL DATES — Next 12 Months
B66: Suite | C66: Tenant | E66: Event Type | F66: Due Date | G66: Days Away | H66: Action Required
B67: 602 | Capital Credit Solutions | D67: Lease EXPIRED | E67: 46142 | F67: =IFERROR(INT(E67-TODAY()),"") -> -169 | G67: =IFERROR(INT(E67-TODAY()),"") -> -169 | H67: Suite vacant — begin make good & marketing
B68: 101&2 | Blitzem PTY LTD | D68: Lease Expiry | E68: 46203 | F68: =IFERROR(INT(E68-TODAY()),"") -> -108 | G68: =IFERROR(INT(E68-TODAY()),"") -> -108 | H68: Issue make good notice; confirm not renewing; market suite
B69: 104 | TJC#1 PTY LTD | D69: Lease Expiry | E69: 46234 | F69: =IFERROR(INT(E69-TODAY()),"") -> -77 | G69: =IFERROR(INT(E69-TODAY()),"") -> -77 | H69: Confirm renewal or vacating; issue make good notice
B70: 1102 | Pharmx Technologies | D70: Lease Expiry | E70: 46248 | F70: =IFERROR(INT(E70-TODAY()),"") -> -63 | G70: =IFERROR(INT(E70-TODAY()),"") -> -63 | H70: Sublease in place — confirm make good; market suite
B71: 1101 | Michael Flegg | D71: Lease Expiry | E71: 46356 | F71: =IFERROR(INT(E71-TODAY()),"") -> 45 | G71: =IFERROR(INT(E71-TODAY()),"") -> 45 | H71: David Wear to reach out; no works required
B72: 501 | Montgomery Investment | D72: Rent Review | E72: 46327 | F72: =IFERROR(INT(E72-TODAY()),"") -> 16 | G72: =IFERROR(INT(E72-TODAY()),"") -> 16 | H72: 3.75% fixed review — confirm calculation and issue
B73: 701 | Pinpoint Talent | D73: Rent Review | E73: 46241 | F73: =IFERROR(INT(E73-TODAY()),"") -> -70 | G73: =IFERROR(INT(E73-TODAY()),"") -> -70 | H73: 4% fixed review — confirm calculation and issue
B74: 702 | Satellite Office | D74: Rent Review | E74: 46174 | F74: =IFERROR(INT(E74-TODAY()),"") -> -137 | G74: =IFERROR(INT(E74-TODAY()),"") -> -137 | H74: 3.75% fixed review — imminent; action now
B75: 301&2 | IPM Residential | D75: Rent Review | E75: 46174 | F75: =IFERROR(INT(E75-TODAY()),"") -> -137 | G75: =IFERROR(INT(E75-TODAY()),"") -> -137 | H75: 3.75% fixed review — imminent; action now
B76: 901 | Aitken Investment | D76: Rent Review | E76: 46188 | F76: =IFERROR(INT(E76-TODAY()),"") -> -123 | G76: =IFERROR(INT(E76-TODAY()),"") -> -123 | H76: 4% fixed review — confirm calculation
B77: GF | Recoverie | D77: Rent Review | E77: 46408 | F77: =IFERROR(INT(E77-TODAY()),"") -> 97 | G77: =IFERROR(INT(E77-TODAY()),"") -> 97 | H77: 4% fixed review — mark in calendar
B78: 602 | Capital Credit Solutions | D78: MG Notice Due | E78: 46143 | F78: =IFERROR(INT(E78-TODAY()),"") -> -168 | G78: =IFERROR(INT(E78-TODAY()),"") -> -168 | H78: Issue make good notice immediately
B81: INCOME ANALYSIS — By Floor
B82: Floor | C82: Tenant(s) | E82: NLA (sqm) | F82: Passing PSM ($) | G82: Net Rent PA ($) | H82: % of Total Income | I82: Expiry Year
B83: L12 | C83: =IFERROR(MID(IF(('Input Data'!Z26>TODAY())*('Input Data'!AA26>0),", "&'Input Data'!AB26&" ("&'Input Data'!C26&")",""),3,999),"—") | E83: =SUMIF('Input Data'!B3:B27,"L12",'Input Data'!F3:F27) -> 223.7 | F83: =IFERROR(SUMIF('Input Data'!B3:B27,"L12",'Input Data'!N3:N27)/SUMIF('Input Data'!B3:B27,"L12",'Input Data'!F3:F27),0) -> 0 | G83: =SUMIF('Input Data'!B3:B27,"L12",'Input Data'!N3:N27) -> 0 | H83: =IFERROR(SUMIF('Input Data'!B3:B27,"L12",'Input Data'!N3:N27)/(SUMIF('Input Data'!N3:N27,">0",'Input Data'!N3:N27)),0) -> 0 | I83: =IFERROR(IF(SUMPRODUCT(('Input Data'!B3:B27="L12")*('Input Data'!Z3:Z27>TODAY())*('Input Data'!AA3:AA27>0))=0,"VACANT",TEXT(_xludf.minifs('Input Data'!Z3:Z27,'Input Data'!B3:B27,"L12",'Input Data'!Z3:Z27,">"&TODAY(),'Input Data'!AA3:AA27,">0"),"YYYY")),"—") -> VACANT
B84: L11 | C84: =IFERROR(MID(IF(('Input Data'!Z24>TODAY())*('Input Data'!AA24>0),", "&'Input Data'!AB24&" ("&'Input Data'!C24&")","")&IF(('Input Data'!Z25>TODAY())*('Input Data'!AA25>0),", "&'Input Data'!AB25&" ("&'Input Data'!C25&")","")&IF(('Input Data'!Z27>TODAY())*('Input Data'!AA27>0),", "&'Input Data'!AB27&" ("&'Input Data'!C27&")",""),3,999),"—") -> Michael Flegg (1101), Lewis Woolcott (1102), Interfi Systems (1103) | E84: =SUMIF('Input Data'!B3:B27,"L11",'Input Data'!F3:F27) -> 355.8 | F84: =IFERROR(SUMIF('Input Data'!B3:B27,"L11",'Input Data'!N3:N27)/SUMIF('Input Data'!B3:B27,"L11",'Input Data'!F3:F27),0) -> 992.63815 | G84: =SUMIF('Input Data'!B3:B27,"L11",'Input Data'!N3:N27) -> 353180.65 | H84: =IFERROR(SUMIF('Input Data'!B3:B27,"L11",'Input Data'!N3:N27)/(SUMIF('Input Data'!N3:N27,">0",'Input Data'!N3:N27)),0) -> 0.087558259 | I84: {=IFERROR(IF(SUMPRODUCT(('Input Data'!B3:B27="L11")*('Input Data'!Z3:Z27>TODAY())*('Input Data'!AA3:AA27>0))=0,"VACANT",TEXT(_xlfn.SINGLE(_xlfn.MINIFS('Input Data'!Z3:Z27,'Input Data'!B3:B27,"L11",'Input Data'!Z3:Z27,">"&TODAY(),'Input Data'!AA3:AA27,">0")),"YYYY")),"—")} -> 2026
B85: L10 | C85: =IFERROR(MID(IF(('Input Data'!Z23>TODAY())*('Input Data'!AA23>0),", "&'Input Data'!AB23&" ("&'Input Data'!C23&")",""),3,999),"—") -> Connectus Services (1001&2) | E85: =SUMIF('Input Data'!B3:B27,"L10",'Input Data'!F3:F27) -> 363.2 | F85: =IFERROR(SUMIF('Input Data'!B3:B27,"L10",'Input Data'!N3:N27)/SUMIF('Input Data'!B3:B27,"L10",'Input Data'!F3:F27),0) -> 874.31218 | G85: =SUMIF('Input Data'!B3:B27,"L10",'Input Data'!N3:N27) -> 317550.18 | H85: =IFERROR(SUMIF('Input Data'!B3:B27,"L10",'Input Data'!N3:N27)/(SUMIF('Input Data'!N3:N27,">0",'Input Data'!N3:N27)),0) -> 0.078724985 | I85: =IFERROR(IF(SUMPRODUCT(('Input Data'!B3:B27="L10")*('Input Data'!Z3:Z27>TODAY())*('Input Data'!AA3:AA27>0))=0,"VACANT",TEXT(_xlfn.MINIFS('Input Data'!Z3:Z27,'Input Data'!B3:B27,"L10",'Input Data'!Z3:Z27,">"&TODAY(),'Input Data'!AA3:AA27,">0"),"YYYY")),"—") -> 2029
B86: L09 | C86: =IFERROR(MID(IF(('Input Data'!Z21>TODAY())*('Input Data'!AA21>0),", "&'Input Data'!AB21&" ("&'Input Data'!C21&")","")&IF(('Input Data'!Z22>TODAY())*('Input Data'!AA22>0),", "&'Input Data'!AB22&" ("&'Input Data'!C22&")",""),3,999),"—") -> Aitken Investment Mgmt (901), Capital E Marketing (902&3) | E86: =SUMIF('Input Data'!B3:B27,"L09",'Input Data'!F3:F27) -> 355.8 | F86: =IFERROR(SUMIF('Input Data'!B3:B27,"L09",'Input Data'!N3:N27)/SUMIF('Input Data'!B3:B27,"L09",'Input Data'!F3:F27),0) -> 870.21229 | G86: =SUMIF('Input Data'!B3:B27,"L09",'Input Data'!N3:N27) -> 309621.53 | H86: =IFERROR(SUMIF('Input Data'!B3:B27,"L09",'Input Data'!N3:N27)/(SUMIF('Input Data'!N3:N27,">0",'Input Data'!N3:N27)),0) -> 0.076759365 | I86: =IFERROR(IF(SUMPRODUCT(('Input Data'!B3:B27="L09")*('Input Data'!Z3:Z27>TODAY())*('Input Data'!AA3:AA27>0))=0,"VACANT",TEXT(_xlfn.MINIFS('Input Data'!Z3:Z27,'Input Data'!B3:B27,"L09",'Input Data'!Z3:Z27,">"&TODAY(),'Input Data'!AA3:AA27,">0"),"YYYY")),"—") -> 2028
B87: L08 | C87: =IFERROR(MID(IF(('Input Data'!Z19>TODAY())*('Input Data'!AA19>0),", "&'Input Data'!AB19&" ("&'Input Data'!C19&")","")&IF(('Input Data'!Z20>TODAY())*('Input Data'!AA20>0),", "&'Input Data'!AB20&" ("&'Input Data'!C20&")",""),3,999),"—") -> Arkance Australia (801), Hilliard & Berry (802) | E87: =SUMIF('Input Data'!B3:B27,"L08",'Input Data'!F3:F27) -> 360.5 | F87: =IFERROR(SUMIF('Input Data'!B3:B27,"L08",'Input Data'!N3:N27)/SUMIF('Input Data'!B3:B27,"L08",'Input Data'!F3:F27),0) -> 996.58675 | G87: =SUMIF('Input Data'!B3:B27,"L08",'Input Data'!N3:N27) -> 359269.53 | H87: =IFERROR(SUMIF('Input Data'!B3:B27,"L08",'Input Data'!N3:N27)/(SUMIF('Input Data'!N3:N27,">0",'Input Data'!N3:N27)),0) -> 0.089067773 | I87: {=IFERROR(IF(SUMPRODUCT(('Input Data'!B3:B27="L08")*('Input Data'!Z3:Z27>TODAY())*('Input Data'!AA3:AA27>0))=0,"VACANT",TEXT(_xlfn.SINGLE(_xlfn.MINIFS('Input Data'!Z3:Z27,'Input Data'!B3:B27,"L08",'Input Data'!Z3:Z27,">"&TODAY(),'Input Data'!AA3:AA27,">0")),"YYYY")),"—")} -> 2028
B88: L07 | C88: =IFERROR(MID(IF(('Input Data'!Z17>TODAY())*('Input Data'!AA17>0),", "&'Input Data'!AB17&" ("&'Input Data'!C17&")","")&IF(('Input Data'!Z18>TODAY())*('Input Data'!AA18>0),", "&'Input Data'!AB18&" ("&'Input Data'!C18&")",""),3,999),"—") -> Pinpoint Talent (701), Satellite Office (702) | E88: =SUMIF('Input Data'!B3:B27,"L07",'Input Data'!F3:F27) -> 374.4 | F88: =IFERROR(SUMIF('Input Data'!B3:B27,"L07",'Input Data'!N3:N27)/SUMIF('Input Data'!B3:B27,"L07",'Input Data'!F3:F27),0) -> 831.05161 | G88: =SUMIF('Input Data'!B3:B27,"L07",'Input Data'!N3:N27) -> 311145.72 | H88: =IFERROR(SUMIF('Input Data'!B3:B27,"L07",'Input Data'!N3:N27)/(SUMIF('Input Data'!N3:N27,">0",'Input Data'!N3:N27)),0) -> 0.077137232 | I88: {=IFERROR(IF(SUMPRODUCT(('Input Data'!B3:B27="L07")*('Input Data'!Z3:Z27>TODAY())*('Input Data'!AA3:AA27>0))=0,"VACANT",TEXT(_xlfn.SINGLE(_xlfn.MINIFS('Input Data'!Z3:Z27,'Input Data'!B3:B27,"L07",'Input Data'!Z3:Z27,">"&TODAY(),'Input Data'!AA3:AA27,">0")),"YYYY")),"—")} -> 2027
B89: L06 | C89: =IFERROR(MID(IF(('Input Data'!Z15>TODAY())*('Input Data'!AA15>0),", "&'Input Data'!AB15&" ("&'Input Data'!C15&")","")&IF(('Input Data'!Z16>TODAY())*('Input Data'!AA16>0),", "&'Input Data'!AB16&" ("&'Input Data'!C16&")",""),3,999),"—") -> Fullcrm (601), INNOVIS (602) | E89: =SUMIF('Input Data'!B3:B27,"L06",'Input Data'!F3:F27) -> 378.2 | F89: =IFERROR(SUMIF('Input Data'!B3:B27,"L06",'Input Data'!N3:N27)/SUMIF('Input Data'!B3:B27,"L06",'Input Data'!F3:F27),0) -> 1023.6132 | G89: =SUMIF('Input Data'!B3:B27,"L06",'Input Data'!N3:N27) -> 387130.51 | H89: =IFERROR(SUMIF('Input Data'!B3:B27,"L06",'Input Data'!N3:N27)/(SUMIF('Input Data'!N3:N27,">0",'Input Data'!N3:N27)),0) -> 0.095974889 | I89: {=IFERROR(IF(SUMPRODUCT(('Input Data'!B3:B27="L06")*('Input Data'!Z3:Z27>TODAY())*('Input Data'!AA3:AA27>0))=0,"VACANT",TEXT(_xlfn.SINGLE(_xlfn.MINIFS('Input Data'!Z3:Z27,'Input Data'!B3:B27,"L06",'Input Data'!Z3:Z27,">"&TODAY(),'Input Data'!AA3:AA27,">0")),"YYYY")),"—")} -> 2027
B90: L05 | C90: =IFERROR(MID(IF(('Input Data'!Z13>TODAY())*('Input Data'!AA13>0),", "&'Input Data'!AB13&" ("&'Input Data'!C13&")","")&IF(('Input Data'!Z14>TODAY())*('Input Data'!AA14>0),", "&'Input Data'!AB14&" ("&'Input Data'!C14&")",""),3,999),"—") -> Montgomery Investment (501), Threat Defence (502) | E90: =SUMIF('Input Data'!B3:B27,"L05",'Input Data'!F3:F27) -> 376.1 | F90: =IFERROR(SUMIF('Input Data'!B3:B27,"L05",'Input Data'!N3:N27)/SUMIF('Input Data'!B3:B27,"L05",'Input Data'!F3:F27),0) -> 974.30629 | G90: =SUMIF('Input Data'!B3:B27,"L05",'Input Data'!N3:N27) -> 366436.6 | H90: =IFERROR(SUMIF('Input Data'!B3:B27,"L05",'Input Data'!N3:N27)/(SUMIF('Input Data'!N3:N27,">0",'Input Data'!N3:N27)),0) -> 0.090844587 | I90: {=IFERROR(IF(SUMPRODUCT(('Input Data'!B3:B27="L05")*('Input Data'!Z3:Z27>TODAY())*('Input Data'!AA3:AA27>0))=0,"VACANT",TEXT(_xlfn.SINGLE(_xlfn.MINIFS('Input Data'!Z3:Z27,'Input Data'!B3:B27,"L05",'Input Data'!Z3:Z27,">"&TODAY(),'Input Data'!AA3:AA27,">0")),"YYYY")),"—")} -> 2027
B91: L04 | C91: =IFERROR(MID(IF(('Input Data'!Z11>TODAY())*('Input Data'!AA11>0),", "&'Input Data'!AB11&" ("&'Input Data'!C11&")","")&IF(('Input Data'!Z12>TODAY())*('Input Data'!AA12>0),", "&'Input Data'!AB12&" ("&'Input Data'!C12&")",""),3,999),"—") -> B-W International (401), Gray Dawes Travel (402) | E91: =SUMIF('Input Data'!B3:B27,"L04",'Input Data'!F3:F27) -> 359.7 | F91: =IFERROR(SUMIF('Input Data'!B3:B27,"L04",'Input Data'!N3:N27)/SUMIF('Input Data'!B3:B27,"L04",'Input Data'!F3:F27),0) -> 896.06467 | G91: =SUMIF('Input Data'!B3:B27,"L04",'Input Data'!N3:N27) -> 322314.46 | H91: =IFERROR(SUMIF('Input Data'!B3:B27,"L04",'Input Data'!N3:N27)/(SUMIF('Input Data'!N3:N27,">0",'Input Data'!N3:N27)),0) -> 0.079906113 | I91: {=IFERROR(IF(SUMPRODUCT(('Input Data'!B3:B27="L04")*('Input Data'!Z3:Z27>TODAY())*('Input Data'!AA3:AA27>0))=0,"VACANT",TEXT(_xlfn.SINGLE(_xlfn.MINIFS('Input Data'!Z3:Z27,'Input Data'!B3:B27,"L04",'Input Data'!Z3:Z27,">"&TODAY(),'Input Data'!AA3:AA27,">0")),"YYYY")),"—")} -> 2029
B92: L03 | C92: =IFERROR(MID(IF(('Input Data'!Z9>TODAY())*('Input Data'!AA9>0),", "&'Input Data'!AB9&" ("&'Input Data'!C9&")","")&IF(('Input Data'!Z10>TODAY())*('Input Data'!AA10>0),", "&'Input Data'!AB10&" ("&'Input Data'!C10&")",""),3,999),"—") -> IPM Residential (301&2), Broadridge (303&4) | E92: =SUMIF('Input Data'!B3:B27,"L03",'Input Data'!F3:F27) -> 357.6 | F92: =IFERROR(SUMIF('Input Data'!B3:B27,"L03",'Input Data'!N3:N27)/SUMIF('Input Data'!B3:B27,"L03",'Input Data'!F3:F27),0) -> 961.60662 | G92: =SUMIF('Input Data'!B3:B27,"L03",'Input Data'!N3:N27) -> 343870.53 | H92: =IFERROR(SUMIF('Input Data'!B3:B27,"L03",'Input Data'!N3:N27)/(SUMIF('Input Data'!N3:N27,">0",'Input Data'!N3:N27)),0) -> 0.085250153 | I92: {=IFERROR(IF(SUMPRODUCT(('Input Data'!B3:B27="L03")*('Input Data'!Z3:Z27>TODAY())*('Input Data'!AA3:AA27>0))=0,"VACANT",TEXT(_xlfn.SINGLE(_xlfn.MINIFS('Input Data'!Z3:Z27,'Input Data'!B3:B27,"L03",'Input Data'!Z3:Z27,">"&TODAY(),'Input Data'!AA3:AA27,">0")),"YYYY")),"—")} -> 2027
B93: L02 | C93: =IFERROR(MID(IF(('Input Data'!Z8>TODAY())*('Input Data'!AA8>0),", "&'Input Data'!AB8&" ("&'Input Data'!C8&")",""),3,999),"—") -> Princeton Financial Services (WHOLE) | E93: =SUMIF('Input Data'!B3:B27,"L02",'Input Data'!F3:F27) -> 393.2 | F93: =IFERROR(SUMIF('Input Data'!B3:B27,"L02",'Input Data'!N3:N27)/SUMIF('Input Data'!B3:B27,"L02",'Input Data'!F3:F27),0) -> 1021.6259 | G93: =SUMIF('Input Data'!B3:B27,"L02",'Input Data'!N3:N27) -> 401703.32 | H93: =IFERROR(SUMIF('Input Data'!B3:B27,"L02",'Input Data'!N3:N27)/(SUMIF('Input Data'!N3:N27,">0",'Input Data'!N3:N27)),0) -> 0.099587685 | I93: {=IFERROR(IF(SUMPRODUCT(('Input Data'!B3:B27="L02")*('Input Data'!Z3:Z27>TODAY())*('Input Data'!AA3:AA27>0))=0,"VACANT",TEXT(_xlfn.SINGLE(_xlfn.MINIFS('Input Data'!Z3:Z27,'Input Data'!B3:B27,"L02",'Input Data'!Z3:Z27,">"&TODAY(),'Input Data'!AA3:AA27,">0")),"YYYY")),"—")} -> 2028
B94: L01 | C94: =IFERROR(MID(IF(('Input Data'!Z5>TODAY())*('Input Data'!AA5>0),", "&'Input Data'!AB5&" ("&'Input Data'!C5&")","")&IF(('Input Data'!Z6>TODAY())*('Input Data'!AA6>0),", "&'Input Data'!AB6&" ("&'Input Data'!C6&")","")&IF(('Input Data'!Z7>TODAY())*('Input Data'!AA7>0),", "&'Input Data'!AB7&" ("&'Input Data'!C7&")",""),3,999),"—") -> PU Prime Trading (103), TJC#1 (104) | E94: =SUMIF('Input Data'!B3:B27,"L01",'Input Data'!F3:F27) -> 356.8 | F94: =IFERROR(SUMIF('Input Data'!B3:B27,"L01",'Input Data'!N3:N27)/SUMIF('Input Data'!B3:B27,"L01",'Input Data'!F3:F27),0) -> 463.75196 | G94: =SUMIF('Input Data'!B3:B27,"L01",'Input Data'!N3:N27) -> 165466.7 | H94: =IFERROR(SUMIF('Input Data'!B3:B27,"L01",'Input Data'!N3:N27)/(SUMIF('Input Data'!N3:N27,">0",'Input Data'!N3:N27)),0) -> 0.041021433 | I94: {=IFERROR(IF(SUMPRODUCT(('Input Data'!B3:B27="L01")*('Input Data'!Z3:Z27>TODAY())*('Input Data'!AA3:AA27>0))=0,"VACANT",TEXT(_xlfn.SINGLE(_xlfn.MINIFS('Input Data'!Z3:Z27,'Input Data'!B3:B27,"L01",'Input Data'!Z3:Z27,">"&TODAY(),'Input Data'!AA3:AA27,">0")),"YYYY")),"—")} -> 2028
B95: GF | C95: =IFERROR(MID(IF(('Input Data'!Z4>TODAY())*('Input Data'!AA4>0),", "&'Input Data'!AB4&" ("&'Input Data'!C4&")",""),3,999),"—") -> Recoverie (GROUND) | E95: =SUMIF('Input Data'!B3:B27,"GF",'Input Data'!F3:F27) -> 298.3 | F95: =IFERROR(SUMIF('Input Data'!B3:B27,"GF",'Input Data'!N3:N27)/SUMIF('Input Data'!B3:B27,"GF",'Input Data'!F3:F27),0) -> 913.46227 | G95: =SUMIF('Input Data'!B3:B27,"GF",'Input Data'!N3:N27) -> 272485.8 | H95: =IFERROR(SUMIF('Input Data'!B3:B27,"GF",'Input Data'!N3:N27)/(SUMIF('Input Data'!N3:N27,">0",'Input Data'!N3:N27)),0) -> 0.067552913 | I95: {=IFERROR(IF(SUMPRODUCT(('Input Data'!B3:B27="GF")*('Input Data'!Z3:Z27>TODAY())*('Input Data'!AA3:AA27>0))=0,"VACANT",TEXT(_xlfn.SINGLE(_xlfn.MINIFS('Input Data'!Z3:Z27,'Input Data'!B3:B27,"GF",'Input Data'!Z3:Z27,">"&TODAY(),'Input Data'!AA3:AA27,">0")),"YYYY")),"—")} -> 2032
B96: LWR GND | C96: =IFERROR(MID(IF(('Input Data'!Z3>TODAY())*('Input Data'!AA3>0),", "&'Input Data'!AB3&" ("&'Input Data'!C3&")",""),3,999),"—") -> Opulent Two Enterprises (LWR GROUND) | E96: =SUMIF('Input Data'!B3:B27,"LWR GND",'Input Data'!F3:F27) -> 0 | F96: =IFERROR(SUMIF('Input Data'!B3:B27,"LWR GND",'Input Data'!N3:N27)/SUMIF('Input Data'!B3:B27,"LWR GND",'Input Data'!F3:F27),0) -> 0 | G96: =SUMIF('Input Data'!B3:B27,"LWR GND",'Input Data'!N3:N27) -> 0 | H96: =IFERROR(SUMIF('Input Data'!B3:B27,"LWR GND",'Input Data'!N3:N27)/(SUMIF('Input Data'!N3:N27,">0",'Input Data'!N3:N27)),0) -> 0 | I96: 2029
B97: TOTAL | E97: =SUM('Input Data'!F3:F27) -> 4704.5 | G97: =SUMPRODUCT(('Input Data'!K3:K27>0)*('Input Data'!Y3:Y27<>"EXPIRED")*'Input Data'!N3:N27) -> 4033664.6 | H97: 1
B100: ASSET VALUATION SUMMARY
E101: Latest Valuation (Val 1) | F101: Previous Valuation (Val 2) | H101: Prior Valuation (Val 3) | J101: Movement (Val 1 vs Val 2)
B102: Valuation Amount ($) | E102: =Valuations!C6 -> 76500000 | F102: =Valuations!D6 -> 85000000 | H102: =Valuations!E6 -> 79000000 | J102: =IFERROR(E102-F102,"") -> -8500000 | L102: =IFERROR((E102-F102)/F102,"") -> -0.1
B103: Date of Valuation | E103: =Valuations!C7 -> 45455 | F103: =Valuations!D7 -> 44327 | H103: =Valuations!E7 -> 43194 | J103: —
B104: Valuer / Firm | E104: =Valuations!C8 -> Knight Frank | F104: =Valuations!D8 -> Knight Frank | H104: =Valuations!E8 -> JLL | J104: —
B105: Capitalisation Rate | E105: =Valuations!C10 -> 0.0525 | F105: =Valuations!D10 -> 0.0475 | H105: =Valuations!E10 -> 0.0475 | J105: =IFERROR(E105-F105,"") -> 0.005
B106: Passing Yield | E106: =Valuations!C11 -> 0.0367 | F106: =Valuations!D11 -> 0.0373 | H106: =Valuations!E11 -> 0.0323 | J106: =IFERROR(E106-F106,"") -> -0.0006
B107: Land Value | E107: =Valuations!C12 -> 14900000 | F107: =Valuations!D12 -> 11000000 | H107: =Valuations!E12 -> 9480000 | J107: =IFERROR(E107-F107,"") -> 3900000
B108: Valuation Basis | E108: =Valuations!F9 -> First Mortgage Security Purposes | F108: =Valuations!D9 -> Market Value 'As Is' | H108: =Valuations!E9 -> Market Value 'As Is' | J108: —
B110: LAND TAX SUMMARY — NSW
E111: Assessment 1 (Latest) | F111: Assessment 2 | H111: Assessment 3 | J111: Land Value Movement (Assess 1 vs 2)
B112: Land Tax Year | E112: =Valuations!C20 -> FY26 | F112: =Valuations!D20 -> FY25 | H112: =Valuations!E20 -> FY24 | J112: —
B113: Assessed Land Value ($) | E113: =Valuations!C21 -> 16500000 | F113: =Valuations!D21 -> 16500000 | H113: =Valuations!E21 -> 14900000 | J113: =IFERROR(E113-G113,"") -> 16500000 | L113: =IFERROR((E113-F113)/F113,"") -> 0
B114: Land Tax Payable ($) | E114: =Valuations!C22 -> 293049.3 | F114: =Valuations!D22 -> 273049.3 | H114: =Valuations!E22 -> 236382.65 | J114: =IFERROR(E114-G114,"") -> 293049.3 | L114: =IFERROR((E114-F114)/F114,"") -> 0.073246846
B115: Assessment Date | E115: =Valuations!C23 -> 45839 | F115: =Valuations!D23 -> 45474 | H115: =Valuations!E23 -> 45108 | J115: —
B117: Mortgage details recorded in Valuations tab only (not displayed here for confidentiality). | Last updated: enter in Valuations tab

Sheet Valuations
A1: 17 CASTLEREAGH STREET — VALUATIONS, LAND TAX & MORTGAGE REGISTER
A2: Yellow cells = input. All Dashboard valuation figures pull from this tab automatically. Update each time a new valuation or assessment is received.
B4: PROPERTY VALUATIONS
C5: Valuation 1 (Most Recent) | D5: Valuation 2 | E5: Valuation 3 | F5: Notes
B6: Valuation Amount | C6: 76500000 | D6: 85000000 | E6: 79000000
B7: Date of Valuation | C7: 45455 | D7: 44327 | E7: 43194
B8: Valuer / Firm | C8: Knight Frank | D8: Knight Frank | E8: JLL
B9: Valuation Basis | C9: Market Value 'As Is' | D9: Market Value 'As Is' | E9: Market Value 'As Is' | F9: First Mortgage Security Purposes
B10: Capitalisation Rate (%) | C10: 0.0525 | D10: 0.0475 | E10: 0.0475
B11: Passing Yield (%) | C11: 0.0367 | D11: 0.0373 | E11: 0.0323
B12: Land Value ($) | C12: 14900000 | D12: 11000000 | E12: 9480000
B13: Improvement Value ($) | C13: 55600000 | D13: 38700000
B14: VALUATION MOVEMENT
B15: Val 1 vs Val 2 Movement ($) | C15: =IFERROR(C6-D6,"") -> -8500000 | E15: =IFERROR((C6-D6)/D6,"") -> -0.1 | F15: Positive = appreciation | Negative = decline
B16: Val 2 vs Val 3 Movement ($) | C16: =IFERROR(D6-E6,"") -> 6000000 | E16: =IFERROR((D6-E6)/E6,"") -> 0.075949367
B18: LAND TAX ASSESSMENTS — NSW
C19: Assessment 1 (Most Recent) | D19: Assessment 2 | E19: Assessment 3 | F19: Notes
B20: Land Tax Year | C20: FY26 | D20: FY25 | E20: FY24
B21: Assessed Land Value ($) | C21: 16500000 | D21: 16500000 | E21: 14900000
B22: Land Tax Payable ($) | C22: 293049.3 | D22: 273049.3 | E22: 236382.65
B23: Assessment Date | C23: 45839 | D23: 45474 | E23: 45108
B24: Threshold Applied ($)
B25: Tax Rate Applied (%)
B26: Payment Due Date
B27: Assessment Reference / Notice
B29: LAND VALUE MOVEMENT
B30: Assessment 1 vs 2 Land Value Change | C30: =IFERROR(C21-D21,"") -> 0 | E30: =IFERROR((C21-D21)/D21,"") -> 0
B31: Assessment 2 vs 3 Land Value Change | C31: =IFERROR(D21-E21,"") -> 1600000 | E31: =IFERROR((D21-E21)/E21,"") -> 0.10738255
B33: MORTGAGE / DEBT DETAILS — (Not displayed on Dashboard)
B34: Field | D34: Current | G34: Prior
B35: Lender / Bank | D35: ANZ
B36: Loan Amount ($) | D36: 27000000
B37: As at Date | D37: 45473
B38: Interest Rate (%) | G38: e.g. IO / P&I
B39: Loan Type
B40: Facility Expiry / Review Date
B41: LVR (%) | D41: =IFERROR(D36/Valuations!C6,"") -> 0.35294118
B42: Interest Cover Ratio (ICR)
B43: Loan Covenants / Notes
B45: LEGEND: Yellow cells = input (enter your data here) | Teal cells = calculated automatically | Valuation 1 = most recent

Sheet Expiry Profile
A1: 17 CASTLEREAGH STREET — LEASE EXPIRY PROFILE | As at 30/04/2026 | ALL DATA FORMULA-DRIVEN FROM INPUT DATA TAB
A2: Update Input Data tab only | This tab recalculates automatically | Sorted by Input Data row order | Use 'Expiry Year' column to filter | As at 30/04/2026
B3: Floor | C3: Suite # | D3: Tenant / Trading Name | E3: NLA (sqm) | F3: Lease Start | G3: Lease Expiry | H3: Term (Yrs) | I3: Remaining (Yrs) | J3: PSM ($) | K3: Net Rent PA ($) | L3: Expiry Year | M3: Car Parks | N3: Review Type | O3: Mkt PSM ($) | P3: Var to Mkt ($)
B4: ='Input Data'!B3 -> BSMT | C4: ='Input Data'!C3 -> LWR GROUND | D4: =IFERROR('Input Data'!D3&" ("&'Input Data'!E3&")",'Input Data'!D3) -> OPULENT TWO ENTERPRISES (OPULENT TWO ENTERPRISES) | E4: ='Input Data'!F3 -> 151.2 | F4: =IFERROR('Input Data'!G3,"") -> 42401 | G4: =IFERROR('Input Data'!H3,"") -> 47149 | H4: ='Input Data'!I3 -> 13 | I4: ='Input Data'!V3 -> 2.294319 | J4: ='Input Data'!J3 -> 1002.01 | K4: ='Input Data'!N3 -> 123489.07 | L4: =IF(Z3="","VACANT",IF(OR(Z3<TODAY(),YEAR(Z3)<=2026),"2026",IF(YEAR(Z3)=2027,"2027",IF(YEAR(Z3)=2028,"2028",IF(YEAR(Z3)=2029,"2029",IF(YEAR(Z3)=2030,"2030","2031+")))))) -> VACANT | M4: ='Input Data'!O3 -> 0 | N4: ='Input Data'!P3 -> FIXED 4% | O4: ='Input Data'!S3 -> 930 | P4: ='Input Data'!T3 -> 72.01
B5: ='Input Data'!B4 -> GF | C5: ='Input Data'!C4 -> GROUND | D5: =IFERROR('Input Data'!D4&" ("&'Input Data'!E4&")",'Input Data'!D4) -> RCVRI MARTIN PLACE PTY LTD (RECOVERIE) | E5: ='Input Data'!F4 -> 298.3 | F5: =IFERROR('Input Data'!G4,"") -> 45678 | G5: =IFERROR('Input Data'!H4,"") -> 48233 | H5: ='Input Data'!I4 -> 7 | I5: ='Input Data'!V4 -> 5.2621492 | J5: ='Input Data'!J4 -> 1150.52 | K5: ='Input Data'!N4 -> 272485.8 | L5: =IF(Z4="","VACANT",IF(OR(Z4<TODAY(),YEAR(Z4)<=2026),"2026",IF(YEAR(Z4)=2027,"2027",IF(YEAR(Z4)=2028,"2028",IF(YEAR(Z4)=2029,"2029",IF(YEAR(Z4)=2030,"2030","2031+")))))) -> VACANT | M5: ='Input Data'!O4 -> 0 | N5: ='Input Data'!P4 -> FIXED 4% | O5: ='Input Data'!S4 -> 1100 | P5: ='Input Data'!T4 -> 50.52
B6: ='Input Data'!B5 -> L01 | C6: ='Input Data'!C5 -> 101&2 | D6: =IFERROR('Input Data'!D5&" ("&'Input Data'!E5&")",'Input Data'!D5) -> VACANT () | E6: ='Input Data'!F5 -> 162.4 | F6: =IFERROR('Input Data'!G5,"") -> 0 | G6: =IFERROR('Input Data'!H5,"") | H6: ='Input Data'!I5 -> 3 | I6: ='Input Data'!V5 -> 0 | J6: ='Input Data'!J5 -> 0 | K6: ='Input Data'!N5 -> 0 | L6: =IF(Z5="","VACANT",IF(OR(Z5<TODAY(),YEAR(Z5)<=2026),"2026",IF(YEAR(Z5)=2027,"2027",IF(YEAR(Z5)=2028,"2028",IF(YEAR(Z5)=2029,"2029",IF(YEAR(Z5)=2030,"2030","2031+")))))) -> VACANT | M6: ='Input Data'!O5 -> 0 | N6: ='Input Data'!P5 -> 0 | O6: ='Input Data'!S5 -> 1115 | P6: ='Input Data'!T5
B7: ='Input Data'!B6 -> L01 | C7: ='Input Data'!C6 -> 103 | D7: =IFERROR('Input Data'!D6&" ("&'Input Data'!E6&")",'Input Data'!D6) -> PU PRIME TRADING PTY LTD (PU PRIME TRADING PTY LTD) | E7: ='Input Data'!F6 -> 96.3 | F7: =IFERROR('Input Data'!G6,"") -> 44378 | G7: =IFERROR('Input Data'!H6,"") -> 46918 | H7: ='Input Data'!I6 -> 7 | I7: ='Input Data'!V6 -> 1.6618754 | J7: ='Input Data'!J6 -> 1021.99 | K7: ='Input Data'!N6 -> 89396.037 | L7: =IF(Z6="","VACANT",IF(OR(Z6<TODAY(),YEAR(Z6)<=2026),"2026",IF(YEAR(Z6)=2027,"2027",IF(YEAR(Z6)=2028,"2028",IF(YEAR(Z6)=2029,"2029",IF(YEAR(Z6)=2030,"2030","2031+")))))) -> VACANT | M7: ='Input Data'!O6 -> 0 | N7: ='Input Data'!P6 -> FIXED 4% | O7: ='Input Data'!S6 -> 960 | P7: ='Input Data'!T6 -> 61.99
B8: ='Input Data'!B7 -> L01 | C8: ='Input Data'!C7 -> 104 | D8: =IFERROR('Input Data'!D7&" ("&'Input Data'!E7&")",'Input Data'!D7) -> TJC#1 PTY LTD (BALANCE INSOLVENCY) | E8: ='Input Data'!F7 -> 98.1 | F8: =IFERROR('Input Data'!G7,"") -> 45139 | G8: =IFERROR('Input Data'!H7,"") -> 47330 | H8: ='Input Data'!I7 -> 3 | I8: ='Input Data'!V7 -> 2.78987 | J8: ='Input Data'!J7 -> 973.44 | K8: ='Input Data'!N7 -> 76070.664 | L8: =IF(Z7="","VACANT",IF(OR(Z7<TODAY(),YEAR(Z7)<=2026),"2026",IF(YEAR(Z7)=2027,"2027",IF(YEAR(Z7)=2028,"2028",IF(YEAR(Z7)=2029,"2029",IF(YEAR(Z7)=2030,"2030","2031+")))))) -> VACANT | M8: ='Input Data'!O7 -> 0 | N8: ='Input Data'!P7 -> FIXED 4% | O8: ='Input Data'!S7 -> 960 | P8: ='Input Data'!T7 -> 13.44
B9: ='Input Data'!B8 -> L02 | C9: ='Input Data'!C8 -> WHOLE | D9: =IFERROR('Input Data'!D8&" ("&'Input Data'!E8&")",'Input Data'!D8) -> PRINCETON FINANCIAL SERVICES (PRINCETON FINANCIAL SERVICES) | E9: ='Input Data'!F8 -> 393.2 | F9: =IFERROR('Input Data'!G8,"") -> 45292 | G9: =IFERROR('Input Data'!H8,"") -> 47118 | H9: ='Input Data'!I8 -> 5 | I9: ='Input Data'!V8 -> 2.2094456 | J9: ='Input Data'!J8 -> 1081.6 | K9: ='Input Data'!N8 -> 401703.32 | L9: =IF(Z8="","VACANT",IF(OR(Z8<TODAY(),YEAR(Z8)<=2026),"2026",IF(YEAR(Z8)=2027,"2027",IF(YEAR(Z8)=2028,"2028",IF(YEAR(Z8)=2029,"2029",IF(YEAR(Z8)=2030,"2030","2031+")))))) -> VACANT | M9: ='Input Data'!O8 -> 0 | N9: ='Input Data'!P8 -> FIXED 4% | O9: ='Input Data'!S8 -> 1095 | P9: ='Input Data'!T8 -> -13.4
B10: ='Input Data'!B9 -> L03 | C10: ='Input Data'!C9 -> 301&2 | D10: =IFERROR('Input Data'!D9&" ("&'Input Data'!E9&")",'Input Data'!D9) -> IPM RESIDENTIAL PTY LTD (IPM RESIDENTIAL PTY LTD) | E10: ='Input Data'!F9 -> 164.2 | F10: =IFERROR('Input Data'!G9,"") -> 44713 | G10: =IFERROR('Input Data'!H9,"") -> 46538 | H10: ='Input Data'!I9 -> 5 | I10: ='Input Data'!V9 -> 0.62149213 | J10: ='Input Data'!J9 -> 1216.58 | K10: ='Input Data'!N9 -> 184245.48 | L10: =IF(Z9="","VACANT",IF(OR(Z9<TODAY(),YEAR(Z9)<=2026),"2026",IF(YEAR(Z9)=2027,"2027",IF(YEAR(Z9)=2028,"2028",IF(YEAR(Z9)=2029,"2029",IF(YEAR(Z9)=2030,"2030","2031+")))))) -> VACANT | M10: ='Input Data'!O9 -> 2 | N10: ='Input Data'!P9 -> LEASE RENEWAL | O10: ='Input Data'!S9 -> 1135 | P10: ='Input Data'!T9 -> 81.58
B11: ='Input Data'!B10 -> L03 | C11: ='Input Data'!C10 -> 303&4 | D11: =IFERROR('Input Data'!D10&" ("&'Input Data'!E10&")",'Input Data'!D10) -> BROADRIDGE (AUSTRALIA) PTY LTD (BROADRIDGE (AUSTRALI) PTY LTD) | E11: ='Input Data'!F10 -> 193.4 | F11: =IFERROR('Input Data'!G10,"") -> 45566 | G11: =IFERROR('Input Data'!H10,"") -> 47026 | H11: ='Input Data'!I10 -> 4 | I11: ='Input Data'!V10 -> 1.9575633 | J11: ='Input Data'!J10 -> 933.75 | K11: ='Input Data'!N10 -> 159625.05 | L11: =IF(Z10="","VACANT",IF(OR(Z10<TODAY(),YEAR(Z10)<=2026),"2026",IF(YEAR(Z10)=2027,"2027",IF(YEAR(Z10)=2028,"2028",IF(YEAR(Z10)=2029,"2029",IF(YEAR(Z10)=2030,"2030","2031+")))))) -> VACANT | M11: ='Input Data'!O10 -> 0 | N11: ='Input Data'!P10 -> FIXED 3.75% | O11: ='Input Data'!S10 -> 920 | P11: ='Input Data'!T10 -> 13.75
B12: ='Input Data'!B11 -> L04 | C12: ='Input Data'!C11 -> 401 | D12: =IFERROR('Input Data'!D11&" ("&'Input Data'!E11&")",'Input Data'!D11) -> B-W INTERNATIONAL AUSTRALIA PTY LTD (B-W INTERNATIONAL AUSTRALIA PTY LTD) | E12: ='Input Data'!F11 -> 214.1 | F12: =IFERROR('Input Data'!G11,"") -> 45352 | G12: =IFERROR('Input Data'!H11,"") -> 47177 | H12: ='Input Data'!I11 -> 5 | I12: ='Input Data'!V11 -> 2.3709788 | J12: ='Input Data'!J11 -> 1135.61 | K12: ='Input Data'!N11 -> 188930.34 | L12: =IF(Z11="","VACANT",IF(OR(Z11<TODAY(),YEAR(Z11)<=2026),"2026",IF(YEAR(Z11)=2027,"2027",IF(YEAR(Z11)=2028,"2028",IF(YEAR(Z11)=2029,"2029",IF(YEAR(Z11)=2030,"2030","2031+")))))) -> VACANT | M12: ='Input Data'!O11 -> 0 | N12: ='Input Data'!P11 -> FIXED 3.75% | O12: ='Input Data'!S11 -> 1145 | P12: ='Input Data'!T11 -> -9.39
B13: ='Input Data'!B12 -> L04 | C13: ='Input Data'!C12 -> 402 | D13: =IFERROR('Input Data'!D12&" ("&'Input Data'!E12&")",'Input Data'!D12) -> MP TRAVEL PTY LTD (GRAY DAWES TRAVEL) | E13: ='Input Data'!F12 -> 145.6 | F13: =IFERROR('Input Data'!G12,"") -> 45658 | G13: =IFERROR('Input Data'!H12,"") -> 47483 | H13: ='Input Data'!I12 -> 5 | I13: ='Input Data'!V12 -> 3.2087611 | J13: ='Input Data'!J12 -> 1037.5 | K13: ='Input Data'!N12 -> 133384.12 | L13: =IF(Z12="","VACANT",IF(OR(Z12<TODAY(),YEAR(Z12)<=2026),"2026",IF(YEAR(Z12)=2027,"2027",IF(YEAR(Z12)=2028,"2028",IF(YEAR(Z12)=2029,"2029",IF(YEAR(Z12)=2030,"2030","2031+")))))) -> VACANT | M13: ='Input Data'!O12 -> 0 | N13: ='Input Data'!P12 -> FIXED 3.75% | O13: ='Input Data'!S12 -> 1000 | P13: ='Input Data'!T12 -> 37.5
B14: ='Input Data'!B13 -> L05 | C14: ='Input Data'!C13 -> 501 | D14: =IFERROR('Input Data'!D13&" ("&'Input Data'!E13&")",'Input Data'!D13) -> MONTGOMERY INVESTMENT (MONTGOMERY INVESTMENT) | E14: ='Input Data'!F13 -> 212.3 | F14: =IFERROR('Input Data'!G13,"") -> 43770 | G14: =IFERROR('Input Data'!H13,"") -> 46691 | H14: ='Input Data'!I13 -> 8 | I14: ='Input Data'!V13 -> 1.0403833 | J14: ='Input Data'!J13 -> 1341.24 | K14: ='Input Data'!N13 -> 235383.49 | L14: =IF(Z13="","VACANT",IF(OR(Z13<TODAY(),YEAR(Z13)<=2026),"2026",IF(YEAR(Z13)=2027,"2027",IF(YEAR(Z13)=2028,"2028",IF(YEAR(Z13)=2029,"2029",IF(YEAR(Z13)=2030,"2030","2031+")))))) -> VACANT | M14: ='Input Data'!O13 -> 0 | N14: ='Input Data'!P13 -> FIXED 4% | O14: ='Input Data'!S13 -> 1155 | P14: ='Input Data'!T13 -> 186.24
B15: ='Input Data'!B14 -> L05 | C15: ='Input Data'!C14 -> 502 | D15: =IFERROR('Input Data'!D14&" ("&'Input Data'!E14&")",'Input Data'!D14) -> THREAT DEFENCE (THREAT DEFENCE PTY LTD) | E15: ='Input Data'!F14 -> 163.8 | F15: =IFERROR('Input Data'!G14,"") -> 45474 | G15: =IFERROR('Input Data'!H14,"") -> 46568 | H15: ='Input Data'!I14 -> 3 | I15: ='Input Data'!V14 -> 0.70362765 | J15: ='Input Data'!J14 -> 1054.88 | K15: ='Input Data'!N14 -> 131053.1 | L15: =IF(Z14="","VACANT",IF(OR(Z14<TODAY(),YEAR(Z14)<=2026),"2026",IF(YEAR(Z14)=2027,"2027",IF(YEAR(Z14)=2028,"2028",IF(YEAR(Z14)=2029,"2029",IF(YEAR(Z14)=2030,"2030","2031+")))))) -> VACANT | M15: ='Input Data'!O14 -> 0 | N15: ='Input Data'!P14 -> LEASE RENEWAL | O15: ='Input Data'!S14 -> 1020 | P15: ='Input Data'!T14 -> 34.88
... B28: ='Input Data'!B27 -> L11 | C28: ='Input Data'!C27 -> 1103 | D28: =IFERROR('Input Data'!D27&" ("&'Input Data'!E27&")",'Input Data'!D27) -> INTERFI SYSTEMS PTY LTD (INTERFI SYSTEMS) | E28: ='Input Data'!F27 -> 160.3 | F28: =IFERROR('Input Data'!G27,"") -> 46218 | G28: =IFERROR('Input Data'!H27,"") -> 47313 | H28: ='Input Data'!I27 -> 3 | I28: ='Input Data'!V27 -> 2.7433265 | J28: ='Input Data'!J27 -> 1150 | K28: ='Input Data'!N27 -> 129041.5 | L28: =IF(Z27="","VACANT",IF(OR(Z27<TODAY(),YEAR(Z27)<=2026),"2026",IF(YEAR(Z27)=2027,"2027",IF(YEAR(Z27)=2028,"2028",IF(YEAR(Z27)=2029,"2029",IF(YEAR(Z27)=2030,"2030","2031+")))))) -> VACANT | M28: ='Input Data'!O27 -> 0 | N28: ='Input Data'!P27 -> FIXED 4.0% | O28: ='Input Data'!S27 -> 1060 | P28: ='Input Data'!T27 -> 90
B29: BUILDING TOTALS | E29: =SUM('Input Data'!F3:F27) -> 4704.5 | I29: {=IFERROR(SUMPRODUCT(('Input Data'!H3:H25<>"")*'Input Data'!F3:F25*MAX(('Input Data'!H3:H25-TODAY())/365.25,0))/SUMPRODUCT(('Input Data'!H3:H25<>"")*'Input Data'!F3:F25),0)} -> 0 | K29: =SUM('Input Data'!N3:N27) -> 4033664.6

Sheet Leases
A1: 17 CASTLEREAGH STREET — LEASE REGISTER | As at 30/04/2026 | Source: Input Data tab
A2: Floor | B2: Suite # | C2: Tenant Name | D2: Trading Name | E2: NLA (sqm) | F2: Lease Start | G2: Lease Expiry | H2: Term (Yrs) | I2: Remaining (Yrs) | J2: Face Rent PSM ($) | K2: Market PSM ($) | L2: Net Rent PA ($) | M2: Incentive PA ($) | N2: Outgoings PA ($) | O2: Car Parks | P2: Review Type | Q2: Next Review | R2: Outgoings Type | S2: Var to Mkt PSM ($) | T2: Var to Mkt (%) | U2: WALE Contribution | V2: Notes
A3: ='Input Data'!B26 -> L12 | B3: ='Input Data'!C26 -> L12 | C3: ='Input Data'!D26 -> DAKOTA CORPORATION | D3: ='Input Data'!E26 -> OWNER OCCUPIED | E3: ='Input Data'!F26 -> 223.7 | F3: =IFERROR('Input Data'!G26,"") -> 42736 | G3: =IFERROR('Input Data'!H26,"") -> 47118 | H3: ='Input Data'!I26 -> 7 | I3: ='Input Data'!V26 -> 2.2094456 | J3: ='Input Data'!J26 -> 0 | K3: ='Input Data'!S26 -> 384 | L3: ='Input Data'!N26 -> 0 | M3: ='Input Data'!L26 -> 0 | N3: ='Input Data'!M26 -> 0 | O3: ='Input Data'!O26 -> 2 | P3: ='Input Data'!P26 -> MONTHLY TENANT | Q3: =IFERROR('Input Data'!Q26,"") -> 45291 | R3: ='Input Data'!R26 -> N/A | S3: ='Input Data'!T26 | T3: ='Input Data'!U26 | U3: ='Input Data'!W26 -> 494.25298 | V3: ='Input Data'!X26 -> 0
A4: ='Input Data'!B21 -> L09 | B4: ='Input Data'!C21 -> 901 | C4: ='Input Data'!D21 -> AITKEN INVESTMENT MANAGEMENT PTY LTD | D4: ='Input Data'!E21 -> AITKEN INVESTMENT MANAGEMENT | E4: ='Input Data'!F21 -> 52.8 | F4: =IFERROR('Input Data'!G21,"") -> 45823 | G4: =IFERROR('Input Data'!H21,"") -> 46918 | H4: ='Input Data'!I21 -> 3 | I4: ='Input Data'!V21 -> 1.6618754 | J4: ='Input Data'!J21 -> 1338.88 | K4: ='Input Data'!S21 -> 1350 | L4: ='Input Data'!N21 -> 54298.464 | M4: ='Input Data'!L21 -> -16394.4 | N4: ='Input Data'!M21 -> 3780 | O4: ='Input Data'!O21 -> 0 | P4: ='Input Data'!P21 -> FIXED 4% | Q4: =IFERROR('Input Data'!Q21,"") -> 46918 | R4: ='Input Data'!R21 -> Net | S4: ='Input Data'!T21 -> -11.12 | T4: ='Input Data'!U21 -> -0.008237037 | U4: ='Input Data'!W21 -> 87.747023 | V4: ='Input Data'!X21 -> 0
A5: ='Input Data'!B16 -> L06 | B5: ='Input Data'!C16 -> 602 | C5: ='Input Data'!D16 -> INNOVIS | D5: ='Input Data'!E16 -> INNOVIS | E5: ='Input Data'!F16 -> 152.1 | F5: =IFERROR('Input Data'!G16,"") -> 46327 | G5: =IFERROR('Input Data'!H16,"") -> 47421 | H5: ='Input Data'!I16 -> 3 | I5: ='Input Data'!V16 -> 3.0390144 | J5: ='Input Data'!J16 -> 1090 | K5: ='Input Data'!S16 -> 1030 | L5: ='Input Data'!N16 -> 135946.98 | M5: ='Input Data'!L16 -> -29842.02 | N5: ='Input Data'!M16 -> 0 | O5: ='Input Data'!O16 -> 0 | P5: ='Input Data'!P16 -> FIXED 3.75% | Q5: =IFERROR('Input Data'!Q16,"") -> 46692 | R5: ='Input Data'!R16 -> Net | S5: ='Input Data'!T16 -> 60 | T5: ='Input Data'!U16 -> 0.058252427 | U5: ='Input Data'!W16 -> 462.23409 | V5: ='Input Data'!X16 -> 0
A6: ='Input Data'!B5 -> L01 | B6: ='Input Data'!C5 -> 101&2 | C6: ='Input Data'!D5 -> VACANT | D6: ='Input Data'!E5 -> 0 | E6: ='Input Data'!F5 -> 162.4 | F6: =IFERROR('Input Data'!G5,"") -> 0 | G6: =IFERROR('Input Data'!H5,"") | H6: ='Input Data'!I5 -> 3 | I6: ='Input Data'!V5 -> 0 | J6: ='Input Data'!J5 -> 0 | K6: ='Input Data'!S5 -> 1115 | L6: ='Input Data'!N5 -> 0 | M6: ='Input Data'!L5 -> 0 | N6: ='Input Data'!M5 -> 0 | O6: ='Input Data'!O5 -> 0 | P6: ='Input Data'!P5 -> 0 | Q6: =IFERROR('Input Data'!Q5,"") -> 0 | R6: ='Input Data'!R5 -> 0 | S6: ='Input Data'!T5 | T6: ='Input Data'!U5 -> 0 | U6: ='Input Data'!W5 -> 0 | V6: ='Input Data'!X5 -> 0
A7: ='Input Data'!B7 -> L01 | B7: ='Input Data'!C7 -> 104 | C7: ='Input Data'!D7 -> TJC#1 PTY LTD | D7: ='Input Data'!E7 -> BALANCE INSOLVENCY | E7: ='Input Data'!F7 -> 98.1 | F7: =IFERROR('Input Data'!G7,"") -> 45139 | G7: =IFERROR('Input Data'!H7,"") -> 47330 | H7: ='Input Data'!I7 -> 3 | I7: ='Input Data'!V7 -> 2.78987 | J7: ='Input Data'!J7 -> 973.44 | K7: ='Input Data'!S7 -> 960 | L7: ='Input Data'!N7 -> 76070.664 | M7: ='Input Data'!L7 -> -19423.8 | N7: ='Input Data'!M7 -> 4500 | O7: ='Input Data'!O7 -> 0 | P7: ='Input Data'!P7 -> FIXED 4% | Q7: =IFERROR('Input Data'!Q7,"") -> 46600 | R7: ='Input Data'!R7 -> Net | S7: ='Input Data'!T7 -> 13.44 | T7: ='Input Data'!U7 -> 0.014 | U7: ='Input Data'!W7 -> 273.68624 | V7: ='Input Data'!X7 -> 0
A8: ='Input Data'!B25 -> L11 | B8: ='Input Data'!C25 -> 1102 | C8: ='Input Data'!D25 -> LEWIS WOOLCOTT | D8: ='Input Data'!E25 -> LEWIS WOOLCOTT | E8: ='Input Data'!F25 -> 133.1 | F8: =IFERROR('Input Data'!G25,"") -> 46249 | G8: =IFERROR('Input Data'!H25,"") -> 46979 | H8: ='Input Data'!I25 -> 2 | I8: ='Input Data'!V25 -> 1.8288843 | J8: ='Input Data'!J25 -> 1271.1 | K8: ='Input Data'!S25 -> 1250 | L8: ='Input Data'!N25 -> 138730.4 | M8: ='Input Data'!L25 -> -30453.01 | N8: ='Input Data'!M25 -> 5820 | O8: ='Input Data'!O25 -> 0 | P8: ='Input Data'!P25 -> FIXED 4.0% | Q8: =IFERROR('Input Data'!Q25,"") -> 46614 | R8: ='Input Data'!R25 -> Net | S8: ='Input Data'!T25 -> 21.1 | T8: ='Input Data'!U25 -> 0.01688 | U8: ='Input Data'!W25 -> 243.4245 | V8: ='Input Data'!X25 -> Lewis Woolcott new lease commences 15/8/26 (day after PharmX's lease ends), 2 yr term to 14/8/28, $1,271.10 psm. Outgoings carried forward at PharmX's existing rate pending TS confirmation.
A9: ='Input Data'!B24 -> L11 | B9: ='Input Data'!C24 -> 1101 | C9: ='Input Data'!D24 -> MICHAEL FLEGG PTY LTD | D9: ='Input Data'!E24 -> MICHAEL FLEGG PTY LTD | E9: ='Input Data'!F24 -> 62.4 | F9: =IFERROR('Input Data'!G24,"") -> 44531 | G9: =IFERROR('Input Data'!H24,"") -> 46356 | H9: ='Input Data'!I24 -> 5 | I9: ='Input Data'!V24 -> 0.12320329 | J9: ='Input Data'!J24 -> 1368.73 | K9: ='Input Data'!S24 -> 1405 | L9: ='Input Data'!N24 -> 85408.752 | M9: ='Input Data'!L24 -> 0 | N9: ='Input Data'!M24 -> 4200 | O9: ='Input Data'!O24 -> 0 | P9: ='Input Data'!P24 -> LEASE RENEWAL | Q9: =IFERROR('Input Data'!Q24,"") -> 46357 | R9: ='Input Data'!R24 -> Net | S9: ='Input Data'!T24 -> -36.27 | T9: ='Input Data'!U24 -> -0.025814947 | U9: ='Input Data'!W24 -> 7.687885 | V9: ='Input Data'!X24 -> 0
A10: ='Input Data'!B15 -> L06 | B10: ='Input Data'!C15 -> 601 | C10: ='Input Data'!D15 -> FULLCRM PTY LTD | D10: ='Input Data'!E15 -> FULLCRM PTY LTD | E10: ='Input Data'!F15 -> 226.1 | F10: =IFERROR('Input Data'!G15,"") -> 44531 | G10: =IFERROR('Input Data'!H15,"") -> 46418 | H10: ='Input Data'!I15 -> 5.2 | I10: ='Input Data'!V15 -> 0.29295003 | J10: ='Input Data'!J15 -> 1251.34 | K10: ='Input Data'!S15 -> 1165 | L10: ='Input Data'!N15 -> 251183.53 | M10: ='Input Data'!L15 -> -31744.44 | N10: ='Input Data'!M15 -> 13800 | O10: ='Input Data'!O15 -> 0 | P10: ='Input Data'!P15 -> LEASE RENEWAL | Q10: =IFERROR('Input Data'!Q15,"") -> 46419 | R10: ='Input Data'!R15 -> Net | S10: ='Input Data'!T15 -> 86.34 | T10: ='Input Data'!U15 -> 0.074111588 | U10: ='Input Data'!W15 -> 66.236003 | V10: ='Input Data'!X15 -> 0
A11: ='Input Data'!B9 -> L03 | B11: ='Input Data'!C9 -> 301&2 | C11: ='Input Data'!D9 -> IPM RESIDENTIAL PTY LTD | D11: ='Input Data'!E9 -> IPM RESIDENTIAL PTY LTD | E11: ='Input Data'!F9 -> 164.2 | F11: =IFERROR('Input Data'!G9,"") -> 44713 | G11: =IFERROR('Input Data'!H9,"") -> 46538 | H11: ='Input Data'!I9 -> 5 | I11: ='Input Data'!V9 -> 0.62149213 | J11: ='Input Data'!J9 -> 1216.58 | K11: ='Input Data'!S9 -> 1135 | L11: ='Input Data'!N9 -> 184245.48 | M11: ='Input Data'!L9 -> -15516.96 | N11: ='Input Data'!M9 -> 9900 | O11: ='Input Data'!O9 -> 2 | P11: ='Input Data'!P9 -> LEASE RENEWAL | Q11: =IFERROR('Input Data'!Q9,"") -> 46539 | R11: ='Input Data'!R9 -> Net | S11: ='Input Data'!T9 -> 81.58 | T11: ='Input Data'!U9 -> 0.071876652 | U11: ='Input Data'!W9 -> 102.04901 | V11: ='Input Data'!X9 -> 0
A12: ='Input Data'!B14 -> L05 | B12: ='Input Data'!C14 -> 502 | C12: ='Input Data'!D14 -> THREAT DEFENCE | D12: ='Input Data'!E14 -> THREAT DEFENCE PTY LTD | E12: ='Input Data'!F14 -> 163.8 | F12: =IFERROR('Input Data'!G14,"") -> 45474 | G12: =IFERROR('Input Data'!H14,"") -> 46568 | H12: ='Input Data'!I14 -> 3 | I12: ='Input Data'!V14 -> 0.70362765 | J12: ='Input Data'!J14 -> 1054.88 | K12: ='Input Data'!S14 -> 1020 | L12: ='Input Data'!N14 -> 131053.1 | M12: ='Input Data'!L14 -> -41736.24 | N12: ='Input Data'!M14 -> 7140 | O12: ='Input Data'!O14 -> 0 | P12: ='Input Data'!P14 -> LEASE RENEWAL | Q12: =IFERROR('Input Data'!Q14,"") -> 46569 | R12: ='Input Data'!R14 -> Net | S12: ='Input Data'!T14 -> 34.88 | T12: ='Input Data'!U14 -> 0.034196078 | U12: ='Input Data'!W14 -> 115.25421 | V12: ='Input Data'!X14 -> 0
A13: ='Input Data'!B17 -> L07 | B13: ='Input Data'!C17 -> 701 | C13: ='Input Data'!D17 -> PINPOINT TALENT PTY LTD | D13: ='Input Data'!E17 -> PINPOINT TALENT PTY LTD | E13: ='Input Data'!F17 -> 210.5 | F13: =IFERROR('Input Data'!G17,"") -> 45145 | G13: =IFERROR('Input Data'!H17,"") -> 46605 | H13: ='Input Data'!I17 -> 4 | I13: ='Input Data'!V17 -> 0.80492813 | J13: ='Input Data'!J17 -> 1173.54 | K13: ='Input Data'!S17 -> 1175 | L13: ='Input Data'!N17 -> 178512.45 | M13: ='Input Data'!L17 -> -68517.72 | N13: ='Input Data'!M17 -> 13800 | O13: ='Input Data'!O17 -> 0 | P13: ='Input Data'!P17 -> LEASE RENEWAL | Q13: =IFERROR('Input Data'!Q17,"") -> 46606 | R13: ='Input Data'!R17 -> Net | S13: ='Input Data'!T17 -> -1.46 | T13: ='Input Data'!U17 -> -0.0012425532 | U13: ='Input Data'!W17 -> 169.43737 | V13: ='Input Data'!X17 -> 0
A14: ='Input Data'!B13 -> L05 | B14: ='Input Data'!C13 -> 501 | C14: ='Input Data'!D13 -> MONTGOMERY INVESTMENT | D14: ='Input Data'!E13 -> MONTGOMERY INVESTMENT | E14: ='Input Data'!F13 -> 212.3 | F14: =IFERROR('Input Data'!G13,"") -> 43770 | G14: =IFERROR('Input Data'!H13,"") -> 46691 | H14: ='Input Data'!I13 -> 8 | I14: ='Input Data'!V13 -> 1.0403833 | J14: ='Input Data'!J13 -> 1341.24 | K14: ='Input Data'!S13 -> 1155 | L14: ='Input Data'!N13 -> 235383.49 | M14: ='Input Data'!L13 -> -49361.76 | N14: ='Input Data'!M13 -> 9900 | O14: ='Input Data'!O13 -> 0 | P14: ='Input Data'!P13 -> FIXED 4% | Q14: =IFERROR('Input Data'!Q13,"") -> 46327 | R14: ='Input Data'!R13 -> Net | S14: ='Input Data'!T13 -> 186.24 | T14: ='Input Data'!U13 -> 0.16124675 | U14: ='Input Data'!W13 -> 220.87337 | V14: ='Input Data'!X13 -> 0
A15: ='Input Data'!B18 -> L07 | B15: ='Input Data'!C18 -> 702 | C15: ='Input Data'!D18 -> SATELLITE OFFICE PTY LTD | D15: ='Input Data'!E18 -> SATELLITE OFFICE PTY LTD | E15: ='Input Data'!F18 -> 163.9 | F15: =IFERROR('Input Data'!G18,"") -> 45444 | G15: =IFERROR('Input Data'!H18,"") -> 46904 | H15: ='Input Data'!I18 -> 4 | I15: ='Input Data'!V18 -> 1.6235455 | J15: ='Input Data'!J18 -> 1054.88 | K15: ='Input Data'!S18 -> 1040 | L15: ='Input Data'!N18 -> 132633.27 | M15: ='Input Data'!L18 -> -40261.56 | N15: ='Input Data'!M18 -> 7020 | O15: ='Input Data'!O18 -> 0 | P15: ='Input Data'!P18 -> FIXED 3.75% | Q15: =IFERROR('Input Data'!Q18,"") -> 46539 | R15: ='Input Data'!R18 -> Net | S15: ='Input Data'!T18 -> 14.88 | T15: ='Input Data'!U18 -> 0.014307692 | U15: ='Input Data'!W18 -> 266.09911 | V15: ='Input Data'!X18 -> 0
A16: ='Input Data'!B6 -> L01 | B16: ='Input Data'!C6 -> 103 | C16: ='Input Data'!D6 -> PU PRIME TRADING PTY LTD | D16: ='Input Data'!E6 -> PU PRIME TRADING PTY LTD | E16: ='Input Data'!F6 -> 96.3 | F16: =IFERROR('Input Data'!G6,"") -> 44378 | G16: =IFERROR('Input Data'!H6,"") -> 46918 | H16: ='Input Data'!I6 -> 7 | I16: ='Input Data'!V6 -> 1.6618754 | J16: ='Input Data'!J6 -> 1021.99 | K16: ='Input Data'!S6 -> 960 | L16: ='Input Data'!N6 -> 89396.037 | M16: ='Input Data'!L6 -> -9021.6 | N16: ='Input Data'!M6 -> 6780 | O16: ='Input Data'!O6 -> 0 | P16: ='Input Data'!P6 -> FIXED 4% | Q16: =IFERROR('Input Data'!Q6,"") -> 46461 | R16: ='Input Data'!R6 -> Net | S16: ='Input Data'!T6 -> 61.99 | T16: ='Input Data'!U6 -> 0.064572917 | U16: ='Input Data'!W6 -> 160.0386 | V16: ='Input Data'!X6 -> 0
A17: ='Input Data'!B20 -> L08 | B17: ='Input Data'!C20 -> 802 | C17: ='Input Data'!D20 -> HILLIARD & BERRY | D17: ='Input Data'!E20 -> HILLIARD & BERRY | E17: ='Input Data'!F20 -> 138.5 | F17: =IFERROR('Input Data'!G20,"") -> 41654 | G17: =IFERROR('Input Data'!H20,"") -> 46965 | H17: ='Input Data'!I20 -> 14.6 | I17: ='Input Data'!V20 -> 1.7905544 | J17: ='Input Data'!J20 -> 843.65 | K17: ='Input Data'!S20 -> 1030 | L17: ='Input Data'!N20 -> 116845.52 | M17: ='Input Data'!L20 -> 0 | N17: ='Input Data'!M20 -> 12240 | O17: ='Input Data'!O20 -> 0 | P17: ='Input Data'!P20 -> FIXED 4% | Q17: =IFERROR('Input Data'!Q20,"") -> 46600 | R17: ='Input Data'!R20 -> Net | S17: ='Input Data'!T20 -> -186.35 | T17: ='Input Data'!U20 -> -0.18092233 | U17: ='Input Data'!W20 -> 247.99179 | V17: ='Input Data'!X20 -> 0
A18: ='Input Data'!B10 -> L03 | B18: ='Input Data'!C10 -> 303&4 | C18: ='Input Data'!D10 -> BROADRIDGE (AUSTRALIA) PTY LTD | D18: ='Input Data'!E10 -> BROADRIDGE (AUSTRALI) PTY LTD | E18: ='Input Data'!F10 -> 193.4 | F18: =IFERROR('Input Data'!G10,"") -> 45566 | G18: =IFERROR('Input Data'!H10,"") -> 47026 | H18: ='Input Data'!I10 -> 4 | I18: ='Input Data'!V10 -> 1.9575633 | J18: ='Input Data'!J10 -> 933.75 | K18: ='Input Data'!S10 -> 920 | L18: ='Input Data'!N10 -> 159625.05 | M18: ='Input Data'!L10 -> -20962.2 | N18: ='Input Data'!M10 -> 6300 | O18: ='Input Data'!O10 -> 0 | P18: ='Input Data'!P10 -> FIXED 3.75% | Q18: =IFERROR('Input Data'!Q10,"") -> 46296 | R18: ='Input Data'!R10 -> Net | S18: ='Input Data'!T10 -> 13.75 | T18: ='Input Data'!U10 -> 0.014945652 | U18: ='Input Data'!W10 -> 378.59274 | V18: ='Input Data'!X10 -> 0
A19: ='Input Data'!B8 -> L02 | B19: ='Input Data'!C8 -> WHOLE | C19: ='Input Data'!D8 -> PRINCETON FINANCIAL SERVICES | D19: ='Input Data'!E8 -> PRINCETON FINANCIAL SERVICES | E19: ='Input Data'!F8 -> 393.2 | F19: =IFERROR('Input Data'!G8,"") -> 45292 | G19: =IFERROR('Input Data'!H8,"") -> 47118 | H19: ='Input Data'!I8 -> 5 | I19: ='Input Data'!V8 -> 2.2094456 | J19: ='Input Data'!J8 -> 1081.6 | K19: ='Input Data'!S8 -> 1095 | L19: ='Input Data'!N8 -> 401703.32 | M19: ='Input Data'!L8 -> -23581.8 | N19: ='Input Data'!M8 -> 16200 | O19: ='Input Data'!O8 -> 0 | P19: ='Input Data'!P8 -> FIXED 4% | Q19: =IFERROR('Input Data'!Q8,"") -> 46388 | R19: ='Input Data'!R8 -> Net | S19: ='Input Data'!T8 -> -13.4 | T19: ='Input Data'!U8 -> -0.012237443 | U19: ='Input Data'!W8 -> 868.754 | V19: ='Input Data'!X8 -> 0
A20: ='Input Data'!B3 -> BSMT | B20: ='Input Data'!C3 -> LWR GROUND | C20: ='Input Data'!D3 -> OPULENT TWO ENTERPRISES | D20: ='Input Data'!E3 -> OPULENT TWO ENTERPRISES | E20: ='Input Data'!F3 -> 151.2 | F20: =IFERROR('Input Data'!G3,"") -> 42401 | G20: =IFERROR('Input Data'!H3,"") -> 47149 | H20: ='Input Data'!I3 -> 13 | I20: ='Input Data'!V3 -> 2.294319 | J20: ='Input Data'!J3 -> 1002.01 | K20: ='Input Data'!S3 -> 930 | L20: ='Input Data'!N3 -> 123489.07 | M20: ='Input Data'!L3 -> -28014.84 | N20: ='Input Data'!M3 -> 15000 | O20: ='Input Data'!O3 -> 0 | P20: ='Input Data'!P3 -> FIXED 4% | Q20: =IFERROR('Input Data'!Q3,"") -> 46419 | R20: ='Input Data'!R3 -> Net | S20: ='Input Data'!T3 -> 72.01 | T20: ='Input Data'!U3 -> 0.077430108 | U20: ='Input Data'!W3 -> 346.90103 | V20: ='Input Data'!X3 -> 0
A21: ='Input Data'!B11 -> L04 | B21: ='Input Data'!C11 -> 401 | C21: ='Input Data'!D11 -> B-W INTERNATIONAL AUSTRALIA PTY LTD | D21: ='Input Data'!E11 -> B-W INTERNATIONAL AUSTRALIA PTY LTD | E21: ='Input Data'!F11 -> 214.1 | F21: =IFERROR('Input Data'!G11,"") -> 45352 | G21: =IFERROR('Input Data'!H11,"") -> 47177 | H21: ='Input Data'!I11 -> 5 | I21: ='Input Data'!V11 -> 2.3709788 | J21: ='Input Data'!J11 -> 1135.61 | K21: ='Input Data'!S11 -> 1145 | L21: ='Input Data'!N11 -> 188930.34 | M21: ='Input Data'!L11 -> -54203.76 | N21: ='Input Data'!M11 -> 8700 | O21: ='Input Data'!O11 -> 0 | P21: ='Input Data'!P11 -> FIXED 3.75% | Q21: =IFERROR('Input Data'!Q11,"") -> 46447 | R21: ='Input Data'!R11 -> Net | S21: ='Input Data'!T11 -> -9.39 | T21: ='Input Data'!U11 -> -0.0082008734 | U21: ='Input Data'!W11 -> 507.62656 | V21: ='Input Data'!X11 -> 0
A22: ='Input Data'!B23 -> L10 | B22: ='Input Data'!C23 -> 1001&2 | C22: ='Input Data'!D23 -> CONNECTUS SERVICES PTY LTD | D22: ='Input Data'!E23 -> CONNECTUS | E22: ='Input Data'!F23 -> 363.2 | F22: =IFERROR('Input Data'!G23,"") -> 45261 | G22: =IFERROR('Input Data'!H23,"") -> 47452 | H22: ='Input Data'!I23 -> 6 | I22: ='Input Data'!V23 -> 3.1238877 | J22: ='Input Data'!J23 -> 1189.67 | K22: ='Input Data'!S23 -> 1200 | L22: ='Input Data'!N23 -> 317550.18 | M22: ='Input Data'!L23 -> -114537.96 | N22: ='Input Data'!M23 -> 15000 | O22: ='Input Data'!O23 -> 0 | P22: ='Input Data'!P23 -> FIXED | Q22: =IFERROR('Input Data'!Q23,"") -> 46357 | R22: ='Input Data'!R23 -> Net | S22: ='Input Data'!T23 -> -10.33 | T22: ='Input Data'!U23 -> -0.0086083333 | U22: ='Input Data'!W23 -> 1134.596 | V22: ='Input Data'!X23 -> 0
A23: ='Input Data'!B12 -> L04 | B23: ='Input Data'!C12 -> 402 | C23: ='Input Data'!D12 -> MP TRAVEL PTY LTD | D23: ='Input Data'!E12 -> GRAY DAWES TRAVEL | E23: ='Input Data'!F12 -> 145.6 | F23: =IFERROR('Input Data'!G12,"") -> 45658 | G23: =IFERROR('Input Data'!H12,"") -> 47483 | H23: ='Input Data'!I12 -> 5 | I23: ='Input Data'!V12 -> 3.2087611 | J23: ='Input Data'!J12 -> 1037.5 | K23: ='Input Data'!S12 -> 1000 | L23: ='Input Data'!N12 -> 133384.12 | M23: ='Input Data'!L12 -> -17675.88 | N23: ='Input Data'!M12 -> 6000 | O23: ='Input Data'!O12 -> 0 | P23: ='Input Data'!P12 -> FIXED 3.75% | Q23: =IFERROR('Input Data'!Q12,"") -> 46388 | R23: ='Input Data'!R12 -> Net | S23: ='Input Data'!T12 -> 37.5 | T23: ='Input Data'!U12 -> 0.0375 | U23: ='Input Data'!W12 -> 467.19562 | V23: ='Input Data'!X12 -> 0
A24: ='Input Data'!B22 -> L09 | B24: ='Input Data'!C22 -> 902&3 | C24: ='Input Data'!D22 -> CAPITAL E MARKETING AND EVENTS PTY LTD | D24: ='Input Data'!E22 -> CAPITAL E MARKETING AND EVENTS | E24: ='Input Data'!F22 -> 303 | F24: =IFERROR('Input Data'!G22,"") -> 44562 | G24: =IFERROR('Input Data'!H22,"") -> 47573 | H24: ='Input Data'!I22 -> 8.2 | I24: ='Input Data'!V22 -> 3.4551677 | J24: ='Input Data'!J22 -> 1141.25 | K24: ='Input Data'!S22 -> 1125 | L24: ='Input Data'!N22 -> 255323.07 | M24: ='Input Data'!L22 -> -90475.68 | N24: ='Input Data'!M22 -> 9300 | O24: ='Input Data'!O22 -> 0 | P24: ='Input Data'!P22 -> FIXED 3.75% | Q24: =IFERROR('Input Data'!Q22,"") -> 46478 | R24: ='Input Data'!R22 -> Net | S24: ='Input Data'!T22 -> 16.25 | T24: ='Input Data'!U22 -> 0.014444444 | U24: ='Input Data'!W22 -> 1046.9158 | V24: ='Input Data'!X22 -> 0
A25: ='Input Data'!B19 -> L08 | B25: ='Input Data'!C19 -> 801 | C25: ='Input Data'!D19 -> ARKANCE AUSTRALIA PTY LTD | D25: ='Input Data'!E19 -> ARKANCE AUSTRALIA PTY LTD | E25: ='Input Data'!F19 -> 222 | F25: =IFERROR('Input Data'!G19,"") -> 45931 | G25: =IFERROR('Input Data'!H19,"") -> 47756 | H25: ='Input Data'!I19 -> 5 | I25: ='Input Data'!V19 -> 3.9561944 | J25: ='Input Data'!J19 -> 1300 | K25: ='Input Data'!S19 -> 1300 | L25: ='Input Data'!N19 -> 242424 | M25: ='Input Data'!L19 -> -46176 | N25: ='Input Data'!M19 -> 1500 | O25: ='Input Data'!O19 -> 0 | P25: ='Input Data'!P19 -> FIXED 3.75% | Q25: =IFERROR('Input Data'!Q19,"") -> 46296 | R25: ='Input Data'!R19 -> Net | S25: ='Input Data'!T19 -> 0 | T25: ='Input Data'!U19 -> 0 | U25: ='Input Data'!W19 -> 878.27515 | V25: ='Input Data'!X19 -> 0
A26: ='Input Data'!B4 -> GF | B26: ='Input Data'!C4 -> GROUND | C26: ='Input Data'!D4 -> RCVRI MARTIN PLACE PTY LTD | D26: ='Input Data'!E4 -> RECOVERIE | E26: ='Input Data'!F4 -> 298.3 | F26: =IFERROR('Input Data'!G4,"") -> 45678 | G26: =IFERROR('Input Data'!H4,"") -> 48233 | H26: ='Input Data'!I4 -> 7 | I26: ='Input Data'!V4 -> 5.2621492 | J26: ='Input Data'!J4 -> 1150.52 | K26: ='Input Data'!S4 -> 1100 | L26: ='Input Data'!N4 -> 272485.8 | M26: ='Input Data'!L4 -> -70714.32 | N26: ='Input Data'!M4 -> 10408.32 | O26: ='Input Data'!O4 -> 0 | P26: ='Input Data'!P4 -> FIXED 4% | Q26: =IFERROR('Input Data'!Q4,"") -> 46408 | R26: ='Input Data'!R4 -> Gross | S26: ='Input Data'!T4 -> 50.52 | T26: ='Input Data'!U4 -> 0.045927273 | U26: ='Input Data'!W4 -> 1569.6991 | V26: ='Input Data'!X4 -> 0
A27: ='Input Data'!B27 -> L11 | B27: ='Input Data'!C27 -> 1103 | C27: ='Input Data'!D27 -> INTERFI SYSTEMS PTY LTD | D27: ='Input Data'!E27 -> INTERFI SYSTEMS | E27: ='Input Data'!F27 -> 160.3 | F27: =IFERROR('Input Data'!G27,"") -> 46218 | G27: =IFERROR('Input Data'!H27,"") -> 47313 | H27: ='Input Data'!I27 -> 3 | I27: ='Input Data'!V27 -> 2.7433265 | J27: ='Input Data'!J27 -> 1150 | K27: ='Input Data'!S27 -> 1060 | L27: ='Input Data'!N27 -> 129041.5 | M27: ='Input Data'!L27 -> -55303.5 | N27: ='Input Data'!M27 -> 0 | O27: ='Input Data'!O27 -> 0 | P27: ='Input Data'!P27 -> FIXED 4.0% | Q27: =IFERROR('Input Data'!Q27,"") -> 46583 | R27: ='Input Data'!R27 -> Net | S27: ='Input Data'!T27 -> 90 | T27: ='Input Data'!U27 -> 0.08490566 | U27: ='Input Data'!W27 -> 439.75524 | V27: ='Input Data'!X27 -> Interfi Systems (correct spelling per Jul26 TS, previously recorded as "Inferni Systems") — 3 yr term from 15/7/26 to 14/7/29, $1,150 psm. Jul26 TS confirms no Outgoings Cont or car parks for this suite (cleaning charged separately, not tracked in Outgoings PA column).

Sheet Leasing Activity
A1: 17 CASTLEREAGH STREET — LEASING ACTIVITY LOG | Past 12 Months
A2: Date | B2: Tenant Name | C2: Type | D2: Suite | E2: NLA (sqm) | F2: Rent PSM ($) | G2: Review % | H2: Commencement | I2: Expiry | J2: Term | K2: Incentive % | L2: Fitout ($) | M2: Abatement ($) | N2: TR Fee ($) | O2: Notes
A3: 45931 | B3: Broadridge (Australia) Pty Ltd | C3: New Lease | D3: 3.02 | E3: 193.4 | F3: 900 | G3: 0.0375 | H3: 45931 | I3: 46660 | J3: 4 Years | K3: 0.31 | L3: 110228 | M3: 83849 | N3: 21758
A4: 45839 | B4: MP Travel Pty Ltd / Gray Dawes Travel | C4: New Lease | D4: 4.02 | E4: 145.6 | F4: 1000 | G4: 0.0375 | H4: 45658 | I4: 47483 | J4: 5 Years | K4: 0.32 | L4: 144581 | M4: 88357 | N4: 0
A5: 45678 | B5: RCVRI Martin Place Pty Ltd (Recoverie) | C5: New Lease | D5: GF | E5: 298.3 | F5: 1106.27 | G5: 0.04 | H5: 45678 | I5: 48233 | J5: 7 Years | K5: 0.25 | L5: 82500 | M5: 495000 | N5: 0
A6: 45292 | B6: Capital E Marketing & Events | C6: Renewal | D6: 9.02 | E6: 303 | F6: 1100 | G6: 0.0375 | H6: 44562 | I6: 47573 | J6: 5 Years | K6: 0.34 | L6: 0 | M6: 533280 | N6: 33330
A7: 46189 | B7: TJC | C7: Renewal | D7: 1.04 | E7: 162.4 | F7: 1012.37 | G7: 0.04 | H7: 42795 | I7: 46203 | J7: 3 Years | K7: 0.22 | L7: 0 | M7: 44690 | N7: 0
A8: 46058 | B8: PU Prime Trading Pty Ltd | C8: Renewal | D8: 1.03 | E8: 96.3 | F8: 1022 | G8: 0.04 | H8: 44378 | I8: 46918 | J8: 2 Years | K8: 0.085 | L8: 0 | M8: 18043.21 | N8: 0
A9: 46176 | B9: Lewis Woolcott | C9: New Lease | D9: 11.02 | E9: 133.1 | F9: 1271.1 | G9: 0.04 | H9: 46249 | I9: 46979 | J9: 2 Years | K9: 0.18 | L9: 0 | M9: 60906.02 | N9: 0
A10: 46192 | B10: Inferni Systems | C10: New Lease | D10: 11.03 | E10: 160.3 | F10: 1150 | G10: 0.04 | H10: 46218 | I10: 47313 | J10: 3 Years | K10: 0.3 | L10: 0 | M10: =1035*E10 -> 165910.5 | N10: 0
A13: LEASING ACTIVITY SUMMARY (LIVE)
A14: =CONCATENATE("WALE by NLA (Current — ",TEXT(TODAY(),"mmm yyyy"),")") -> WALE by NLA (Current — Oct 2026) | C14: =Dashboard!D14 -> 2.3298144
A15: =CONCATENATE("Occupancy (Current — ",TEXT(TODAY(),"mmm yyyy"),")") -> Occupancy (Current — Oct 2026) | C15: =Dashboard!H5 -> 0.96547986
A16: WALE by NLA (May 2025) | C16: 3.11 years
A17: Occupancy (May 2025) | C17: 95.3%
A18: WALE by NLA (May 2024) | C18: 3.28 years
A19: Occupancy (May 2024) | C19: 81.7%
A21: LEASING ACTIVITY — LAST 12 MONTHS (LIVE FROM LOG ABOVE)
A22: Total Deals | C22: =COUNT(A3:A10) -> 8
A23: New Leases | C23: =COUNTIF(C3:C10,"New Lease") -> 5
A24: Renewals | C24: =COUNTIF(C3:C10,"Renewal") -> 3
A25: Total NLA Transacted (sqm) | C25: =SUM(E3:E10) -> 1492.4
A26: Avg Incentive % | C26: =AVERAGE(K3:K10) -> 0.250625
A27: Total Fitout Contribution ($) | C27: =SUM(L3:L10) -> 337309
A28: Total Rent Abatement ($) | C28: =SUM(M3:M10) -> 1490035.7
A29: Total Leasing Fees ($) | C29: =SUM(N3:N10) -> 55088
A30: Total Leasing Cost ($) | C30: =SUM(L3:L10)+SUM(M3:M10)+SUM(N3:N10) -> 1882432.7

Sheet Market Rents 26-27
A1: 17 CASTLEREAGH STREET — MARKET RENTS 2026-27 | Face Rent PSM & Incentive Benchmarks
A2: Source: Market assessment 2025/2026 | Update annually or as market conditions change
A3: Suite | B3: Size (sqm) | C3: Current Tenant | D3: Passing PSM ($) | E3: Market Rent PSM ($) | F3: Var ($) | G3: Var (%) | H3: New Tenant Incentive 3yr | I3: 4yr | J3: 5yr | K3: Renewal Incentive 3yr | L3: 5yr
A4: LWR GROUND | B4: =IFERROR(INDEX('Input Data'!F:F,MATCH(A4,'Input Data'!$C:$C,0)),"") -> 151.2 | C4: =IFERROR(INDEX('Input Data'!D:D,MATCH(A4,'Input Data'!$C:$C,0)),"") -> OPULENT TWO ENTERPRISES | D4: =IFERROR(INDEX('Input Data'!J:J,MATCH(A4,'Input Data'!$C:$C,0)),0) -> 1002.01 | E4: 930 | F4: =IFERROR(D4-E4,"") -> 72.01 | G4: =IFERROR((D4-E4)/E4,"") -> 0.077430108 | H4: 0.23 | I4: 0.24 | J4: 0.25 | K4: 0.22 | L4: 0.25
A5: GROUND | B5: =IFERROR(INDEX('Input Data'!F:F,MATCH(A5,'Input Data'!$C:$C,0)),"") -> 298.3 | C5: =IFERROR(INDEX('Input Data'!D:D,MATCH(A5,'Input Data'!$C:$C,0)),"") -> RCVRI MARTIN PLACE PTY LTD | D5: =IFERROR(INDEX('Input Data'!J:J,MATCH(A5,'Input Data'!$C:$C,0)),0) -> 1150.52 | E5: 1100 | F5: =IFERROR(D5-E5,"") -> 50.52 | G5: =IFERROR((D5-E5)/E5,"") -> 0.045927273 | H5: 0.28 | I5: 0.3 | J5: 0.31 | K5: 0.26 | L5: 0.29
A6: 101&2 | B6: =IFERROR(INDEX('Input Data'!F:F,MATCH(A6,'Input Data'!$C:$C,0)),"") -> 162.4 | C6: =IFERROR(INDEX('Input Data'!D:D,MATCH(A6,'Input Data'!$C:$C,0)),"") -> VACANT | D6: =IFERROR(INDEX('Input Data'!J:J,MATCH(A6,'Input Data'!$C:$C,0)),0) -> 0 | E6: 1115 | F6: =IFERROR(D6-E6,"") -> -1115 | G6: =IFERROR((D6-E6)/E6,"") -> -1 | H6: 0.26 | I6: 0.27 | J6: 0.29 | K6: 0.24 | L6: 0.27
A7: 103 | B7: =IFERROR(INDEX('Input Data'!F:F,MATCH(A7,'Input Data'!$C:$C,0)),"") -> 96.3 | C7: =IFERROR(INDEX('Input Data'!D:D,MATCH(A7,'Input Data'!$C:$C,0)),"") -> PU PRIME TRADING PTY LTD | D7: =IFERROR(INDEX('Input Data'!J:J,MATCH(A7,'Input Data'!$C:$C,0)),0) -> 1021.99 | E7: 960 | F7: =IFERROR(D7-E7,"") -> 61.99 | G7: =IFERROR((D7-E7)/E7,"") -> 0.064572917 | H7: 0.23 | I7: 0.24 | J7: 0.25 | K7: 0.22 | L7: 0.24
A8: 104 | B8: =IFERROR(INDEX('Input Data'!F:F,MATCH(A8,'Input Data'!$C:$C,0)),"") -> 98.1 | C8: =IFERROR(INDEX('Input Data'!D:D,MATCH(A8,'Input Data'!$C:$C,0)),"") -> TJC#1 PTY LTD | D8: =IFERROR(INDEX('Input Data'!J:J,MATCH(A8,'Input Data'!$C:$C,0)),0) -> 973.44 | E8: 960 | F8: =IFERROR(D8-E8,"") -> 13.44 | G8: =IFERROR((D8-E8)/E8,"") -> 0.014 | H8: 0.23 | I8: 0.24 | J8: 0.25 | K8: 0.22 | L8: 0.24
A9: WHOLE | B9: =IFERROR(INDEX('Input Data'!F:F,MATCH(A9,'Input Data'!$C:$C,0)),"") -> 393.2 | C9: =IFERROR(INDEX('Input Data'!D:D,MATCH(A9,'Input Data'!$C:$C,0)),"") -> PRINCETON FINANCIAL SERVICES | D9: =IFERROR(INDEX('Input Data'!J:J,MATCH(A9,'Input Data'!$C:$C,0)),0) -> 1081.6 | E9: 1095 | F9: =IFERROR(D9-E9,"") -> -13.4 | G9: =IFERROR((D9-E9)/E9,"") -> -0.012237443 | H9: 0.3 | I9: 0.33 | J9: 0.35 | K9: 0.3 | L9: 0.35
A10: 301&2 | B10: =IFERROR(INDEX('Input Data'!F:F,MATCH(A10,'Input Data'!$C:$C,0)),"") -> 164.2 | C10: =IFERROR(INDEX('Input Data'!D:D,MATCH(A10,'Input Data'!$C:$C,0)),"") -> IPM RESIDENTIAL PTY LTD | D10: =IFERROR(INDEX('Input Data'!J:J,MATCH(A10,'Input Data'!$C:$C,0)),0) -> 1216.58 | E10: 1135 | F10: =IFERROR(D10-E10,"") -> 81.58 | G10: =IFERROR((D10-E10)/E10,"") -> 0.071876652 | H10: 0.26 | I10: 0.27 | J10: 0.29 | K10: 0.24 | L10: 0.27
A11: 303&4 | B11: =IFERROR(INDEX('Input Data'!F:F,MATCH(A11,'Input Data'!$C:$C,0)),"") -> 193.4 | C11: =IFERROR(INDEX('Input Data'!D:D,MATCH(A11,'Input Data'!$C:$C,0)),"") -> BROADRIDGE (AUSTRALIA) PTY LTD | D11: =IFERROR(INDEX('Input Data'!J:J,MATCH(A11,'Input Data'!$C:$C,0)),0) -> 933.75 | E11: 920 | F11: =IFERROR(D11-E11,"") -> 13.75 | G11: =IFERROR((D11-E11)/E11,"") -> 0.014945652 | H11: 0.29 | I11: 0.31 | J11: 0.34 | K11: 0.28 | L11: 0.33
A12: 401 | B12: =IFERROR(INDEX('Input Data'!F:F,MATCH(A12,'Input Data'!$C:$C,0)),"") -> 214.1 | C12: =IFERROR(INDEX('Input Data'!D:D,MATCH(A12,'Input Data'!$C:$C,0)),"") -> B-W INTERNATIONAL AUSTRALIA PTY LTD | D12: =IFERROR(INDEX('Input Data'!J:J,MATCH(A12,'Input Data'!$C:$C,0)),0) -> 1135.61 | E12: 1145 | F12: =IFERROR(D12-E12,"") -> -9.39 | G12: =IFERROR((D12-E12)/E12,"") -> -0.0082008734 | H12: 0.28 | I12: 0.3 | J12: 0.31 | K12: 0.26 | L12: 0.29
A13: 402 | B13: =IFERROR(INDEX('Input Data'!F:F,MATCH(A13,'Input Data'!$C:$C,0)),"") -> 145.6 | C13: =IFERROR(INDEX('Input Data'!D:D,MATCH(A13,'Input Data'!$C:$C,0)),"") -> MP TRAVEL PTY LTD | D13: =IFERROR(INDEX('Input Data'!J:J,MATCH(A13,'Input Data'!$C:$C,0)),0) -> 1037.5 | E13: 1000 | F13: =IFERROR(D13-E13,"") -> 37.5 | G13: =IFERROR((D13-E13)/E13,"") -> 0.0375 | H13: 0.26 | I13: 0.27 | J13: 0.29 | K13: 0.24 | L13: 0.27
A14: 501 | B14: =IFERROR(INDEX('Input Data'!F:F,MATCH(A14,'Input Data'!$C:$C,0)),"") -> 212.3 | C14: =IFERROR(INDEX('Input Data'!D:D,MATCH(A14,'Input Data'!$C:$C,0)),"") -> MONTGOMERY INVESTMENT | D14: =IFERROR(INDEX('Input Data'!J:J,MATCH(A14,'Input Data'!$C:$C,0)),0) -> 1341.24 | E14: 1155 | F14: =IFERROR(D14-E14,"") -> 186.24 | G14: =IFERROR((D14-E14)/E14,"") -> 0.16124675 | H14: 0.28 | I14: 0.3 | J14: 0.31 | K14: 0.26 | L14: 0.29
A15: 502 | B15: =IFERROR(INDEX('Input Data'!F:F,MATCH(A15,'Input Data'!$C:$C,0)),"") -> 163.8 | C15: =IFERROR(INDEX('Input Data'!D:D,MATCH(A15,'Input Data'!$C:$C,0)),"") -> THREAT DEFENCE | D15: =IFERROR(INDEX('Input Data'!J:J,MATCH(A15,'Input Data'!$C:$C,0)),0) -> 1054.88 | E15: 1020 | F15: =IFERROR(D15-E15,"") -> 34.88 | G15: =IFERROR((D15-E15)/E15,"") -> 0.034196078 | H15: 0.26 | I15: 0.27 | J15: 0.29 | K15: 0.24 | L15: 0.27
... A28: L12 | B28: =IFERROR(INDEX('Input Data'!F:F,MATCH(A28,'Input Data'!$C:$C,0)),"") -> 223.7 | C28: =IFERROR(INDEX('Input Data'!D:D,MATCH(A28,'Input Data'!$C:$C,0)),"") -> DAKOTA CORPORATION | D28: =IFERROR(INDEX('Input Data'!J:J,MATCH(A28,'Input Data'!$C:$C,0)),0) -> 0 | E28: 384 | F28: =IFERROR(D28-E28,"") -> -384 | G28: =IFERROR((D28-E28)/E28,"") -> -1 | H28: 0 | I28: 0 | J28: 0 | K28: 0 | L28: 0
A30: PORTFOLIO MARKET RENT SUMMARY | D30: =IFERROR(SUMIF('Input Data'!K3:K27,">0",'Input Data'!J3:J27)/SUMIF('Input Data'!K3:K27,">0",'Input Data'!F3:F27),0) -> 6.0490367 | E30: 1118.5883 | F30: -14.725652 | G30: -0.013164497
A32: LEGEND: | C32: Passing > Market (above mkt) | E32: Passing < Market (reversion upside) | G32: At Market (within 5%)

Sheet Building Expiry Profile
A1: 17 CASTLEREAGH STREET — BUILDING LEASE EXPIRY PROFILE | As at 30/04/2026
A2: Floor-by-floor lease status | Colour indicates expiry year | ▲ = Above Market ▼ = Below Market ≈ = At Market
B3: Floor | C3: Suite | D3: Tenant / Trading Name | E3: NLA (sqm) | F3: Lease Start | G3: Lease Expiry | H3: Yrs Remain | I3: PSM ($) | J3: Net Rent PA ($) | K3: Expiry Year | L3: Car Parks | M3: Notes
B4: LEVEL 12
B5: ='Input Data'!B26 -> L12 | C5: ='Input Data'!C26 -> L12 | D5: ='Input Data'!D26 -> DAKOTA CORPORATION | E5: ='Input Data'!F26 -> 223.7 | F5: =IFERROR('Input Data'!G26,"") -> 42736 | G5: =IFERROR('Input Data'!H26,"") -> 47118 | H5: ='Input Data'!V26 -> 2.2094456 | I5: ='Input Data'!J26 -> 0 | J5: ='Input Data'!N26 -> 0 | K5: =IF('Input Data'!H26="","VACANT",IF(OR('Input Data'!H26<TODAY(),YEAR('Input Data'!H26)<=2026),"2026",IF(YEAR('Input Data'!H26)=2027,"2027",IF(YEAR('Input Data'!H26)=2028,"2028",IF(YEAR('Input Data'!H26)=2029,"2029",IF(YEAR('Input Data'!H26)=2030,"2030","2031+")))))) -> 2028 | L5: ='Input Data'!O26 -> 2 | M5: =IF(AND('Input Data'!J26>0,'Input Data'!S26>0),IF(('Input Data'!J26-'Input Data'!S26)/'Input Data'!S26>0.05,"▲ Above Mkt",IF(('Input Data'!J26-'Input Data'!S26)/'Input Data'!S26<-0.05,"▼ Below Mkt","≈ At Market")),"—") -> —
B7: LEVEL 11
B8: ='Input Data'!B24 -> L11 | C8: ='Input Data'!C24 -> 1101 | D8: ='Input Data'!D24 -> MICHAEL FLEGG PTY LTD | E8: ='Input Data'!F24 -> 62.4 | F8: =IFERROR('Input Data'!G24,"") -> 44531 | G8: =IFERROR('Input Data'!H24,"") -> 46356 | H8: ='Input Data'!V24 -> 0.12320329 | I8: ='Input Data'!J24 -> 1368.73 | J8: ='Input Data'!N24 -> 85408.752 | K8: =IF('Input Data'!H24="","VACANT",IF(OR('Input Data'!H24<TODAY(),YEAR('Input Data'!H24)<=2026),"2026",IF(YEAR('Input Data'!H24)=2027,"2027",IF(YEAR('Input Data'!H24)=2028,"2028",IF(YEAR('Input Data'!H24)=2029,"2029",IF(YEAR('Input Data'!H24)=2030,"2030","2031+")))))) -> 2026 | L8: ='Input Data'!O24 -> 0 | M8: =IF(AND('Input Data'!J24>0,'Input Data'!S24>0),IF(('Input Data'!J24-'Input Data'!S24)/'Input Data'!S24>0.05,"▲ Above Mkt",IF(('Input Data'!J24-'Input Data'!S24)/'Input Data'!S24<-0.05,"▼ Below Mkt","≈ At Market")),"—") -> ≈ At Market
B9: ='Input Data'!B25 -> L11 | C9: ='Input Data'!C25 -> 1102 | D9: ='Input Data'!D25 -> LEWIS WOOLCOTT | E9: ='Input Data'!F25 -> 133.1 | F9: =IFERROR('Input Data'!G25,"") -> 46249 | G9: =IFERROR('Input Data'!H25,"") -> 46979 | H9: ='Input Data'!V25 -> 1.8288843 | I9: ='Input Data'!J25 -> 1271.1 | J9: ='Input Data'!N25 -> 138730.4 | K9: =IF('Input Data'!H25="","VACANT",IF(OR('Input Data'!H25<TODAY(),YEAR('Input Data'!H25)<=2026),"2026",IF(YEAR('Input Data'!H25)=2027,"2027",IF(YEAR('Input Data'!H25)=2028,"2028",IF(YEAR('Input Data'!H25)=2029,"2029",IF(YEAR('Input Data'!H25)=2030,"2030","2031+")))))) -> 2028 | L9: ='Input Data'!O25 -> 0 | M9: =IF(AND('Input Data'!J25>0,'Input Data'!S25>0),IF(('Input Data'!J25-'Input Data'!S25)/'Input Data'!S25>0.05,"▲ Above Mkt",IF(('Input Data'!J25-'Input Data'!S25)/'Input Data'!S25<-0.05,"▼ Below Mkt","≈ At Market")),"—") -> ≈ At Market
B10: ='Input Data'!B27 -> L11 | C10: ='Input Data'!C27 -> 1103 | D10: ='Input Data'!D27 -> INTERFI SYSTEMS PTY LTD | E10: ='Input Data'!F27 -> 160.3 | F10: =IFERROR('Input Data'!G27,"") -> 46218 | G10: =IFERROR('Input Data'!H27,"") -> 47313 | H10: ='Input Data'!V27 -> 2.7433265 | I10: ='Input Data'!J27 -> 1150 | J10: ='Input Data'!N27 -> 129041.5 | K10: =IF('Input Data'!H27="","VACANT",IF(OR('Input Data'!H27<TODAY(),YEAR('Input Data'!H27)<=2026),"2026",IF(YEAR('Input Data'!H27)=2027,"2027",IF(YEAR('Input Data'!H27)=2028,"2028",IF(YEAR('Input Data'!H27)=2029,"2029",IF(YEAR('Input Data'!H27)=2030,"2030","2031+")))))) -> 2029 | L10: ='Input Data'!O27 -> 0 | M10: =IF(AND('Input Data'!J27>0,'Input Data'!S27>0),IF(('Input Data'!J27-'Input Data'!S27)/'Input Data'!S27>0.05,"▲ Above Mkt",IF(('Input Data'!J27-'Input Data'!S27)/'Input Data'!S27<-0.05,"▼ Below Mkt","≈ At Market")),"—") -> ▲ Above Mkt
B12: LEVEL 10
B13: ='Input Data'!B23 -> L10 | C13: ='Input Data'!C23 -> 1001&2 | D13: ='Input Data'!D23 -> CONNECTUS SERVICES PTY LTD | E13: ='Input Data'!F23 -> 363.2 | F13: =IFERROR('Input Data'!G23,"") -> 45261 | G13: =IFERROR('Input Data'!H23,"") -> 47452 | H13: ='Input Data'!V23 -> 3.1238877 | I13: ='Input Data'!J23 -> 1189.67 | J13: ='Input Data'!N23 -> 317550.18 | K13: =IF('Input Data'!H23="","VACANT",IF(OR('Input Data'!H23<TODAY(),YEAR('Input Data'!H23)<=2026),"2026",IF(YEAR('Input Data'!H23)=2027,"2027",IF(YEAR('Input Data'!H23)=2028,"2028",IF(YEAR('Input Data'!H23)=2029,"2029",IF(YEAR('Input Data'!H23)=2030,"2030","2031+")))))) -> 2029 | L13: ='Input Data'!O23 -> 0 | M13: =IF(AND('Input Data'!J23>0,'Input Data'!S23>0),IF(('Input Data'!J23-'Input Data'!S23)/'Input Data'!S23>0.05,"▲ Above Mkt",IF(('Input Data'!J23-'Input Data'!S23)/'Input Data'!S23<-0.05,"▼ Below Mkt","≈ At Market")),"—") -> ≈ At Market
B15: LEVEL 9
B16: ='Input Data'!B21 -> L09 | C16: ='Input Data'!C21 -> 901 | D16: ='Input Data'!D21 -> AITKEN INVESTMENT MANAGEMENT PTY LTD | E16: ='Input Data'!F21 -> 52.8 | F16: =IFERROR('Input Data'!G21,"") -> 45823 | G16: =IFERROR('Input Data'!H21,"") -> 46918 | H16: ='Input Data'!V21 -> 1.6618754 | I16: ='Input Data'!J21 -> 1338.88 | J16: ='Input Data'!N21 -> 54298.464 | K16: =IF('Input Data'!H21="","VACANT",IF(OR('Input Data'!H21<TODAY(),YEAR('Input Data'!H21)<=2026),"2026",IF(YEAR('Input Data'!H21)=2027,"2027",IF(YEAR('Input Data'!H21)=2028,"2028",IF(YEAR('Input Data'!H21)=2029,"2029",IF(YEAR('Input Data'!H21)=2030,"2030","2031+")))))) -> 2028 | L16: ='Input Data'!O21 -> 0 | M16: =IF(AND('Input Data'!J21>0,'Input Data'!S21>0),IF(('Input Data'!J21-'Input Data'!S21)/'Input Data'!S21>0.05,"▲ Above Mkt",IF(('Input Data'!J21-'Input Data'!S21)/'Input Data'!S21<-0.05,"▼ Below Mkt","≈ At Market")),"—") -> ≈ At Market
B17: ='Input Data'!B22 -> L09 | C17: ='Input Data'!C22 -> 902&3 | D17: ='Input Data'!D22 -> CAPITAL E MARKETING AND EVENTS PTY LTD | E17: ='Input Data'!F22 -> 303 | F17: =IFERROR('Input Data'!G22,"") -> 44562 | G17: =IFERROR('Input Data'!H22,"") -> 47573 | H17: ='Input Data'!V22 -> 3.4551677 | I17: ='Input Data'!J22 -> 1141.25 | J17: ='Input Data'!N22 -> 255323.07 | K17: =IF('Input Data'!H22="","VACANT",IF(OR('Input Data'!H22<TODAY(),YEAR('Input Data'!H22)<=2026),"2026",IF(YEAR('Input Data'!H22)=2027,"2027",IF(YEAR('Input Data'!H22)=2028,"2028",IF(YEAR('Input Data'!H22)=2029,"2029",IF(YEAR('Input Data'!H22)=2030,"2030","2031+")))))) -> 2030 | L17: ='Input Data'!O22 -> 0 | M17: =IF(AND('Input Data'!J22>0,'Input Data'!S22>0),IF(('Input Data'!J22-'Input Data'!S22)/'Input Data'!S22>0.05,"▲ Above Mkt",IF(('Input Data'!J22-'Input Data'!S22)/'Input Data'!S22<-0.05,"▼ Below Mkt","≈ At Market")),"—") -> ≈ At Market
B19: LEVEL 8
B20: ='Input Data'!B19 -> L08 | C20: ='Input Data'!C19 -> 801 | D20: ='Input Data'!D19 -> ARKANCE AUSTRALIA PTY LTD | E20: ='Input Data'!F19 -> 222 | F20: =IFERROR('Input Data'!G19,"") -> 45931 | G20: =IFERROR('Input Data'!H19,"") -> 47756 | H20: ='Input Data'!V19 -> 3.9561944 | I20: ='Input Data'!J19 -> 1300 | J20: ='Input Data'!N19 -> 242424 | K20: =IF('Input Data'!H19="","VACANT",IF(OR('Input Data'!H19<TODAY(),YEAR('Input Data'!H19)<=2026),"2026",IF(YEAR('Input Data'!H19)=2027,"2027",IF(YEAR('Input Data'!H19)=2028,"2028",IF(YEAR('Input Data'!H19)=2029,"2029",IF(YEAR('Input Data'!H19)=2030,"2030","2031+")))))) -> 2030 | L20: ='Input Data'!O19 -> 0 | M20: =IF(AND('Input Data'!J19>0,'Input Data'!S19>0),IF(('Input Data'!J19-'Input Data'!S19)/'Input Data'!S19>0.05,"▲ Above Mkt",IF(('Input Data'!J19-'Input Data'!S19)/'Input Data'!S19<-0.05,"▼ Below Mkt","≈ At Market")),"—") -> ≈ At Market
B21: ='Input Data'!B20 -> L08 | C21: ='Input Data'!C20 -> 802 | D21: ='Input Data'!D20 -> HILLIARD & BERRY | E21: ='Input Data'!F20 -> 138.5 | F21: =IFERROR('Input Data'!G20,"") -> 41654 | G21: =IFERROR('Input Data'!H20,"") -> 46965 | H21: ='Input Data'!V20 -> 1.7905544 | I21: ='Input Data'!J20 -> 843.65 | J21: ='Input Data'!N20 -> 116845.52 | K21: =IF('Input Data'!H20="","VACANT",IF(OR('Input Data'!H20<TODAY(),YEAR('Input Data'!H20)<=2026),"2026",IF(YEAR('Input Data'!H20)=2027,"2027",IF(YEAR('Input Data'!H20)=2028,"2028",IF(YEAR('Input Data'!H20)=2029,"2029",IF(YEAR('Input Data'!H20)=2030,"2030","2031+")))))) -> 2028 | L21: ='Input Data'!O20 -> 0 | M21: =IF(AND('Input Data'!J20>0,'Input Data'!S20>0),IF(('Input Data'!J20-'Input Data'!S20)/'Input Data'!S20>0.05,"▲ Above Mkt",IF(('Input Data'!J20-'Input Data'!S20)/'Input Data'!S20<-0.05,"▼ Below Mkt","≈ At Market")),"—") -> ▼ Below Mkt
B23: LEVEL 7
B24: ='Input Data'!B17 -> L07 | C24: ='Input Data'!C17 -> 701 | D24: ='Input Data'!D17 -> PINPOINT TALENT PTY LTD | E24: ='Input Data'!F17 -> 210.5 | F24: =IFERROR('Input Data'!G17,"") -> 45145 | G24: =IFERROR('Input Data'!H17,"") -> 46605 | H24: ='Input Data'!V17 -> 0.80492813 | I24: ='Input Data'!J17 -> 1173.54 | J24: ='Input Data'!N17 -> 178512.45 | K24: =IF('Input Data'!H17="","VACANT",IF(OR('Input Data'!H17<TODAY(),YEAR('Input Data'!H17)<=2026),"2026",IF(YEAR('Input Data'!H17)=2027,"2027",IF(YEAR('Input Data'!H17)=2028,"2028",IF(YEAR('Input Data'!H17)=2029,"2029",IF(YEAR('Input Data'!H17)=2030,"2030","2031+")))))) -> 2027 | L24: ='Input Data'!O17 -> 0 | M24: =IF(AND('Input Data'!J17>0,'Input Data'!S17>0),IF(('Input Data'!J17-'Input Data'!S17)/'Input Data'!S17>0.05,"▲ Above Mkt",IF(('Input Data'!J17-'Input Data'!S17)/'Input Data'!S17<-0.05,"▼ Below Mkt","≈ At Market")),"—") -> ≈ At Market
B25: ='Input Data'!B18 -> L07 | C25: ='Input Data'!C18 -> 702 | D25: ='Input Data'!D18 -> SATELLITE OFFICE PTY LTD | E25: ='Input Data'!F18 -> 163.9 | F25: =IFERROR('Input Data'!G18,"") -> 45444 | G25: =IFERROR('Input Data'!H18,"") -> 46904 | H25: ='Input Data'!V18 -> 1.6235455 | I25: ='Input Data'!J18 -> 1054.88 | J25: ='Input Data'!N18 -> 132633.27 | K25: =IF('Input Data'!H18="","VACANT",IF(OR('Input Data'!H18<TODAY(),YEAR('Input Data'!H18)<=2026),"2026",IF(YEAR('Input Data'!H18)=2027,"2027",IF(YEAR('Input Data'!H18)=2028,"2028",IF(YEAR('Input Data'!H18)=2029,"2029",IF(YEAR('Input Data'!H18)=2030,"2030","2031+")))))) -> 2028 | L25: ='Input Data'!O18 -> 0 | M25: =IF(AND('Input Data'!J18>0,'Input Data'!S18>0),IF(('Input Data'!J18-'Input Data'!S18)/'Input Data'!S18>0.05,"▲ Above Mkt",IF(('Input Data'!J18-'Input Data'!S18)/'Input Data'!S18<-0.05,"▼ Below Mkt","≈ At Market")),"—") -> ≈ At Market
B27: LEVEL 6
B28: ='Input Data'!B15 -> L06 | C28: ='Input Data'!C15 -> 601 | D28: ='Input Data'!D15 -> FULLCRM PTY LTD | E28: ='Input Data'!F15 -> 226.1 | F28: =IFERROR('Input Data'!G15,"") -> 44531 | G28: =IFERROR('Input Data'!H15,"") -> 46418 | H28: ='Input Data'!V15 -> 0.29295003 | I28: ='Input Data'!J15 -> 1251.34 | J28: ='Input Data'!N15 -> 251183.53 | K28: =IF('Input Data'!H15="","VACANT",IF(OR('Input Data'!H15<TODAY(),YEAR('Input Data'!H15)<=2026),"2026",IF(YEAR('Input Data'!H15)=2027,"2027",IF(YEAR('Input Data'!H15)=2028,"2028",IF(YEAR('Input Data'!H15)=2029,"2029",IF(YEAR('Input Data'!H15)=2030,"2030","2031+")))))) -> 2027 | L28: ='Input Data'!O15 -> 0 | M28: =IF(AND('Input Data'!J15>0,'Input Data'!S15>0),IF(('Input Data'!J15-'Input Data'!S15)/'Input Data'!S15>0.05,"▲ Above Mkt",IF(('Input Data'!J15-'Input Data'!S15)/'Input Data'!S15<-0.05,"▼ Below Mkt","≈ At Market")),"—") -> ▲ Above Mkt
B29: ='Input Data'!B16 -> L06 | C29: ='Input Data'!C16 -> 602 | D29: ='Input Data'!D16 -> INNOVIS | E29: ='Input Data'!F16 -> 152.1 | F29: =IFERROR('Input Data'!G16,"") -> 46327 | G29: =IFERROR('Input Data'!H16,"") -> 47421 | H29: ='Input Data'!V16 -> 3.0390144 | I29: ='Input Data'!J16 -> 1090 | J29: ='Input Data'!N16 -> 135946.98 | K29: =IF('Input Data'!H16="","VACANT",IF(OR('Input Data'!H16<TODAY(),YEAR('Input Data'!H16)<=2026),"2026",IF(YEAR('Input Data'!H16)=2027,"2027",IF(YEAR('Input Data'!H16)=2028,"2028",IF(YEAR('Input Data'!H16)=2029,"2029",IF(YEAR('Input Data'!H16)=2030,"2030","2031+")))))) -> 2029 | L29: ='Input Data'!O16 -> 0 | M29: =IF(AND('Input Data'!J16>0,'Input Data'!S16>0),IF(('Input Data'!J16-'Input Data'!S16)/'Input Data'!S16>0.05,"▲ Above Mkt",IF(('Input Data'!J16-'Input Data'!S16)/'Input Data'!S16<-0.05,"▼ Below Mkt","≈ At Market")),"—") -> ▲ Above Mkt
B31: LEVEL 5
B32: ='Input Data'!B13 -> L05 | C32: ='Input Data'!C13 -> 501 | D32: ='Input Data'!D13 -> MONTGOMERY INVESTMENT | E32: ='Input Data'!F13 -> 212.3 | F32: =IFERROR('Input Data'!G13,"") -> 43770 | G32: =IFERROR('Input Data'!H13,"") -> 46691 | H32: ='Input Data'!V13 -> 1.0403833 | I32: ='Input Data'!J13 -> 1341.24 | J32: ='Input Data'!N13 -> 235383.49 | K32: =IF('Input Data'!H13="","VACANT",IF(OR('Input Data'!H13<TODAY(),YEAR('Input Data'!H13)<=2026),"2026",IF(YEAR('Input Data'!H13)=2027,"2027",IF(YEAR('Input Data'!H13)=2028,"2028",IF(YEAR('Input Data'!H13)=2029,"2029",IF(YEAR('Input Data'!H13)=2030,"2030","2031+")))))) -> 2027 | L32: ='Input Data'!O13 -> 0 | M32: =IF(AND('Input Data'!J13>0,'Input Data'!S13>0),IF(('Input Data'!J13-'Input Data'!S13)/'Input Data'!S13>0.05,"▲ Above Mkt",IF(('Input Data'!J13-'Input Data'!S13)/'Input Data'!S13<-0.05,"▼ Below Mkt","≈ At Market")),"—") -> ▲ Above Mkt
B33: ='Input Data'!B14 -> L05 | C33: ='Input Data'!C14 -> 502 | D33: ='Input Data'!D14 -> THREAT DEFENCE | E33: ='Input Data'!F14 -> 163.8 | F33: =IFERROR('Input Data'!G14,"") -> 45474 | G33: =IFERROR('Input Data'!H14,"") -> 46568 | H33: ='Input Data'!V14 -> 0.70362765 | I33: ='Input Data'!J14 -> 1054.88 | J33: ='Input Data'!N14 -> 131053.1 | K33: =IF('Input Data'!H14="","VACANT",IF(OR('Input Data'!H14<TODAY(),YEAR('Input Data'!H14)<=2026),"2026",IF(YEAR('Input Data'!H14)=2027,"2027",IF(YEAR('Input Data'!H14)=2028,"2028",IF(YEAR('Input Data'!H14)=2029,"2029",IF(YEAR('Input Data'!H14)=2030,"2030","2031+")))))) -> 2027 | L33: ='Input Data'!O14 -> 0 | M33: =IF(AND('Input Data'!J14>0,'Input Data'!S14>0),IF(('Input Data'!J14-'Input Data'!S14)/'Input Data'!S14>0.05,"▲ Above Mkt",IF(('Input Data'!J14-'Input Data'!S14)/'Input Data'!S14<-0.05,"▼ Below Mkt","≈ At Market")),"—") -> ≈ At Market
B35: LEVEL 4
B36: ='Input Data'!B11 -> L04 | C36: ='Input Data'!C11 -> 401 | D36: ='Input Data'!D11 -> B-W INTERNATIONAL AUSTRALIA PTY LTD | E36: ='Input Data'!F11 -> 214.1 | F36: =IFERROR('Input Data'!G11,"") -> 45352 | G36: =IFERROR('Input Data'!H11,"") -> 47177 | H36: ='Input Data'!V11 -> 2.3709788 | I36: ='Input Data'!J11 -> 1135.61 | J36: ='Input Data'!N11 -> 188930.34 | K36: =IF('Input Data'!H11="","VACANT",IF(OR('Input Data'!H11<TODAY(),YEAR('Input Data'!H11)<=2026),"2026",IF(YEAR('Input Data'!H11)=2027,"2027",IF(YEAR('Input Data'!H11)=2028,"2028",IF(YEAR('Input Data'!H11)=2029,"2029",IF(YEAR('Input Data'!H11)=2030,"2030","2031+")))))) -> 2029 | L36: ='Input Data'!O11 -> 0 | M36: =IF(AND('Input Data'!J11>0,'Input Data'!S11>0),IF(('Input Data'!J11-'Input Data'!S11)/'Input Data'!S11>0.05,"▲ Above Mkt",IF(('Input Data'!J11-'Input Data'!S11)/'Input Data'!S11<-0.05,"▼ Below Mkt","≈ At Market")),"—") -> ≈ At Market
B37: ='Input Data'!B12 -> L04 | C37: ='Input Data'!C12 -> 402 | D37: ='Input Data'!D12 -> MP TRAVEL PTY LTD | E37: ='Input Data'!F12 -> 145.6 | F37: =IFERROR('Input Data'!G12,"") -> 45658 | G37: =IFERROR('Input Data'!H12,"") -> 47483 | H37: ='Input Data'!V12 -> 3.2087611 | I37: ='Input Data'!J12 -> 1037.5 | J37: ='Input Data'!N12 -> 133384.12 | K37: =IF('Input Data'!H12="","VACANT",IF(OR('Input Data'!H12<TODAY(),YEAR('Input Data'!H12)<=2026),"2026",IF(YEAR('Input Data'!H12)=2027,"2027",IF(YEAR('Input Data'!H12)=2028,"2028",IF(YEAR('Input Data'!H12)=2029,"2029",IF(YEAR('Input Data'!H12)=2030,"2030","2031+")))))) -> 2029 | L37: ='Input Data'!O12 -> 0 | M37: =IF(AND('Input Data'!J12>0,'Input Data'!S12>0),IF(('Input Data'!J12-'Input Data'!S12)/'Input Data'!S12>0.05,"▲ Above Mkt",IF(('Input Data'!J12-'Input Data'!S12)/'Input Data'!S12<-0.05,"▼ Below Mkt","≈ At Market")),"—") -> ≈ At Market
B39: LEVEL 3
B40: ='Input Data'!B9 -> L03 | C40: ='Input Data'!C9 -> 301&2 | D40: ='Input Data'!D9 -> IPM RESIDENTIAL PTY LTD | E40: ='Input Data'!F9 -> 164.2 | F40: =IFERROR('Input Data'!G9,"") -> 44713 | G40: =IFERROR('Input Data'!H9,"") -> 46538 | H40: ='Input Data'!V9 -> 0.62149213 | I40: ='Input Data'!J9 -> 1216.58 | J40: ='Input Data'!N9 -> 184245.48 | K40: =IF('Input Data'!H9="","VACANT",IF(OR('Input Data'!H9<TODAY(),YEAR('Input Data'!H9)<=2026),"2026",IF(YEAR('Input Data'!H9)=2027,"2027",IF(YEAR('Input Data'!H9)=2028,"2028",IF(YEAR('Input Data'!H9)=2029,"2029",IF(YEAR('Input Data'!H9)=2030,"2030","2031+")))))) -> 2027 | L40: ='Input Data'!O9 -> 2 | M40: =IF(AND('Input Data'!J9>0,'Input Data'!S9>0),IF(('Input Data'!J9-'Input Data'!S9)/'Input Data'!S9>0.05,"▲ Above Mkt",IF(('Input Data'!J9-'Input Data'!S9)/'Input Data'!S9<-0.05,"▼ Below Mkt","≈ At Market")),"—") -> ▲ Above Mkt
B41: ='Input Data'!B10 -> L03 | C41: ='Input Data'!C10 -> 303&4 | D41: ='Input Data'!D10 -> BROADRIDGE (AUSTRALIA) PTY LTD | E41: ='Input Data'!F10 -> 193.4 | F41: =IFERROR('Input Data'!G10,"") -> 45566 | G41: =IFERROR('Input Data'!H10,"") -> 47026 | H41: ='Input Data'!V10 -> 1.9575633 | I41: ='Input Data'!J10 -> 933.75 | J41: ='Input Data'!N10 -> 159625.05 | K41: =IF('Input Data'!H10="","VACANT",IF(OR('Input Data'!H10<TODAY(),YEAR('Input Data'!H10)<=2026),"2026",IF(YEAR('Input Data'!H10)=2027,"2027",IF(YEAR('Input Data'!H10)=2028,"2028",IF(YEAR('Input Data'!H10)=2029,"2029",IF(YEAR('Input Data'!H10)=2030,"2030","2031+")))))) -> 2028 | L41: ='Input Data'!O10 -> 0 | M41: =IF(AND('Input Data'!J10>0,'Input Data'!S10>0),IF(('Input Data'!J10-'Input Data'!S10)/'Input Data'!S10>0.05,"▲ Above Mkt",IF(('Input Data'!J10-'Input Data'!S10)/'Input Data'!S10<-0.05,"▼ Below Mkt","≈ At Market")),"—") -> ≈ At Market
B43: LEVEL 2
B44: ='Input Data'!B8 -> L02 | C44: ='Input Data'!C8 -> WHOLE | D44: ='Input Data'!D8 -> PRINCETON FINANCIAL SERVICES | E44: ='Input Data'!F8 -> 393.2 | F44: =IFERROR('Input Data'!G8,"") -> 45292 | G44: =IFERROR('Input Data'!H8,"") -> 47118 | H44: ='Input Data'!V8 -> 2.2094456 | I44: ='Input Data'!J8 -> 1081.6 | J44: ='Input Data'!N8 -> 401703.32 | K44: =IF('Input Data'!H8="","VACANT",IF(OR('Input Data'!H8<TODAY(),YEAR('Input Data'!H8)<=2026),"2026",IF(YEAR('Input Data'!H8)=2027,"2027",IF(YEAR('Input Data'!H8)=2028,"2028",IF(YEAR('Input Data'!H8)=2029,"2029",IF(YEAR('Input Data'!H8)=2030,"2030","2031+")))))) -> 2028 | L44: ='Input Data'!O8 -> 0 | M44: =IF(AND('Input Data'!J8>0,'Input Data'!S8>0),IF(('Input Data'!J8-'Input Data'!S8)/'Input Data'!S8>0.05,"▲ Above Mkt",IF(('Input Data'!J8-'Input Data'!S8)/'Input Data'!S8<-0.05,"▼ Below Mkt","≈ At Market")),"—") -> ≈ At Market
B46: LEVEL 1
B47: ='Input Data'!B5 -> L01 | C47: ='Input Data'!C5 -> 101&2 | D47: ='Input Data'!D5 -> VACANT | E47: ='Input Data'!F5 -> 162.4 | F47: =IFERROR('Input Data'!G5,"") -> 0 | G47: =IFERROR('Input Data'!H5,"") | H47: ='Input Data'!V5 -> 0 | I47: ='Input Data'!J5 -> 0 | J47: ='Input Data'!N5 -> 0 | K47: =IF('Input Data'!H5="","VACANT",IF(OR('Input Data'!H5<TODAY(),YEAR('Input Data'!H5)<=2026),"2026",IF(YEAR('Input Data'!H5)=2027,"2027",IF(YEAR('Input Data'!H5)=2028,"2028",IF(YEAR('Input Data'!H5)=2029,"2029",IF(YEAR('Input Data'!H5)=2030,"2030","2031+")))))) -> VACANT | L47: ='Input Data'!O5 -> 0 | M47: =IF(AND('Input Data'!J5>0,'Input Data'!S5>0),IF(('Input Data'!J5-'Input Data'!S5)/'Input Data'!S5>0.05,"▲ Above Mkt",IF(('Input Data'!J5-'Input Data'!S5)/'Input Data'!S5<-0.05,"▼ Below Mkt","≈ At Market")),"—") -> —
B48: ='Input Data'!B6 -> L01 | C48: ='Input Data'!C6 -> 103 | D48: ='Input Data'!D6 -> PU PRIME TRADING PTY LTD | E48: ='Input Data'!F6 -> 96.3 | F48: =IFERROR('Input Data'!G6,"") -> 44378 | G48: =IFERROR('Input Data'!H6,"") -> 46918 | H48: ='Input Data'!V6 -> 1.6618754 | I48: ='Input Data'!J6 -> 1021.99 | J48: ='Input Data'!N6 -> 89396.037 | K48: =IF('Input Data'!H6="","VACANT",IF(OR('Input Data'!H6<TODAY(),YEAR('Input Data'!H6)<=2026),"2026",IF(YEAR('Input Data'!H6)=2027,"2027",IF(YEAR('Input Data'!H6)=2028,"2028",IF(YEAR('Input Data'!H6)=2029,"2029",IF(YEAR('Input Data'!H6)=2030,"2030","2031+")))))) -> 2028 | L48: ='Input Data'!O6 -> 0 | M48: =IF(AND('Input Data'!J6>0,'Input Data'!S6>0),IF(('Input Data'!J6-'Input Data'!S6)/'Input Data'!S6>0.05,"▲ Above Mkt",IF(('Input Data'!J6-'Input Data'!S6)/'Input Data'!S6<-0.05,"▼ Below Mkt","≈ At Market")),"—") -> ▲ Above Mkt
B49: ='Input Data'!B7 -> L01 | C49: ='Input Data'!C7 -> 104 | D49: ='Input Data'!D7 -> TJC#1 PTY LTD | E49: ='Input Data'!F7 -> 98.1 | F49: =IFERROR('Input Data'!G7,"") -> 45139 | G49: =IFERROR('Input Data'!H7,"") -> 47330 | H49: ='Input Data'!V7 -> 2.78987 | I49: ='Input Data'!J7 -> 973.44 | J49: ='Input Data'!N7 -> 76070.664 | K49: =IF('Input Data'!H7="","VACANT",IF(OR('Input Data'!H7<TODAY(),YEAR('Input Data'!H7)<=2026),"2026",IF(YEAR('Input Data'!H7)=2027,"2027",IF(YEAR('Input Data'!H7)=2028,"2028",IF(YEAR('Input Data'!H7)=2029,"2029",IF(YEAR('Input Data'!H7)=2030,"2030","2031+")))))) -> 2029 | L49: ='Input Data'!O7 -> 0 | M49: =IF(AND('Input Data'!J7>0,'Input Data'!S7>0),IF(('Input Data'!J7-'Input Data'!S7)/'Input Data'!S7>0.05,"▲ Above Mkt",IF(('Input Data'!J7-'Input Data'!S7)/'Input Data'!S7<-0.05,"▼ Below Mkt","≈ At Market")),"—") -> ≈ At Market
B51: LEVEL Ground Floor
B52: ='Input Data'!B4 -> GF | C52: ='Input Data'!C4 -> GROUND | D52: ='Input Data'!D4 -> RCVRI MARTIN PLACE PTY LTD | E52: ='Input Data'!F4 -> 298.3 | F52: =IFERROR('Input Data'!G4,"") -> 45678 | G52: =IFERROR('Input Data'!H4,"") -> 48233 | H52: ='Input Data'!V4 -> 5.2621492 | I52: ='Input Data'!J4 -> 1150.52 | J52: ='Input Data'!N4 -> 272485.8 | K52: =IF('Input Data'!H4="","VACANT",IF(OR('Input Data'!H4<TODAY(),YEAR('Input Data'!H4)<=2026),"2026",IF(YEAR('Input Data'!H4)=2027,"2027",IF(YEAR('Input Data'!H4)=2028,"2028",IF(YEAR('Input Data'!H4)=2029,"2029",IF(YEAR('Input Data'!H4)=2030,"2030","2031+")))))) -> 2031+ | L52: ='Input Data'!O4 -> 0 | M52: =IF(AND('Input Data'!J4>0,'Input Data'!S4>0),IF(('Input Data'!J4-'Input Data'!S4)/'Input Data'!S4>0.05,"▲ Above Mkt",IF(('Input Data'!J4-'Input Data'!S4)/'Input Data'!S4<-0.05,"▼ Below Mkt","≈ At Market")),"—") -> ≈ At Market
B54: LEVEL WR GND
B55: ='Input Data'!B3 -> BSMT | C55: ='Input Data'!C3 -> LWR GROUND | D55: ='Input Data'!D3 -> OPULENT TWO ENTERPRISES | E55: ='Input Data'!F3 -> 151.2 | F55: =IFERROR('Input Data'!G3,"") -> 42401 | G55: =IFERROR('Input Data'!H3,"") -> 47149 | H55: ='Input Data'!V3 -> 2.294319 | I55: ='Input Data'!J3 -> 1002.01 | J55: ='Input Data'!N3 -> 123489.07 | K55: =IF('Input Data'!H3="","VACANT",IF(OR('Input Data'!H3<TODAY(),YEAR('Input Data'!H3)<=2026),"2026",IF(YEAR('Input Data'!H3)=2027,"2027",IF(YEAR('Input Data'!H3)=2028,"2028",IF(YEAR('Input Data'!H3)=2029,"2029",IF(YEAR('Input Data'!H3)=2030,"2030","2031+")))))) -> 2029 | L55: ='Input Data'!O3 -> 0 | M55: =IF(AND('Input Data'!J3>0,'Input Data'!S3>0),IF(('Input Data'!J3-'Input Data'!S3)/'Input Data'!S3>0.05,"▲ Above Mkt",IF(('Input Data'!J3-'Input Data'!S3)/'Input Data'!S3<-0.05,"▼ Below Mkt","≈ At Market")),"—") -> ▲ Above Mkt
B58: LEGEND
B60: Expiring 2026 | C60: Expiring 2027 | D60: Expiring 2028 | E60: Expiring 2029 | F60: Expiring 2030 | G60: Expiring 2031+ | H60: Vacant | I60: Owner Occupied
B62: GARAGES: 2 garages — each contains 1 tandem car space. 74 bay licences currently leased to tenants.

Sheet Make Good Obligations
A1: 17 CASTLEREAGH STREET — MAKE GOOD OBLIGATIONS REGISTER | As at 30/04/2026
A2: Track make-good obligations, notice periods and estimated costs for each suite. Update when leases are signed or when condition changes.
B4: MAKE GOOD SUMMARY
B5: Leases with Make Good Obligation | E5: Total Estimated Cost ($) | H5: High Risk (expiring <12 mths) | K5: Make Good Notice Period
B6: Input below | E6: Input below | H6: Input below | K6: See per lease
B8: MAKE GOOD OBLIGATIONS — Per Lease (update from lease schedule & inspections)
B9: Floor | C9: Suite | D9: Tenant Name | E9: Lease Expiry | F9: Notice Period | G9: MG Obligation in Lease? | H9: Estimated Cost ($) | I9: Cost PSM ($) | J9: Last Inspected | K9: Condition Rating | L9: MG Status | M9: Action Required | N9: Notes / Scope of Works | P9: Further detail
B10: LWR GND | C10: LWR GND | D10: =IFERROR(INDEX('Input Data'!D:D,MATCH("LWR GROUND",'Input Data'!$C:$C,0)),"") -> OPULENT TWO ENTERPRISES | E10: =IFERROR(INDEX('Input Data'!H:H,MATCH("LWR GROUND",'Input Data'!$C:$C,0)),"") -> 47149 | F10: 60 days | G10: Yes | I10: =IFERROR(H10/INDEX('Input Data'!F:F,MATCH("LWR GROUND",'Input Data'!$C:$C,0)),"") -> 0 | K10: Not Inspected | L10: =IF(OR(E10="—",E10="N/A",E10=""),"N/A",IF(NOT(ISNUMBER(E10)),"N/A",IF(E10<TODAY(),"Overdue",IF(E10<TODAY()+183,"Due < 6 Mths",IF(E10<TODAY()+365,"Due < 12 Mths","Not Due"))))) -> Not Due | M10: None | N10: Repaint, steam clean carpet, remove tenant fit-out
B11: GF | C11: GF | D11: =IFERROR(INDEX('Input Data'!D:D,MATCH("GROUND",'Input Data'!$C:$C,0)),"") -> RCVRI MARTIN PLACE PTY LTD | E11: =IFERROR(INDEX('Input Data'!H:H,MATCH("GROUND",'Input Data'!$C:$C,0)),"") -> 48233 | F11: 90 days | G11: Yes | I11: =IFERROR(H11/INDEX('Input Data'!F:F,MATCH("GROUND",'Input Data'!$C:$C,0)),"") -> 0 | K11: Not Inspected | L11: =IF(OR(E11="—",E11="N/A",E11=""),"N/A",IF(NOT(ISNUMBER(E11)),"N/A",IF(E11<TODAY(),"Overdue",IF(E11<TODAY()+183,"Due < 6 Mths",IF(E11<TODAY()+365,"Due < 12 Mths","Not Due"))))) -> Not Due | M11: None | N11: Retail strip-out, restore to base build | P11: Payment in Lieu $250sqm ($74,575)
B12: L01 | C12: 101&2 | D12: =IFERROR(INDEX('Input Data'!D:D,MATCH("101&2",'Input Data'!$C:$C,0)),"") -> VACANT | E12: =IFERROR(INDEX('Input Data'!H:H,MATCH("101&2",'Input Data'!$C:$C,0)),"") | F12: 10 days | G12: Yes | I12: =IFERROR(H12/INDEX('Input Data'!F:F,MATCH("101&2",'Input Data'!$C:$C,0)),"") -> 0 | K12: Not Inspected | L12: =IF(OR(E12="—",E12="N/A",E12=""),"N/A",IF(NOT(ISNUMBER(E12)),"N/A",IF(E12<TODAY(),"Overdue",IF(E12<TODAY()+183,"Due < 6 Mths",IF(E12<TODAY()+365,"Due < 12 Mths","Not Due"))))) -> N/A | M12: None | N12: Repaint walls, replace carpet, patch partitions — contact HasBuilt re spec fitout
B13: L01 | C13: 103 | D13: =IFERROR(INDEX('Input Data'!D:D,MATCH("103",'Input Data'!$C:$C,0)),"") -> PU PRIME TRADING PTY LTD | E13: =IFERROR(INDEX('Input Data'!H:H,MATCH("103",'Input Data'!$C:$C,0)),"") -> 46918 | F13: 60 days | G13: Yes | I13: =IFERROR(H13/INDEX('Input Data'!F:F,MATCH("103",'Input Data'!$C:$C,0)),"") -> 0 | K13: Not Inspected | L13: =IF(OR(E13="—",E13="N/A",E13=""),"N/A",IF(NOT(ISNUMBER(E13)),"N/A",IF(E13<TODAY(),"Overdue",IF(E13<TODAY()+183,"Due < 6 Mths",IF(E13<TODAY()+365,"Due < 12 Mths","Not Due"))))) -> Not Due | M13: None | N13: Standard office make good — repaint, steam clean | P13: Payment in Lieu $200sqm ($19.260)
B14: L01 | C14: 104 | D14: =IFERROR(INDEX('Input Data'!D:D,MATCH("104",'Input Data'!$C:$C,0)),"") -> TJC#1 PTY LTD | E14: =IFERROR(INDEX('Input Data'!H:H,MATCH("104",'Input Data'!$C:$C,0)),"") -> 47330 | F14: 60 days | G14: Yes | I14: =IFERROR(H14/INDEX('Input Data'!F:F,MATCH("104",'Input Data'!$C:$C,0)),"") -> 0 | K14: Not Inspected | L14: =IF(OR(E14="—",E14="N/A",E14=""),"N/A",IF(NOT(ISNUMBER(E14)),"N/A",IF(E14<TODAY(),"Overdue",IF(E14<TODAY()+183,"Due < 6 Mths",IF(E14<TODAY()+365,"Due < 12 Mths","Not Due"))))) -> Not Due | M14: None | N14: TBC — confirm notice period in lease; repaint & carpet | P14: Reinstate any alterations and restore premies The Lessor may nominate an amount per square metre + GST for costs 1 June
B15: L02 | C15: WHOLE | D15: =IFERROR(INDEX('Input Data'!D:D,MATCH("WHOLE",'Input Data'!$C:$C,0)),"") -> PRINCETON FINANCIAL SERVICES | E15: =IFERROR(INDEX('Input Data'!H:H,MATCH("WHOLE",'Input Data'!$C:$C,0)),"") -> 47118 | F15: 30 days | G15: Yes | I15: =IFERROR(H15/INDEX('Input Data'!F:F,MATCH("WHOLE",'Input Data'!$C:$C,0)),"") -> 0 | K15: Not Inspected | L15: =IF(OR(E15="—",E15="N/A",E15=""),"N/A",IF(NOT(ISNUMBER(E15)),"N/A",IF(E15<TODAY(),"Overdue",IF(E15<TODAY()+183,"Due < 6 Mths",IF(E15<TODAY()+365,"Due < 12 Mths","Not Due"))))) -> Not Due | M15: None | N15: Full floor — strip fit-out, repaint, replace carpet | P15: Payment in Lieu of $200sqm + GST indexed annually to CPI) ($78,640)
B16: L03 | C16: 301&2 | D16: =IFERROR(INDEX('Input Data'!D:D,MATCH("301&2",'Input Data'!$C:$C,0)),"") -> IPM RESIDENTIAL PTY LTD | E16: =IFERROR(INDEX('Input Data'!H:H,MATCH("301&2",'Input Data'!$C:$C,0)),"") -> 46538 | F16: 60 days | G16: Yes | I16: =IFERROR(H16/INDEX('Input Data'!F:F,MATCH("301&2",'Input Data'!$C:$C,0)),"") -> 0 | K16: Not Inspected | L16: =IF(OR(E16="—",E16="N/A",E16=""),"N/A",IF(NOT(ISNUMBER(E16)),"N/A",IF(E16<TODAY(),"Overdue",IF(E16<TODAY()+183,"Due < 6 Mths",IF(E16<TODAY()+365,"Due < 12 Mths","Not Due"))))) -> Due < 12 Mths | M16: None | N16: Repaint, carpet, remove internal joinery | P16: Payment in Lieu of $140sqm + GST ($22,736)
B17: L03 | C17: 303&4 | D17: =IFERROR(INDEX('Input Data'!D:D,MATCH("303&4",'Input Data'!$C:$C,0)),"") -> BROADRIDGE (AUSTRALIA) PTY LTD | E17: =IFERROR(INDEX('Input Data'!H:H,MATCH("303&4",'Input Data'!$C:$C,0)),"") -> 47026 | F17: 60 days | G17: Yes | I17: =IFERROR(H17/INDEX('Input Data'!F:F,MATCH("303&4",'Input Data'!$C:$C,0)),"") -> 0 | K17: Not Inspected | L17: =IF(OR(E17="—",E17="N/A",E17=""),"N/A",IF(NOT(ISNUMBER(E17)),"N/A",IF(E17<TODAY(),"Overdue",IF(E17<TODAY()+183,"Due < 6 Mths",IF(E17<TODAY()+365,"Due < 12 Mths","Not Due"))))) -> Not Due | M17: None | N17: Standard office make good — repaint, carpet | P17: Payment in Lieu of $150 sqm + GST ($29,010)
B18: L04 | C18: 401 | D18: =IFERROR(INDEX('Input Data'!D:D,MATCH("401",'Input Data'!$C:$C,0)),"") -> B-W INTERNATIONAL AUSTRALIA PTY LTD | E18: =IFERROR(INDEX('Input Data'!H:H,MATCH("401",'Input Data'!$C:$C,0)),"") -> 47177 | F18: 60 days | G18: Yes | I18: =IFERROR(H18/INDEX('Input Data'!F:F,MATCH("401",'Input Data'!$C:$C,0)),"") -> 0 | K18: Not Inspected | L18: =IF(OR(E18="—",E18="N/A",E18=""),"N/A",IF(NOT(ISNUMBER(E18)),"N/A",IF(E18<TODAY(),"Overdue",IF(E18<TODAY()+183,"Due < 6 Mths",IF(E18<TODAY()+365,"Due < 12 Mths","Not Due"))))) -> Not Due | M18: None | N18: Repaint, carpet, remove partitions
B19: L04 | C19: 402 | D19: =IFERROR(INDEX('Input Data'!D:D,MATCH("402",'Input Data'!$C:$C,0)),"") -> MP TRAVEL PTY LTD | E19: =IFERROR(INDEX('Input Data'!H:H,MATCH("402",'Input Data'!$C:$C,0)),"") -> 47483 | F19: 60 days | G19: Yes | I19: =IFERROR(H19/INDEX('Input Data'!F:F,MATCH("402",'Input Data'!$C:$C,0)),"") -> 0 | K19: Not Inspected | L19: =IF(OR(E19="—",E19="N/A",E19=""),"N/A",IF(NOT(ISNUMBER(E19)),"N/A",IF(E19<TODAY(),"Overdue",IF(E19<TODAY()+183,"Due < 6 Mths",IF(E19<TODAY()+365,"Due < 12 Mths","Not Due"))))) -> Not Due | M19: None | N19: Standard office make good | P19: In Addition, a payment of $100sqm + GST ($14,560)
B20: L05 | C20: 501 | D20: =IFERROR(INDEX('Input Data'!D:D,MATCH("501",'Input Data'!$C:$C,0)),"") -> MONTGOMERY INVESTMENT | E20: =IFERROR(INDEX('Input Data'!H:H,MATCH("501",'Input Data'!$C:$C,0)),"") -> 46691 | F20: 60 days | G20: Yes | I20: =IFERROR(H20/INDEX('Input Data'!F:F,MATCH("501",'Input Data'!$C:$C,0)),"") -> 0 | K20: Not Inspected | L20: =IF(OR(E20="—",E20="N/A",E20=""),"N/A",IF(NOT(ISNUMBER(E20)),"N/A",IF(E20<TODAY(),"Overdue",IF(E20<TODAY()+183,"Due < 6 Mths",IF(E20<TODAY()+365,"Due < 12 Mths","Not Due"))))) -> Not Due | M20: None | N20: Repaint, carpet, joinery removal | P20: Payment in Lieu of $250 sqm + GST ($53,075)
B21: L05 | C21: 502 | D21: =IFERROR(INDEX('Input Data'!D:D,MATCH("502",'Input Data'!$C:$C,0)),"") -> THREAT DEFENCE | E21: =IFERROR(INDEX('Input Data'!H:H,MATCH("502",'Input Data'!$C:$C,0)),"") -> 46568 | F21: 30 days | G21: Yes | I21: =IFERROR(H21/INDEX('Input Data'!F:F,MATCH("502",'Input Data'!$C:$C,0)),"") -> 0 | K21: Not Inspected | L21: =IF(OR(E21="—",E21="N/A",E21=""),"N/A",IF(NOT(ISNUMBER(E21)),"N/A",IF(E21<TODAY(),"Overdue",IF(E21<TODAY()+183,"Due < 6 Mths",IF(E21<TODAY()+365,"Due < 12 Mths","Not Due"))))) -> Due < 12 Mths | M21: None | N21: Repaint, steam clean carpet | P21: Payment in Lieu of $250 sqm + GST ($)
B22: L06 | C22: 601 | D22: =IFERROR(INDEX('Input Data'!D:D,MATCH("601",'Input Data'!$C:$C,0)),"") -> FULLCRM PTY LTD | E22: =IFERROR(INDEX('Input Data'!H:H,MATCH("601",'Input Data'!$C:$C,0)),"") -> 46418 | F22: 60 days | G22: Yes | I22: =IFERROR(H22/INDEX('Input Data'!F:F,MATCH("601",'Input Data'!$C:$C,0)),"") -> 0 | K22: Not Inspected | L22: =IF(OR(E22="—",E22="N/A",E22=""),"N/A",IF(NOT(ISNUMBER(E22)),"N/A",IF(E22<TODAY(),"Overdue",IF(E22<TODAY()+183,"Due < 6 Mths",IF(E22<TODAY()+365,"Due < 12 Mths","Not Due"))))) -> Due < 6 Mths | M22: None | N22: Tenant leaving — repaint $150/sqm notice required; internal partitions
B23: L06 | C23: 602 | D23: =IFERROR(INDEX('Input Data'!D:D,MATCH("602",'Input Data'!$C:$C,0)),"") -> INNOVIS | E23: =IFERROR(INDEX('Input Data'!H:H,MATCH("602",'Input Data'!$C:$C,0)),"") -> 47421 | F23: 60 days | G23: Yes | H23: 14000 | I23: =IFERROR(H23/INDEX('Input Data'!F:F,MATCH("602",'Input Data'!$C:$C,0)),"") -> 92.044707 | J23: 46146 | K23: Not Inspected | L23: =IF(OR(E23="—",E23="N/A",E23=""),"N/A",IF(NOT(ISNUMBER(E23)),"N/A",IF(E23<TODAY(),"Overdue",IF(E23<TODAY()+183,"Due < 6 Mths",IF(E23<TODAY()+365,"Due < 12 Mths","Not Due"))))) -> Not Due | M23: None | N23: EXPIRED — tenant left early April. Clean carpets and repaint.
B24: L07 | C24: 701 | D24: =IFERROR(INDEX('Input Data'!D:D,MATCH("701",'Input Data'!$C:$C,0)),"") -> PINPOINT TALENT PTY LTD | E24: =IFERROR(INDEX('Input Data'!H:H,MATCH("701",'Input Data'!$C:$C,0)),"") -> 46605 | F24: 60 days | G24: Yes | I24: =IFERROR(H24/INDEX('Input Data'!F:F,MATCH("701",'Input Data'!$C:$C,0)),"") -> 0 | K24: Not Inspected | L24: =IF(OR(E24="—",E24="N/A",E24=""),"N/A",IF(NOT(ISNUMBER(E24)),"N/A",IF(E24<TODAY(),"Overdue",IF(E24<TODAY()+183,"Due < 6 Mths",IF(E24<TODAY()+365,"Due < 12 Mths","Not Due"))))) -> Due < 12 Mths | M24: None | N24: No works required per David Wear — $200/sqm make good notice | P24: The Lessor may nominate an amount per square metre + GST for costs
B25: L07 | C25: 702 | D25: =IFERROR(INDEX('Input Data'!D:D,MATCH("702",'Input Data'!$C:$C,0)),"") -> SATELLITE OFFICE PTY LTD | E25: =IFERROR(INDEX('Input Data'!H:H,MATCH("702",'Input Data'!$C:$C,0)),"") -> 46904 | F25: 60 days | G25: Yes | I25: =IFERROR(H25/INDEX('Input Data'!F:F,MATCH("702",'Input Data'!$C:$C,0)),"") -> 0 | K25: Not Inspected | L25: =IF(OR(E25="—",E25="N/A",E25=""),"N/A",IF(NOT(ISNUMBER(E25)),"N/A",IF(E25<TODAY(),"Overdue",IF(E25<TODAY()+183,"Due < 6 Mths",IF(E25<TODAY()+365,"Due < 12 Mths","Not Due"))))) -> Not Due | M25: None | N25: Standard office make good
B26: L08 | C26: 801 | D26: =IFERROR(INDEX('Input Data'!D:D,MATCH("801",'Input Data'!$C:$C,0)),"") -> ARKANCE AUSTRALIA PTY LTD | E26: =IFERROR(INDEX('Input Data'!H:H,MATCH("801",'Input Data'!$C:$C,0)),"") -> 47756 | F26: 90 days | G26: Yes | I26: =IFERROR(H26/INDEX('Input Data'!F:F,MATCH("801",'Input Data'!$C:$C,0)),"") -> 0 | K26: Not Inspected | L26: =IF(OR(E26="—",E26="N/A",E26=""),"N/A",IF(NOT(ISNUMBER(E26)),"N/A",IF(E26<TODAY(),"Overdue",IF(E26<TODAY()+183,"Due < 6 Mths",IF(E26<TODAY()+365,"Due < 12 Mths","Not Due"))))) -> Not Due | M26: None | N26: Full spec fitout — strip out at lease end
B27: L08 | C27: 802 | D27: =IFERROR(INDEX('Input Data'!D:D,MATCH("802",'Input Data'!$C:$C,0)),"") -> HILLIARD & BERRY | E27: =IFERROR(INDEX('Input Data'!H:H,MATCH("802",'Input Data'!$C:$C,0)),"") -> 46965 | F27: 60 days | G27: Yes | I27: =IFERROR(H27/INDEX('Input Data'!F:F,MATCH("802",'Input Data'!$C:$C,0)),"") -> 0 | K27: Not Inspected | L27: =IF(OR(E27="—",E27="N/A",E27=""),"N/A",IF(NOT(ISNUMBER(E27)),"N/A",IF(E27<TODAY(),"Overdue",IF(E27<TODAY()+183,"Due < 6 Mths",IF(E27<TODAY()+365,"Due < 12 Mths","Not Due"))))) -> Not Due | M27: None | N27: Long-term tenant — repaint, carpet, minor remediation
B28: L09 | C28: 901 | D28: =IFERROR(INDEX('Input Data'!D:D,MATCH("901",'Input Data'!$C:$C,0)),"") -> AITKEN INVESTMENT MANAGEMENT PTY LTD | E28: =IFERROR(INDEX('Input Data'!H:H,MATCH("901",'Input Data'!$C:$C,0)),"") -> 46918 | F28: 60 days | G28: Yes | I28: =IFERROR(H28/INDEX('Input Data'!F:F,MATCH("901",'Input Data'!$C:$C,0)),"") -> 0 | K28: Not Inspected | L28: =IF(OR(E28="—",E28="N/A",E28=""),"N/A",IF(NOT(ISNUMBER(E28)),"N/A",IF(E28<TODAY(),"Overdue",IF(E28<TODAY()+183,"Due < 6 Mths",IF(E28<TODAY()+365,"Due < 12 Mths","Not Due"))))) -> Not Due | M28: None | N28: Holdover — no works required per notes; repaint & carpet on vacating
B29: L09 | C29: 902&3 | D29: =IFERROR(INDEX('Input Data'!D:D,MATCH("902&3",'Input Data'!$C:$C,0)),"") -> CAPITAL E MARKETING AND EVENTS PTY LTD | E29: =IFERROR(INDEX('Input Data'!H:H,MATCH("902&3",'Input Data'!$C:$C,0)),"") -> 47573 | F29: 90 days | G29: Yes | I29: =IFERROR(H29/INDEX('Input Data'!F:F,MATCH("902&3",'Input Data'!$C:$C,0)),"") -> 0 | K29: Not Inspected | L29: =IF(OR(E29="—",E29="N/A",E29=""),"N/A",IF(NOT(ISNUMBER(E29)),"N/A",IF(E29<TODAY(),"Overdue",IF(E29<TODAY()+183,"Due < 6 Mths",IF(E29<TODAY()+365,"Due < 12 Mths","Not Due"))))) -> Not Due | M29: None | N29: Full floor — strip fit-out and restore base build
B30: L10 | C30: 1001&2 | D30: =IFERROR(INDEX('Input Data'!D:D,MATCH("1001&2",'Input Data'!$C:$C,0)),"") -> CONNECTUS SERVICES PTY LTD | E30: =IFERROR(INDEX('Input Data'!H:H,MATCH("1001&2",'Input Data'!$C:$C,0)),"") -> 47452 | F30: 90 days | G30: Yes | I30: =IFERROR(H30/INDEX('Input Data'!F:F,MATCH("1001&2",'Input Data'!$C:$C,0)),"") -> 0 | K30: Not Inspected | L30: =IF(OR(E30="—",E30="N/A",E30=""),"N/A",IF(NOT(ISNUMBER(E30)),"N/A",IF(E30<TODAY(),"Overdue",IF(E30<TODAY()+183,"Due < 6 Mths",IF(E30<TODAY()+365,"Due < 12 Mths","Not Due"))))) -> Not Due | M30: None | N30: Full floor — strip fit-out, repaint, carpet | P30: The Lessor may nominate an amount per square metre + GST for costs Quotes from both parties - amount will be lowest of both quotes
B31: L11 | C31: 1101 | D31: =IFERROR(INDEX('Input Data'!D:D,MATCH("1101",'Input Data'!$C:$C,0)),"") -> MICHAEL FLEGG PTY LTD | E31: =IFERROR(INDEX('Input Data'!H:H,MATCH("1101",'Input Data'!$C:$C,0)),"") -> 46356 | F31: 60 days | G31: Yes | I31: =IFERROR(H31/INDEX('Input Data'!F:F,MATCH("1101",'Input Data'!$C:$C,0)),"") -> 0 | K31: Not Inspected | L31: =IF(OR(E31="—",E31="N/A",E31=""),"N/A",IF(NOT(ISNUMBER(E31)),"N/A",IF(E31<TODAY(),"Overdue",IF(E31<TODAY()+183,"Due < 6 Mths",IF(E31<TODAY()+365,"Due < 12 Mths","Not Due"))))) -> Due < 6 Mths | M31: None | N31: David Wear to reach out — no works required; repaint $200/sqm | P31: Payment in Lieu of $200 sqm + GST ($)
B32: L11 | C32: 1102 | D32: =IFERROR(INDEX('Input Data'!D:D,MATCH("1102",'Input Data'!$C:$C,0)),"") -> LEWIS WOOLCOTT | E32: =IFERROR(INDEX('Input Data'!H:H,MATCH("1102",'Input Data'!$C:$C,0)),"") -> 46979 | F32: 60 days | G32: Yes | I32: =IFERROR(H32/INDEX('Input Data'!F:F,MATCH("1102",'Input Data'!$C:$C,0)),"") -> 0 | K32: Not Inspected | L32: =IF(OR(E32="—",E32="N/A",E32=""),"N/A",IF(NOT(ISNUMBER(E32)),"N/A",IF(E32<TODAY(),"Overdue",IF(E32<TODAY()+183,"Due < 6 Mths",IF(E32<TODAY()+365,"Due < 12 Mths","Not Due"))))) -> Not Due | M32: None | N32: Current sublease — repaint & steam carpet; alterations/damage to assess
B33: L11 | C33: 1103 | D33: =IFERROR(INDEX('Input Data'!D:D,MATCH("1103",'Input Data'!$C:$C,0)),"") -> INTERFI SYSTEMS PTY LTD | E33: — | F33: — | G33: — | I33: =IFERROR(H33/INDEX('Input Data'!F:F,MATCH("1103",'Input Data'!$C:$C,0)),"") -> 0 | K33: Not Inspected | L33: =IF(OR(E33="—",E33="N/A",E33=""),"N/A",IF(NOT(ISNUMBER(E33)),"N/A",IF(E33<TODAY(),"Overdue",IF(E33<TODAY()+183,"Due < 6 Mths",IF(E33<TODAY()+365,"Due < 12 Mths","Not Due"))))) -> N/A | M33: None | N33: Suite vacant — repaint and carpet remediation complete
B34: L12 | C34: L12 | D34: =IFERROR(INDEX('Input Data'!D:D,MATCH("L12",'Input Data'!$C:$C,0)),"") -> DAKOTA CORPORATION | E34: 45291 | F34: N/A | G34: N/A | I34: =IFERROR(H34/INDEX('Input Data'!F:F,MATCH("L12",'Input Data'!$C:$C,0)),"") -> 0 | K34: Not Inspected | L34: =IF(OR(E34="—",E34="N/A",E34=""),"N/A",IF(NOT(ISNUMBER(E34)),"N/A",IF(E34<TODAY(),"Overdue",IF(E34<TODAY()+183,"Due < 6 Mths",IF(E34<TODAY()+365,"Due < 12 Mths","Not Due"))))) -> Overdue | M34: None | N34: Owner occupied — monthly; no make good obligation
B36: KEY | Amber cells = user input required | Status automatically set from expiry date
C37: LIGHT_RED (expired/overdue) | F37: LT_ORANGE (<6 mths) | I37: LT_AMBER (<12 mths) | L37: Blue/White (>12 mths)

Sheet Spec Fitouts
A1: 17 CASTLEREAGH STREET — SPEC FITOUT REGISTER | As at 30/04/2026
A2: Track approved and completed spec fitout works. Update when capex is approved, in progress, or completed. All costs ex-GST.
B4: SPEC FITOUT SUMMARY (auto-calculated from table below)
B5: Total Approved ($) | D5: Total Spent ($) | F5: Remaining Budget ($) | H5: Avg Cost PSM ($) | J5: Suites in Progress | L5: Suites Completed
B6: — | D6: — | F6: — | H6: — | J6: — | L6: —
B8: SPEC FITOUT DETAILS — one row per suite / project
B9: Floor | C9: Suite | D9: Suite Description / Last Tenant | E9: NLA (sqm) | F9: Date Approved | G9: Status | H9: Total Budget ($) | I9: Cost PSM ($) | J9: Fitout Allowance ($) | K9: Net Cost ($) | L9: Contractor | M9: Date Completed | N9: Estimated Rent PSM ($) | O9: Incentive % (new tenant) | P9: Notes / Scope
B10: L11 | C10: 1103 | D10: =IFERROR(INDEX('Input Data'!D:D,MATCH("1103",'Input Data'!$C:$C,0))&IF(INDEX('Input Data'!H:H,MATCH("1103",'Input Data'!$C:$C,0))=""," (Vacant)"," (Exp: "&TEXT(INDEX('Input Data'!H:H,MATCH("1103",'Input Data'!$C:$C,0)),"DD/MM/YY")&")"),"") -> INTERFI SYSTEMS PTY LTD (Exp: 14/07/29) | E10: =IFERROR(INDEX('Input Data'!F:F,MATCH("1103",'Input Data'!$C:$C,0)),"") -> 160.3 | G10: Pending Approval | I10: =IFERROR(H10/E10,"") -> 0 | K10: =IFERROR(H10-J10,"") -> 0 | N10: =IFERROR(INDEX('Input Data'!S:S,MATCH("1103",'Input Data'!$C:$C,0)),"") -> 1060
B11: L06 | C11: 602 | D11: =IFERROR(INDEX('Input Data'!D:D,MATCH("602",'Input Data'!$C:$C,0))&IF(INDEX('Input Data'!H:H,MATCH("602",'Input Data'!$C:$C,0))=""," (Vacant)"," (Exp: "&TEXT(INDEX('Input Data'!H:H,MATCH("602",'Input Data'!$C:$C,0)),"DD/MM/YY")&")"),"") -> INNOVIS (Exp: 30/10/29) | E11: =IFERROR(INDEX('Input Data'!F:F,MATCH("602",'Input Data'!$C:$C,0)),"") -> 152.1 | F11: 46146 | G11: Approved | H11: 13970 | I11: =IFERROR(H11/E11,"") -> 91.847469 | K11: =IFERROR(H11-J11,"") -> 13970 | L11: JC Painting Solutions King Commercial | N11: =IFERROR(INDEX('Input Data'!S:S,MATCH("602",'Input Data'!$C:$C,0)),"") -> 1030
B12: L01 | C12: 101&2 | D12: =IFERROR(INDEX('Input Data'!D:D,MATCH("101&2",'Input Data'!$C:$C,0))&IF(INDEX('Input Data'!H:H,MATCH("101&2",'Input Data'!$C:$C,0))=""," (Vacant)"," (Exp: "&TEXT(INDEX('Input Data'!H:H,MATCH("101&2",'Input Data'!$C:$C,0)),"DD/MM/YY")&")"),"") -> VACANT (Vacant) | E12: =IFERROR(INDEX('Input Data'!F:F,MATCH("101&2",'Input Data'!$C:$C,0)),"") -> 162.4 | F12: 46148 | G12: Approved | H12: 231499.4 | I12: =IFERROR(H12/E12,"") -> 1425.4889 | J12: =1200*E12 -> 194880 | K12: =IFERROR(H12-J12,"") -> 36619.4 | L12: HasBuilt | N12: =IFERROR(INDEX('Input Data'!S:S,MATCH("101&2",'Input Data'!$C:$C,0)),"") -> 1115
B13: L01 | C13: 104 | D13: =IFERROR(INDEX('Input Data'!D:D,MATCH("104",'Input Data'!$C:$C,0))&IF(INDEX('Input Data'!H:H,MATCH("104",'Input Data'!$C:$C,0))=""," (Vacant)"," (Exp: "&TEXT(INDEX('Input Data'!H:H,MATCH("104",'Input Data'!$C:$C,0)),"DD/MM/YY")&")"),"") -> TJC#1 PTY LTD (Exp: 31/07/29) | E13: =IFERROR(INDEX('Input Data'!F:F,MATCH("104",'Input Data'!$C:$C,0)),"") -> 98.1 | G13: Pending Approval | I13: =IFERROR(H13/E13,"") -> 0 | K13: =IFERROR(H13-J13,"") -> 0 | N13: =IFERROR(INDEX('Input Data'!S:S,MATCH("104",'Input Data'!$C:$C,0)),"") -> 960
B14: L11 | C14: 1102 | D14: =IFERROR(INDEX('Input Data'!D:D,MATCH("1102",'Input Data'!$C:$C,0))&IF(INDEX('Input Data'!H:H,MATCH("1102",'Input Data'!$C:$C,0))=""," (Vacant)"," (Exp: "&TEXT(INDEX('Input Data'!H:H,MATCH("1102",'Input Data'!$C:$C,0)),"DD/MM/YY")&")"),"") -> LEWIS WOOLCOTT (Exp: 14/08/28) | E14: =IFERROR(INDEX('Input Data'!F:F,MATCH("1102",'Input Data'!$C:$C,0)),"") -> 133.1 | G14: Pending Approval | I14: =IFERROR(H14/E14,"") -> 0 | K14: =IFERROR(H14-J14,"") -> 0 | N14: =IFERROR(INDEX('Input Data'!S:S,MATCH("1102",'Input Data'!$C:$C,0)),"") -> 1250
B15: L11 | C15: 1101 | D15: =IFERROR(INDEX('Input Data'!D:D,MATCH("1101",'Input Data'!$C:$C,0))&IF(INDEX('Input Data'!H:H,MATCH("1101",'Input Data'!$C:$C,0))=""," (Vacant)"," (Exp: "&TEXT(INDEX('Input Data'!H:H,MATCH("1101",'Input Data'!$C:$C,0)),"DD/MM/YY")&")"),"") -> MICHAEL FLEGG PTY LTD (Exp: 30/11/26) | E15: =IFERROR(INDEX('Input Data'!F:F,MATCH("1101",'Input Data'!$C:$C,0)),"") -> 62.4 | G15: Pending Approval | I15: =IFERROR(H15/E15,"") -> 0 | K15: =IFERROR(H15-J15,"") -> 0 | N15: =IFERROR(INDEX('Input Data'!S:S,MATCH("1101",'Input Data'!$C:$C,0)),"") -> 1405
B16: L11 | E16: 162.4 | H16: 354254.37 | I16: =IFERROR(H16/E16,"") -> 2181.3693
H17: =H16-48000 -> 306254.37 | I17: =H17/E16 -> 1885.8028
B26: COST REFERENCE GUIDE — Typical Spec Fitout Costs (update from market quotes)
B27: Category | C27: Low ($ psm) | D27: Mid ($ psm) | E27: High ($ psm) | F27: Notes
B28: Partition offices + open plan | C28: $350 | D28: $550 | E28: $750 | F28: Includes demolition, new partitions, doors
B29: Carpet / floor coverings | C29: $65 | D29: $90 | E29: $130 | F29: Quality commercial carpet tiles
B30: Painting – full repaint | C30: $25 | D30: $40 | E30: $55 | F30: Per sqm NLA
B31: Lighting upgrade (LED) | C31: $40 | D31: $70 | E31: $110 | F31: Per sqm; assume if >10yrs old
B32: Joinery / kitchen | C32: $15,000 | D32: $25,000 | E32: $40,000 | F32: Per kitchen (per fitout)
B33: A/C servicing & balancing | C33: $20 | D33: $35 | E33: $55 | F33: Per sqm NLA
B34: Full blank canvas fitout | C34: $600 | D34: $850 | E34: $1,200 | F34: Complete stripped and refitted suite
B35: Cosmetic refresh only | C35: $100 | D35: $180 | E35: $260 | F35: Carpet + paint + lighting only

Sheet Stack Plan
A1: 17 CASTLEREAGH STREET, SYDNEY — BUILDING STACK PLAN | As at 30/04/2026
A2: Blocks sized proportionally by NLA | Colour = lease expiry year | Source: Input Data tab
B3: Floor | C3: Floor NLA (sqm) | D3: ◄────────────────────────────────────── BUILDING STACK (blocks proportional to NLA) ──────────────────────────────────────►
B5: Level 12 | C5: =SUMIF('Input Data'!B:B,"L12",'Input Data'!F:F) -> 223.7 | D5: =IFERROR(INDEX('Input Data'!D:D,MATCH("L12",'Input Data'!$C:$C,0)),"VACANT") -> DAKOTA CORPORATION
D6: ="Suite "&"L12" -> Suite L12
D7: =IFERROR(TEXT(INDEX('Input Data'!F:F,MATCH("L12",'Input Data'!$C:$C,0)),"#,##0.0")&" sqm"&IF(INDEX('Input Data'!O:O,MATCH("L12",'Input Data'!$C:$C,0))>0," | "&TEXT(INDEX('Input Data'!O:O,MATCH("L12",'Input Data'!$C:$C,0)),"0")&" car parks",""),"") -> 223.7 sqm | 2 car parks
D8: =IFERROR("Face PSM: $"&TEXT(INDEX('Input Data'!J:J,MATCH("L12",'Input Data'!$C:$C,0)),"#,##0")&" | Incent: "&IF(INDEX('Input Data'!L:L,MATCH("L12",'Input Data'!$C:$C,0))<0,"$"&TEXT(-INDEX('Input Data'!L:L,MATCH("L12",'Input Data'!$C:$C,0))/INDEX('Input Data'!F:F,MATCH("L12",'Input Data'!$C:$C,0)),"#,##0.00"),"nil"),"—") -> Face PSM: $0 | Incent: nil
D9: =IFERROR("Outgoings: $"&TEXT(INDEX('Input Data'!M:M,MATCH("L12",'Input Data'!$C:$C,0))/INDEX('Input Data'!F:F,MATCH("L12",'Input Data'!$C:$C,0)),"#,##0.00")&" psm | Net: $"&TEXT(INDEX('Input Data'!N:N,MATCH("L12",'Input Data'!$C:$C,0)),"#,##0")&" pa","—") -> Outgoings: $0.00 psm | Net: $0 pa
D10: =IFERROR("Start: "&TEXT(INDEX('Input Data'!G:G,MATCH("L12",'Input Data'!$C:$C,0)),"DD/MM/YY")&" → Expiry: "&TEXT(INDEX('Input Data'!H:H,MATCH("L12",'Input Data'!$C:$C,0)),"DD/MM/YY"),"—") -> Start: 01/01/17 → Expiry: 31/12/28
D11: =IFERROR(IF((INDEX('Input Data'!H:H,MATCH("L12",'Input Data'!$C:$C,0))-TODAY())>0,TEXT((INDEX('Input Data'!H:H,MATCH("L12",'Input Data'!$C:$C,0))-TODAY())/365.25,"0.0")&" yrs remaining","⚠ EXPIRED"),"—") -> 2.2 yrs remaining
D12: =""
D13: =""
B15: Level 11 | C15: =SUMIF('Input Data'!B:B,"L11",'Input Data'!F:F) -> 355.8 | D15: =IFERROR(INDEX('Input Data'!D:D,MATCH("1101",'Input Data'!$C:$C,0)),"VACANT") -> MICHAEL FLEGG PTY LTD | J15: =IFERROR(INDEX('Input Data'!D:D,MATCH("1102",'Input Data'!$C:$C,0)),"VACANT") -> LEWIS WOOLCOTT | T15: =IFERROR(INDEX('Input Data'!D:D,MATCH("1103",'Input Data'!$C:$C,0)),"VACANT") -> INTERFI SYSTEMS PTY LTD
D16: ="Suite "&"1101" -> Suite 1101 | J16: ="Suite "&"1102" -> Suite 1102 | T16: ="Suite "&"1103" -> Suite 1103
D17: =IFERROR(TEXT(INDEX('Input Data'!F:F,MATCH("1101",'Input Data'!$C:$C,0)),"#,##0.0")&" sqm"&IF(INDEX('Input Data'!O:O,MATCH("1101",'Input Data'!$C:$C,0))>0," | "&TEXT(INDEX('Input Data'!O:O,MATCH("1101",'Input Data'!$C:$C,0)),"0")&" car parks",""),"") -> 62.4 sqm | J17: =IFERROR(TEXT(INDEX('Input Data'!F:F,MATCH("1102",'Input Data'!$C:$C,0)),"#,##0.0")&" sqm"&IF(INDEX('Input Data'!O:O,MATCH("1102",'Input Data'!$C:$C,0))>0," | "&TEXT(INDEX('Input Data'!O:O,MATCH("1102",'Input Data'!$C:$C,0)),"0")&" car parks",""),"") -> 133.1 sqm | T17: =IFERROR(TEXT(INDEX('Input Data'!F:F,MATCH("1103",'Input Data'!$C:$C,0)),"#,##0.0")&" sqm"&IF(INDEX('Input Data'!O:O,MATCH("1103",'Input Data'!$C:$C,0))>0," | "&TEXT(INDEX('Input Data'!O:O,MATCH("1103",'Input Data'!$C:$C,0)),"0")&" car parks",""),"") -> 160.3 sqm
D18: =IFERROR("Face PSM: $"&TEXT(INDEX('Input Data'!J:J,MATCH("1101",'Input Data'!$C:$C,0)),"#,##0")&" | Incent: "&IF(INDEX('Input Data'!L:L,MATCH("1101",'Input Data'!$C:$C,0))<0,"$"&TEXT(-INDEX('Input Data'!L:L,MATCH("1101",'Input Data'!$C:$C,0))/INDEX('Input Data'!F:F,MATCH("1101",'Input Data'!$C:$C,0)),"#,##0.00"),"nil"),"—") -> Face PSM: $1,369 | Incent: nil | J18: =IFERROR("Face PSM: $"&TEXT(INDEX('Input Data'!J:J,MATCH("1102",'Input Data'!$C:$C,0)),"#,##0")&" | Incent: "&IF(INDEX('Input Data'!L:L,MATCH("1102",'Input Data'!$C:$C,0))<0,"$"&TEXT(-INDEX('Input Data'!L:L,MATCH("1102",'Input Data'!$C:$C,0))/INDEX('Input Data'!F:F,MATCH("1102",'Input Data'!$C:$C,0)),"#,##0.00"),"nil"),"—") -> Face PSM: $1,271 | Incent: $228.80 | T18: =IFERROR("Face PSM: $"&TEXT(INDEX('Input Data'!J:J,MATCH("1103",'Input Data'!$C:$C,0)),"#,##0")&" | Incent: "&IF(INDEX('Input Data'!L:L,MATCH("1103",'Input Data'!$C:$C,0))<0,"$"&TEXT(-INDEX('Input Data'!L:L,MATCH("1103",'Input Data'!$C:$C,0))/INDEX('Input Data'!F:F,MATCH("1103",'Input Data'!$C:$C,0)),"#,##0.00"),"nil"),"—") -> Face PSM: $1,150 | Incent: $345.00
D19: =IFERROR("Outgoings: $"&TEXT(INDEX('Input Data'!M:M,MATCH("1101",'Input Data'!$C:$C,0))/INDEX('Input Data'!F:F,MATCH("1101",'Input Data'!$C:$C,0)),"#,##0.00")&" psm | Net: $"&TEXT(INDEX('Input Data'!N:N,MATCH("1101",'Input Data'!$C:$C,0)),"#,##0")&" pa","—") -> Outgoings: $67.31 psm | Net: $85,409 pa | J19: =IFERROR("Outgoings: $"&TEXT(INDEX('Input Data'!M:M,MATCH("1102",'Input Data'!$C:$C,0))/INDEX('Input Data'!F:F,MATCH("1102",'Input Data'!$C:$C,0)),"#,##0.00")&" psm | Net: $"&TEXT(INDEX('Input Data'!N:N,MATCH("1102",'Input Data'!$C:$C,0)),"#,##0")&" pa","—") -> Outgoings: $43.73 psm | Net: $138,730 pa | T19: =IFERROR("Outgoings: $"&TEXT(INDEX('Input Data'!M:M,MATCH("1103",'Input Data'!$C:$C,0))/INDEX('Input Data'!F:F,MATCH("1103",'Input Data'!$C:$C,0)),"#,##0.00")&" psm | Net: $"&TEXT(INDEX('Input Data'!N:N,MATCH("1103",'Input Data'!$C:$C,0)),"#,##0")&" pa","—") -> Outgoings: $0.00 psm | Net: $129,042 pa
D20: =IFERROR("Start: "&TEXT(INDEX('Input Data'!G:G,MATCH("1101",'Input Data'!$C:$C,0)),"DD/MM/YY")&" → Expiry: "&TEXT(INDEX('Input Data'!H:H,MATCH("1101",'Input Data'!$C:$C,0)),"DD/MM/YY"),"—") -> Start: 01/12/21 → Expiry: 30/11/26 | J20: =IFERROR("Start: "&TEXT(INDEX('Input Data'!G:G,MATCH("1102",'Input Data'!$C:$C,0)),"DD/MM/YY")&" → Expiry: "&TEXT(INDEX('Input Data'!H:H,MATCH("1102",'Input Data'!$C:$C,0)),"DD/MM/YY"),"—") -> Start: 15/08/26 → Expiry: 14/08/28 | T20: =IFERROR("Start: "&TEXT(INDEX('Input Data'!G:G,MATCH("1103",'Input Data'!$C:$C,0)),"DD/MM/YY")&" → Expiry: "&TEXT(INDEX('Input Data'!H:H,MATCH("1103",'Input Data'!$C:$C,0)),"DD/MM/YY"),"—") -> Start: 15/07/26 → Expiry: 14/07/29
D21: =IFERROR(IF((INDEX('Input Data'!H:H,MATCH("1101",'Input Data'!$C:$C,0))-TODAY())>0,TEXT((INDEX('Input Data'!H:H,MATCH("1101",'Input Data'!$C:$C,0))-TODAY())/365.25,"0.0")&" yrs remaining","⚠ EXPIRED"),"—") -> 0.1 yrs remaining | J21: =IFERROR(IF((INDEX('Input Data'!H:H,MATCH("1102",'Input Data'!$C:$C,0))-TODAY())>0,TEXT((INDEX('Input Data'!H:H,MATCH("1102",'Input Data'!$C:$C,0))-TODAY())/365.25,"0.0")&" yrs remaining","⚠ EXPIRED"),"—") -> 1.8 yrs remaining | T21: =IFERROR(IF((INDEX('Input Data'!H:H,MATCH("1103",'Input Data'!$C:$C,0))-TODAY())>0,TEXT((INDEX('Input Data'!H:H,MATCH("1103",'Input Data'!$C:$C,0))-TODAY())/365.25,"0.0")&" yrs remaining","⚠ EXPIRED"),"—") -> 2.7 yrs remaining
D22: ="" | J22: ="" | T22: =""
D23: ="" | J23: ="" | T23: =""
B25: Level 10 | C25: =SUMIF('Input Data'!B:B,"L10",'Input Data'!F:F) -> 363.2 | D25: =IFERROR(INDEX('Input Data'!D:D,MATCH("1001&2",'Input Data'!$C:$C,0)),"VACANT") -> CONNECTUS SERVICES PTY LTD
D26: ="Suite "&"1001&2" -> Suite 1001&2
D27: =IFERROR(TEXT(INDEX('Input Data'!F:F,MATCH("1001&2",'Input Data'!$C:$C,0)),"#,##0.0")&" sqm"&IF(INDEX('Input Data'!O:O,MATCH("1001&2",'Input Data'!$C:$C,0))>0," | "&TEXT(INDEX('Input Data'!O:O,MATCH("1001&2",'Input Data'!$C:$C,0)),"0")&" car parks",""),"") -> 363.2 sqm
D28: =IFERROR("Face PSM: $"&TEXT(INDEX('Input Data'!J:J,MATCH("1001&2",'Input Data'!$C:$C,0)),"#,##0")&" | Incent: "&IF(INDEX('Input Data'!L:L,MATCH("1001&2",'Input Data'!$C:$C,0))<0,"$"&TEXT(-INDEX('Input Data'!L:L,MATCH("1001&2",'Input Data'!$C:$C,0))/INDEX('Input Data'!F:F,MATCH("1001&2",'Input Data'!$C:$C,0)),"#,##0.00"),"nil"),"—") -> Face PSM: $1,190 | Incent: $315.36
D29: =IFERROR("Outgoings: $"&TEXT(INDEX('Input Data'!M:M,MATCH("1001&2",'Input Data'!$C:$C,0))/INDEX('Input Data'!F:F,MATCH("1001&2",'Input Data'!$C:$C,0)),"#,##0.00")&" psm | Net: $"&TEXT(INDEX('Input Data'!N:N,MATCH("1001&2",'Input Data'!$C:$C,0)),"#,##0")&" pa","—") -> Outgoings: $41.30 psm | Net: $317,550 pa
D30: =IFERROR("Start: "&TEXT(INDEX('Input Data'!G:G,MATCH("1001&2",'Input Data'!$C:$C,0)),"DD/MM/YY")&" → Expiry: "&TEXT(INDEX('Input Data'!H:H,MATCH("1001&2",'Input Data'!$C:$C,0)),"DD/MM/YY"),"—") -> Start: 01/12/23 → Expiry: 30/11/29
D31: =IFERROR(IF((INDEX('Input Data'!H:H,MATCH("1001&2",'Input Data'!$C:$C,0))-TODAY())>0,TEXT((INDEX('Input Data'!H:H,MATCH("1001&2",'Input Data'!$C:$C,0))-TODAY())/365.25,"0.0")&" yrs remaining","⚠ EXPIRED"),"—") -> 3.1 yrs remaining
D32: =""
D33: =""
B35: Level 9 | C35: =SUMIF('Input Data'!B:B,"L09",'Input Data'!F:F) -> 355.8 | D35: =IFERROR(INDEX('Input Data'!D:D,MATCH("901",'Input Data'!$C:$C,0)),"VACANT") -> AITKEN INVESTMENT MANAGEMENT PTY LTD | J35: =IFERROR(INDEX('Input Data'!D:D,MATCH("902&3",'Input Data'!$C:$C,0)),"VACANT") -> CAPITAL E MARKETING AND EVENTS PTY LTD
D36: ="Suite "&"901" -> Suite 901 | J36: ="Suite "&"902&3" -> Suite 902&3
D37: =IFERROR(TEXT(INDEX('Input Data'!F:F,MATCH("901",'Input Data'!$C:$C,0)),"#,##0.0")&" sqm"&IF(INDEX('Input Data'!O:O,MATCH("901",'Input Data'!$C:$C,0))>0," | "&TEXT(INDEX('Input Data'!O:O,MATCH("901",'Input Data'!$C:$C,0)),"0")&" car parks",""),"") -> 52.8 sqm | J37: =IFERROR(TEXT(INDEX('Input Data'!F:F,MATCH("902&3",'Input Data'!$C:$C,0)),"#,##0.0")&" sqm"&IF(INDEX('Input Data'!O:O,MATCH("902&3",'Input Data'!$C:$C,0))>0," | "&TEXT(INDEX('Input Data'!O:O,MATCH("902&3",'Input Data'!$C:$C,0)),"0")&" car parks",""),"") -> 303.0 sqm
D38: =IFERROR("Face PSM: $"&TEXT(INDEX('Input Data'!J:J,MATCH("901",'Input Data'!$C:$C,0)),"#,##0")&" | Incent: "&IF(INDEX('Input Data'!L:L,MATCH("901",'Input Data'!$C:$C,0))<0,"$"&TEXT(-INDEX('Input Data'!L:L,MATCH("901",'Input Data'!$C:$C,0))/INDEX('Input Data'!F:F,MATCH("901",'Input Data'!$C:$C,0)),"#,##0.00"),"nil"),"—") -> Face PSM: $1,339 | Incent: $310.50 | J38: =IFERROR("Face PSM: $"&TEXT(INDEX('Input Data'!J:J,MATCH("902&3",'Input Data'!$C:$C,0)),"#,##0")&" | Incent: "&IF(INDEX('Input Data'!L:L,MATCH("902&3",'Input Data'!$C:$C,0))<0,"$"&TEXT(-INDEX('Input Data'!L:L,MATCH("902&3",'Input Data'!$C:$C,0))/INDEX('Input Data'!F:F,MATCH("902&3",'Input Data'!$C:$C,0)),"#,##0.00"),"nil"),"—") -> Face PSM: $1,141 | Incent: $298.60
D39: =IFERROR("Outgoings: $"&TEXT(INDEX('Input Data'!M:M,MATCH("901",'Input Data'!$C:$C,0))/INDEX('Input Data'!F:F,MATCH("901",'Input Data'!$C:$C,0)),"#,##0.00")&" psm | Net: $"&TEXT(INDEX('Input Data'!N:N,MATCH("901",'Input Data'!$C:$C,0)),"#,##0")&" pa","—") -> Outgoings: $71.59 psm | Net: $54,298 pa | J39: =IFERROR("Outgoings: $"&TEXT(INDEX('Input Data'!M:M,MATCH("902&3",'Input Data'!$C:$C,0))/INDEX('Input Data'!F:F,MATCH("902&3",'Input Data'!$C:$C,0)),"#,##0.00")&" psm | Net: $"&TEXT(INDEX('Input Data'!N:N,MATCH("902&3",'Input Data'!$C:$C,0)),"#,##0")&" pa","—") -> Outgoings: $30.69 psm | Net: $255,323 pa
D40: =IFERROR("Start: "&TEXT(INDEX('Input Data'!G:G,MATCH("901",'Input Data'!$C:$C,0)),"DD/MM/YY")&" → Expiry: "&TEXT(INDEX('Input Data'!H:H,MATCH("901",'Input Data'!$C:$C,0)),"DD/MM/YY"),"—") -> Start: 15/06/25 → Expiry: 14/06/28 | J40: =IFERROR("Start: "&TEXT(INDEX('Input Data'!G:G,MATCH("902&3",'Input Data'!$C:$C,0)),"DD/MM/YY")&" → Expiry: "&TEXT(INDEX('Input Data'!H:H,MATCH("902&3",'Input Data'!$C:$C,0)),"DD/MM/YY"),"—") -> Start: 01/01/22 → Expiry: 31/03/30
D41: =IFERROR(IF((INDEX('Input Data'!H:H,MATCH("901",'Input Data'!$C:$C,0))-TODAY())>0,TEXT((INDEX('Input Data'!H:H,MATCH("901",'Input Data'!$C:$C,0))-TODAY())/365.25,"0.0")&" yrs remaining","⚠ EXPIRED"),"—") -> 1.7 yrs remaining | J41: =IFERROR(IF((INDEX('Input Data'!H:H,MATCH("902&3",'Input Data'!$C:$C,0))-TODAY())>0,TEXT((INDEX('Input Data'!H:H,MATCH("902&3",'Input Data'!$C:$C,0))-TODAY())/365.25,"0.0")&" yrs remaining","⚠ EXPIRED"),"—") -> 3.5 yrs remaining
D42: ="" | J42: =""
D43: ="" | J43: =""
B45: Level 8 | C45: =SUMIF('Input Data'!B:B,"L08",'Input Data'!F:F) -> 360.5 | D45: =IFERROR(INDEX('Input Data'!D:D,MATCH("801",'Input Data'!$C:$C,0)),"VACANT") -> ARKANCE AUSTRALIA PTY LTD | U45: =IFERROR(INDEX('Input Data'!D:D,MATCH("802",'Input Data'!$C:$C,0)),"VACANT") -> HILLIARD & BERRY
D46: ="Suite "&"801" -> Suite 801 | U46: ="Suite "&"802" -> Suite 802
D47: =IFERROR(TEXT(INDEX('Input Data'!F:F,MATCH("801",'Input Data'!$C:$C,0)),"#,##0.0")&" sqm"&IF(INDEX('Input Data'!O:O,MATCH("801",'Input Data'!$C:$C,0))>0," | "&TEXT(INDEX('Input Data'!O:O,MATCH("801",'Input Data'!$C:$C,0)),"0")&" car parks",""),"") -> 222.0 sqm | U47: =IFERROR(TEXT(INDEX('Input Data'!F:F,MATCH("802",'Input Data'!$C:$C,0)),"#,##0.0")&" sqm"&IF(INDEX('Input Data'!O:O,MATCH("802",'Input Data'!$C:$C,0))>0," | "&TEXT(INDEX('Input Data'!O:O,MATCH("802",'Input Data'!$C:$C,0)),"0")&" car parks",""),"") -> 138.5 sqm
D48: =IFERROR("Face PSM: $"&TEXT(INDEX('Input Data'!J:J,MATCH("801",'Input Data'!$C:$C,0)),"#,##0")&" | Incent: "&IF(INDEX('Input Data'!L:L,MATCH("801",'Input Data'!$C:$C,0))<0,"$"&TEXT(-INDEX('Input Data'!L:L,MATCH("801",'Input Data'!$C:$C,0))/INDEX('Input Data'!F:F,MATCH("801",'Input Data'!$C:$C,0)),"#,##0.00"),"nil"),"—") -> Face PSM: $1,300 | Incent: $208.00 | U48: =IFERROR("Face PSM: $"&TEXT(INDEX('Input Data'!J:J,MATCH("802",'Input Data'!$C:$C,0)),"#,##0")&" | Incent: "&IF(INDEX('Input Data'!L:L,MATCH("802",'Input Data'!$C:$C,0))<0,"$"&TEXT(-INDEX('Input Data'!L:L,MATCH("802",'Input Data'!$C:$C,0))/INDEX('Input Data'!F:F,MATCH("802",'Input Data'!$C:$C,0)),"#,##0.00"),"nil"),"—") -> Face PSM: $844 | Incent: nil
D49: =IFERROR("Outgoings: $"&TEXT(INDEX('Input Data'!M:M,MATCH("801",'Input Data'!$C:$C,0))/INDEX('Input Data'!F:F,MATCH("801",'Input Data'!$C:$C,0)),"#,##0.00")&" psm | Net: $"&TEXT(INDEX('Input Data'!N:N,MATCH("801",'Input Data'!$C:$C,0)),"#,##0")&" pa","—") -> Outgoings: $6.76 psm | Net: $242,424 pa | U49: =IFERROR("Outgoings: $"&TEXT(INDEX('Input Data'!M:M,MATCH("802",'Input Data'!$C:$C,0))/INDEX('Input Data'!F:F,MATCH("802",'Input Data'!$C:$C,0)),"#,##0.00")&" psm | Net: $"&TEXT(INDEX('Input Data'!N:N,MATCH("802",'Input Data'!$C:$C,0)),"#,##0")&" pa","—") -> Outgoings: $88.38 psm | Net: $116,846 pa
D50: =IFERROR("Start: "&TEXT(INDEX('Input Data'!G:G,MATCH("801",'Input Data'!$C:$C,0)),"DD/MM/YY")&" → Expiry: "&TEXT(INDEX('Input Data'!H:H,MATCH("801",'Input Data'!$C:$C,0)),"DD/MM/YY"),"—") -> Start: 01/10/25 → Expiry: 30/09/30 | U50: =IFERROR("Start: "&TEXT(INDEX('Input Data'!G:G,MATCH("802",'Input Data'!$C:$C,0)),"DD/MM/YY")&" → Expiry: "&TEXT(INDEX('Input Data'!H:H,MATCH("802",'Input Data'!$C:$C,0)),"DD/MM/YY"),"—") -> Start: 15/01/14 → Expiry: 31/07/28
D51: =IFERROR(IF((INDEX('Input Data'!H:H,MATCH("801",'Input Data'!$C:$C,0))-TODAY())>0,TEXT((INDEX('Input Data'!H:H,MATCH("801",'Input Data'!$C:$C,0))-TODAY())/365.25,"0.0")&" yrs remaining","⚠ EXPIRED"),"—") -> 4.0 yrs remaining | U51: =IFERROR(IF((INDEX('Input Data'!H:H,MATCH("802",'Input Data'!$C:$C,0))-TODAY())>0,TEXT((INDEX('Input Data'!H:H,MATCH("802",'Input Data'!$C:$C,0))-TODAY())/365.25,"0.0")&" yrs remaining","⚠ EXPIRED"),"—") -> 1.8 yrs remaining
D52: ="" | U52: =""
D53: ="" | U53: =""
B55: Level 7 | C55: =SUMIF('Input Data'!B:B,"L07",'Input Data'!F:F) -> 374.4 | D55: =IFERROR(INDEX('Input Data'!D:D,MATCH("701",'Input Data'!$C:$C,0)),"VACANT") -> PINPOINT TALENT PTY LTD | S55: =IFERROR(INDEX('Input Data'!D:D,MATCH("702",'Input Data'!$C:$C,0)),"VACANT") -> SATELLITE OFFICE PTY LTD
D56: ="Suite "&"701" -> Suite 701 | S56: ="Suite "&"702" -> Suite 702
D57: =IFERROR(TEXT(INDEX('Input Data'!F:F,MATCH("701",'Input Data'!$C:$C,0)),"#,##0.0")&" sqm"&IF(INDEX('Input Data'!O:O,MATCH("701",'Input Data'!$C:$C,0))>0," | "&TEXT(INDEX('Input Data'!O:O,MATCH("701",'Input Data'!$C:$C,0)),"0")&" car parks",""),"") -> 210.5 sqm | S57: =IFERROR(TEXT(INDEX('Input Data'!F:F,MATCH("702",'Input Data'!$C:$C,0)),"#,##0.0")&" sqm"&IF(INDEX('Input Data'!O:O,MATCH("702",'Input Data'!$C:$C,0))>0," | "&TEXT(INDEX('Input Data'!O:O,MATCH("702",'Input Data'!$C:$C,0)),"0")&" car parks",""),"") -> 163.9 sqm
D58: =IFERROR("Face PSM: $"&TEXT(INDEX('Input Data'!J:J,MATCH("701",'Input Data'!$C:$C,0)),"#,##0")&" | Incent: "&IF(INDEX('Input Data'!L:L,MATCH("701",'Input Data'!$C:$C,0))<0,"$"&TEXT(-INDEX('Input Data'!L:L,MATCH("701",'Input Data'!$C:$C,0))/INDEX('Input Data'!F:F,MATCH("701",'Input Data'!$C:$C,0)),"#,##0.00"),"nil"),"—") -> Face PSM: $1,174 | Incent: $325.50 | S58: =IFERROR("Face PSM: $"&TEXT(INDEX('Input Data'!J:J,MATCH("702",'Input Data'!$C:$C,0)),"#,##0")&" | Incent: "&IF(INDEX('Input Data'!L:L,MATCH("702",'Input Data'!$C:$C,0))<0,"$"&TEXT(-INDEX('Input Data'!L:L,MATCH("702",'Input Data'!$C:$C,0))/INDEX('Input Data'!F:F,MATCH("702",'Input Data'!$C:$C,0)),"#,##0.00"),"nil"),"—") -> Face PSM: $1,055 | Incent: $245.65
D59: =IFERROR("Outgoings: $"&TEXT(INDEX('Input Data'!M:M,MATCH("701",'Input Data'!$C:$C,0))/INDEX('Input Data'!F:F,MATCH("701",'Input Data'!$C:$C,0)),"#,##0.00")&" psm | Net: $"&TEXT(INDEX('Input Data'!N:N,MATCH("701",'Input Data'!$C:$C,0)),"#,##0")&" pa","—") -> Outgoings: $65.56 psm | Net: $178,512 pa | S59: =IFERROR("Outgoings: $"&TEXT(INDEX('Input Data'!M:M,MATCH("702",'Input Data'!$C:$C,0))/INDEX('Input Data'!F:F,MATCH("702",'Input Data'!$C:$C,0)),"#,##0.00")&" psm | Net: $"&TEXT(INDEX('Input Data'!N:N,MATCH("702",'Input Data'!$C:$C,0)),"#,##0")&" pa","—") -> Outgoings: $42.83 psm | Net: $132,633 pa
D60: =IFERROR("Start: "&TEXT(INDEX('Input Data'!G:G,MATCH("701",'Input Data'!$C:$C,0)),"DD/MM/YY")&" → Expiry: "&TEXT(INDEX('Input Data'!H:H,MATCH("701",'Input Data'!$C:$C,0)),"DD/MM/YY"),"—") -> Start: 07/08/23 → Expiry: 06/08/27 | S60: =IFERROR("Start: "&TEXT(INDEX('Input Data'!G:G,MATCH("702",'Input Data'!$C:$C,0)),"DD/MM/YY")&" → Expiry: "&TEXT(INDEX('Input Data'!H:H,MATCH("702",'Input Data'!$C:$C,0)),"DD/MM/YY"),"—") -> Start: 01/06/24 → Expiry: 31/05/28
D61: =IFERROR(IF((INDEX('Input Data'!H:H,MATCH("701",'Input Data'!$C:$C,0))-TODAY())>0,TEXT((INDEX('Input Data'!H:H,MATCH("701",'Input Data'!$C:$C,0))-TODAY())/365.25,"0.0")&" yrs remaining","⚠ EXPIRED"),"—") -> 0.8 yrs remaining | S61: =IFERROR(IF((INDEX('Input Data'!H:H,MATCH("702",'Input Data'!$C:$C,0))-TODAY())>0,TEXT((INDEX('Input Data'!H:H,MATCH("702",'Input Data'!$C:$C,0))-TODAY())/365.25,"0.0")&" yrs remaining","⚠ EXPIRED"),"—") -> 1.6 yrs remaining
D62: ="" | S62: =""
D63: ="" | S63: =""
B65: Level 6 | C65: =SUMIF('Input Data'!B:B,"L06",'Input Data'!F:F) -> 378.2 | D65: =IFERROR(INDEX('Input Data'!D:D,MATCH("601",'Input Data'!$C:$C,0)),"VACANT") -> FULLCRM PTY LTD | T65: =IFERROR(INDEX('Input Data'!D:D,MATCH("602",'Input Data'!$C:$C,0)),"VACANT") -> INNOVIS
D66: ="Suite "&"601" -> Suite 601 | T66: ="Suite "&"602" -> Suite 602
D67: =IFERROR(TEXT(INDEX('Input Data'!F:F,MATCH("601",'Input Data'!$C:$C,0)),"#,##0.0")&" sqm"&IF(INDEX('Input Data'!O:O,MATCH("601",'Input Data'!$C:$C,0))>0," | "&TEXT(INDEX('Input Data'!O:O,MATCH("601",'Input Data'!$C:$C,0)),"0")&" car parks",""),"") -> 226.1 sqm | T67: =IFERROR(TEXT(INDEX('Input Data'!F:F,MATCH("602",'Input Data'!$C:$C,0)),"#,##0.0")&" sqm"&IF(INDEX('Input Data'!O:O,MATCH("602",'Input Data'!$C:$C,0))>0," | "&TEXT(INDEX('Input Data'!O:O,MATCH("602",'Input Data'!$C:$C,0)),"0")&" car parks",""),"") -> 152.1 sqm
D68: =IFERROR("Face PSM: $"&TEXT(INDEX('Input Data'!J:J,MATCH("601",'Input Data'!$C:$C,0)),"#,##0")&" | Incent: "&IF(INDEX('Input Data'!L:L,MATCH("601",'Input Data'!$C:$C,0))<0,"$"&TEXT(-INDEX('Input Data'!L:L,MATCH("601",'Input Data'!$C:$C,0))/INDEX('Input Data'!F:F,MATCH("601",'Input Data'!$C:$C,0)),"#,##0.00"),"nil"),"—") -> Face PSM: $1,251 | Incent: $140.40 | T68: =IFERROR("Face PSM: $"&TEXT(INDEX('Input Data'!J:J,MATCH("602",'Input Data'!$C:$C,0)),"#,##0")&" | Incent: "&IF(INDEX('Input Data'!L:L,MATCH("602",'Input Data'!$C:$C,0))<0,"$"&TEXT(-INDEX('Input Data'!L:L,MATCH("602",'Input Data'!$C:$C,0))/INDEX('Input Data'!F:F,MATCH("602",'Input Data'!$C:$C,0)),"#,##0.00"),"nil"),"—") -> Face PSM: $1,090 | Incent: $196.20
D69: =IFERROR("Outgoings: $"&TEXT(INDEX('Input Data'!M:M,MATCH("601",'Input Data'!$C:$C,0))/INDEX('Input Data'!F:F,MATCH("601",'Input Data'!$C:$C,0)),"#,##0.00")&" psm | Net: $"&TEXT(INDEX('Input Data'!N:N,MATCH("601",'Input Data'!$C:$C,0)),"#,##0")&" pa","—") -> Outgoings: $61.03 psm | Net: $251,184 pa | T69: =IFERROR("Outgoings: $"&TEXT(INDEX('Input Data'!M:M,MATCH("602",'Input Data'!$C:$C,0))/INDEX('Input Data'!F:F,MATCH("602",'Input Data'!$C:$C,0)),"#,##0.00")&" psm | Net: $"&TEXT(INDEX('Input Data'!N:N,MATCH("602",'Input Data'!$C:$C,0)),"#,##0")&" pa","—") -> Outgoings: $0.00 psm | Net: $135,947 pa
D70: =IFERROR("Start: "&TEXT(INDEX('Input Data'!G:G,MATCH("601",'Input Data'!$C:$C,0)),"DD/MM/YY")&" → Expiry: "&TEXT(INDEX('Input Data'!H:H,MATCH("601",'Input Data'!$C:$C,0)),"DD/MM/YY"),"—") -> Start: 01/12/21 → Expiry: 31/01/27 | T70: =IFERROR("Start: "&TEXT(INDEX('Input Data'!G:G,MATCH("602",'Input Data'!$C:$C,0)),"DD/MM/YY")&" → Expiry: "&TEXT(INDEX('Input Data'!H:H,MATCH("602",'Input Data'!$C:$C,0)),"DD/MM/YY"),"—") -> Start: 01/11/26 → Expiry: 30/10/29
D71: =IFERROR(IF((INDEX('Input Data'!H:H,MATCH("601",'Input Data'!$C:$C,0))-TODAY())>0,TEXT((INDEX('Input Data'!H:H,MATCH("601",'Input Data'!$C:$C,0))-TODAY())/365.25,"0.0")&" yrs remaining","⚠ EXPIRED"),"—") -> 0.3 yrs remaining | T71: =IFERROR(IF((INDEX('Input Data'!H:H,MATCH("602",'Input Data'!$C:$C,0))-TODAY())>0,TEXT((INDEX('Input Data'!H:H,MATCH("602",'Input Data'!$C:$C,0))-TODAY())/365.25,"0.0")&" yrs remaining","⚠ EXPIRED"),"—") -> 3.0 yrs remaining
D72: ="" | T72: =""
D73: ="" | T73: =""
B75: Level 5 | C75: =SUMIF('Input Data'!B:B,"L05",'Input Data'!F:F) -> 376.1 | D75: =IFERROR(INDEX('Input Data'!D:D,MATCH("501",'Input Data'!$C:$C,0)),"VACANT") -> MONTGOMERY INVESTMENT | S75: =IFERROR(INDEX('Input Data'!D:D,MATCH("502",'Input Data'!$C:$C,0)),"VACANT") -> THREAT DEFENCE
D76: ="Suite "&"501" -> Suite 501 | S76: ="Suite "&"502" -> Suite 502
D77: =IFERROR(TEXT(INDEX('Input Data'!F:F,MATCH("501",'Input Data'!$C:$C,0)),"#,##0.0")&" sqm"&IF(INDEX('Input Data'!O:O,MATCH("501",'Input Data'!$C:$C,0))>0," | "&TEXT(INDEX('Input Data'!O:O,MATCH("501",'Input Data'!$C:$C,0)),"0")&" car parks",""),"") -> 212.3 sqm | S77: =IFERROR(TEXT(INDEX('Input Data'!F:F,MATCH("502",'Input Data'!$C:$C,0)),"#,##0.0")&" sqm"&IF(INDEX('Input Data'!O:O,MATCH("502",'Input Data'!$C:$C,0))>0," | "&TEXT(INDEX('Input Data'!O:O,MATCH("502",'Input Data'!$C:$C,0)),"0")&" car parks",""),"") -> 163.8 sqm
D78: =IFERROR("Face PSM: $"&TEXT(INDEX('Input Data'!J:J,MATCH("501",'Input Data'!$C:$C,0)),"#,##0")&" | Incent: "&IF(INDEX('Input Data'!L:L,MATCH("501",'Input Data'!$C:$C,0))<0,"$"&TEXT(-INDEX('Input Data'!L:L,MATCH("501",'Input Data'!$C:$C,0))/INDEX('Input Data'!F:F,MATCH("501",'Input Data'!$C:$C,0)),"#,##0.00"),"nil"),"—") -> Face PSM: $1,341 | Incent: $232.51 | S78: =IFERROR("Face PSM: $"&TEXT(INDEX('Input Data'!J:J,MATCH("502",'Input Data'!$C:$C,0)),"#,##0")&" | Incent: "&IF(INDEX('Input Data'!L:L,MATCH("502",'Input Data'!$C:$C,0))<0,"$"&TEXT(-INDEX('Input Data'!L:L,MATCH("502",'Input Data'!$C:$C,0))/INDEX('Input Data'!F:F,MATCH("502",'Input Data'!$C:$C,0)),"#,##0.00"),"nil"),"—") -> Face PSM: $1,055 | Incent: $254.80
D79: =IFERROR("Outgoings: $"&TEXT(INDEX('Input Data'!M:M,MATCH("501",'Input Data'!$C:$C,0))/INDEX('Input Data'!F:F,MATCH("501",'Input Data'!$C:$C,0)),"#,##0.00")&" psm | Net: $"&TEXT(INDEX('Input Data'!N:N,MATCH("501",'Input Data'!$C:$C,0)),"#,##0")&" pa","—") -> Outgoings: $46.63 psm | Net: $235,383 pa | S79: =IFERROR("Outgoings: $"&TEXT(INDEX('Input Data'!M:M,MATCH("502",'Input Data'!$C:$C,0))/INDEX('Input Data'!F:F,MATCH("502",'Input Data'!$C:$C,0)),"#,##0.00")&" psm | Net: $"&TEXT(INDEX('Input Data'!N:N,MATCH("502",'Input Data'!$C:$C,0)),"#,##0")&" pa","—") -> Outgoings: $43.59 psm | Net: $131,053 pa
D80: =IFERROR("Start: "&TEXT(INDEX('Input Data'!G:G,MATCH("501",'Input Data'!$C:$C,0)),"DD/MM/YY")&" → Expiry: "&TEXT(INDEX('Input Data'!H:H,MATCH("501",'Input Data'!$C:$C,0)),"DD/MM/YY"),"—") -> Start: 01/11/19 → Expiry: 31/10/27 | S80: =IFERROR("Start: "&TEXT(INDEX('Input Data'!G:G,MATCH("502",'Input Data'!$C:$C,0)),"DD/MM/YY")&" → Expiry: "&TEXT(INDEX('Input Data'!H:H,MATCH("502",'Input Data'!$C:$C,0)),"DD/MM/YY"),"—") -> Start: 01/07/24 → Expiry: 30/06/27
D81: =IFERROR(IF((INDEX('Input Data'!H:H,MATCH("501",'Input Data'!$C:$C,0))-TODAY())>0,TEXT((INDEX('Input Data'!H:H,MATCH("501",'Input Data'!$C:$C,0))-TODAY())/365.25,"0.0")&" yrs remaining","⚠ EXPIRED"),"—") -> 1.0 yrs remaining | S81: =IFERROR(IF((INDEX('Input Data'!H:H,MATCH("502",'Input Data'!$C:$C,0))-TODAY())>0,TEXT((INDEX('Input Data'!H:H,MATCH("502",'Input Data'!$C:$C,0))-TODAY())/365.25,"0.0")&" yrs remaining","⚠ EXPIRED"),"—") -> 0.7 yrs remaining
D82: ="" | S82: =""
D83: ="" | S83: =""
B85: Level 4 | C85: =SUMIF('Input Data'!B:B,"L04",'Input Data'!F:F) -> 359.7 | D85: =IFERROR(INDEX('Input Data'!D:D,MATCH("401",'Input Data'!$C:$C,0)),"VACANT") -> B-W INTERNATIONAL AUSTRALIA PTY LTD | T85: =IFERROR(INDEX('Input Data'!D:D,MATCH("402",'Input Data'!$C:$C,0)),"VACANT") -> MP TRAVEL PTY LTD
D86: ="Suite "&"401" -> Suite 401 | T86: ="Suite "&"402" -> Suite 402
D87: =IFERROR(TEXT(INDEX('Input Data'!F:F,MATCH("401",'Input Data'!$C:$C,0)),"#,##0.0")&" sqm"&IF(INDEX('Input Data'!O:O,MATCH("401",'Input Data'!$C:$C,0))>0," | "&TEXT(INDEX('Input Data'!O:O,MATCH("401",'Input Data'!$C:$C,0)),"0")&" car parks",""),"") -> 214.1 sqm | T87: =IFERROR(TEXT(INDEX('Input Data'!F:F,MATCH("402",'Input Data'!$C:$C,0)),"#,##0.0")&" sqm"&IF(INDEX('Input Data'!O:O,MATCH("402",'Input Data'!$C:$C,0))>0," | "&TEXT(INDEX('Input Data'!O:O,MATCH("402",'Input Data'!$C:$C,0)),"0")&" car parks",""),"") -> 145.6 sqm
D88: =IFERROR("Face PSM: $"&TEXT(INDEX('Input Data'!J:J,MATCH("401",'Input Data'!$C:$C,0)),"#,##0")&" | Incent: "&IF(INDEX('Input Data'!L:L,MATCH("401",'Input Data'!$C:$C,0))<0,"$"&TEXT(-INDEX('Input Data'!L:L,MATCH("401",'Input Data'!$C:$C,0))/INDEX('Input Data'!F:F,MATCH("401",'Input Data'!$C:$C,0)),"#,##0.00"),"nil"),"—") -> Face PSM: $1,136 | Incent: $253.17 | T88: =IFERROR("Face PSM: $"&TEXT(INDEX('Input Data'!J:J,MATCH("402",'Input Data'!$C:$C,0)),"#,##0")&" | Incent: "&IF(INDEX('Input Data'!L:L,MATCH("402",'Input Data'!$C:$C,0))<0,"$"&TEXT(-INDEX('Input Data'!L:L,MATCH("402",'Input Data'!$C:$C,0))/INDEX('Input Data'!F:F,MATCH("402",'Input Data'!$C:$C,0)),"#,##0.00"),"nil"),"—") -> Face PSM: $1,038 | Incent: $121.40
D89: =IFERROR("Outgoings: $"&TEXT(INDEX('Input Data'!M:M,MATCH("401",'Input Data'!$C:$C,0))/INDEX('Input Data'!F:F,MATCH("401",'Input Data'!$C:$C,0)),"#,##0.00")&" psm | Net: $"&TEXT(INDEX('Input Data'!N:N,MATCH("401",'Input Data'!$C:$C,0)),"#,##0")&" pa","—") -> Outgoings: $40.64 psm | Net: $188,930 pa | T89: =IFERROR("Outgoings: $"&TEXT(INDEX('Input Data'!M:M,MATCH("402",'Input Data'!$C:$C,0))/INDEX('Input Data'!F:F,MATCH("402",'Input Data'!$C:$C,0)),"#,##0.00")&" psm | Net: $"&TEXT(INDEX('Input Data'!N:N,MATCH("402",'Input Data'!$C:$C,0)),"#,##0")&" pa","—") -> Outgoings: $41.21 psm | Net: $133,384 pa
D90: =IFERROR("Start: "&TEXT(INDEX('Input Data'!G:G,MATCH("401",'Input Data'!$C:$C,0)),"DD/MM/YY")&" → Expiry: "&TEXT(INDEX('Input Data'!H:H,MATCH("401",'Input Data'!$C:$C,0)),"DD/MM/YY"),"—") -> Start: 01/03/24 → Expiry: 28/02/29 | T90: =IFERROR("Start: "&TEXT(INDEX('Input Data'!G:G,MATCH("402",'Input Data'!$C:$C,0)),"DD/MM/YY")&" → Expiry: "&TEXT(INDEX('Input Data'!H:H,MATCH("402",'Input Data'!$C:$C,0)),"DD/MM/YY"),"—") -> Start: 01/01/25 → Expiry: 31/12/29
D91: =IFERROR(IF((INDEX('Input Data'!H:H,MATCH("401",'Input Data'!$C:$C,0))-TODAY())>0,TEXT((INDEX('Input Data'!H:H,MATCH("401",'Input Data'!$C:$C,0))-TODAY())/365.25,"0.0")&" yrs remaining","⚠ EXPIRED"),"—") -> 2.4 yrs remaining | T91: =IFERROR(IF((INDEX('Input Data'!H:H,MATCH("402",'Input Data'!$C:$C,0))-TODAY())>0,TEXT((INDEX('Input Data'!H:H,MATCH("402",'Input Data'!$C:$C,0))-TODAY())/365.25,"0.0")&" yrs remaining","⚠ EXPIRED"),"—") -> 3.2 yrs remaining
D92: ="" | T92: =""
D93: ="" | T93: =""
B95: Level 3 | C95: =SUMIF('Input Data'!B:B,"L03",'Input Data'!F:F) -> 357.6 | D95: =IFERROR(INDEX('Input Data'!D:D,MATCH("301&2",'Input Data'!$C:$C,0)),"VACANT") -> IPM RESIDENTIAL PTY LTD | P95: =IFERROR(INDEX('Input Data'!D:D,MATCH("303&4",'Input Data'!$C:$C,0)),"VACANT") -> BROADRIDGE (AUSTRALIA) PTY LTD
D96: ="Suite "&"301&2" -> Suite 301&2 | P96: ="Suite "&"303&4" -> Suite 303&4
D97: =IFERROR(TEXT(INDEX('Input Data'!F:F,MATCH("301&2",'Input Data'!$C:$C,0)),"#,##0.0")&" sqm"&IF(INDEX('Input Data'!O:O,MATCH("301&2",'Input Data'!$C:$C,0))>0," | "&TEXT(INDEX('Input Data'!O:O,MATCH("301&2",'Input Data'!$C:$C,0)),"0")&" car parks",""),"") -> 164.2 sqm | 2 car parks | P97: =IFERROR(TEXT(INDEX('Input Data'!F:F,MATCH("303&4",'Input Data'!$C:$C,0)),"#,##0.0")&" sqm"&IF(INDEX('Input Data'!O:O,MATCH("303&4",'Input Data'!$C:$C,0))>0," | "&TEXT(INDEX('Input Data'!O:O,MATCH("303&4",'Input Data'!$C:$C,0)),"0")&" car parks",""),"") -> 193.4 sqm
D98: =IFERROR("Face PSM: $"&TEXT(INDEX('Input Data'!J:J,MATCH("301&2",'Input Data'!$C:$C,0)),"#,##0")&" | Incent: "&IF(INDEX('Input Data'!L:L,MATCH("301&2",'Input Data'!$C:$C,0))<0,"$"&TEXT(-INDEX('Input Data'!L:L,MATCH("301&2",'Input Data'!$C:$C,0))/INDEX('Input Data'!F:F,MATCH("301&2",'Input Data'!$C:$C,0)),"#,##0.00"),"nil"),"—") -> Face PSM: $1,217 | Incent: $94.50 | P98: =IFERROR("Face PSM: $"&TEXT(INDEX('Input Data'!J:J,MATCH("303&4",'Input Data'!$C:$C,0)),"#,##0")&" | Incent: "&IF(INDEX('Input Data'!L:L,MATCH("303&4",'Input Data'!$C:$C,0))<0,"$"&TEXT(-INDEX('Input Data'!L:L,MATCH("303&4",'Input Data'!$C:$C,0))/INDEX('Input Data'!F:F,MATCH("303&4",'Input Data'!$C:$C,0)),"#,##0.00"),"nil"),"—") -> Face PSM: $934 | Incent: $108.39
D99: =IFERROR("Outgoings: $"&TEXT(INDEX('Input Data'!M:M,MATCH("301&2",'Input Data'!$C:$C,0))/INDEX('Input Data'!F:F,MATCH("301&2",'Input Data'!$C:$C,0)),"#,##0.00")&" psm | Net: $"&TEXT(INDEX('Input Data'!N:N,MATCH("301&2",'Input Data'!$C:$C,0)),"#,##0")&" pa","—") -> Outgoings: $60.29 psm | Net: $184,245 pa | P99: =IFERROR("Outgoings: $"&TEXT(INDEX('Input Data'!M:M,MATCH("303&4",'Input Data'!$C:$C,0))/INDEX('Input Data'!F:F,MATCH("303&4",'Input Data'!$C:$C,0)),"#,##0.00")&" psm | Net: $"&TEXT(INDEX('Input Data'!N:N,MATCH("303&4",'Input Data'!$C:$C,0)),"#,##0")&" pa","—") -> Outgoings: $32.57 psm | Net: $159,625 pa
