Workbook

Sheet Cover
B3: GOLDBERG FAMILY OFFICE
B9: 1 Elizabeth Plaza
B16: Asset Summary — Tenancy Schedule
B18: As at 29 June 2026
B27: — | C27: Prepared by jake goldberg

Sheet Last Updated
A1: 1 ELIZABETH PLAZA, NORTH SYDNEY — TRACKER VERSION CONTROL
A2: Update Input Data tab each month from the tenancy schedule. All other tabs recalculate automatically.
B4: CURRENT TRACKER STATUS
B5: Property | D5: 1 Elizabeth Plaza, North Sydney
B6: Current As At | D6: 46295
B7: Total NLA | D7: 8940.9
B8: Occupancy | D8: ='Input Data'!B53 -> 0
B9: Vacancy | D9: ='Input Data'!B54 -> 0
B10: WALE by NLA | D10: ='Input Data'!V53 -> 0
B11: Gross Income PA | D11: ='Input Data'!K53 -> 0
B12: Occupied Suites | D12: 17 | 4 Vacant
B13: Car Parks | D13: Monthly + individual licences
B14: Last Updated By
B15: Next Update Due
B16: Notes / Changes
B18: UPDATE LOG
B19: Date Updated | C19: Updated By | D19: As At Date | E19: Occupancy | F19: WALE (NLA) | G19: Key Changes
B20: 46142 | D20: 30/04/2026 | E20: 79.74% | F20: ~4.0 yrs | G20: Initial build from April 2026 tenancy schedule
B21: 46296 | C21: Jake | D21: 30/09/2026 | E21: ='Input Data'!K26 -> 0.91197754 | F21: ='Input Data'!V25 -> 5.9575633 | G21: Refreshed from Sept26 TS (dated 01/10/26): FIXED reviews applied for Sydney Smiletree, Keeping Company, Elekta, Can Too Foundation, Pitt & Sherry, Vanderlande (all PSM ups); outgoings/cleaning refreshed across most tenants. Asterx (0503) lease dates corrected (01/07/24–30/06/29, was 01/06/24–31/05/29) plus abatement/car park/cleaning/outgoings now confirmed. IMPORTANT correction: Smile Partners (0902) and Hulsbosch Design (1201) had swapped NLA/financials in this file — 0902 is actually 344.5 sqm, 1201 is actually 251 sqm — now fixed, cross-checked against the Fitout Costs register. Sungrow L7 (0701/0702) combined rent reset to $925,326 pa total, an 82% jump — flagged in row notes for verification. Caladas Constructions renamed to correct spelling 'Caldas', lease start corrected to 01/07/26. Luxasia (1101) entered as occupied per Jake's instruction: outgoings $9,728.72 pa, cleaning $4,015.80 pa, fitout contribution $369,812.50 (added to Fitout Costs register), abatement $192,787.50 over term (Yr1-3 $25,705 pa now reflected; Yr4-5 $57,836.25 pa needs manual update at the Yr4 anniversary). New ROOF1 (Pipe Networks/Vocus) comms licence ($2,500 pa) identified on the TS but NOT added to this table (zero NLA, would need a new row/range change) — flagged for Jake's decision on where to capture it. Note: TS's own vacancy count still shows 1101 as vacant (lease not yet in the PM system) — this file now diverges from that by design. Cross-tab sweep: corrected the same Smile Partners/Hulsbosch swap in the Leasing Activity log; moved Luxasia out of the 'vacant suites' sections in Expiry Profile/Leases into its proper occupied row; updated Make Good Obligations, Dashboard (critical dates, suite count, header), Market Rents (hardcoded NLA), Leasing Fees (vacancy register — removed 6.01/11.01/11.02, now leased) and Stack Plan (roof tenant name corrected to Pipe Networks/Vocus, portfolio summary refreshed) so all tabs now agree with Input Data.
B39: MONTHLY UPDATE CHECKLIST
B40: 1 | C40: Download tenancy schedule from property management system (Strata/SHP2)
B41: 2 | C41: Update Input Data — check rent, dates, PSM, abatement, outgoings per suite
B42: 3 | C42: Update Market Rents section in Dashboard if market has moved
B43: 4 | C43: Check Dashboard KPIs reconcile with tenancy schedule totals
B44: 5 | C44: Update Leasing Activity tab with new deals, HOAs, renewals
B45: 6 | C45: Update Fitout Costs with any new capex approved or completed
B46: 7 | C46: Update Leasing Fees with current vacancy and asking rents
B47: 8 | C47: Update Rental Analysis for any new deals being analysed
B48: 9 | C48: Record update in Log above — date, occupancy, WALE, key changes
B49: 10 | C49: Save as 1ElizabethPlaza_[MonthYY].xlsx

Sheet Input Data
A1: 1 ELIZABETH PLAZA, NORTH SYDNEY — TENANCY SCHEDULE INPUT | As at 30.9.2026
A2: Suite ID | B2: Floor | C2: Suite # | D2: Tenant Name | E2: Trading Name | F2: NLA (sqm) | G2: Lease Start | H2: Lease Expiry | I2: Term (Yrs) | J2: Face PSM ($) | K2: Office Rent PA ($) | L2: Abatement PA ($) | M2: Outgoings PA ($) | N2: Cleaning PA ($) | O2: Car Park Rent PA ($) | P2: Car Park Levy PA ($) | Q2: Net Effective PA ($) | R2: Car Parks | S2: Review Type | T2: Next Review | U2: Lease Type | V2: WALE (yrs) | W2: Wtd NLA | X2: Market PSM ($) | Y2: Var to Mkt ($) | Z2: Var to Mkt (%) | AA2: Bank Guarantee ($) | AB2: Notes | AC2: Status | AD2: Expiry Source (Enter Here) | AE2: PSM Source | AF2: Display Name
A3: 0301 | B3: L03 | C3: 3.01 | D3: Sydney Smiletree Pty Ltd | E3: The Trustee for Sydney Smiletree Unit Trust | F3: 107.7 | G3: 44013 | H3: 47118 | I3: 8.5 | J3: 1395.94 | K3: =IF(J3>0,J3*F3,0) -> 150342.74 | L3: 0 | M3: 9156 | N3: 0 | O3: 9032.64 | P3: 3030 | Q3: =K3+L3+M3+N3+O3+P3 -> 171561.38 | R3: 1 | S3: FIXED 4% | T3: 46569 | U3: Net | V3: =IFERROR(MAX((H3-TODAY())/365.25,0),0) -> 2.2094456 | W3: =F3*V3 -> 237.95729 | X3: 950 | Y3: =IF(J3>0,J3-X3,0) -> 445.94 | Z3: =IFERROR(IF(J3>0,(J3-X3)/X3,0),0) -> 0.46941053 | AA3: 86814.00 | AB3: Option: 5 yrs. BG: $86,814. Car Space 16. | AC3: =IF(AD3="","VACANT",IF(AD3<TODAY(),"EXPIRED","ACTIVE")) -> ACTIVE | AD3: 47118 | AE3: 1395.94 | AF3: Sydney Smiletree
A4: 0302 | B4: L03 | C4: 3.02 | D4: Fitness First Australia Pty Limited | E4: Fitness First Australia Pty Limited | F4: 795.5 | G4: 44378 | H4: 48029 | I4: 10 | J4: 855.7 | K4: =IF(J4>0,J4*F4,0) -> 680709.35 | L4: 0 | M4: 0 | N4: 0 | O4: 0 | P4: 0 | Q4: =K4+L4+M4+N4+O4+P4 -> 680709.35 | R4: 0 | S4: FIXED 4% | T4: 46204 | U4: Gross | V4: =IFERROR(MAX((H4-TODAY())/365.25,0),0) -> 4.7036277 | W4: =F4*V4 -> 3741.7358 | X4: 870 | Y4: =IF(J4>0,J4-X4,0) -> -14.3 | Z4: =IFERROR(IF(J4>0,(J4-X4)/X4,0),0) -> -0.016436782 | AA4: 300000.40 | AB4: Gross lease - Nil outgoings. Includes direct AC recovery $108.09 psm. Option: 5 yrs (01/07/26-30/06/31). | AC4: =IF(AD4="","VACANT",IF(AD4<TODAY(),"EXPIRED","ACTIVE")) -> ACTIVE | AD4: 48029 | AE4: 855.7 | AF4: Fitness First (L3)
A5: 0401 | B5: L04 | C5: 4.01 | D5: Fitness First Australia Pty Limited | E5: Fitness First Australia Pty Limited | F5: 1047 | G5: 44378 | H5: 48029 | I5: 10 | J5: 855.7 | K5: =IF(J5>0,J5*F5,0) -> 895917.9 | L5: 0 | M5: 0 | N5: 0 | O5: 10160.4 | P5: 0 | Q5: =K5+L5+M5+N5+O5+P5 -> 906078.3 | R5: 1 | S5: FIXED 4% | T5: 46204 | U5: Gross | V5: =IFERROR(MAX((H5-TODAY())/365.25,0),0) -> 4.7036277 | W5: =F5*V5 -> 4924.6982 | X5: 870 | Y5: =IF(J5>0,J5-X5,0) -> -14.3 | Z5: =IFERROR(IF(J5>0,(J5-X5)/X5,0),0) -> -0.016436782 | AA5: 300000.40 | AB5: Gross lease - Nil outgoings. 1 car space. | AC5: =IF(AD5="","VACANT",IF(AD5<TODAY(),"EXPIRED","ACTIVE")) -> ACTIVE | AD5: 48029 | AE5: 855.7 | AF5: Fitness First (L4)
A6: 0501 | B6: L05 | C6: 5.01 | D6: Fitness First Australia Pty Limited | E6: Fitness First North Sydney | F6: 437.1 | G6: 44378 | H6: 48029 | I6: 10 | J6: 855.7 | K6: =IF(J6>0,J6*F6,0) -> 374026.47 | L6: 0 | M6: 0 | N6: 0 | O6: 0 | P6: 3030 | Q6: =K6+L6+M6+N6+O6+P6 -> 377056.47 | R6: 0 | S6: FIXED 4% | T6: 46204 | U6: Gross | V6: =IFERROR(MAX((H6-TODAY())/365.25,0),0) -> 4.7036277 | W6: =F6*V6 -> 2055.9556 | X6: 870 | Y6: =IF(J6>0,J6-X6,0) -> -14.3 | Z6: =IFERROR(IF(J6>0,(J6-X6)/X6,0),0) -> -0.016436782 | AA6: 300000.40 | AB6: Gross lease - Nil outgoings. Car park levy only. | AC6: =IF(AD6="","VACANT",IF(AD6<TODAY(),"EXPIRED","ACTIVE")) -> ACTIVE | AD6: 48029 | AE6: 855.7 | AF6: Fitness First N. Sydney
A7: 0503 | B7: L05 | C7: 5.03 | D7: Asterx Pty Ltd | E7: Asterx Pty Ltd (MediRecords) | F7: 229.8 | G7: 45474 | H7: 47299 | I7: 5 | J7: 985.53 | K7: =IF(J7>0,J7*F7,0) -> 226474.79 | L7: -46511.52 | M7: 10521.96 | N7: 3805.44 | O7: 7712.76 | P7: 3030 | Q7: =K7+L7+M7+N7+O7+P7 -> 205033.43 | R7: 1 | S7: FIXED 3.5% | T7: 46569 | U7: Semi-Gross | V7: =IFERROR(MAX((H7-TODAY())/365.25,0),0) -> 2.7049966 | W7: =F7*V7 -> 621.60821 | X7: 950 | Y7: =IF(J7>0,J7-X7,0) -> 35.53 | Z7: =IFERROR(IF(J7>0,(J7-X7)/X7,0),0) -> 0.0374 | AA7: 135234.00 | AB7: Semi-gross base year FY24. BG: $135,234. 1 car space. Lease start/expiry corrected to 01/07/24–30/06/29 per Sept26 TS (previously recorded as 01/06/24–31/05/29). Abatement, car park rent, cleaning and outgoings all confirmed/updated per Sept26 TS. | AC7: =IF(AD7="","VACANT",IF(AD7<TODAY(),"EXPIRED","ACTIVE")) -> ACTIVE | AD7: 47299 | AE7: 985.53 | AF7: Asterx (MediRecords)
A8: 0504 | B8: L05 | C8: 5.04 | D8: Auctionsplus Pty Ltd | E8: Auctionsplus Pty Ltd | F8: 413.5 | G8: 45352 | H8: 47177 | I8: 5 | J8: 1005.89 | K8: =IF(J8>0,J8*F8,0) -> 415935.52 | L8: -104594.82 | M8: 40068.6 | N8: 6847.56 | O8: 5381.04 | P8: 3030 | Q8: =K8+L8+M8+N8+O8+P8 -> 366667.89 | R8: 1 | S8: FIXED 4% | T8: 46447 | U8: Semi-Gross | V8: =IFERROR(MAX((H8-TODAY())/365.25,0),0) -> 2.3709788 | W8: =F8*V8 -> 980.39973 | X8: 990 | Y8: =IF(J8>0,J8-X8,0) -> 15.89 | Z8: =IFERROR(IF(J8>0,(J8-X8)/X8,0),0) -> 0.016050505 | AA8: 199187.44 | AB8: Semi-gross base year FY24 2.4%. BG equiv $199,187 incl GST. Incentive: fitout contribution $672,971. | AC8: =IF(AD8="","VACANT",IF(AD8<TODAY(),"EXPIRED","ACTIVE")) -> ACTIVE | AD8: 47177 | AE8: 1005.89 | AF8: Auctionsplus
A9: 0602 | B9: L06 | C9: 6.02 | D9: Sungrow Australia Group | E9: Sungrow Australia Group Pty Ltd | F9: 451.7 | G9: 45762 | H9: 47375 | I9: 4.4 | J9: 954.5 | K9: =IF(J9>0,J9*F9,0) -> 431147.65 | L9: -211720.82 | M9: 45907.32 | N9: 7480.2 | O9: 7416 | P9: 3030 | Q9: =K9+L9+M9+N9+O9+P9 -> 283260.35 | R9: 1 | S9: FIXED 3.75% | T9: 46492 | U9: Semi-Gross | V9: =IFERROR(MAX((H9-TODAY())/365.25,0),0) -> 2.9130732 | W9: =F9*V9 -> 1315.8352 | X9: 955 | Y9: =IF(J9>0,J9-X9,0) -> -0.5 | Z9: =IFERROR(IF(J9>0,(J9-X9)/X9,0),0) -> -0.00052356021 | AA9: 291050.49 | AB9: BG: $291,050 (6 mths last yr gross rent). Incentive: 50% of rent as abatement. Make Good: $200 psm. | AC9: =IF(AD9="","VACANT",IF(AD9<TODAY(),"EXPIRED","ACTIVE")) -> ACTIVE | AD9: 47375 | AE9: 954.5 | AF9: Sungrow (L6)
A10: 0603 | B10: L06 | C10: 6.03 | D10: Keeping Company Pty Ltd | E10: Keeping Company Pty Ltd | F10: 189.4 | G10: 44713 | H10: 46538 | I10: 5 | J10: 1055.72 | K10: =IF(J10>0,J10*F10,0) -> 199953.37 | L10: -23525.37 | M10: 19249.32 | N10: 3136.44 | O10: 14183.28 | P10: 6060 | Q10: =K10+L10+M10+N10+O10+P10 -> 219057.04 | R10: 2 | S10: FIXED 3.5% | T10: 46539 | U10: Semi-Gross | V10: =IFERROR(MAX((H10-TODAY())/365.25,0),0) -> 0.62149213 | W10: =F10*V10 -> 117.71061 | X10: 990 | Y10: =IF(J10>0,J10-X10,0) -> 65.72 | Z10: =IFERROR(IF(J10>0,(J10-X10)/X10,0),0) -> 0.066383838 | AA10: 110738.92 | AB10: 2 car spaces. BG: $110,739. Incentive: fitout $177,810 + abatement. Base year FY2021. | AC10: =IF(AD10="","VACANT",IF(AD10<TODAY(),"EXPIRED","ACTIVE")) -> ACTIVE | AD10: 46538 | AE10: 1055.72 | AF10: Keeping Company
A11: 0604 | B11: L06 | C11: 6.04 | D11: Elekta Pty Limited | E11: Elekta Pty Limited | F11: 267.9 | G11: 45870 | H11: 48426 | I11: 7 | J11: 954.5 | K11: =IF(J11>0,J11*F11,0) -> 255710.55 | L11: -98587.2 | M11: 6957 | N11: 4436.4 | O11: 3030 | P11: 0 | Q11: =K11+L11+M11+N11+O11+P11 -> 171546.75 | R11: 1 | S11: FIXED (3.75%) | T11: 46600 | U11: Semi-Gross | V11: =IFERROR(MAX((H11-TODAY())/365.25,0),0) -> 5.7905544 | W11: =F11*V11 -> 1551.2895 | X11: 955 | Y11: =IF(J11>0,J11-X11,0) -> -0.5 | Z11: =IFERROR(IF(J11>0,(J11-X11)/X11,0),0) -> -0.00052356021 | AA11: 210969.39 | AB11: New lease 01/08/25. BG: $210,969. Abatement: $2,576 psm over term. Outgoings 2.95% base FY2025. | AC11: =IF(AD11="","VACANT",IF(AD11<TODAY(),"EXPIRED","ACTIVE")) -> ACTIVE | AD11: 48426 | AE11: 954.5 | AF11: Elekta
A12: 0701 | B12: L07 | C12: 7.01 | D12: Sungrow Australia Group | E12: Sungrow Australia Group Pty Ltd | F12: 484.1 | G12: 45184 | H12: 47375 | I12: 6 | J12: 1911.44 | K12: =IF(J12>0,J12*F12,0) -> 925328.1 | L12: -319000.32 | M12: 49200.48 | N12: 14069.4 | O12: 18074.64 | P12: 6060 | Q12: =K12+L12+M12+N12+O12+P12 -> 693732.3 | R12: 2 | S12: FIXED 3.75% | T12: 46645 | U12: Semi-Gross | V12: =IFERROR(MAX((H12-TODAY())/365.25,0),0) -> 2.9130732 | W12: =F12*V12 -> 1410.2188 | X12: 1020 | Y12: =IF(J12>0,J12-X12,0) -> 891.44 | Z12: =IFERROR(IF(J12>0,(J12-X12)/X12,0),0) -> 0.87396078 | AA12: 536314.24 | AB12: Tandem bays x2. BG: $536,314. Base year FY2021 9.41%. Sept26 TS shows office rent reset to a combined total of $925,326 pa across 7.01+7.02 (849.6 sqm) — PSM above is a blended rate ($925,326/484.1 sqm) to keep this in the existing K=PSM×NLA formula; not a genuine per-sqm market rate, so Var to Mkt for this row is not meaningful. This is an 82% jump on the prior $508k combined rent — flagging for verification against the lease before relying on it. | AC12: =IF(AD12="","VACANT",IF(AD12<TODAY(),"EXPIRED","ACTIVE")) -> ACTIVE | AD12: 47375 | AE12: 1911.44 | AF12: Sungrow (L7 Main)
A13: 0702 | B13: L07 | C13: 7.02 | D13: Sungrow Australia Group | E13: Additional Space (Sungrow) | F13: 365.5 | G13: 45184 | H13: 47375 | I13: 6 | J13: 0 | K13: =IF(J13>0,J13*F13,0) -> 0 | L13: 0 | M13: 37146.72 | N13: 0 | O13: 0 | P13: 0 | Q13: =K13+L13+M13+N13+O13+P13 -> 37146.72 | R13: 0 | S13: FIXED 3.75% | T13: 46645 | U13: Semi-Gross | V13: =IFERROR(MAX((H13-TODAY())/365.25,0),0) -> 2.9130732 | W13: =F13*V13 -> 1064.7283 | X13: 1020 | Y13: =IF(J13>0,J13-X13,0) -> 0 | Z13: =IFERROR(IF(J13>0,(J13-X13)/X13,0),0) -> 0 | AA13: 0 | AB13: Additional space - office rent included in Suite 7.01 totals (same lease). Sept26 TS now shows a separate Outgoings Recoverable charge of $37,146.72 pa billed against this suite. | AC13: =IF(AD13="","VACANT",IF(AD13<TODAY(),"EXPIRED","ACTIVE")) -> ACTIVE | AD13: 47375 | AE13: 0 | AF13: Sungrow (L7 Add.)
A14: 0801 | B14: L08 | C14: 8.01 | D14: Vanderlande Industries Australia Pty Ltd | E14: Vanderlande Industries Australia Pty Ltd | F14: 686.7 | G14: 43282 | H14: 46934 | I14: 10 | J14: 1029.25 | K14: =IF(J14>0,J14*F14,0) -> 706785.98 | L14: -219915.72 | M14: 78859.8 | N14: 11371.8 | O14: 0 | P14: 0 | Q14: =K14+L14+M14+N14+O14+P14 -> 577101.86 | R14: 0 | S14: FIXED 4% | T14: 46569 | U14: Semi-Gross | V14: =IFERROR(MAX((H14-TODAY())/365.25,0),0) -> 1.705681 | W14: =F14*V14 -> 1171.2912 | X14: 990 | Y14: =IF(J14>0,J14-X14,0) -> 39.25 | Z14: =IFERROR(IF(J14>0,(J14-X14)/X14,0),0) -> 0.039646465 | AA14: 288500.00 | AB14: Base year FY2015 7.57%. BG: $288,500. Make good: full open plan. Cleaning $15 psm. | AC14: =IF(AD14="","VACANT",IF(AD14<TODAY(),"EXPIRED","ACTIVE")) -> ACTIVE | AD14: 46934 | AE14: 1029.25 | AF14: Vanderlande Industries
... A19: 1202 | B19: L12 | C19: 12.02 | D19: AEI Insurance Group Pty Ltd | E19: AEI Insurance Group Pty Ltd | F19: 536 | G19: 45642 | H19: 47832 | I19: 6 | J19: 988 | K19: =IF(J19>0,J19*F19,0) -> 529568 | L19: -51200.76 | M19: 24542.16 | N19: 8876.16 | O19: 96647.64 | P19: 30300 | Q19: =K19+L19+M19+N19+O19+P19 -> 638733.2 | R19: 10 | S19: FIXED 4% | T19: 46372 | U19: Semi-Gross | V19: =IFERROR(MAX((H19-TODAY())/365.25,0),0) -> 4.164271 | W19: =F19*V19 -> 2232.0493 | X19: 1010 | Y19: =IF(J19>0,J19-X19,0) -> -22 | Z19: =IFERROR(IF(J19>0,(J19-X19)/X19,0),0) -> -0.021782178 | AA19: 440704.03 | AB19: Option: 6 mths. BG: $440,704 (no expiry). 10 car spaces. Formerly Austbrokers. | AC19: =IF(AD19="","VACANT",IF(AD19<TODAY(),"EXPIRED","ACTIVE")) -> ACTIVE | AD19: 47832 | AE19: 988 | AF19: AEI Insurance Group
A20: 0601 | B20: L06 | C20: 6.01 | D20: Caldas Constructions Pty Ltd | E20: Caldas Constructions Pty Ltd | F20: 186.4 | G20: 46204 | H20: 48395 | I20: 6 | J20: 920 | K20: =IF(J20>0,J20*F20,0) -> 171488 | L20: -512255 | Q20: =K20+L20+M20+N20+O20+P20 -> -340767 | V20: =IFERROR(MAX((H20-TODAY())/365.25,0),0) -> 5.705681 | W20: =F20*V20 -> 1063.5389 | Y20: =IF(J20>0,J20-X20,0) -> 920 | Z20: =IFERROR(IF(J20>0,(J20-X20)/X20,0),0) -> 0 | AB20: Caldas Constructions — new lease 01/07/26 (corrected from 30/06/26), 6 yr term, $920 psm. Prepaid rent held (no BG). Outgoings/cleaning/car park still TBC pending TS confirmation (still NIL on Sept26 TS). Tenant legal name corrected to "Caldas" (previously "Caladas"). | AC20: =IF(AD20="","VACANT",IF(AD20<TODAY(),"EXPIRED","ACTIVE")) -> ACTIVE | AD20: 48395 | AE20: 920 | AF20: Caldas Constructions
A21: 1001 | B21: L10 | C21: 10.01 | D21: VACANT | F21: 438 | K21: =IF(J21>0,J21*F21,0) -> 0 | Q21: =K21+L21+M21+N21+O21+P21 -> 0 | V21: =IFERROR(MAX((H21-TODAY())/365.25,0),0) -> 0 | W21: =F21*V21 -> 0 | Y21: =IF(J21>0,J21-X21,0) -> 0 | Z21: =IFERROR(IF(J21>0,(J21-X21)/X21,0),0) -> 0 | AC21: =IF(AD21="","VACANT",IF(AD21<TODAY(),"EXPIRED","ACTIVE")) -> VACANT | AE21: 0 | AF21: VACANT
A22: 1002 | B22: L10 | C22: 10.02 | D22: VACANT | F22: 349 | K22: =IF(J22>0,J22*F22,0) -> 0 | Q22: =K22+L22+M22+N22+O22+P22 -> 0 | V22: =IFERROR(MAX((H22-TODAY())/365.25,0),0) -> 0 | W22: =F22*V22 -> 0 | Y22: =IF(J22>0,J22-X22,0) -> 0 | Z22: =IFERROR(IF(J22>0,(J22-X22)/X22,0),0) -> 0 | AC22: =IF(AD22="","VACANT",IF(AD22<TODAY(),"EXPIRED","ACTIVE")) -> VACANT | AE22: 0 | AF22: VACANT
A23: 1101 | B23: L11 | C23: 11.01 | D23: Luxasia | E23: LUXASIA | F23: 242.5 | G23: 46296 | H23: 48121 | I23: 5 | J23: 1060 | K23: =IF(J23>0,J23*F23,0) -> 257050 | L23: -25705 | M23: 9728.72 | N23: 4015.8 | O23: 15600 | P23: 6060 | Q23: =K23+L23+M23+N23+O23+P23 -> 266749.52 | R23: 2 | S23: FIXED 3.75% | T23: 46661 | U23: Semi-Gross | V23: =IFERROR(MAX((H23-TODAY())/365.25,0),0) -> 4.9555099 | W23: =F23*V23 -> 1201.7112 | X23: 1060 | Y23: =IF(J23>0,J23-X23,0) -> 0 | Z23: =IFERROR(IF(J23>0,(J23-X23)/X23,0),0) -> 0 | AA23: 181149 | AB23: Break at 3 years. Lease commenced 1/10/26, 5 yr term, $1,060 psm. Incentive: landlord fitout contribution $369,812.50 (see Fitout Costs register) + rent abatement totalling $192,787.50 over the term — Yr 1-3 $25,705 pa (reflected in Abatement PA), Yr 4-5 $57,836.25 pa. Abatement PA will need manual updating to -$57,836.25 from the Yr 4 anniversary (1/10/29). | AC23: =IF(AD23="","VACANT",IF(AD23<TODAY(),"EXPIRED","ACTIVE")) -> ACTIVE | AD23: 48121 | AE23: 1060 | AF23: Luxasia
A24: 1102 | B24: L11 | C24: 11.02 | D24: Haskoning Australia Pty Ltd | E24: Haskoning Australia Pty Ltd | F24: 548 | G24: 46296 | H24: 48487 | I24: 6 | J24: 1040 | K24: =IF(J24>0,J24*F24,0) -> 569920 | L24: -111845.33 | Q24: =K24+L24+M24+N24+O24+P24 -> 458074.67 | S24: FIXED 3.5% | T24: 46661 | V24: =IFERROR(MAX((H24-TODAY())/365.25,0),0) -> 5.9575633 | W24: =F24*V24 -> 3264.7447 | X24: 1040 | Y24: =IF(J24>0,J24-X24,0) -> 0 | Z24: =IFERROR(IF(J24>0,(J24-X24)/X24,0),0) -> 0 | AB24: Haskoning Australia Pty Ltd — new lease commencing 01/10/26, 6 yr term, $1,040 psm, fixed 3.5% review. Fitout contribution $750,400 (landlord funded). Outgoings/cleaning/car park TBC pending TS confirmation. Next review date estimated. | AC24: =IF(AD24="","VACANT",IF(AD24<TODAY(),"EXPIRED","ACTIVE")) -> ACTIVE | AD24: 49582 | AE24: 1040 | AF24: Haskoning Australia
A25: TOTALS / BUILDING SUMMARY | F25: =SUM(F3:F24) -> 8940.9 | K25: =SUM(K3:K24) -> 7981402 | L25: =SUM(L3:L24) -> -2123734.2 | Q25: =SUM(Q3:Q24) -> 6606792.7 | V25: =IFERROR(SUMPRODUCT((H3:H24<>"")*F3:F24*MAX((H3:H24-TODAY())/365.25,0))/SUMPRODUCT((H3:H24<>"")*F3:F24),0) -> 5.9575633 | W25: =SUM(W3:W24) -> 29867.852
A26: OCCUPANCY % | D26: Occupied NLA | E26: =SUMPRODUCT((H3:H24<>"")*F3:F24) -> 8153.9 | F26: Vacant NLA | G26: =SUMPRODUCT((H3:H24="")*F3:F24) -> 787 | H26: Total NLA | I26: =SUM(F3:F24) -> 8940.9 | J26: Occupancy % | K26: =IFERROR(E26/I26,0) -> 0.91197754 | L26: Vacancy % | M26: =IFERROR(G26/I26,0) -> 0.088022459

Sheet Dashboard
A1: 1 ELIZABETH PLAZA, NORTH SYDNEY — ASSET MANAGEMENT DASHBOARD
A2: As at 30 September 2026 | Data sourced from Input Data tab | All amounts in AUD
B4: TOTAL NLA | D4: OCCUPIED NLA | F4: VACANT NLA | H4: OCCUPANCY | J4: VACANCY | L4: SUITES
B5: =SUM('Input Data'!F3:F24) -> 8940.9 | D5: =SUMPRODUCT(('Input Data'!H3:H24<>"")*'Input Data'!F3:F24) -> 8153.9 | F5: =SUMPRODUCT(('Input Data'!H3:H24="")*'Input Data'!F3:F24) -> 787 | H5: =IFERROR(SUMPRODUCT(('Input Data'!H3:H24<>"")*'Input Data'!F3:F24)/SUM('Input Data'!F3:F24),0) -> 0.91197754 | J5: =IFERROR(SUMPRODUCT(('Input Data'!H3:H24="")*'Input Data'!F3:F24)/SUM('Input Data'!F3:F24),0) -> 0.088022459 | L5: 20 occ | 2 vacant
B8: GROSS INCOME PA | D8: NET EFFECTIVE PA | F8: ABATEMENT PA | H8: WALE by NLA | J8: WALE by Income | L8: OUTGOINGS %
B9: =SUM('Input Data'!K3:K24) -> 7981402 | D9: =SUM('Input Data'!Q3:Q24) -> 6606792.7 | F9: =SUM('Input Data'!L3:L24) -> -2123734.2 | H9: =E14 -> 3.9091468 | J9: =E15 -> 3.8025989 | L9: 92.3%
B12: WEIGHTED AVERAGE LEASE EXPIRY (WALE)
B13: Measure | E13: WALE | F13: Basis
B14: WALE by NLA | E14: =IFERROR(SUMPRODUCT(('Input Data'!AD3:AD24>TODAY())*('Input Data'!AE3:AE24>0)*'Input Data'!F3:F24*('Input Data'!AD3:AD24-TODAY())/365.25)/SUMPRODUCT(('Input Data'!AD3:AD24>TODAY())*('Input Data'!AE3:AE24>0)*'Input Data'!F3:F24),0) -> 3.9091468 | F14: Area-weighted average of remaining lease terms (occupied suites only)
B15: WALE by Income | E15: =IFERROR(SUMPRODUCT(('Input Data'!AD3:AD24>TODAY())*('Input Data'!AE3:AE24>0)*'Input Data'!AE3:AE24*'Input Data'!F3:F24*('Input Data'!AD3:AD24-TODAY())/365.25)/SUMPRODUCT(('Input Data'!AD3:AD24>TODAY())*('Input Data'!AE3:AE24>0)*'Input Data'!AE3:AE24*'Input Data'!F3:F24),0) -> 3.8025989 | F15: Income-weighted average of remaining lease terms
B17: LEASE EXPIRY PROFILE — BY INCOME & AREA (5 YEAR FORWARD VIEW)
B18: Expiry Year | D18: Net Effective ($) | F18: Income % | G18: NLA (sqm) | H18: Area % | I18: # Leases | J18: Tenants Expiring
B19: 2026 | D19: =SUMPRODUCT(('Input Data'!AD3:AD24<>"")*('Input Data'!AD3:AD24<=DATE(2026,12,31))*'Input Data'!AE3:AE24*'Input Data'!F3:F24) -> 0 | F19: =IFERROR(D19/(SUMPRODUCT(('Input Data'!AD3:AD24>TODAY())*('Input Data'!AE3:AE24>0)*'Input Data'!AE3:AE24*'Input Data'!F3:F24)),0) -> 0 | G19: =SUMPRODUCT(('Input Data'!AD3:AD24<>"")*('Input Data'!AD3:AD24<=DATE(2026,12,31))*'Input Data'!F3:F24) -> 0 | H19: =IFERROR(G19/(SUMPRODUCT(('Input Data'!AD3:AD24>TODAY())*('Input Data'!AE3:AE24>0)*'Input Data'!F3:F24)),0) -> 0 | I19: =SUMPRODUCT(('Input Data'!AD3:AD24<>"")*('Input Data'!AD3:AD24<=DATE(2026,12,31))*1) -> 0 | J19: =IFERROR(MID(IF(('Input Data'!AD3<>"")*('Input Data'!AD3<=DATE(2026,12,31)),", "&'Input Data'!AF3&" ("&'Input Data'!C3&")","")&IF(('Input Data'!AD4<>"")*('Input Data'!AD4<=DATE(2026,12,31)),", "&'Input Data'!AF4&" ("&'Input Data'!C4&")","")&IF(('Input Data'!AD5<>"")*('Input Data'!AD5<=DATE(2026,12,31)),", "&'Input Data'!AF5&" ("&'Input Data'!C5&")","")&IF(('Input Data'!AD6<>"")*('Input Data'!AD6<=DATE(2026,12,31)),", "&'Input Data'!AF6&" ("&'Input Data'!C6&")","")&IF(('Input Data'!AD7<>"")*('Input Data'!AD7<=DATE(2026,12,31)),", "&'Input Data'!AF7&" ("&'Input Data'!C7&")","")&IF(('Input Data'!AD8<>"")*('Input Data'!AD8<=DATE(2026,12,31)),", "&'Input Data'!AF8&" ("&'Input Data'!C8&")","")&IF(('Input Data'!AD9<>"")*('Input Data'!AD9<=DATE(2026,12,31)),", "&'Input Data'!AF9&" ("&'Input Data'!C9&")","")&IF(('Input Data'!AD10<>"")*('Input Data'!AD10<=DATE(2026,12,31)),", "&'Input Data'!AF10&" ("&'Input Data'!C10&")","")&IF(('Input Data'!AD11<>"")*('Input Data'!AD11<=DATE(2026,12,31)),", "&'Input Data'!AF11&" ("&'Input Data'!C11&")","")&IF(('Input Data'!AD12<>"")*('Input Data'!AD12<=DATE(2026,12,31)),", "&'Input Data'!AF12&" ("&'Input Data'!C12&")","")&IF(('Input Data'!AD13<>"")*('Input Data'!AD13<=DATE(2026,12,31)),", "&'Input Data'!AF13&" ("&'Input Data'!C13&")","")&IF(('Input Data'!AD14<>"")*('Input Data'!AD14<=DATE(2026,12,31)),", "&'Input Data'!AF14&" ("&'Input Data'!C14&")","")&IF(('Input Data'!AD15<>"")*('Input Data'!AD15<=DATE(2026,12,31)),", "&'Input Data'!AF15&" ("&'Input Data'!C15&")","")&IF(('Input Data'!AD16<>"")*('Input Data'!AD16<=DATE(2026,12,31)),", "&'Input Data'!AF16&" ("&'Input Data'!C16&")","")&IF(('Input Data'!AD17<>"")*('Input Data'!AD17<=DATE(2026,12,31)),", "&'Input Data'!AF17&" ("&'Input Data'!C17&")","")&IF(('Input Data'!AD18<>"")*('Input Data'!AD18<=DATE(2026,12,31)),", "&'Input Data'!AF18&" ("&'Input Data'!C18&")","")&IF(('Input Data'!AD19<>"")*('Input Data'!AD19<=DATE(2026,12,31)),", "&'Input Data'!AF19&" ("&'Input Data'!C19&")","")&IF(('Input Data'!AD20<>"")*('Input Data'!AD20<=DATE(2026,12,31)),", "&'Input Data'!AF20&" ("&'Input Data'!C20&")","")&IF(('Input Data'!AD21<>"")*('Input Data'!AD21<=DATE(2026,12,31)),", "&'Input Data'!AF21&" ("&'Input Data'!C21&")","")&IF(('Input Data'!AD22<>"")*('Input Data'!AD22<=DATE(2026,12,31)),", "&'Input Data'!AF22&" ("&'Input Data'!C22&")","")&IF(('Input Data'!AD23<>"")*('Input Data'!AD23<=DATE(2026,12,31)),", "&'Input Data'!AF23&" ("&'Input Data'!C23&")","")&IF(('Input Data'!AD24<>"")*('Input Data'!AD24<=DATE(2026,12,31)),", "&'Input Data'!AF24&" ("&'Input Data'!C24&")",""),3,999),"—")
B20: 2027 | D20: {=SUMPRODUCT(('Input Data'!AD3:AD24>TODAY())*(YEAR('Input Data'!AD3:AD24)=2027)*('Input Data'!AE3:AE24>0)*'Input Data'!AE3:AE24*'Input Data'!F3:F24)} -> 683153.04 | F20: =IFERROR(D20/(SUMPRODUCT(('Input Data'!AD3:AD24>TODAY())*('Input Data'!AE3:AE24>0)*'Input Data'!AE3:AE24*'Input Data'!F3:F24)),0) -> 0.085593112 | G20: =SUMPRODUCT(('Input Data'!AD3:AD24>TODAY())*(YEAR('Input Data'!AD3:AD24)=2027)*('Input Data'!AE3:AE24>0)*'Input Data'!F3:F24) -> 642.7 | H20: =IFERROR(G20/(SUMPRODUCT(('Input Data'!AD3:AD24>TODAY())*('Input Data'!AE3:AE24>0)*'Input Data'!F3:F24)),0) -> 0.082520158 | I20: =SUMPRODUCT(('Input Data'!AD3:AD24>TODAY())*(YEAR('Input Data'!AD3:AD24)=2027)*('Input Data'!AE3:AE24>0)*1) -> 2 | J20: =IFERROR(MID(IF(('Input Data'!AD3>TODAY())*(YEAR('Input Data'!AD3)=2027)*('Input Data'!AE3>0),", "&'Input Data'!AF3&" ("&'Input Data'!C3&")","")&IF(('Input Data'!AD4>TODAY())*(YEAR('Input Data'!AD4)=2027)*('Input Data'!AE4>0),", "&'Input Data'!AF4&" ("&'Input Data'!C4&")","")&IF(('Input Data'!AD5>TODAY())*(YEAR('Input Data'!AD5)=2027)*('Input Data'!AE5>0),", "&'Input Data'!AF5&" ("&'Input Data'!C5&")","")&IF(('Input Data'!AD6>TODAY())*(YEAR('Input Data'!AD6)=2027)*('Input Data'!AE6>0),", "&'Input Data'!AF6&" ("&'Input Data'!C6&")","")&IF(('Input Data'!AD7>TODAY())*(YEAR('Input Data'!AD7)=2027)*('Input Data'!AE7>0),", "&'Input Data'!AF7&" ("&'Input Data'!C7&")","")&IF(('Input Data'!AD8>TODAY())*(YEAR('Input Data'!AD8)=2027)*('Input Data'!AE8>0),", "&'Input Data'!AF8&" ("&'Input Data'!C8&")","")&IF(('Input Data'!AD9>TODAY())*(YEAR('Input Data'!AD9)=2027)*('Input Data'!AE9>0),", "&'Input Data'!AF9&" ("&'Input Data'!C9&")","")&IF(('Input Data'!AD10>TODAY())*(YEAR('Input Data'!AD10)=2027)*('Input Data'!AE10>0),", "&'Input Data'!AF10&" ("&'Input Data'!C10&")","")&IF(('Input Data'!AD11>TODAY())*(YEAR('Input Data'!AD11)=2027)*('Input Data'!AE11>0),", "&'Input Data'!AF11&" ("&'Input Data'!C11&")","")&IF(('Input Data'!AD12>TODAY())*(YEAR('Input Data'!AD12)=2027)*('Input Data'!AE12>0),", "&'Input Data'!AF12&" ("&'Input Data'!C12&")","")&IF(('Input Data'!AD13>TODAY())*(YEAR('Input Data'!AD13)=2027)*('Input Data'!AE13>0),", "&'Input Data'!AF13&" ("&'Input Data'!C13&")","")&IF(('Input Data'!AD14>TODAY())*(YEAR('Input Data'!AD14)=2027)*('Input Data'!AE14>0),", "&'Input Data'!AF14&" ("&'Input Data'!C14&")","")&IF(('Input Data'!AD15>TODAY())*(YEAR('Input Data'!AD15)=2027)*('Input Data'!AE15>0),", "&'Input Data'!AF15&" ("&'Input Data'!C15&")","")&IF(('Input Data'!AD16>TODAY())*(YEAR('Input Data'!AD16)=2027)*('Input Data'!AE16>0),", "&'Input Data'!AF16&" ("&'Input Data'!C16&")","")&IF(('Input Data'!AD17>TODAY())*(YEAR('Input Data'!AD17)=2027)*('Input Data'!AE17>0),", "&'Input Data'!AF17&" ("&'Input Data'!C17&")","")&IF(('Input Data'!AD18>TODAY())*(YEAR('Input Data'!AD18)=2027)*('Input Data'!AE18>0),", "&'Input Data'!AF18&" ("&'Input Data'!C18&")","")&IF(('Input Data'!AD19>TODAY())*(YEAR('Input Data'!AD19)=2027)*('Input Data'!AE19>0),", "&'Input Data'!AF19&" ("&'Input Data'!C19&")","")&IF(('Input Data'!AD20>TODAY())*(YEAR('Input Data'!AD20)=2027)*('Input Data'!AE20>0),", "&'Input Data'!AF20&" ("&'Input Data'!C20&")","")&IF(('Input Data'!AD21>TODAY())*(YEAR('Input Data'!AD21)=2027)*('Input Data'!AE21>0),", "&'Input Data'!AF21&" ("&'Input Data'!C21&")","")&IF(('Input Data'!AD22>TODAY())*(YEAR('Input Data'!AD22)=2027)*('Input Data'!AE22>0),", "&'Input Data'!AF22&" ("&'Input Data'!C22&")","")&IF(('Input Data'!AD23>TODAY())*(YEAR('Input Data'!AD23)=2027)*('Input Data'!AE23>0),", "&'Input Data'!AF23&" ("&'Input Data'!C23&")","")&IF(('Input Data'!AD24>TODAY())*(YEAR('Input Data'!AD24)=2027)*('Input Data'!AE24>0),", "&'Input Data'!AF24&" ("&'Input Data'!C24&")",""),3,999),"—") -> Keeping Company (6.03), Pitt & Sherry (9.01)
B21: 2028 | D21: =SUMPRODUCT(('Input Data'!AD3:AD24>TODAY())*(YEAR('Input Data'!AD3:AD24)=2028)*('Input Data'!AE3:AE24>0)*'Input Data'!AE3:AE24*'Input Data'!F3:F24) -> 857128.71 | F21: =IFERROR(D21/(SUMPRODUCT(('Input Data'!AD3:AD24>TODAY())*('Input Data'!AE3:AE24>0)*'Input Data'!AE3:AE24*'Input Data'!F3:F24)),0) -> 0.10739075 | G21: =SUMPRODUCT(('Input Data'!AD3:AD24>TODAY())*(YEAR('Input Data'!AD3:AD24)=2028)*('Input Data'!AE3:AE24>0)*'Input Data'!F3:F24) -> 794.4 | H21: =IFERROR(G21/(SUMPRODUCT(('Input Data'!AD3:AD24>TODAY())*('Input Data'!AE3:AE24>0)*'Input Data'!F3:F24)),0) -> 0.10199784 | I21: =SUMPRODUCT(('Input Data'!AD3:AD24>TODAY())*(YEAR('Input Data'!AD3:AD24)=2028)*('Input Data'!AE3:AE24>0)*1) -> 2 | J21: =IFERROR(MID(IF(('Input Data'!AD3>TODAY())*(YEAR('Input Data'!AD3)=2028)*('Input Data'!AE3>0),", "&'Input Data'!AF3&" ("&'Input Data'!C3&")","")&IF(('Input Data'!AD4>TODAY())*(YEAR('Input Data'!AD4)=2028)*('Input Data'!AE4>0),", "&'Input Data'!AF4&" ("&'Input Data'!C4&")","")&IF(('Input Data'!AD5>TODAY())*(YEAR('Input Data'!AD5)=2028)*('Input Data'!AE5>0),", "&'Input Data'!AF5&" ("&'Input Data'!C5&")","")&IF(('Input Data'!AD6>TODAY())*(YEAR('Input Data'!AD6)=2028)*('Input Data'!AE6>0),", "&'Input Data'!AF6&" ("&'Input Data'!C6&")","")&IF(('Input Data'!AD7>TODAY())*(YEAR('Input Data'!AD7)=2028)*('Input Data'!AE7>0),", "&'Input Data'!AF7&" ("&'Input Data'!C7&")","")&IF(('Input Data'!AD8>TODAY())*(YEAR('Input Data'!AD8)=2028)*('Input Data'!AE8>0),", "&'Input Data'!AF8&" ("&'Input Data'!C8&")","")&IF(('Input Data'!AD9>TODAY())*(YEAR('Input Data'!AD9)=2028)*('Input Data'!AE9>0),", "&'Input Data'!AF9&" ("&'Input Data'!C9&")","")&IF(('Input Data'!AD10>TODAY())*(YEAR('Input Data'!AD10)=2028)*('Input Data'!AE10>0),", "&'Input Data'!AF10&" ("&'Input Data'!C10&")","")&IF(('Input Data'!AD11>TODAY())*(YEAR('Input Data'!AD11)=2028)*('Input Data'!AE11>0),", "&'Input Data'!AF11&" ("&'Input Data'!C11&")","")&IF(('Input Data'!AD12>TODAY())*(YEAR('Input Data'!AD12)=2028)*('Input Data'!AE12>0),", "&'Input Data'!AF12&" ("&'Input Data'!C12&")","")&IF(('Input Data'!AD13>TODAY())*(YEAR('Input Data'!AD13)=2028)*('Input Data'!AE13>0),", "&'Input Data'!AF13&" ("&'Input Data'!C13&")","")&IF(('Input Data'!AD14>TODAY())*(YEAR('Input Data'!AD14)=2028)*('Input Data'!AE14>0),", "&'Input Data'!AF14&" ("&'Input Data'!C14&")","")&IF(('Input Data'!AD15>TODAY())*(YEAR('Input Data'!AD15)=2028)*('Input Data'!AE15>0),", "&'Input Data'!AF15&" ("&'Input Data'!C15&")","")&IF(('Input Data'!AD16>TODAY())*(YEAR('Input Data'!AD16)=2028)*('Input Data'!AE16>0),", "&'Input Data'!AF16&" ("&'Input Data'!C16&")","")&IF(('Input Data'!AD17>TODAY())*(YEAR('Input Data'!AD17)=2028)*('Input Data'!AE17>0),", "&'Input Data'!AF17&" ("&'Input Data'!C17&")","")&IF(('Input Data'!AD18>TODAY())*(YEAR('Input Data'!AD18)=2028)*('Input Data'!AE18>0),", "&'Input Data'!AF18&" ("&'Input Data'!C18&")","")&IF(('Input Data'!AD19>TODAY())*(YEAR('Input Data'!AD19)=2028)*('Input Data'!AE19>0),", "&'Input Data'!AF19&" ("&'Input Data'!C19&")","")&IF(('Input Data'!AD20>TODAY())*(YEAR('Input Data'!AD20)=2028)*('Input Data'!AE20>0),", "&'Input Data'!AF20&" ("&'Input Data'!C20&")","")&IF(('Input Data'!AD21>TODAY())*(YEAR('Input Data'!AD21)=2028)*('Input Data'!AE21>0),", "&'Input Data'!AF21&" ("&'Input Data'!C21&")","")&IF(('Input Data'!AD22>TODAY())*(YEAR('Input Data'!AD22)=2028)*('Input Data'!AE22>0),", "&'Input Data'!AF22&" ("&'Input Data'!C22&")","")&IF(('Input Data'!AD23>TODAY())*(YEAR('Input Data'!AD23)=2028)*('Input Data'!AE23>0),", "&'Input Data'!AF23&" ("&'Input Data'!C23&")","")&IF(('Input Data'!AD24>TODAY())*(YEAR('Input Data'!AD24)=2028)*('Input Data'!AE24>0),", "&'Input Data'!AF24&" ("&'Input Data'!C24&")",""),3,999),"—") -> Sydney Smiletree (3.01), Vanderlande Industries (8.01)
B22: 2029 | D22: =SUMPRODUCT(('Input Data'!AD3:AD24>TODAY())*(YEAR('Input Data'!AD3:AD24)=2029)*('Input Data'!AE3:AE24>0)*'Input Data'!AE3:AE24*'Input Data'!F3:F24) -> 2340041 | F22: =IFERROR(D22/(SUMPRODUCT(('Input Data'!AD3:AD24>TODAY())*('Input Data'!AE3:AE24>0)*'Input Data'!AE3:AE24*'Input Data'!F3:F24)),0) -> 0.29318671 | G22: =SUMPRODUCT(('Input Data'!AD3:AD24>TODAY())*(YEAR('Input Data'!AD3:AD24)=2029)*('Input Data'!AE3:AE24>0)*'Input Data'!F3:F24) -> 1923.6 | H22: =IFERROR(G22/(SUMPRODUCT(('Input Data'!AD3:AD24>TODAY())*('Input Data'!AE3:AE24>0)*'Input Data'!F3:F24)),0) -> 0.24698269 | I22: =SUMPRODUCT(('Input Data'!AD3:AD24>TODAY())*(YEAR('Input Data'!AD3:AD24)=2029)*('Input Data'!AE3:AE24>0)*1) -> 5 | J22: =IFERROR(MID(IF(('Input Data'!AD3>TODAY())*(YEAR('Input Data'!AD3)=2029)*('Input Data'!AE3>0),", "&'Input Data'!AF3&" ("&'Input Data'!C3&")","")&IF(('Input Data'!AD4>TODAY())*(YEAR('Input Data'!AD4)=2029)*('Input Data'!AE4>0),", "&'Input Data'!AF4&" ("&'Input Data'!C4&")","")&IF(('Input Data'!AD5>TODAY())*(YEAR('Input Data'!AD5)=2029)*('Input Data'!AE5>0),", "&'Input Data'!AF5&" ("&'Input Data'!C5&")","")&IF(('Input Data'!AD6>TODAY())*(YEAR('Input Data'!AD6)=2029)*('Input Data'!AE6>0),", "&'Input Data'!AF6&" ("&'Input Data'!C6&")","")&IF(('Input Data'!AD7>TODAY())*(YEAR('Input Data'!AD7)=2029)*('Input Data'!AE7>0),", "&'Input Data'!AF7&" ("&'Input Data'!C7&")","")&IF(('Input Data'!AD8>TODAY())*(YEAR('Input Data'!AD8)=2029)*('Input Data'!AE8>0),", "&'Input Data'!AF8&" ("&'Input Data'!C8&")","")&IF(('Input Data'!AD9>TODAY())*(YEAR('Input Data'!AD9)=2029)*('Input Data'!AE9>0),", "&'Input Data'!AF9&" ("&'Input Data'!C9&")","")&IF(('Input Data'!AD10>TODAY())*(YEAR('Input Data'!AD10)=2029)*('Input Data'!AE10>0),", "&'Input Data'!AF10&" ("&'Input Data'!C10&")","")&IF(('Input Data'!AD11>TODAY())*(YEAR('Input Data'!AD11)=2029)*('Input Data'!AE11>0),", "&'Input Data'!AF11&" ("&'Input Data'!C11&")","")&IF(('Input Data'!AD12>TODAY())*(YEAR('Input Data'!AD12)=2029)*('Input Data'!AE12>0),", "&'Input Data'!AF12&" ("&'Input Data'!C12&")","")&IF(('Input Data'!AD13>TODAY())*(YEAR('Input Data'!AD13)=2029)*('Input Data'!AE13>0),", "&'Input Data'!AF13&" ("&'Input Data'!C13&")","")&IF(('Input Data'!AD14>TODAY())*(YEAR('Input Data'!AD14)=2029)*('Input Data'!AE14>0),", "&'Input Data'!AF14&" ("&'Input Data'!C14&")","")&IF(('Input Data'!AD15>TODAY())*(YEAR('Input Data'!AD15)=2029)*('Input Data'!AE15>0),", "&'Input Data'!AF15&" ("&'Input Data'!C15&")","")&IF(('Input Data'!AD16>TODAY())*(YEAR('Input Data'!AD16)=2029)*('Input Data'!AE16>0),", "&'Input Data'!AF16&" ("&'Input Data'!C16&")","")&IF(('Input Data'!AD17>TODAY())*(YEAR('Input Data'!AD17)=2029)*('Input Data'!AE17>0),", "&'Input Data'!AF17&" ("&'Input Data'!C17&")","")&IF(('Input Data'!AD18>TODAY())*(YEAR('Input Data'!AD18)=2029)*('Input Data'!AE18>0),", "&'Input Data'!AF18&" ("&'Input Data'!C18&")","")&IF(('Input Data'!AD19>TODAY())*(YEAR('Input Data'!AD19)=2029)*('Input Data'!AE19>0),", "&'Input Data'!AF19&" ("&'Input Data'!C19&")","")&IF(('Input Data'!AD20>TODAY())*(YEAR('Input Data'!AD20)=2029)*('Input Data'!AE20>0),", "&'Input Data'!AF20&" ("&'Input Data'!C20&")","")&IF(('Input Data'!AD21>TODAY())*(YEAR('Input Data'!AD21)=2029)*('Input Data'!AE21>0),", "&'Input Data'!AF21&" ("&'Input Data'!C21&")","")&IF(('Input Data'!AD22>TODAY())*(YEAR('Input Data'!AD22)=2029)*('Input Data'!AE22>0),", "&'Input Data'!AF22&" ("&'Input Data'!C22&")","")&IF(('Input Data'!AD23>TODAY())*(YEAR('Input Data'!AD23)=2029)*('Input Data'!AE23>0),", "&'Input Data'!AF23&" ("&'Input Data'!C23&")","")&IF(('Input Data'!AD24>TODAY())*(YEAR('Input Data'!AD24)=2029)*('Input Data'!AE24>0),", "&'Input Data'!AF24&" ("&'Input Data'!C24&")",""),3,999),"—") -> Asterx (MediRecords) (5.03), Auctionsplus (5.04), Sungrow (L6) (6.02), Sungrow (L7 Main) (7.01), Smile Partners Australia (9.02)
B23: 2030 | D23: =SUMPRODUCT(('Input Data'!AD3:AD24>TODAY())*(YEAR('Input Data'!AD3:AD24)=2030)*('Input Data'!AE3:AE24>0)*'Input Data'!AE3:AE24*'Input Data'!F3:F24) -> 896257.06 | F23: =IFERROR(D23/(SUMPRODUCT(('Input Data'!AD3:AD24>TODAY())*('Input Data'!AE3:AE24>0)*'Input Data'!AE3:AE24*'Input Data'!F3:F24)),0) -> 0.11229318 | G23: =SUMPRODUCT(('Input Data'!AD3:AD24>TODAY())*(YEAR('Input Data'!AD3:AD24)=2030)*('Input Data'!AE3:AE24>0)*'Input Data'!F3:F24) -> 903.3 | H23: =IFERROR(G23/(SUMPRODUCT(('Input Data'!AD3:AD24>TODAY())*('Input Data'!AE3:AE24>0)*'Input Data'!F3:F24)),0) -> 0.11598018 | I23: =SUMPRODUCT(('Input Data'!AD3:AD24>TODAY())*(YEAR('Input Data'!AD3:AD24)=2030)*('Input Data'!AE3:AE24>0)*1) -> 3 | J23: =IFERROR(MID(IF(('Input Data'!AD3>TODAY())*(YEAR('Input Data'!AD3)=2030)*('Input Data'!AE3>0),", "&'Input Data'!AF3&" ("&'Input Data'!C3&")","")&IF(('Input Data'!AD4>TODAY())*(YEAR('Input Data'!AD4)=2030)*('Input Data'!AE4>0),", "&'Input Data'!AF4&" ("&'Input Data'!C4&")","")&IF(('Input Data'!AD5>TODAY())*(YEAR('Input Data'!AD5)=2030)*('Input Data'!AE5>0),", "&'Input Data'!AF5&" ("&'Input Data'!C5&")","")&IF(('Input Data'!AD6>TODAY())*(YEAR('Input Data'!AD6)=2030)*('Input Data'!AE6>0),", "&'Input Data'!AF6&" ("&'Input Data'!C6&")","")&IF(('Input Data'!AD7>TODAY())*(YEAR('Input Data'!AD7)=2030)*('Input Data'!AE7>0),", "&'Input Data'!AF7&" ("&'Input Data'!C7&")","")&IF(('Input Data'!AD8>TODAY())*(YEAR('Input Data'!AD8)=2030)*('Input Data'!AE8>0),", "&'Input Data'!AF8&" ("&'Input Data'!C8&")","")&IF(('Input Data'!AD9>TODAY())*(YEAR('Input Data'!AD9)=2030)*('Input Data'!AE9>0),", "&'Input Data'!AF9&" ("&'Input Data'!C9&")","")&IF(('Input Data'!AD10>TODAY())*(YEAR('Input Data'!AD10)=2030)*('Input Data'!AE10>0),", "&'Input Data'!AF10&" ("&'Input Data'!C10&")","")&IF(('Input Data'!AD11>TODAY())*(YEAR('Input Data'!AD11)=2030)*('Input Data'!AE11>0),", "&'Input Data'!AF11&" ("&'Input Data'!C11&")","")&IF(('Input Data'!AD12>TODAY())*(YEAR('Input Data'!AD12)=2030)*('Input Data'!AE12>0),", "&'Input Data'!AF12&" ("&'Input Data'!C12&")","")&IF(('Input Data'!AD13>TODAY())*(YEAR('Input Data'!AD13)=2030)*('Input Data'!AE13>0),", "&'Input Data'!AF13&" ("&'Input Data'!C13&")","")&IF(('Input Data'!AD14>TODAY())*(YEAR('Input Data'!AD14)=2030)*('Input Data'!AE14>0),", "&'Input Data'!AF14&" ("&'Input Data'!C14&")","")&IF(('Input Data'!AD15>TODAY())*(YEAR('Input Data'!AD15)=2030)*('Input Data'!AE15>0),", "&'Input Data'!AF15&" ("&'Input Data'!C15&")","")&IF(('Input Data'!AD16>TODAY())*(YEAR('Input Data'!AD16)=2030)*('Input Data'!AE16>0),", "&'Input Data'!AF16&" ("&'Input Data'!C16&")","")&IF(('Input Data'!AD17>TODAY())*(YEAR('Input Data'!AD17)=2030)*('Input Data'!AE17>0),", "&'Input Data'!AF17&" ("&'Input Data'!C17&")","")&IF(('Input Data'!AD18>TODAY())*(YEAR('Input Data'!AD18)=2030)*('Input Data'!AE18>0),", "&'Input Data'!AF18&" ("&'Input Data'!C18&")","")&IF(('Input Data'!AD19>TODAY())*(YEAR('Input Data'!AD19)=2030)*('Input Data'!AE19>0),", "&'Input Data'!AF19&" ("&'Input Data'!C19&")","")&IF(('Input Data'!AD20>TODAY())*(YEAR('Input Data'!AD20)=2030)*('Input Data'!AE20>0),", "&'Input Data'!AF20&" ("&'Input Data'!C20&")","")&IF(('Input Data'!AD21>TODAY())*(YEAR('Input Data'!AD21)=2030)*('Input Data'!AE21>0),", "&'Input Data'!AF21&" ("&'Input Data'!C21&")","")&IF(('Input Data'!AD22>TODAY())*(YEAR('Input Data'!AD22)=2030)*('Input Data'!AE22>0),", "&'Input Data'!AF22&" ("&'Input Data'!C22&")","")&IF(('Input Data'!AD23>TODAY())*(YEAR('Input Data'!AD23)=2030)*('Input Data'!AE23>0),", "&'Input Data'!AF23&" ("&'Input Data'!C23&")","")&IF(('Input Data'!AD24>TODAY())*(YEAR('Input Data'!AD24)=2030)*('Input Data'!AE24>0),", "&'Input Data'!AF24&" ("&'Input Data'!C24&")",""),3,999),"—") -> Can Too Foundation (8.03), Hulsbosch Design (12.01), AEI Insurance Group (12.02)
B24: 2031+ | D24: =SUMPRODUCT(('Input Data'!AD3:AD24>TODAY())*(YEAR('Input Data'!AD3:AD24)>=2031)*('Input Data'!AE3:AE24>0)*'Input Data'!AE3:AE24*'Input Data'!F3:F24) -> 3204822.3 | F24: =IFERROR(D24/(SUMPRODUCT(('Input Data'!AD3:AD24>TODAY())*('Input Data'!AE3:AE24>0)*'Input Data'!AE3:AE24*'Input Data'!F3:F24)),0) -> 0.40153625 | G24: =SUMPRODUCT(('Input Data'!AD3:AD24>TODAY())*(YEAR('Input Data'!AD3:AD24)>=2031)*('Input Data'!AE3:AE24>0)*'Input Data'!F3:F24) -> 3524.4 | H24: =IFERROR(G24/(SUMPRODUCT(('Input Data'!AD3:AD24>TODAY())*('Input Data'!AE3:AE24>0)*'Input Data'!F3:F24)),0) -> 0.45251913 | I24: =SUMPRODUCT(('Input Data'!AD3:AD24>TODAY())*(YEAR('Input Data'!AD3:AD24)>=2031)*('Input Data'!AE3:AE24>0)*1) -> 7 | J24: =IFERROR(MID(IF(('Input Data'!AD3>TODAY())*(YEAR('Input Data'!AD3)>=2031)*('Input Data'!AE3>0),", "&'Input Data'!AF3&" ("&'Input Data'!C3&")","")&IF(('Input Data'!AD4>TODAY())*(YEAR('Input Data'!AD4)>=2031)*('Input Data'!AE4>0),", "&'Input Data'!AF4&" ("&'Input Data'!C4&")","")&IF(('Input Data'!AD5>TODAY())*(YEAR('Input Data'!AD5)>=2031)*('Input Data'!AE5>0),", "&'Input Data'!AF5&" ("&'Input Data'!C5&")","")&IF(('Input Data'!AD6>TODAY())*(YEAR('Input Data'!AD6)>=2031)*('Input Data'!AE6>0),", "&'Input Data'!AF6&" ("&'Input Data'!C6&")","")&IF(('Input Data'!AD7>TODAY())*(YEAR('Input Data'!AD7)>=2031)*('Input Data'!AE7>0),", "&'Input Data'!AF7&" ("&'Input Data'!C7&")","")&IF(('Input Data'!AD8>TODAY())*(YEAR('Input Data'!AD8)>=2031)*('Input Data'!AE8>0),", "&'Input Data'!AF8&" ("&'Input Data'!C8&")","")&IF(('Input Data'!AD9>TODAY())*(YEAR('Input Data'!AD9)>=2031)*('Input Data'!AE9>0),", "&'Input Data'!AF9&" ("&'Input Data'!C9&")","")&IF(('Input Data'!AD10>TODAY())*(YEAR('Input Data'!AD10)>=2031)*('Input Data'!AE10>0),", "&'Input Data'!AF10&" ("&'Input Data'!C10&")","")&IF(('Input Data'!AD11>TODAY())*(YEAR('Input Data'!AD11)>=2031)*('Input Data'!AE11>0),", "&'Input Data'!AF11&" ("&'Input Data'!C11&")","")&IF(('Input Data'!AD12>TODAY())*(YEAR('Input Data'!AD12)>=2031)*('Input Data'!AE12>0),", "&'Input Data'!AF12&" ("&'Input Data'!C12&")","")&IF(('Input Data'!AD13>TODAY())*(YEAR('Input Data'!AD13)>=2031)*('Input Data'!AE13>0),", "&'Input Data'!AF13&" ("&'Input Data'!C13&")","")&IF(('Input Data'!AD14>TODAY())*(YEAR('Input Data'!AD14)>=2031)*('Input Data'!AE14>0),", "&'Input Data'!AF14&" ("&'Input Data'!C14&")","")&IF(('Input Data'!AD15>TODAY())*(YEAR('Input Data'!AD15)>=2031)*('Input Data'!AE15>0),", "&'Input Data'!AF15&" ("&'Input Data'!C15&")","")&IF(('Input Data'!AD16>TODAY())*(YEAR('Input Data'!AD16)>=2031)*('Input Data'!AE16>0),", "&'Input Data'!AF16&" ("&'Input Data'!C16&")","")&IF(('Input Data'!AD17>TODAY())*(YEAR('Input Data'!AD17)>=2031)*('Input Data'!AE17>0),", "&'Input Data'!AF17&" ("&'Input Data'!C17&")","")&IF(('Input Data'!AD18>TODAY())*(YEAR('Input Data'!AD18)>=2031)*('Input Data'!AE18>0),", "&'Input Data'!AF18&" ("&'Input Data'!C18&")","")&IF(('Input Data'!AD19>TODAY())*(YEAR('Input Data'!AD19)>=2031)*('Input Data'!AE19>0),", "&'Input Data'!AF19&" ("&'Input Data'!C19&")","")&IF(('Input Data'!AD20>TODAY())*(YEAR('Input Data'!AD20)>=2031)*('Input Data'!AE20>0),", "&'Input Data'!AF20&" ("&'Input Data'!C20&")","")&IF(('Input Data'!AD21>TODAY())*(YEAR('Input Data'!AD21)>=2031)*('Input Data'!AE21>0),", "&'Input Data'!AF21&" ("&'Input Data'!C21&")","")&IF(('Input Data'!AD22>TODAY())*(YEAR('Input Data'!AD22)>=2031)*('Input Data'!AE22>0),", "&'Input Data'!AF22&" ("&'Input Data'!C22&")","")&IF(('Input Data'!AD23>TODAY())*(YEAR('Input Data'!AD23)>=2031)*('Input Data'!AE23>0),", "&'Input Data'!AF23&" ("&'Input Data'!C23&")","")&IF(('Input Data'!AD24>TODAY())*(YEAR('Input Data'!AD24)>=2031)*('Input Data'!AE24>0),", "&'Input Data'!AF24&" ("&'Input Data'!C24&")",""),3,999),"—") -> Fitness First (L3) (3.02), Fitness First (L4) (4.01), Fitness First N. Sydney (5.01), Elekta (6.04), Caldas Constructions (6.01), Luxasia (11.01), Haskoning Australia (11.02)
B25: TOTAL | D25: =SUMPRODUCT(('Input Data'!AD3:AD24>TODAY())*('Input Data'!AE3:AE24>0)*'Input Data'!AE3:AE24*'Input Data'!F3:F24) -> 7981402 | F25: 1 | G25: =SUMPRODUCT(('Input Data'!AD3:AD24>TODAY())*('Input Data'!AE3:AE24>0)*'Input Data'!F3:F24) -> 7788.4 | H25: 1
B27: PASSING RENT vs MARKET RENT — By Suite
B28: Suite | C28: Tenant | E28: NLA | F28: Face PSM | G28: Market PSM | H28: Var ($) | I28: Var (%) | J28: Position
B29: ='Input Data'!C3 -> 3.01 | C29: ='Input Data'!D3 -> Sydney Smiletree Pty Ltd | E29: ='Input Data'!F3 -> 107.7 | F29: ='Input Data'!J3 -> 1395.94 | G29: ='Input Data'!X3 -> 950 | H29: ='Input Data'!Y3 -> 445.94 | I29: ='Input Data'!Z3 -> 0.46941053 | J29: =IF('Input Data'!Y3>0,"▲ Above Mkt",IF('Input Data'!Y3<0,"▼ Below Mkt","≈ At Market")) -> ▲ Above Mkt
B30: ='Input Data'!C4 -> 3.02 | C30: ='Input Data'!D4 -> Fitness First Australia Pty Limited | E30: ='Input Data'!F4 -> 795.5 | F30: ='Input Data'!J4 -> 855.7 | G30: ='Input Data'!X4 -> 870 | H30: ='Input Data'!Y4 -> -14.3 | I30: ='Input Data'!Z4 -> -0.016436782 | J30: =IF('Input Data'!Y4>0,"▲ Above Mkt",IF('Input Data'!Y4<0,"▼ Below Mkt","≈ At Market")) -> ▼ Below Mkt
B31: ='Input Data'!C5 -> 4.01 | C31: ='Input Data'!D5 -> Fitness First Australia Pty Limited | E31: ='Input Data'!F5 -> 1047 | F31: ='Input Data'!J5 -> 855.7 | G31: ='Input Data'!X5 -> 870 | H31: ='Input Data'!Y5 -> -14.3 | I31: ='Input Data'!Z5 -> -0.016436782 | J31: =IF('Input Data'!Y5>0,"▲ Above Mkt",IF('Input Data'!Y5<0,"▼ Below Mkt","≈ At Market")) -> ▼ Below Mkt
B32: ='Input Data'!C6 -> 5.01 | C32: ='Input Data'!D6 -> Fitness First Australia Pty Limited | E32: ='Input Data'!F6 -> 437.1 | F32: ='Input Data'!J6 -> 855.7 | G32: ='Input Data'!X6 -> 870 | H32: ='Input Data'!Y6 -> -14.3 | I32: ='Input Data'!Z6 -> -0.016436782 | J32: =IF('Input Data'!Y6>0,"▲ Above Mkt",IF('Input Data'!Y6<0,"▼ Below Mkt","≈ At Market")) -> ▼ Below Mkt
B33: ='Input Data'!C7 -> 5.03 | C33: ='Input Data'!D7 -> Asterx Pty Ltd | E33: ='Input Data'!F7 -> 229.8 | F33: ='Input Data'!J7 -> 985.53 | G33: ='Input Data'!X7 -> 950 | H33: ='Input Data'!Y7 -> 35.53 | I33: ='Input Data'!Z7 -> 0.0374 | J33: =IF('Input Data'!Y7>0,"▲ Above Mkt",IF('Input Data'!Y7<0,"▼ Below Mkt","≈ At Market")) -> ▲ Above Mkt
B34: ='Input Data'!C8 -> 5.04 | C34: ='Input Data'!D8 -> Auctionsplus Pty Ltd | E34: ='Input Data'!F8 -> 413.5 | F34: ='Input Data'!J8 -> 1005.89 | G34: ='Input Data'!X8 -> 990 | H34: ='Input Data'!Y8 -> 15.89 | I34: ='Input Data'!Z8 -> 0.016050505 | J34: =IF('Input Data'!Y8>0,"▲ Above Mkt",IF('Input Data'!Y8<0,"▼ Below Mkt","≈ At Market")) -> ▲ Above Mkt
B35: ='Input Data'!C9 -> 6.02 | C35: ='Input Data'!D9 -> Sungrow Australia Group | E35: ='Input Data'!F9 -> 451.7 | F35: ='Input Data'!J9 -> 954.5 | G35: ='Input Data'!X9 -> 955 | H35: ='Input Data'!Y9 -> -0.5 | I35: ='Input Data'!Z9 -> -0.00052356021 | J35: =IF('Input Data'!Y9>0,"▲ Above Mkt",IF('Input Data'!Y9<0,"▼ Below Mkt","≈ At Market")) -> ▼ Below Mkt
B36: ='Input Data'!C10 -> 6.03 | C36: ='Input Data'!D10 -> Keeping Company Pty Ltd | E36: ='Input Data'!F10 -> 189.4 | F36: ='Input Data'!J10 -> 1055.72 | G36: ='Input Data'!X10 -> 990 | H36: ='Input Data'!Y10 -> 65.72 | I36: ='Input Data'!Z10 -> 0.066383838 | J36: =IF('Input Data'!Y10>0,"▲ Above Mkt",IF('Input Data'!Y10<0,"▼ Below Mkt","≈ At Market")) -> ▲ Above Mkt
B37: ='Input Data'!C11 -> 6.04 | C37: ='Input Data'!D11 -> Elekta Pty Limited | E37: ='Input Data'!F11 -> 267.9 | F37: ='Input Data'!J11 -> 954.5 | G37: ='Input Data'!X11 -> 955 | H37: ='Input Data'!Y11 -> -0.5 | I37: ='Input Data'!Z11 -> -0.00052356021 | J37: =IF('Input Data'!Y11>0,"▲ Above Mkt",IF('Input Data'!Y11<0,"▼ Below Mkt","≈ At Market")) -> ▼ Below Mkt
B38: ='Input Data'!C12 -> 7.01 | C38: ='Input Data'!D12 -> Sungrow Australia Group | E38: ='Input Data'!F12 -> 484.1 | F38: ='Input Data'!J12 -> 1911.44 | G38: ='Input Data'!X12 -> 1020 | H38: ='Input Data'!Y12 -> 891.44 | I38: ='Input Data'!Z12 -> 0.87396078 | J38: =IF('Input Data'!Y12>0,"▲ Above Mkt",IF('Input Data'!Y12<0,"▼ Below Mkt","≈ At Market")) -> ▲ Above Mkt
B39: ='Input Data'!C14 -> 8.01 | C39: ='Input Data'!D14 -> Vanderlande Industries Australia Pty Ltd | E39: ='Input Data'!F14 -> 686.7 | F39: ='Input Data'!J14 -> 1029.25 | G39: ='Input Data'!X14 -> 990 | H39: ='Input Data'!Y14 -> 39.25 | I39: ='Input Data'!Z14 -> 0.039646465 | J39: =IF('Input Data'!Y14>0,"▲ Above Mkt",IF('Input Data'!Y14<0,"▼ Below Mkt","≈ At Market")) -> ▲ Above Mkt
B40: ='Input Data'!C15 -> 8.03 | C40: ='Input Data'!D15 -> Can Too Foundation Limited | E40: ='Input Data'!F15 -> 116.3 | F40: ='Input Data'!J15 -> 1027.12 | G40: ='Input Data'!X15 -> 990 | H40: ='Input Data'!Y15 -> 37.12 | I40: ='Input Data'!Z15 -> 0.037494949 | J40: =IF('Input Data'!Y15>0,"▲ Above Mkt",IF('Input Data'!Y15<0,"▼ Below Mkt","≈ At Market")) -> ▲ Above Mkt
B41: ='Input Data'!C16 -> 9.01 | C41: ='Input Data'!D16 -> Pitt & Sherry (Operations) Pty Ltd | E41: ='Input Data'!F16 -> 453.3 | F41: ='Input Data'!J16 -> 1065.96 | G41: ='Input Data'!X16 -> 1040 | H41: ='Input Data'!Y16 -> 25.96 | I41: ='Input Data'!Z16 -> 0.024961538 | J41: =IF('Input Data'!Y16>0,"▲ Above Mkt",IF('Input Data'!Y16<0,"▼ Below Mkt","≈ At Market")) -> ▲ Above Mkt
B42: ='Input Data'!C17 -> 12.01 | C42: ='Input Data'!D17 -> Hulsbosch Design Pty Ltd | E42: ='Input Data'!F17 -> 251 | F42: ='Input Data'!J17 -> 985 | G42: ='Input Data'!X17 -> 1040 | H42: ='Input Data'!Y17 -> -55 | I42: ='Input Data'!Z17 -> -0.052884615 | J42: =IF('Input Data'!Y17>0,"▲ Above Mkt",IF('Input Data'!Y17<0,"▼ Below Mkt","≈ At Market")) -> ▼ Below Mkt
B43: ='Input Data'!C18 -> 9.02 | C43: ='Input Data'!D18 -> Smile Partners Australia | E43: ='Input Data'!F18 -> 344.5 | F43: ='Input Data'!J18 -> 990.29 | G43: ='Input Data'!X18 -> 990 | H43: ='Input Data'!Y18 -> 0.29 | I43: ='Input Data'!Z18 -> 0.00029292929 | J43: =IF('Input Data'!Y18>0,"▲ Above Mkt",IF('Input Data'!Y18<0,"▼ Below Mkt","≈ At Market")) -> ▲ Above Mkt
B44: ='Input Data'!C19 -> 12.02 | C44: ='Input Data'!D19 -> AEI Insurance Group Pty Ltd | E44: ='Input Data'!F19 -> 536 | F44: ='Input Data'!J19 -> 988 | G44: ='Input Data'!X19 -> 1010 | H44: ='Input Data'!Y19 -> -22 | I44: ='Input Data'!Z19 -> -0.021782178 | J44: =IF('Input Data'!Y19>0,"▲ Above Mkt",IF('Input Data'!Y19<0,"▼ Below Mkt","≈ At Market")) -> ▼ Below Mkt
B46: UPCOMING CRITICAL DATES — Next 18 Months
B47: Suite / Tenant | D47: Event | E47: Due Date | F47: Days Away | G47: Action Required
B48: 6.01/Caldas | D48: New Lease Commences | E48: 46204 | F48: =IFERROR(INT(E48-TODAY()),"") -> -107 | G48: Ensure fitout complete, BG received, rent commences
B49: 6.03/Keeping Co | D49: Lease Expiry | E49: 46538 | F49: =IFERROR(INT(E49-TODAY()),"") -> 227 | G49: Renewal negotiations — 13 months away, engage tenant
B50: 5.04/Auctionsplus | D50: Rent Review 4% | E50: 46447 | F50: =IFERROR(INT(E50-TODAY()),"") -> 136 | G50: Fixed review — calculate and issue notice
B51: 5.03/Asterx | D51: Rent Review 3.5% | E51: 46569 | F51: =IFERROR(INT(E51-TODAY()),"") -> 258 | G51: Fixed review — confirm calculation
B52: 6.03/Keeping Co | D52: Rent Review 3.5% | E52: 46539 | F52: =IFERROR(INT(E52-TODAY()),"") -> 228 | G52: Fixed review — imminent, action now
B53: 8.01/Vanderlande | D53: Rent Review 4% | E53: 46569 | F53: =IFERROR(INT(E53-TODAY()),"") -> 258 | G53: Fixed review — imminent
B54: 9.01/Pitt & Sherry | D54: Rent Review 3.75% | E54: 46572 | F54: =IFERROR(INT(E54-TODAY()),"") -> 261 | G54: Fixed review — action now
B55: 3.01/Smiletree | D55: Rent Review 4% | E55: 46569 | F55: =IFERROR(INT(E55-TODAY()),"") -> 258 | G55: Fixed review on lease extension
B56: 9.01/Pitt & Sherry | D56: Lease Expiry | E56: 46571 | F56: =IFERROR(INT(E56-TODAY()),"") -> 260 | G56: Option available — engage tenant in advance
B57: 8.03/Can Too | D57: Rent Review 3.75% | E57: 46539 | F57: =IFERROR(INT(E57-TODAY()),"") -> 228 | G57: Fixed review — imminent
B58: LEVEL 10/Vacant | D58: Vacancy Risk | E58: TBC | F58: =IFERROR(INT(E58-TODAY()),"") | G58: Long vacancy — 787 sqm, marketing required urgently
B59: 11.01/Luxasia | D59: New Lease Commenced | E59: 46296 | F59: =IFERROR(INT(E59-TODAY()),"") -> -15 | G59: Confirm fitout contribution paid, BG/condition received, abatement schedule tracked (steps up 1/10/29)
B60: 11.02/Haskoning | D60: New Lease Commences | E60: 46296 | F60: =IFERROR(INT(E60-TODAY()),"") -> -15 | G60: Ensure fitout contribution paid, lease execution complete
B61: INCOME ANALYSIS — By Floor
B62: Floor | C62: Tenants | E62: NLA (sqm) | G62: Net Eff PA ($) | I62: Income % | K62: Expiry Yr | L62: Notes
B63: L12 | C63: =IFERROR(MID(IF(('Input Data'!AD18>TODAY())*('Input Data'!AE18>0),", "&'Input Data'!AF18&" ("&'Input Data'!C18&")","")&IF(('Input Data'!AD19>TODAY())*('Input Data'!AE19>0),", "&'Input Data'!AF19&" ("&'Input Data'!C19&")",""),3,999),"—") -> Smile Partners Australia (9.02), AEI Insurance Group (12.02) | E63: =SUMPRODUCT(('Input Data'!B3:B24="L12")*'Input Data'!F3:F24) -> 787 | G63: =SUMPRODUCT(('Input Data'!B3:B24="L12")*('Input Data'!AD3:AD24>TODAY())*('Input Data'!AE3:AE24>0)*'Input Data'!Q3:Q24) -> 829892.8 | K63: =IFERROR(IF(SUMPRODUCT(('Input Data'!B3:B24="L12")*('Input Data'!AE3:AE24>0)*('Input Data'!AD3:AD24>TODAY()))=0,"VACANT",TEXT(_xludf.minifs('Input Data'!AD3:AD24,'Input Data'!B3:B24,"L12",'Input Data'!AD3:AD24,">"&TODAY(),'Input Data'!AE3:AE24,">0"),"YYYY")),"—") -> —
B64: L11 | C64: =IFERROR(MID(IF(('Input Data'!AD23>TODAY())*('Input Data'!AE23>0),", "&'Input Data'!AF23&" ("&'Input Data'!C23&")","")&IF(('Input Data'!AD24>TODAY())*('Input Data'!AE24>0),", "&'Input Data'!AF24&" ("&'Input Data'!C24&")",""),3,999),"—") -> Luxasia (11.01), Haskoning Australia (11.02) | E64: =SUMPRODUCT(('Input Data'!B3:B24="L11")*'Input Data'!F3:F24) -> 790.5 | G64: =SUMPRODUCT(('Input Data'!B3:B24="L11")*('Input Data'!AD3:AD24>TODAY())*('Input Data'!AE3:AE24>0)*'Input Data'!Q3:Q24) -> 724824.19 | K64: =IFERROR(IF(SUMPRODUCT(('Input Data'!B3:B24="L11")*('Input Data'!AE3:AE24>0)*('Input Data'!AD3:AD24>TODAY()))=0,"VACANT",TEXT(_xludf.minifs('Input Data'!AD3:AD24,'Input Data'!B3:B24,"L11",'Input Data'!AD3:AD24,">"&TODAY(),'Input Data'!AE3:AE24,">0"),"YYYY")),"—") -> —
B65: L10 | C65: =IFERROR(MID(IF(('Input Data'!AD21>TODAY())*('Input Data'!AE21>0),", "&'Input Data'!AF21&" ("&'Input Data'!C21&")","")&IF(('Input Data'!AD22>TODAY())*('Input Data'!AE22>0),", "&'Input Data'!AF22&" ("&'Input Data'!C22&")",""),3,999),"—") | E65: =SUMPRODUCT(('Input Data'!B3:B24="L10")*'Input Data'!F3:F24) -> 787 | G65: =SUMPRODUCT(('Input Data'!B3:B24="L10")*('Input Data'!AD3:AD24>TODAY())*('Input Data'!AE3:AE24>0)*'Input Data'!Q3:Q24) -> 0 | K65: =IFERROR(IF(SUMPRODUCT(('Input Data'!B3:B24="L10")*('Input Data'!AE3:AE24>0)*('Input Data'!AD3:AD24>TODAY()))=0,"VACANT",TEXT(_xludf.minifs('Input Data'!AD3:AD24,'Input Data'!B3:B24,"L10",'Input Data'!AD3:AD24,">"&TODAY(),'Input Data'!AE3:AE24,">0"),"YYYY")),"—") -> VACANT
B66: L09 | C66: =IFERROR(MID(IF(('Input Data'!AD16>TODAY())*('Input Data'!AE16>0),", "&'Input Data'!AF16&" ("&'Input Data'!C16&")","")&IF(('Input Data'!AD17>TODAY())*('Input Data'!AE17>0),", "&'Input Data'!AF17&" ("&'Input Data'!C17&")",""),3,999),"—") -> Pitt & Sherry (9.01), Hulsbosch Design (12.01) | E66: =SUMPRODUCT(('Input Data'!B3:B24="L09")*'Input Data'!F3:F24) -> 797.8 | G66: =SUMPRODUCT(('Input Data'!B3:B24="L09")*('Input Data'!AD3:AD24>TODAY())*('Input Data'!AE3:AE24>0)*'Input Data'!Q3:Q24) -> 627848.33 | K66: =IFERROR(IF(SUMPRODUCT(('Input Data'!B3:B24="L09")*('Input Data'!AE3:AE24>0)*('Input Data'!AD3:AD24>TODAY()))=0,"VACANT",TEXT(_xludf.minifs('Input Data'!AD3:AD24,'Input Data'!B3:B24,"L09",'Input Data'!AD3:AD24,">"&TODAY(),'Input Data'!AE3:AE24,">0"),"YYYY")),"—") -> —
B67: L08 | C67: =IFERROR(MID(IF(('Input Data'!AD14>TODAY())*('Input Data'!AE14>0),", "&'Input Data'!AF14&" ("&'Input Data'!C14&")","")&IF(('Input Data'!AD15>TODAY())*('Input Data'!AE15>0),", "&'Input Data'!AF15&" ("&'Input Data'!C15&")",""),3,999),"—") -> Vanderlande Industries (8.01), Can Too Foundation (8.03) | E67: =SUMPRODUCT(('Input Data'!B3:B24="L08")*'Input Data'!F3:F24) -> 803 | G67: =SUMPRODUCT(('Input Data'!B3:B24="L08")*('Input Data'!AD3:AD24>TODAY())*('Input Data'!AE3:AE24>0)*'Input Data'!Q3:Q24) -> 653144.41 | K67: =IFERROR(IF(SUMPRODUCT(('Input Data'!B3:B24="L08")*('Input Data'!AE3:AE24>0)*('Input Data'!AD3:AD24>TODAY()))=0,"VACANT",TEXT(_xludf.minifs('Input Data'!AD3:AD24,'Input Data'!B3:B24,"L08",'Input Data'!AD3:AD24,">"&TODAY(),'Input Data'!AE3:AE24,">0"),"YYYY")),"—") -> —
B68: L07 | C68: =IFERROR(MID(IF(('Input Data'!AD12>TODAY())*('Input Data'!AE12>0),", "&'Input Data'!AF12&" ("&'Input Data'!C12&")","")&IF(('Input Data'!AD13>TODAY())*('Input Data'!AE13>0),", "&'Input Data'!AF13&" ("&'Input Data'!C13&")",""),3,999),"—") -> Sungrow (L7 Main) (7.01) | E68: =SUMPRODUCT(('Input Data'!B3:B24="L07")*'Input Data'!F3:F24) -> 849.6 | G68: =SUMPRODUCT(('Input Data'!B3:B24="L07")*('Input Data'!AD3:AD24>TODAY())*('Input Data'!AE3:AE24>0)*'Input Data'!Q3:Q24) -> 693732.3 | K68: =IFERROR(IF(SUMPRODUCT(('Input Data'!B3:B24="L07")*('Input Data'!AE3:AE24>0)*('Input Data'!AD3:AD24>TODAY()))=0,"VACANT",TEXT(_xludf.minifs('Input Data'!AD3:AD24,'Input Data'!B3:B24,"L07",'Input Data'!AD3:AD24,">"&TODAY(),'Input Data'!AE3:AE24,">0"),"YYYY")),"—") -> —
B69: L06 | C69: =IFERROR(MID(IF(('Input Data'!AD9>TODAY())*('Input Data'!AE9>0),", "&'Input Data'!AF9&" ("&'Input Data'!C9&")","")&IF(('Input Data'!AD10>TODAY())*('Input Data'!AE10>0),", "&'Input Data'!AF10&" ("&'Input Data'!C10&")","")&IF(('Input Data'!AD11>TODAY())*('Input Data'!AE11>0),", "&'Input Data'!AF11&" ("&'Input Data'!C11&")","")&IF(('Input Data'!AD20>TODAY())*('Input Data'!AE20>0),", "&'Input Data'!AF20&" ("&'Input Data'!C20&")",""),3,999),"—") -> Sungrow (L6) (6.02), Keeping Company (6.03), Elekta (6.04), Caldas Constructions (6.01) | E69: =SUMPRODUCT(('Input Data'!B3:B24="L06")*'Input Data'!F3:F24) -> 1095.4 | G69: =SUMPRODUCT(('Input Data'!B3:B24="L06")*('Input Data'!AD3:AD24>TODAY())*('Input Data'!AE3:AE24>0)*'Input Data'!Q3:Q24) -> 333097.14 | K69: =IFERROR(IF(SUMPRODUCT(('Input Data'!B3:B24="L06")*('Input Data'!AE3:AE24>0)*('Input Data'!AD3:AD24>TODAY()))=0,"VACANT",TEXT(_xludf.minifs('Input Data'!AD3:AD24,'Input Data'!B3:B24,"L06",'Input Data'!AD3:AD24,">"&TODAY(),'Input Data'!AE3:AE24,">0"),"YYYY")),"—") -> —
B70: L05 | C70: =IFERROR(MID(IF(('Input Data'!AD6>TODAY())*('Input Data'!AE6>0),", "&'Input Data'!AF6&" ("&'Input Data'!C6&")","")&IF(('Input Data'!AD7>TODAY())*('Input Data'!AE7>0),", "&'Input Data'!AF7&" ("&'Input Data'!C7&")","")&IF(('Input Data'!AD8>TODAY())*('Input Data'!AE8>0),", "&'Input Data'!AF8&" ("&'Input Data'!C8&")",""),3,999),"—") -> Fitness First N. Sydney (5.01), Asterx (MediRecords) (5.03), Auctionsplus (5.04) | E70: =SUMPRODUCT(('Input Data'!B3:B24="L05")*'Input Data'!F3:F24) -> 1080.4 | G70: =SUMPRODUCT(('Input Data'!B3:B24="L05")*('Input Data'!AD3:AD24>TODAY())*('Input Data'!AE3:AE24>0)*'Input Data'!Q3:Q24) -> 948757.8 | K70: =IFERROR(IF(SUMPRODUCT(('Input Data'!B3:B24="L05")*('Input Data'!AE3:AE24>0)*('Input Data'!AD3:AD24>TODAY()))=0,"VACANT",TEXT(_xludf.minifs('Input Data'!AD3:AD24,'Input Data'!B3:B24,"L05",'Input Data'!AD3:AD24,">"&TODAY(),'Input Data'!AE3:AE24,">0"),"YYYY")),"—") -> —
B71: L04 | C71: =IFERROR(MID(IF(('Input Data'!AD5>TODAY())*('Input Data'!AE5>0),", "&'Input Data'!AF5&" ("&'Input Data'!C5&")",""),3,999),"—") -> Fitness First (L4) (4.01) | E71: =SUMPRODUCT(('Input Data'!B3:B24="L04")*'Input Data'!F3:F24) -> 1047 | G71: =SUMPRODUCT(('Input Data'!B3:B24="L04")*('Input Data'!AD3:AD24>TODAY())*('Input Data'!AE3:AE24>0)*'Input Data'!Q3:Q24) -> 906078.3 | K71: =IFERROR(IF(SUMPRODUCT(('Input Data'!B3:B24="L04")*('Input Data'!AE3:AE24>0)*('Input Data'!AD3:AD24>TODAY()))=0,"VACANT",TEXT(_xludf.minifs('Input Data'!AD3:AD24,'Input Data'!B3:B24,"L04",'Input Data'!AD3:AD24,">"&TODAY(),'Input Data'!AE3:AE24,">0"),"YYYY")),"—") -> —
B72: L03 | C72: =IFERROR(MID(IF(('Input Data'!AD3>TODAY())*('Input Data'!AE3>0),", "&'Input Data'!AF3&" ("&'Input Data'!C3&")","")&IF(('Input Data'!AD4>TODAY())*('Input Data'!AE4>0),", "&'Input Data'!AF4&" ("&'Input Data'!C4&")",""),3,999),"—") -> Sydney Smiletree (3.01), Fitness First (L3) (3.02) | E72: =SUMPRODUCT(('Input Data'!B3:B24="L03")*'Input Data'!F3:F24) -> 903.2 | G72: =SUMPRODUCT(('Input Data'!B3:B24="L03")*('Input Data'!AD3:AD24>TODAY())*('Input Data'!AE3:AE24>0)*'Input Data'!Q3:Q24) -> 852270.73 | K72: =IFERROR(IF(SUMPRODUCT(('Input Data'!B3:B24="L03")*('Input Data'!AE3:AE24>0)*('Input Data'!AD3:AD24>TODAY()))=0,"VACANT",TEXT(_xludf.minifs('Input Data'!AD3:AD24,'Input Data'!B3:B24,"L03",'Input Data'!AD3:AD24,">"&TODAY(),'Input Data'!AE3:AE24,">0"),"YYYY")),"—") -> —
B73: TOTAL / BUILDING | E73: =SUM('Input Data'!F3:F24) -> 8940.9 | G73: =SUM('Input Data'!Q3:Q24) -> 6606792.7 | I73: 100.0%
B75: ASSET VALUATION SUMMARY
E76: Latest Valuation (Val 1) | F76: Previous (Val 2) | H76: Prior (Val 3) | J76: Movement (Val 1 vs Val 2)
B77: Valuation Amount ($) | E77: =Valuations!C6 -> 0 | F77: =Valuations!D6 -> 0 | H77: =Valuations!E6 -> 0 | J77: =IFERROR(E77-G77,"") -> 0 | L77: =IFERROR((E77-G77)/G77,"")
B78: Date of Valuation | E78: =Valuations!C7 -> 0 | F78: =Valuations!D7 -> 0 | H78: =Valuations!E7 -> 0 | J78: —
B79: Valuer / Firm | E79: =Valuations!C8 -> 0 | F79: =Valuations!D8 -> 0 | H79: =Valuations!E8 -> 0 | J79: —
B80: Capitalisation Rate | E80: =Valuations!C10 -> 0 | F80: =Valuations!D10 -> 0 | H80: =Valuations!E10 -> 0 | J80: =IFERROR(E80-G80,"") -> 0 | L80: =IFERROR((E80-G80)/G80,"")
B81: Passing Yield | E81: =Valuations!C11 -> 0 | F81: =Valuations!D11 -> 0 | H81: =Valuations!E11 -> 0 | J81: =IFERROR(E81-G81,"") -> 0 | L81: =IFERROR((E81-G81)/G81,"")
B82: Land Value | E82: =Valuations!C12 -> 0 | F82: =Valuations!D12 -> 0 | H82: =Valuations!E12 -> 0 | J82: =IFERROR(E82-G82,"") -> 0 | L82: =IFERROR((E82-G82)/G82,"")
B83: Valuation Basis | E83: =Valuations!C9 -> 0 | F83: =Valuations!D9 -> 0 | H83: =Valuations!E9 -> 0 | J83: —
B85: LAND TAX SUMMARY — NSW
E86: Assessment 1 (Latest) | F86: Assessment 2 | H86: Assessment 3 | J86: Land Value Movement
B87: Land Tax Year | E87: =Valuations!C20 -> 0 | F87: =Valuations!D20 -> 0 | H87: =Valuations!E20 -> 0 | J87: —
B88: Assessed Land Value ($) | E88: =Valuations!C21 -> 0 | F88: =Valuations!D21 -> 0 | H88: =Valuations!E21 -> 0 | J88: =IFERROR(E88-G88,"") -> 0 | L88: =IFERROR((E88-G88)/G88,"")
B89: Land Tax Payable ($) | E89: =Valuations!C22 -> 0 | F89: =Valuations!D22 -> 0 | H89: =Valuations!E22 -> 0 | J89: =IFERROR(E89-G89,"") -> 0 | L89: =IFERROR((E89-G89)/G89,"")
B90: Assessment Date | E90: =Valuations!C23 -> 0 | F90: =Valuations!D23 -> 0 | H90: =Valuations!E23 -> 0 | J90: —
B92: Mortgage details recorded in Valuations tab only | Update Valuations tab after each new valuation or land tax assessment

Sheet Valuations
A1: 1 ELIZABETH PLAZA, NORTH SYDNEY — VALUATIONS, LAND TAX & MORTGAGE REGISTER
A2: Yellow cells = input. All Dashboard valuation figures pull from this tab automatically. Update each time a new valuation or assessment is received.
B4: PROPERTY VALUATIONS
C5: Valuation 1 (Most Recent) | D5: Valuation 2 | E5: Valuation 3 | F5: Notes
B6: Valuation Amount
B7: Date of Valuation
B8: Valuer / Firm
B9: Valuation Basis
B10: Capitalisation Rate (%)
B11: Passing Yield (%)
B12: Land Value ($)
B13: Improvement Value ($)
B14: VALUATION MOVEMENT
B15: Val 1 vs Val 2 ($) | C15: =IFERROR(C6-D6,"") -> 0 | E15: =IFERROR((C6-D6)/D6,"")
B16: Val 2 vs Val 3 ($) | C16: =IFERROR(D6-E6,"") -> 0 | E16: =IFERROR((D6-E6)/E6,"")
B18: LAND TAX ASSESSMENTS — NSW
C19: Assessment 1 (Most Recent) | D19: Assessment 2 | E19: Assessment 3 | F19: Notes
B20: Land Tax Year
B21: Assessed Land Value ($)
B22: Land Tax Payable ($)
B23: Assessment Date
B24: Threshold Applied ($)
B25: Tax Rate Applied (%)
B26: Payment Due Date
B27: Assessment Reference / Notice
B29: LAND VALUE MOVEMENT
B30: Assessment 1 vs 2 Land Value Change | C30: =IFERROR(C21-D21,"") -> 0 | E30: =IFERROR((C21-D21)/D21,"")
B31: Assessment 2 vs 3 Land Value Change | C31: =IFERROR(D21-E21,"") -> 0 | E31: =IFERROR((D21-E21)/E21,"")
B33: MORTGAGE / DEBT DETAILS — (Not displayed on Dashboard)
B34: Field | D34: Current | G34: Prior
B35: Lender / Bank
B36: Loan Amount ($)
B37: As at Date
B38: Interest Rate (%)
B39: Loan Type
B40: Facility Expiry / Review Date
B41: LVR (%) | D41: =IFERROR(D36/Valuations!C6,"")
B42: Interest Cover Ratio (ICR)
B43: Covenants / Notes
B45: LEGEND: Yellow = input | Teal = calculated | Valuation 1 = most recent | LVR auto-calculates from Loan Amount ÷ Latest Valuation

Sheet Market Rents 26-27
A1: 1 ELIZABETH PLAZA, NORTH SYDNEY — MARKET RENTS 2026-27 | Face Rent PSM ($) | Update annually or when market moves materially
A2: Source: Market assessment 2026 | Update annually or when market moves | Market PSM (col E) feeds Var to Mkt analysis in Input Data tab | Yellow = input cells
B3: Suite | C3: Size (sqm) | D3: Current Tenant | E3: Passing PSM ($) | F3: Market Rent PSM ($) | G3: Var ($) | H3: Var (%) | I3: New Tenant Incentive 3yr | J3: 4yr | K3: 5yr | L3: Renewal Incentive 3yr | M3: 5yr
B4: 3.01 | C4: =IFERROR(INDEX('Input Data'!F:F,MATCH(B4,'Input Data'!$C:$C,0)),"") -> 107.7 | D4: =IFERROR(INDEX('Input Data'!D:D,MATCH(B4,'Input Data'!$C:$C,0)),"") -> Sydney Smiletree Pty Ltd | E4: =IFERROR(INDEX('Input Data'!J:J,MATCH(B4,'Input Data'!$C:$C,0)),"") -> 1395.94 | F4: 950 | G4: =IFERROR(E4-F4,"") -> 445.94 | H4: =IFERROR((E4-F4)/F4,"") -> 0.46941053 | I4: 35-45% | J4: 38-45% | K4: 40-45% | L4: 28-32% | M4: 35-42%
B5: 3.02 | C5: =IFERROR(INDEX('Input Data'!F:F,MATCH(B5,'Input Data'!$C:$C,0)),"") -> 795.5 | D5: =IFERROR(INDEX('Input Data'!D:D,MATCH(B5,'Input Data'!$C:$C,0)),"") -> Fitness First Australia Pty Limited | E5: =IFERROR(INDEX('Input Data'!J:J,MATCH(B5,'Input Data'!$C:$C,0)),"") -> 855.7 | F5: 870 | G5: =IFERROR(E5-F5,"") -> -14.3 | H5: =IFERROR((E5-F5)/F5,"") -> -0.016436782 | I5: 35-45% | J5: 38-45% | K5: 40-45% | L5: 28-32% | M5: 35-42%
B6: 4.01 | C6: =IFERROR(INDEX('Input Data'!F:F,MATCH(B6,'Input Data'!$C:$C,0)),"") -> 1047 | D6: =IFERROR(INDEX('Input Data'!D:D,MATCH(B6,'Input Data'!$C:$C,0)),"") -> Fitness First Australia Pty Limited | E6: =IFERROR(INDEX('Input Data'!J:J,MATCH(B6,'Input Data'!$C:$C,0)),"") -> 855.7 | F6: 870 | G6: =IFERROR(E6-F6,"") -> -14.3 | H6: =IFERROR((E6-F6)/F6,"") -> -0.016436782 | I6: 35-45% | J6: 38-45% | K6: 40-45% | L6: 28-32% | M6: 35-42%
B7: 5.01 | C7: =IFERROR(INDEX('Input Data'!F:F,MATCH(B7,'Input Data'!$C:$C,0)),"") -> 437.1 | D7: =IFERROR(INDEX('Input Data'!D:D,MATCH(B7,'Input Data'!$C:$C,0)),"") -> Fitness First Australia Pty Limited | E7: =IFERROR(INDEX('Input Data'!J:J,MATCH(B7,'Input Data'!$C:$C,0)),"") -> 855.7 | F7: 870 | G7: =IFERROR(E7-F7,"") -> -14.3 | H7: =IFERROR((E7-F7)/F7,"") -> -0.016436782 | I7: 35-45% | J7: 38-45% | K7: 40-45% | L7: 28-32% | M7: 35-42%
B8: 5.03 | C8: =IFERROR(INDEX('Input Data'!F:F,MATCH(B8,'Input Data'!$C:$C,0)),"") -> 229.8 | D8: =IFERROR(INDEX('Input Data'!D:D,MATCH(B8,'Input Data'!$C:$C,0)),"") -> Asterx Pty Ltd | E8: =IFERROR(INDEX('Input Data'!J:J,MATCH(B8,'Input Data'!$C:$C,0)),"") -> 985.53 | F8: 1005 | G8: =IFERROR(E8-F8,"") -> -19.47 | H8: =IFERROR((E8-F8)/F8,"") -> -0.019373134 | I8: 35-45% | J8: 38-45% | K8: 40-45% | L8: 28-32% | M8: 35-42%
B9: 5.04 | C9: =IFERROR(INDEX('Input Data'!F:F,MATCH(B9,'Input Data'!$C:$C,0)),"") -> 413.5 | D9: =IFERROR(INDEX('Input Data'!D:D,MATCH(B9,'Input Data'!$C:$C,0)),"") -> Auctionsplus Pty Ltd | E9: =IFERROR(INDEX('Input Data'!J:J,MATCH(B9,'Input Data'!$C:$C,0)),"") -> 1005.89 | F9: 1000 | G9: =IFERROR(E9-F9,"") -> 5.89 | H9: =IFERROR((E9-F9)/F9,"") -> 0.00589 | I9: 35-45% | J9: 38-45% | K9: 40-45% | L9: 28-32% | M9: 35-42%
B10: 6.01 | C10: =IFERROR(INDEX('Input Data'!F:F,MATCH(B10,'Input Data'!$C:$C,0)),"") -> 186.4 | D10: =IFERROR(INDEX('Input Data'!D:D,MATCH(B10,'Input Data'!$C:$C,0)),"") -> Caldas Constructions Pty Ltd | E10: =IFERROR(INDEX('Input Data'!J:J,MATCH(B10,'Input Data'!$C:$C,0)),"") -> 920 | F10: 1010 | G10: =IFERROR(E10-F10,"") -> -90 | H10: =IFERROR((E10-F10)/F10,"") -> -0.089108911 | I10: 35-45% | J10: 38-45% | K10: 40-45% | L10: 28-32% | M10: 35-42%
B11: 6.02 | C11: =IFERROR(INDEX('Input Data'!F:F,MATCH(B11,'Input Data'!$C:$C,0)),"") -> 451.7 | D11: =IFERROR(INDEX('Input Data'!D:D,MATCH(B11,'Input Data'!$C:$C,0)),"") -> Sungrow Australia Group | E11: =IFERROR(INDEX('Input Data'!J:J,MATCH(B11,'Input Data'!$C:$C,0)),"") -> 954.5 | F11: 1005 | G11: =IFERROR(E11-F11,"") -> -50.5 | H11: =IFERROR((E11-F11)/F11,"") -> -0.050248756 | I11: 35-45% | J11: 38-45% | K11: 40-45% | L11: 28-32% | M11: 35-42%
B12: 6.03 | C12: =IFERROR(INDEX('Input Data'!F:F,MATCH(B12,'Input Data'!$C:$C,0)),"") -> 189.4 | D12: =IFERROR(INDEX('Input Data'!D:D,MATCH(B12,'Input Data'!$C:$C,0)),"") -> Keeping Company Pty Ltd | E12: =IFERROR(INDEX('Input Data'!J:J,MATCH(B12,'Input Data'!$C:$C,0)),"") -> 1055.72 | F12: 1010 | G12: =IFERROR(E12-F12,"") -> 45.72 | H12: =IFERROR((E12-F12)/F12,"") -> 0.045267327 | I12: 35-45% | J12: 38-45% | K12: 40-45% | L12: 28-32% | M12: 35-42%
B13: 6.04 | C13: =IFERROR(INDEX('Input Data'!F:F,MATCH(B13,'Input Data'!$C:$C,0)),"") -> 267.9 | D13: =IFERROR(INDEX('Input Data'!D:D,MATCH(B13,'Input Data'!$C:$C,0)),"") -> Elekta Pty Limited | E13: =IFERROR(INDEX('Input Data'!J:J,MATCH(B13,'Input Data'!$C:$C,0)),"") -> 954.5 | F13: 1005 | G13: =IFERROR(E13-F13,"") -> -50.5 | H13: =IFERROR((E13-F13)/F13,"") -> -0.050248756 | I13: 35-45% | J13: 38-45% | K13: 40-45% | L13: 28-32% | M13: 35-42%
B14: 7.01 | C14: =IFERROR(INDEX('Input Data'!F:F,MATCH(B14,'Input Data'!$C:$C,0)),"") -> 484.1 | D14: =IFERROR(INDEX('Input Data'!D:D,MATCH(B14,'Input Data'!$C:$C,0)),"") -> Sungrow Australia Group | E14: =IFERROR(INDEX('Input Data'!J:J,MATCH(B14,'Input Data'!$C:$C,0)),"") -> 1911.44 | F14: 1015 | G14: =IFERROR(E14-F14,"") -> 896.44 | H14: =IFERROR((E14-F14)/F14,"") -> 0.88319212 | I14: 35-45% | J14: 38-45% | K14: 40-45% | L14: 28-32% | M14: 35-42%
B15: 7.02 | C15: =IFERROR(INDEX('Input Data'!F:F,MATCH(B15,'Input Data'!$C:$C,0)),"") -> 365.5 | D15: =IFERROR(INDEX('Input Data'!D:D,MATCH(B15,'Input Data'!$C:$C,0)),"") -> Sungrow Australia Group | E15: =IFERROR(INDEX('Input Data'!J:J,MATCH(B15,'Input Data'!$C:$C,0)),"") -> 0 | F15: 1015 | G15: =IFERROR(E15-F15,"") -> -1015 | H15: =IFERROR((E15-F15)/F15,"") -> -1 | I15: 35-45% | J15: 38-45% | K15: 40-45% | L15: 28-32% | M15: 35-42%
... B19: 9.02 | C19: =IFERROR(INDEX('Input Data'!F:F,MATCH(B19,'Input Data'!$C:$C,0)),"") -> 344.5 | D19: =IFERROR(INDEX('Input Data'!D:D,MATCH(B19,'Input Data'!$C:$C,0)),"") -> Smile Partners Australia | E19: =IFERROR(INDEX('Input Data'!J:J,MATCH(B19,'Input Data'!$C:$C,0)),"") -> 990.29 | F19: 1030 | G19: =IFERROR(E19-F19,"") -> -39.71 | H19: =IFERROR((E19-F19)/F19,"") -> -0.038553398 | I19: 35-45% | J19: 38-45% | K19: 40-45% | L19: 28-32% | M19: 35-42%
B20: 10.01 | C20: =IFERROR(INDEX('Input Data'!F:F,MATCH(B20,'Input Data'!$C:$C,0)),"") | D20: =IFERROR(INDEX('Input Data'!D:D,MATCH(B20,'Input Data'!$C:$C,0)),"") | E20: =IFERROR(INDEX('Input Data'!J:J,MATCH(B20,'Input Data'!$C:$C,0)),"") | F20: 1040 | G20: =IFERROR(E20-F20,"") | H20: =IFERROR((E20-F20)/F20,"") | I20: 35-45% | J20: 38-45% | K20: 40-45% | L20: 28-32% | M20: 35-42%
B21: 10.02 | C21: =IFERROR(INDEX('Input Data'!F:F,MATCH(B21,'Input Data'!$C:$C,0)),"") | D21: =IFERROR(INDEX('Input Data'!D:D,MATCH(B21,'Input Data'!$C:$C,0)),"") | E21: =IFERROR(INDEX('Input Data'!J:J,MATCH(B21,'Input Data'!$C:$C,0)),"") | F21: 1040 | G21: =IFERROR(E21-F21,"") | H21: =IFERROR((E21-F21)/F21,"") | I21: 35-45% | J21: 38-45% | K21: 40-45% | L21: 28-32% | M21: 35-42%
B22: 11.01 | C22: =IFERROR(INDEX('Input Data'!F:F,MATCH(B22,'Input Data'!$C:$C,0)),"") | D22: =IFERROR(INDEX('Input Data'!D:D,MATCH(B22,'Input Data'!$C:$C,0)),"") | E22: =IFERROR(INDEX('Input Data'!J:J,MATCH(B22,'Input Data'!$C:$C,0)),"") | F22: 1045 | G22: =IFERROR(E22-F22,"") | H22: =IFERROR((E22-F22)/F22,"") | I22: 35-45% | J22: 38-45% | K22: 40-45% | L22: 28-32% | M22: 35-42%
B23: 11.02 | C23: 536 | D23: =IFERROR(INDEX('Input Data'!D:D,MATCH(B23,'Input Data'!$C:$C,0)),"") | E23: =IFERROR(INDEX('Input Data'!J:J,MATCH(B23,'Input Data'!$C:$C,0)),"") | F23: 1040 | G23: =IFERROR(E23-F23,"") | H23: =IFERROR((E23-F23)/F23,"") | I23: 35-45% | J23: 38-45% | K23: 40-45% | L23: 28-32% | M23: 35-42%
B24: 12.01 | C24: =IFERROR(INDEX('Input Data'!F:F,MATCH(B24,'Input Data'!$C:$C,0)),"") -> 251 | D24: =IFERROR(INDEX('Input Data'!D:D,MATCH(B24,'Input Data'!$C:$C,0)),"") -> Hulsbosch Design Pty Ltd | E24: =IFERROR(INDEX('Input Data'!J:J,MATCH(B24,'Input Data'!$C:$C,0)),"") -> 985 | F24: 1045 | G24: =IFERROR(E24-F24,"") -> -60 | H24: =IFERROR((E24-F24)/F24,"") -> -0.057416268 | I24: 0.24 | J24: 0.27 | K24: 0.3 | L24: 0.22 | M24: 0.27
B25: 12.02 | C25: =IFERROR(INDEX('Input Data'!F:F,MATCH(B25,'Input Data'!$C:$C,0)),"") -> 536 | D25: =IFERROR(INDEX('Input Data'!D:D,MATCH(B25,'Input Data'!$C:$C,0)),"") -> AEI Insurance Group Pty Ltd | E25: =IFERROR(INDEX('Input Data'!J:J,MATCH(B25,'Input Data'!$C:$C,0)),"") -> 988 | F25: 1050 | G25: =IFERROR(E25-F25,"") -> -62 | H25: =IFERROR((E25-F25)/F25,"") -> -0.059047619 | I25: 0.24 | J25: 0.27 | K25: 0.3 | L25: 0.22 | M25: 0.27
B26: PORTFOLIO MARKET RENT SUMMARY | E26: =IFERROR(SUMPRODUCT(C4:C25,E4:E25)/SUM(C4:C25),"") -> 905.6931 | F26: =IFERROR(SUMPRODUCT(C4:C25,F4:F25)/SUM(C4:C25),"") -> 976.65791
B28: LEGEND: Yellow = input (update market PSM and incentive rates each assessment) | Red rows = expired/vacant suites | Var $ and % auto-calculate from Input Data | Incentive rates = gross incentive as % of gross rent

Sheet Expiry Profile
A1: 1 ELIZABETH PLAZA — LEASE EXPIRY PROFILE | As at 30/09/2026 | ALL DATA SOURCED FROM INPUT DATA TAB
B2: Floor | C2: Tenant / Suite | D2: NLA (sqm) | E2: Lease Start | F2: Lease Expiry | G2: Term (Yrs) | H2: Rem. (Yrs) | I2: Face PSM ($) | J2: Net Eff PA ($) | K2: Expiry Year | L2: Cars | M2: Review Type | N2: Var to Mkt ($)
B3: EXPIRY 2027
B4: ='Input Data'!B10 -> L06 | C4: =IFERROR('Input Data'!D10&" ("&'Input Data'!C10&")","—") -> Keeping Company Pty Ltd (6.03) | D4: ='Input Data'!F10 -> 189.4 | E4: =IFERROR('Input Data'!G10,"") -> 44713 | F4: =IFERROR('Input Data'!H10,"") -> 46538 | G4: ='Input Data'!I10 -> 5 | H4: ='Input Data'!V10 -> 0.62149213 | I4: ='Input Data'!J10 -> 1055.72 | J4: ='Input Data'!Q10 -> 219057.04 | K4: =IFERROR(YEAR('Input Data'!H10),"VACANT") -> 2027 | L4: ='Input Data'!R10 -> 2 | M4: ='Input Data'!S10 -> FIXED 3.5% | N4: ='Input Data'!Y10 -> 65.72
B5: ='Input Data'!B16 -> L09 | C5: =IFERROR('Input Data'!D16&" ("&'Input Data'!C16&")","—") -> Pitt & Sherry (Operations) Pty Ltd (9.01) | D5: ='Input Data'!F16 -> 453.3 | E5: =IFERROR('Input Data'!G16,"") -> 44746 | F5: =IFERROR('Input Data'!H16,"") -> 46571 | G5: ='Input Data'!I16 -> 5 | H5: ='Input Data'!V16 -> 0.7118412 | I5: ='Input Data'!J16 -> 1065.96 | J5: ='Input Data'!Q16 -> 403784.51 | K5: =IFERROR(YEAR('Input Data'!H16),"VACANT") -> 2027 | L5: ='Input Data'!R16 -> 1 | M5: ='Input Data'!S16 -> FIXED 3.75% | N5: ='Input Data'!Y16 -> 25.96
B6: EXPIRY 2028
B7: ='Input Data'!B14 -> L08 | C7: =IFERROR('Input Data'!D14&" ("&'Input Data'!C14&")","—") -> Vanderlande Industries Australia Pty Ltd (8.01) | D7: ='Input Data'!F14 -> 686.7 | E7: =IFERROR('Input Data'!G14,"") -> 43282 | F7: =IFERROR('Input Data'!H14,"") -> 46934 | G7: ='Input Data'!I14 -> 10 | H7: ='Input Data'!V14 -> 1.705681 | I7: ='Input Data'!J14 -> 1029.25 | J7: ='Input Data'!Q14 -> 577101.86 | K7: =IFERROR(YEAR('Input Data'!H14),"VACANT") -> 2028 | L7: ='Input Data'!R14 -> 0 | M7: ='Input Data'!S14 -> FIXED 4% | N7: ='Input Data'!Y14 -> 39.25
B8: ='Input Data'!B3 -> L03 | C8: =IFERROR('Input Data'!D3&" ("&'Input Data'!C3&")","—") -> Sydney Smiletree Pty Ltd (3.01) | D8: ='Input Data'!F3 -> 107.7 | E8: =IFERROR('Input Data'!G3,"") -> 44013 | F8: =IFERROR('Input Data'!H3,"") -> 47118 | G8: ='Input Data'!I3 -> 8.5 | H8: ='Input Data'!V3 -> 2.2094456 | I8: ='Input Data'!J3 -> 1395.94 | J8: ='Input Data'!Q3 -> 171561.38 | K8: =IFERROR(YEAR('Input Data'!H3),"VACANT") -> 2028 | L8: ='Input Data'!R3 -> 1 | M8: ='Input Data'!S3 -> FIXED 4% | N8: ='Input Data'!Y3 -> 445.94
B9: EXPIRY 2029
B10: ='Input Data'!B8 -> L05 | C10: =IFERROR('Input Data'!D8&" ("&'Input Data'!C8&")","—") -> Auctionsplus Pty Ltd (5.04) | D10: ='Input Data'!F8 -> 413.5 | E10: =IFERROR('Input Data'!G8,"") -> 45352 | F10: =IFERROR('Input Data'!H8,"") -> 47177 | G10: ='Input Data'!I8 -> 5 | H10: ='Input Data'!V8 -> 2.3709788 | I10: ='Input Data'!J8 -> 1005.89 | J10: ='Input Data'!Q8 -> 366667.89 | K10: =IFERROR(YEAR('Input Data'!H8),"VACANT") -> 2029 | L10: ='Input Data'!R8 -> 1 | M10: ='Input Data'!S8 -> FIXED 4% | N10: ='Input Data'!Y8 -> 15.89
B11: ='Input Data'!B7 -> L05 | C11: =IFERROR('Input Data'!D7&" ("&'Input Data'!C7&")","—") -> Asterx Pty Ltd (5.03) | D11: ='Input Data'!F7 -> 229.8 | E11: =IFERROR('Input Data'!G7,"") -> 45474 | F11: =IFERROR('Input Data'!H7,"") -> 47299 | G11: ='Input Data'!I7 -> 5 | H11: ='Input Data'!V7 -> 2.7049966 | I11: ='Input Data'!J7 -> 985.53 | J11: ='Input Data'!Q7 -> 205033.43 | K11: =IFERROR(YEAR('Input Data'!H7),"VACANT") -> 2029 | L11: ='Input Data'!R7 -> 1 | M11: ='Input Data'!S7 -> FIXED 3.5% | N11: ='Input Data'!Y7 -> 35.53
B12: ='Input Data'!B9 -> L06 | C12: =IFERROR('Input Data'!D9&" ("&'Input Data'!C9&")","—") -> Sungrow Australia Group (6.02) | D12: ='Input Data'!F9 -> 451.7 | E12: =IFERROR('Input Data'!G9,"") -> 45762 | F12: =IFERROR('Input Data'!H9,"") -> 47375 | G12: ='Input Data'!I9 -> 4.4 | H12: ='Input Data'!V9 -> 2.9130732 | I12: ='Input Data'!J9 -> 954.5 | J12: ='Input Data'!Q9 -> 283260.35 | K12: =IFERROR(YEAR('Input Data'!H9),"VACANT") -> 2029 | L12: ='Input Data'!R9 -> 1 | M12: ='Input Data'!S9 -> FIXED 3.75% | N12: ='Input Data'!Y9 -> -0.5
B13: ='Input Data'!B12 -> L07 | C13: =IFERROR('Input Data'!D12&" ("&'Input Data'!C12&")","—") -> Sungrow Australia Group (7.01) | D13: ='Input Data'!F12 -> 484.1 | E13: =IFERROR('Input Data'!G12,"") -> 45184 | F13: =IFERROR('Input Data'!H12,"") -> 47375 | G13: ='Input Data'!I12 -> 6 | H13: ='Input Data'!V12 -> 2.9130732 | I13: ='Input Data'!J12 -> 1911.44 | J13: ='Input Data'!Q12 -> 693732.3 | K13: =IFERROR(YEAR('Input Data'!H12),"VACANT") -> 2029 | L13: ='Input Data'!R12 -> 2 | M13: ='Input Data'!S12 -> FIXED 3.75% | N13: ='Input Data'!Y12 -> 891.44
B14: ='Input Data'!B13 -> L07 | C14: =IFERROR('Input Data'!D13&" ("&'Input Data'!C13&")","—") -> Sungrow Australia Group (7.02) | D14: ='Input Data'!F13 -> 365.5 | E14: =IFERROR('Input Data'!G13,"") -> 45184 | F14: =IFERROR('Input Data'!H13,"") -> 47375 | G14: ='Input Data'!I13 -> 6 | H14: ='Input Data'!V13 -> 2.9130732 | I14: ='Input Data'!J13 -> 0 | J14: ='Input Data'!Q13 -> 37146.72 | K14: =IFERROR(YEAR('Input Data'!H13),"VACANT") -> 2029 | L14: ='Input Data'!R13 -> 0 | M14: ='Input Data'!S13 -> FIXED 3.75% | N14: ='Input Data'!Y13 -> 0
B15: ='Input Data'!B17 -> L12 | C15: =IFERROR('Input Data'!D17&" ("&'Input Data'!C17&")","—") -> Hulsbosch Design Pty Ltd (12.01) | D15: ='Input Data'!F17 -> 251 | E15: =IFERROR('Input Data'!G17,"") -> 45962 | F15: =IFERROR('Input Data'!H17,"") -> 47787 | G15: ='Input Data'!I17 -> 5 | H15: ='Input Data'!V17 -> 4.0410678 | I15: ='Input Data'!J17 -> 985 | J15: ='Input Data'!Q17 -> 191159.6 | K15: =IFERROR(YEAR('Input Data'!H17),"VACANT") -> 2030 | L15: ='Input Data'!R17 -> 0 | M15: ='Input Data'!S17 -> FIXED 3.5% | N15: ='Input Data'!Y17 -> -55
B16: EXPIRY 2030
B17: ='Input Data'!B15 -> L08 | C17: =IFERROR('Input Data'!D15&" ("&'Input Data'!C15&")","—") -> Can Too Foundation Limited (8.03) | D17: ='Input Data'!F15 -> 116.3 | E17: =IFERROR('Input Data'!G15,"") -> 45809 | F17: =IFERROR('Input Data'!H15,"") -> 47787 | G17: ='Input Data'!I15 -> 5.4 | H17: ='Input Data'!V15 -> 4.0410678 | I17: ='Input Data'!J15 -> 1027.12 | J17: ='Input Data'!Q15 -> 76042.556 | K17: =IFERROR(YEAR('Input Data'!H15),"VACANT") -> 2030 | L17: ='Input Data'!R15 -> 0 | M17: ='Input Data'!S15 -> FIXED 3.75% | N17: ='Input Data'!Y15 -> 37.12
B18: ='Input Data'!B18 -> L09 | C18: =IFERROR('Input Data'!D18&" ("&'Input Data'!C18&")","—") -> Smile Partners Australia (9.02) | D18: ='Input Data'!F18 -> 344.5 | E18: =IFERROR('Input Data'!G18,"") -> 45992 | F18: =IFERROR('Input Data'!H18,"") -> 47483 | G18: ='Input Data'!I18 -> 4.1 | H18: ='Input Data'!V18 -> 3.2087611 | I18: ='Input Data'!J18 -> 990.29 | J18: ='Input Data'!Q18 -> 224063.82 | K18: =IFERROR(YEAR('Input Data'!H18),"VACANT") -> 2029 | L18: ='Input Data'!R18 -> 2 | M18: ='Input Data'!S18 -> FIXED 3.5% | N18: ='Input Data'!Y18 -> 0.29
B19: ='Input Data'!B19 -> L12 | C19: =IFERROR('Input Data'!D19&" ("&'Input Data'!C19&")","—") -> AEI Insurance Group Pty Ltd (12.02) | D19: ='Input Data'!F19 -> 536 | E19: =IFERROR('Input Data'!G19,"") -> 45642 | F19: =IFERROR('Input Data'!H19,"") -> 47832 | G19: ='Input Data'!I19 -> 6 | H19: ='Input Data'!V19 -> 4.164271 | I19: ='Input Data'!J19 -> 988 | J19: ='Input Data'!Q19 -> 638733.2 | K19: =IFERROR(YEAR('Input Data'!H19),"VACANT") -> 2030 | L19: ='Input Data'!R19 -> 10 | M19: ='Input Data'!S19 -> FIXED 4% | N19: ='Input Data'!Y19 -> -22
B20: EXPIRY 2031+
B21: ='Input Data'!B4 -> L03 | C21: =IFERROR('Input Data'!D4&" ("&'Input Data'!C4&")","—") -> Fitness First Australia Pty Limited (3.02) | D21: ='Input Data'!F4 -> 795.5 | E21: =IFERROR('Input Data'!G4,"") -> 44378 | F21: =IFERROR('Input Data'!H4,"") -> 48029 | G21: ='Input Data'!I4 -> 10 | H21: ='Input Data'!V4 -> 4.7036277 | I21: ='Input Data'!J4 -> 855.7 | J21: ='Input Data'!Q4 -> 680709.35 | K21: =IFERROR(YEAR('Input Data'!H4),"VACANT") -> 2031 | L21: ='Input Data'!R4 -> 0 | M21: ='Input Data'!S4 -> FIXED 4% | N21: ='Input Data'!Y4 -> -14.3
B22: ='Input Data'!B5 -> L04 | C22: =IFERROR('Input Data'!D5&" ("&'Input Data'!C5&")","—") -> Fitness First Australia Pty Limited (4.01) | D22: ='Input Data'!F5 -> 1047 | E22: =IFERROR('Input Data'!G5,"") -> 44378 | F22: =IFERROR('Input Data'!H5,"") -> 48029 | G22: ='Input Data'!I5 -> 10 | H22: ='Input Data'!V5 -> 4.7036277 | I22: ='Input Data'!J5 -> 855.7 | J22: ='Input Data'!Q5 -> 906078.3 | K22: =IFERROR(YEAR('Input Data'!H5),"VACANT") -> 2031 | L22: ='Input Data'!R5 -> 1 | M22: ='Input Data'!S5 -> FIXED 4% | N22: ='Input Data'!Y5 -> -14.3
B23: ='Input Data'!B6 -> L05 | C23: =IFERROR('Input Data'!D6&" ("&'Input Data'!C6&")","—") -> Fitness First Australia Pty Limited (5.01) | D23: ='Input Data'!F6 -> 437.1 | E23: =IFERROR('Input Data'!G6,"") -> 44378 | F23: =IFERROR('Input Data'!H6,"") -> 48029 | G23: ='Input Data'!I6 -> 10 | H23: ='Input Data'!V6 -> 4.7036277 | I23: ='Input Data'!J6 -> 855.7 | J23: ='Input Data'!Q6 -> 377056.47 | K23: =IFERROR(YEAR('Input Data'!H6),"VACANT") -> 2031 | L23: ='Input Data'!R6 -> 0 | M23: ='Input Data'!S6 -> FIXED 4% | N23: ='Input Data'!Y6 -> -14.3
B24: ='Input Data'!B11 -> L06 | C24: =IFERROR('Input Data'!D11&" ("&'Input Data'!C11&")","—") -> Elekta Pty Limited (6.04) | D24: ='Input Data'!F11 -> 267.9 | E24: =IFERROR('Input Data'!G11,"") -> 45870 | F24: =IFERROR('Input Data'!H11,"") -> 48426 | G24: ='Input Data'!I11 -> 7 | H24: ='Input Data'!V11 -> 5.7905544 | I24: ='Input Data'!J11 -> 954.5 | J24: ='Input Data'!Q11 -> 171546.75 | K24: =IFERROR(YEAR('Input Data'!H11),"VACANT") -> 2032 | L24: ='Input Data'!R11 -> 1 | M24: ='Input Data'!S11 -> FIXED (3.75%) | N24: ='Input Data'!Y11 -> -0.5
B25: ='Input Data'!B24 -> L11 | C25: =IFERROR('Input Data'!D24&" ("&'Input Data'!C24&")","—") -> Haskoning Australia Pty Ltd (11.02) | D25: ='Input Data'!F24 -> 548 | E25: =IFERROR('Input Data'!G24,"") -> 46296 | F25: =IFERROR('Input Data'!H24,"") -> 48487 | G25: ='Input Data'!I24 -> 6 | H25: ='Input Data'!V24 -> 5.9575633 | I25: ='Input Data'!J24 -> 1040 | J25: ='Input Data'!Q24 -> 458074.67 | K25: =IFERROR(YEAR('Input Data'!H24),"VACANT") -> 2032 | L25: ='Input Data'!R24 -> 0 | M25: ='Input Data'!S24 -> FIXED 3.5% | N25: ='Input Data'!Y24 -> 0
B26: ='Input Data'!B20 -> L06 | C26: =IFERROR('Input Data'!D20&" ("&'Input Data'!C20&")","—") -> Caldas Constructions Pty Ltd (6.01) | D26: ='Input Data'!F20 -> 186.4 | E26: =IFERROR('Input Data'!G20,"") -> 46204 | F26: =IFERROR('Input Data'!H20,"") -> 48395 | G26: ='Input Data'!I20 -> 6 | H26: ='Input Data'!V20 -> 5.705681 | I26: ='Input Data'!J20 -> 920 | J26: ='Input Data'!Q20 -> -340767 | K26: =IFERROR(YEAR('Input Data'!H20),"VACANT") -> 2032 | L26: ='Input Data'!R20 -> 0 | M26: ='Input Data'!S20 -> 0 | N26: ='Input Data'!Y20 -> 920
B27: ='Input Data'!B23 -> L11 | C27: =IFERROR('Input Data'!D23&" ("&'Input Data'!C23&")","—") -> Luxasia (11.01) | D27: ='Input Data'!F23 -> 242.5 | E27: =IFERROR('Input Data'!G23,"") -> 46296 | F27: =IFERROR('Input Data'!H23,"") -> 48121 | G27: ='Input Data'!I23 -> 5 | H27: ='Input Data'!V23 -> 4.9555099 | I27: ='Input Data'!J23 -> 1060 | J27: ='Input Data'!Q23 -> 266749.52 | K27: =IFERROR(YEAR('Input Data'!H23),"VACANT") -> 2031 | L27: ='Input Data'!R23 -> 2 | M27: ='Input Data'!S23 -> FIXED 3.75% | N27: ='Input Data'!Y23 -> 0
B28: VACANT SUITES
B29: ='Input Data'!B21 -> L10 | C29: ="VACANT — Suite "&'Input Data'!C21 -> VACANT — Suite 10.01 | D29: ='Input Data'!F21 -> 438 | K29: VACANT | N29: ='Input Data'!X21 -> 0
B30: ='Input Data'!B22 -> L10 | C30: ="VACANT — Suite "&'Input Data'!C22 -> VACANT — Suite 10.02 | D30: ='Input Data'!F22 -> 349 | K30: VACANT | N30: ='Input Data'!X22 -> 0
B32: BUILDING TOTALS | D32: =SUM('Input Data'!F3:F24) -> 8940.9 | I32: =SUMPRODUCT(('Input Data'!H3:H24<>"")*'Input Data'!J3:J24*'Input Data'!F3:F24)/SUMPRODUCT(('Input Data'!H3:H24<>"")*'Input Data'!F3:F24) -> 978.84473 | J32: =SUM('Input Data'!Q3:Q24) -> 6606792.7

Sheet Leases
A1: 1 ELIZABETH PLAZA — LEASE REGISTER | As at 30/09/2026 | ALL DATA SOURCED FROM INPUT DATA TAB
A2: Floor | B2: Suite # | C2: Tenant Name | D2: Trading Name | E2: NLA (sqm) | F2: Lease Start | G2: Lease Expiry | H2: Term (Yrs) | I2: Rem. (Yrs) | J2: Face PSM ($) | K2: Mkt PSM ($) | L2: Net Eff PA ($) | M2: Abatement PA ($) | N2: Outgoings PA ($) | O2: Cleaning PA ($) | P2: Car Park PA ($) | Q2: Cars | R2: Review Type | S2: Next Review | T2: Lease Type | U2: Var ($) | V2: Var (%) | W2: WALE Contrib (sqm.yr) | X2: Notes
A3: EXPIRY 2027
A4: ='Input Data'!B10 -> L06 | B4: ='Input Data'!C10 -> 6.03 | C4: ='Input Data'!D10 -> Keeping Company Pty Ltd | D4: ='Input Data'!E10 -> Keeping Company Pty Ltd | E4: ='Input Data'!F10 -> 189.4 | F4: ='Input Data'!G10 -> 44713 | G4: ='Input Data'!H10 -> 46538 | H4: ='Input Data'!I10 -> 5 | I4: ='Input Data'!V10 -> 0.62149213 | J4: ='Input Data'!J10 -> 1055.72 | K4: ='Input Data'!X10 -> 990 | L4: ='Input Data'!Q10 -> 219057.04 | M4: ='Input Data'!L10 -> -23525.37 | N4: ='Input Data'!M10 -> 19249.32 | O4: ='Input Data'!N10 -> 3136.44 | P4: ='Input Data'!O10+'Input Data'!P10 -> 20243.28 | Q4: ='Input Data'!R10 -> 2 | R4: ='Input Data'!S10 -> FIXED 3.5% | S4: =IFERROR('Input Data'!T10,"") -> 46539 | T4: ='Input Data'!U10 -> Semi-Gross | U4: ='Input Data'!Y10 -> 65.72 | V4: ='Input Data'!Z10 -> 0.066383838 | W4: ='Input Data'!W10 -> 117.71061 | X4: ='Input Data'!AB10 -> 2 car spaces. BG: $110,739. Incentive: fitout $177,810 + abatement. Base year FY2021.
A5: ='Input Data'!B16 -> L09 | B5: ='Input Data'!C16 -> 9.01 | C5: ='Input Data'!D16 -> Pitt & Sherry (Operations) Pty Ltd | D5: ='Input Data'!E16 -> Pitt & Sherry (Operations) Pty Ltd | E5: ='Input Data'!F16 -> 453.3 | F5: ='Input Data'!G16 -> 44746 | G5: ='Input Data'!H16 -> 46571 | H5: ='Input Data'!I16 -> 5 | I5: ='Input Data'!V16 -> 0.7118412 | J5: ='Input Data'!J16 -> 1065.96 | K5: ='Input Data'!X16 -> 1040 | L5: ='Input Data'!Q16 -> 403784.51 | M5: ='Input Data'!L16 -> -145962.6 | N5: ='Input Data'!M16 -> 46069.68 | O5: ='Input Data'!N16 -> 7506.6 | P5: ='Input Data'!O16+'Input Data'!P16 -> 12971.16 | Q5: ='Input Data'!R16 -> 1 | R5: ='Input Data'!S16 -> FIXED 3.75% | S5: =IFERROR('Input Data'!T16,"") -> 46572 | T5: ='Input Data'!U16 -> Semi-Gross | U5: ='Input Data'!Y16 -> 25.96 | V5: ='Input Data'!Z16 -> 0.024961538 | W5: ='Input Data'!W16 -> 322.67762 | X5: ='Input Data'!AB16 -> Option: 5 yrs (04/07/27-03/07/32). BG: $281,758. Base year FY2021 5%.
A6: EXPIRY 2028
A7: ='Input Data'!B14 -> L08 | B7: ='Input Data'!C14 -> 8.01 | C7: ='Input Data'!D14 -> Vanderlande Industries Australia Pty Ltd | D7: ='Input Data'!E14 -> Vanderlande Industries Australia Pty Ltd | E7: ='Input Data'!F14 -> 686.7 | F7: ='Input Data'!G14 -> 43282 | G7: ='Input Data'!H14 -> 46934 | H7: ='Input Data'!I14 -> 10 | I7: ='Input Data'!V14 -> 1.705681 | J7: ='Input Data'!J14 -> 1029.25 | K7: ='Input Data'!X14 -> 990 | L7: ='Input Data'!Q14 -> 577101.86 | M7: ='Input Data'!L14 -> -219915.72 | N7: ='Input Data'!M14 -> 78859.8 | O7: ='Input Data'!N14 -> 11371.8 | P7: ='Input Data'!O14+'Input Data'!P14 -> 0 | Q7: ='Input Data'!R14 -> 0 | R7: ='Input Data'!S14 -> FIXED 4% | S7: =IFERROR('Input Data'!T14,"") -> 46569 | T7: ='Input Data'!U14 -> Semi-Gross | U7: ='Input Data'!Y14 -> 39.25 | V7: ='Input Data'!Z14 -> 0.039646465 | W7: ='Input Data'!W14 -> 1171.2912 | X7: ='Input Data'!AB14 -> Base year FY2015 7.57%. BG: $288,500. Make good: full open plan. Cleaning $15 psm.
A8: ='Input Data'!B3 -> L03 | B8: ='Input Data'!C3 -> 3.01 | C8: ='Input Data'!D3 -> Sydney Smiletree Pty Ltd | D8: ='Input Data'!E3 -> The Trustee for Sydney Smiletree Unit Trust | E8: ='Input Data'!F3 -> 107.7 | F8: ='Input Data'!G3 -> 44013 | G8: ='Input Data'!H3 -> 47118 | H8: ='Input Data'!I3 -> 8.5 | I8: ='Input Data'!V3 -> 2.2094456 | J8: ='Input Data'!J3 -> 1395.94 | K8: ='Input Data'!X3 -> 950 | L8: ='Input Data'!Q3 -> 171561.38 | M8: ='Input Data'!L3 -> 0 | N8: ='Input Data'!M3 -> 9156 | O8: ='Input Data'!N3 -> 0 | P8: ='Input Data'!O3+'Input Data'!P3 -> 12062.64 | Q8: ='Input Data'!R3 -> 1 | R8: ='Input Data'!S3 -> FIXED 4% | S8: =IFERROR('Input Data'!T3,"") -> 46569 | T8: ='Input Data'!U3 -> Net | U8: ='Input Data'!Y3 -> 445.94 | V8: ='Input Data'!Z3 -> 0.46941053 | W8: ='Input Data'!W3 -> 237.95729 | X8: ='Input Data'!AB3 -> Option: 5 yrs. BG: $86,814. Car Space 16.
A9: EXPIRY 2029
A10: ='Input Data'!B8 -> L05 | B10: ='Input Data'!C8 -> 5.04 | C10: ='Input Data'!D8 -> Auctionsplus Pty Ltd | D10: ='Input Data'!E8 -> Auctionsplus Pty Ltd | E10: ='Input Data'!F8 -> 413.5 | F10: ='Input Data'!G8 -> 45352 | G10: ='Input Data'!H8 -> 47177 | H10: ='Input Data'!I8 -> 5 | I10: ='Input Data'!V8 -> 2.3709788 | J10: ='Input Data'!J8 -> 1005.89 | K10: ='Input Data'!X8 -> 990 | L10: ='Input Data'!Q8 -> 366667.89 | M10: ='Input Data'!L8 -> -104594.82 | N10: ='Input Data'!M8 -> 40068.6 | O10: ='Input Data'!N8 -> 6847.56 | P10: ='Input Data'!O8+'Input Data'!P8 -> 8411.04 | Q10: ='Input Data'!R8 -> 1 | R10: ='Input Data'!S8 -> FIXED 4% | S10: =IFERROR('Input Data'!T8,"") -> 46447 | T10: ='Input Data'!U8 -> Semi-Gross | U10: ='Input Data'!Y8 -> 15.89 | V10: ='Input Data'!Z8 -> 0.016050505 | W10: ='Input Data'!W8 -> 980.39973 | X10: ='Input Data'!AB8 -> Semi-gross base year FY24 2.4%. BG equiv $199,187 incl GST. Incentive: fitout contribution $672,971.
A11: ='Input Data'!B7 -> L05 | B11: ='Input Data'!C7 -> 5.03 | C11: ='Input Data'!D7 -> Asterx Pty Ltd | D11: ='Input Data'!E7 -> Asterx Pty Ltd (MediRecords) | E11: ='Input Data'!F7 -> 229.8 | F11: ='Input Data'!G7 -> 45474 | G11: ='Input Data'!H7 -> 47299 | H11: ='Input Data'!I7 -> 5 | I11: ='Input Data'!V7 -> 2.7049966 | J11: ='Input Data'!J7 -> 985.53 | K11: ='Input Data'!X7 -> 950 | L11: ='Input Data'!Q7 -> 205033.43 | M11: ='Input Data'!L7 -> -46511.52 | N11: ='Input Data'!M7 -> 10521.96 | O11: ='Input Data'!N7 -> 3805.44 | P11: ='Input Data'!O7+'Input Data'!P7 -> 10742.76 | Q11: ='Input Data'!R7 -> 1 | R11: ='Input Data'!S7 -> FIXED 3.5% | S11: =IFERROR('Input Data'!T7,"") -> 46569 | T11: ='Input Data'!U7 -> Semi-Gross | U11: ='Input Data'!Y7 -> 35.53 | V11: ='Input Data'!Z7 -> 0.0374 | W11: ='Input Data'!W7 -> 621.60821 | X11: ='Input Data'!AB7 -> Semi-gross base year FY24. BG: $135,234. 1 car space. Lease start/expiry corrected to 01/07/24–30/06/29 per Sept26 TS (previously recorded as 01/06/24–31/05/29). Abatement, car park rent, cleaning and outgoings all confirmed/updated per Sept26 TS.
A12: ='Input Data'!B9 -> L06 | B12: ='Input Data'!C9 -> 6.02 | C12: ='Input Data'!D9 -> Sungrow Australia Group | D12: ='Input Data'!E9 -> Sungrow Australia Group Pty Ltd | E12: ='Input Data'!F9 -> 451.7 | F12: ='Input Data'!G9 -> 45762 | G12: ='Input Data'!H9 -> 47375 | H12: ='Input Data'!I9 -> 4.4 | I12: ='Input Data'!V9 -> 2.9130732 | J12: ='Input Data'!J9 -> 954.5 | K12: ='Input Data'!X9 -> 955 | L12: ='Input Data'!Q9 -> 283260.35 | M12: ='Input Data'!L9 -> -211720.82 | N12: ='Input Data'!M9 -> 45907.32 | O12: ='Input Data'!N9 -> 7480.2 | P12: ='Input Data'!O9+'Input Data'!P9 -> 10446 | Q12: ='Input Data'!R9 -> 1 | R12: ='Input Data'!S9 -> FIXED 3.75% | S12: =IFERROR('Input Data'!T9,"") -> 46492 | T12: ='Input Data'!U9 -> Semi-Gross | U12: ='Input Data'!Y9 -> -0.5 | V12: ='Input Data'!Z9 -> -0.00052356021 | W12: ='Input Data'!W9 -> 1315.8352 | X12: ='Input Data'!AB9 -> BG: $291,050 (6 mths last yr gross rent). Incentive: 50% of rent as abatement. Make Good: $200 psm.
A13: ='Input Data'!B12 -> L07 | B13: ='Input Data'!C12 -> 7.01 | C13: ='Input Data'!D12 -> Sungrow Australia Group | D13: ='Input Data'!E12 -> Sungrow Australia Group Pty Ltd | E13: ='Input Data'!F12 -> 484.1 | F13: ='Input Data'!G12 -> 45184 | G13: ='Input Data'!H12 -> 47375 | H13: ='Input Data'!I12 -> 6 | I13: ='Input Data'!V12 -> 2.9130732 | J13: ='Input Data'!J12 -> 1911.44 | K13: ='Input Data'!X12 -> 1020 | L13: ='Input Data'!Q12 -> 693732.3 | M13: ='Input Data'!L12 -> -319000.32 | N13: ='Input Data'!M12 -> 49200.48 | O13: ='Input Data'!N12 -> 14069.4 | P13: ='Input Data'!O12+'Input Data'!P12 -> 24134.64 | Q13: ='Input Data'!R12 -> 2 | R13: ='Input Data'!S12 -> FIXED 3.75% | S13: =IFERROR('Input Data'!T12,"") -> 46645 | T13: ='Input Data'!U12 -> Semi-Gross | U13: ='Input Data'!Y12 -> 891.44 | V13: ='Input Data'!Z12 -> 0.87396078 | W13: ='Input Data'!W12 -> 1410.2188 | X13: ='Input Data'!AB12 -> Tandem bays x2. BG: $536,314. Base year FY2021 9.41%. Sept26 TS shows office rent reset to a combined total of $925,326 pa across 7.01+7.02 (849.6 sqm) — PSM above is a blended rate ($925,326/484.1 sqm) to keep this in the existing K=PSM×NLA formula; not a genuine per-sqm market rate, so Var to Mkt for this row is not meaningful. This is an 82% jump on the prior $508k combined rent — flagging for verification against the lease before relying on it.
A14: ='Input Data'!B13 -> L07 | B14: ='Input Data'!C13 -> 7.02 | C14: ='Input Data'!D13 -> Sungrow Australia Group | D14: ='Input Data'!E13 -> Additional Space (Sungrow) | E14: ='Input Data'!F13 -> 365.5 | F14: ='Input Data'!G13 -> 45184 | G14: ='Input Data'!H13 -> 47375 | H14: ='Input Data'!I13 -> 6 | I14: ='Input Data'!V13 -> 2.9130732 | J14: ='Input Data'!J13 -> 0 | K14: ='Input Data'!X13 -> 1020 | L14: ='Input Data'!Q13 -> 37146.72 | M14: ='Input Data'!L13 -> 0 | N14: ='Input Data'!M13 -> 37146.72 | O14: ='Input Data'!N13 -> 0 | P14: ='Input Data'!O13+'Input Data'!P13 -> 0 | Q14: ='Input Data'!R13 -> 0 | R14: ='Input Data'!S13 -> FIXED 3.75% | S14: =IFERROR('Input Data'!T13,"") -> 46645 | T14: ='Input Data'!U13 -> Semi-Gross | U14: ='Input Data'!Y13 -> 0 | V14: ='Input Data'!Z13 -> 0 | W14: ='Input Data'!W13 -> 1064.7283 | X14: ='Input Data'!AB13 -> Additional space - office rent included in Suite 7.01 totals (same lease). Sept26 TS now shows a separate Outgoings Recoverable charge of $37,146.72 pa billed against this suite.
A15: ='Input Data'!B17 -> L12 | B15: ='Input Data'!C17 -> 12.01 | C15: ='Input Data'!D17 -> Hulsbosch Design Pty Ltd | D15: ='Input Data'!E17 -> Hulsbosch Design Pty Ltd | E15: ='Input Data'!F17 -> 251 | F15: ='Input Data'!G17 -> 45962 | G15: ='Input Data'!H17 -> 47787 | H15: ='Input Data'!I17 -> 5 | I15: ='Input Data'!V17 -> 4.0410678 | J15: ='Input Data'!J17 -> 985 | K15: ='Input Data'!X17 -> 1040 | L15: ='Input Data'!Q17 -> 191159.6 | M15: ='Input Data'!L17 -> -66750.12 | N15: ='Input Data'!M17 -> 6518.16 | O15: ='Input Data'!N17 -> 4156.56 | P15: ='Input Data'!O17+'Input Data'!P17 -> 0 | Q15: ='Input Data'!R17 -> 0 | R15: ='Input Data'!S17 -> FIXED 3.5% | S15: =IFERROR('Input Data'!T17,"") -> 46327 | T15: ='Input Data'!U17 -> Semi-Gross | U15: ='Input Data'!Y17 -> -55 | V15: ='Input Data'!Z17 -> -0.052884615 | W15: ='Input Data'!W17 -> 1014.308 | X15: ='Input Data'!AB17 -> Base year FY25 3.8%. Corrected per Sept26 TS: this row's NLA/financials were previously swapped with Smile Partners (0902) in the master file. Suite 1201 (Hulsbosch) is actually 251 sqm, 01/11/25–31/10/30, 5 yr term — not 344.5 sqm/4.1 yrs as previously recorded. No car park charges shown for this suite on the TS.
A16: EXPIRY 2030
A17: ='Input Data'!B15 -> L08 | B17: ='Input Data'!C15 -> 8.03 | C17: ='Input Data'!D15 -> Can Too Foundation Limited | D17: ='Input Data'!E15 -> Can Too Foundation Limited | E17: ='Input Data'!F15 -> 116.3 | F17: ='Input Data'!G15 -> 45809 | G17: ='Input Data'!H15 -> 47787 | H17: ='Input Data'!I15 -> 5.4 | I17: ='Input Data'!V15 -> 4.0410678 | J17: ='Input Data'!J15 -> 1027.12 | K17: ='Input Data'!X15 -> 990 | L17: ='Input Data'!Q15 -> 76042.556 | M17: ='Input Data'!L15 -> -48357.54 | N17: ='Input Data'!M15 -> 3020.16 | O17: ='Input Data'!N15 -> 1925.88 | P17: ='Input Data'!O15+'Input Data'!P15 -> 0 | Q17: ='Input Data'!R15 -> 0 | R17: ='Input Data'!S15 -> FIXED 3.75% | S17: =IFERROR('Input Data'!T15,"") -> 46539 | T17: ='Input Data'!U15 -> Semi-Gross | U17: ='Input Data'!Y15 -> 37.12 | V17: ='Input Data'!Z15 -> 0.037494949 | W17: ='Input Data'!W15 -> 469.97618 | X17: ='Input Data'!AB15 -> BG: $74,934. Base year 2025 1.29%. Cleaning $15.77 psm.
A18: ='Input Data'!B18 -> L09 | B18: ='Input Data'!C18 -> 9.02 | C18: ='Input Data'!D18 -> Smile Partners Australia | D18: ='Input Data'!E18 -> Smile Partners Australia Pty Ltd | E18: ='Input Data'!F18 -> 344.5 | F18: ='Input Data'!G18 -> 45992 | G18: ='Input Data'!H18 -> 47483 | H18: ='Input Data'!I18 -> 4.1 | I18: ='Input Data'!V18 -> 3.2087611 | J18: ='Input Data'!J18 -> 990.29 | K18: ='Input Data'!X18 -> 990 | L18: ='Input Data'!Q18 -> 224063.82 | M18: ='Input Data'!L18 -> -137802.12 | N18: ='Input Data'!M18 -> 8946.12 | O18: ='Input Data'!N18 -> 5704.92 | P18: ='Input Data'!O18+'Input Data'!P18 -> 6060 | Q18: ='Input Data'!R18 -> 2 | R18: ='Input Data'!S18 -> FIXED 3.5% | S18: =IFERROR('Input Data'!T18,"") -> 46357 | T18: ='Input Data'!U18 -> Semi-Gross | U18: ='Input Data'!Y18 -> 0.29 | V18: ='Input Data'!Z18 -> 0.00029292929 | W18: ='Input Data'!W18 -> 1105.4182 | X18: ='Input Data'!AB18 -> Corrected per Sept26 TS: this row's NLA/financials were previously swapped with Hulsbosch Design (1201) in the master file. Suite 0902 (Smile Partners) is actually 344.5 sqm, 01/12/25–31/12/29, 4.1 yr term, 2 car spaces ($6,060 pa levy) — not 251 sqm/5 yrs/no car parks as previously recorded.
A19: ='Input Data'!B19 -> L12 | B19: ='Input Data'!C19 -> 12.02 | C19: ='Input Data'!D19 -> AEI Insurance Group Pty Ltd | D19: ='Input Data'!E19 -> AEI Insurance Group Pty Ltd | E19: ='Input Data'!F19 -> 536 | F19: ='Input Data'!G19 -> 45642 | G19: ='Input Data'!H19 -> 47832 | H19: ='Input Data'!I19 -> 6 | I19: ='Input Data'!V19 -> 4.164271 | J19: ='Input Data'!J19 -> 988 | K19: ='Input Data'!X19 -> 1010 | L19: ='Input Data'!Q19 -> 638733.2 | M19: ='Input Data'!L19 -> -51200.76 | N19: ='Input Data'!M19 -> 24542.16 | O19: ='Input Data'!N19 -> 8876.16 | P19: ='Input Data'!O19+'Input Data'!P19 -> 126947.64 | Q19: ='Input Data'!R19 -> 10 | R19: ='Input Data'!S19 -> FIXED 4% | S19: =IFERROR('Input Data'!T19,"") -> 46372 | T19: ='Input Data'!U19 -> Semi-Gross | U19: ='Input Data'!Y19 -> -22 | V19: ='Input Data'!Z19 -> -0.021782178 | W19: ='Input Data'!W19 -> 2232.0493 | X19: ='Input Data'!AB19 -> Option: 6 mths. BG: $440,704 (no expiry). 10 car spaces. Formerly Austbrokers.
A20: EXPIRY 2031+
A21: ='Input Data'!B4 -> L03 | B21: ='Input Data'!C4 -> 3.02 | C21: ='Input Data'!D4 -> Fitness First Australia Pty Limited | D21: ='Input Data'!E4 -> Fitness First Australia Pty Limited | E21: ='Input Data'!F4 -> 795.5 | F21: ='Input Data'!G4 -> 44378 | G21: ='Input Data'!H4 -> 48029 | H21: ='Input Data'!I4 -> 10 | I21: ='Input Data'!V4 -> 4.7036277 | J21: ='Input Data'!J4 -> 855.7 | K21: ='Input Data'!X4 -> 870 | L21: ='Input Data'!Q4 -> 680709.35 | M21: ='Input Data'!L4 -> 0 | N21: ='Input Data'!M4 -> 0 | O21: ='Input Data'!N4 -> 0 | P21: ='Input Data'!O4+'Input Data'!P4 -> 0 | Q21: ='Input Data'!R4 -> 0 | R21: ='Input Data'!S4 -> FIXED 4% | S21: =IFERROR('Input Data'!T4,"") -> 46204 | T21: ='Input Data'!U4 -> Gross | U21: ='Input Data'!Y4 -> -14.3 | V21: ='Input Data'!Z4 -> -0.016436782 | W21: ='Input Data'!W4 -> 3741.7358 | X21: ='Input Data'!AB4 -> Gross lease - Nil outgoings. Includes direct AC recovery $108.09 psm. Option: 5 yrs (01/07/26-30/06/31).
A22: ='Input Data'!B5 -> L04 | B22: ='Input Data'!C5 -> 4.01 | C22: ='Input Data'!D5 -> Fitness First Australia Pty Limited | D22: ='Input Data'!E5 -> Fitness First Australia Pty Limited | E22: ='Input Data'!F5 -> 1047 | F22: ='Input Data'!G5 -> 44378 | G22: ='Input Data'!H5 -> 48029 | H22: ='Input Data'!I5 -> 10 | I22: ='Input Data'!V5 -> 4.7036277 | J22: ='Input Data'!J5 -> 855.7 | K22: ='Input Data'!X5 -> 870 | L22: ='Input Data'!Q5 -> 906078.3 | M22: ='Input Data'!L5 -> 0 | N22: ='Input Data'!M5 -> 0 | O22: ='Input Data'!N5 -> 0 | P22: ='Input Data'!O5+'Input Data'!P5 -> 10160.4 | Q22: ='Input Data'!R5 -> 1 | R22: ='Input Data'!S5 -> FIXED 4% | S22: =IFERROR('Input Data'!T5,"") -> 46204 | T22: ='Input Data'!U5 -> Gross | U22: ='Input Data'!Y5 -> -14.3 | V22: ='Input Data'!Z5 -> -0.016436782 | W22: ='Input Data'!W5 -> 4924.6982 | X22: ='Input Data'!AB5 -> Gross lease - Nil outgoings. 1 car space.
A23: ='Input Data'!B6 -> L05 | B23: ='Input Data'!C6 -> 5.01 | C23: ='Input Data'!D6 -> Fitness First Australia Pty Limited | D23: ='Input Data'!E6 -> Fitness First North Sydney | E23: ='Input Data'!F6 -> 437.1 | F23: ='Input Data'!G6 -> 44378 | G23: ='Input Data'!H6 -> 48029 | H23: ='Input Data'!I6 -> 10 | I23: ='Input Data'!V6 -> 4.7036277 | J23: ='Input Data'!J6 -> 855.7 | K23: ='Input Data'!X6 -> 870 | L23: ='Input Data'!Q6 -> 377056.47 | M23: ='Input Data'!L6 -> 0 | N23: ='Input Data'!M6 -> 0 | O23: ='Input Data'!N6 -> 0 | P23: ='Input Data'!O6+'Input Data'!P6 -> 3030 | Q23: ='Input Data'!R6 -> 0 | R23: ='Input Data'!S6 -> FIXED 4% | S23: =IFERROR('Input Data'!T6,"") -> 46204 | T23: ='Input Data'!U6 -> Gross | U23: ='Input Data'!Y6 -> -14.3 | V23: ='Input Data'!Z6 -> -0.016436782 | W23: ='Input Data'!W6 -> 2055.9556 | X23: ='Input Data'!AB6 -> Gross lease - Nil outgoings. Car park levy only.
A24: ='Input Data'!B11 -> L06 | B24: ='Input Data'!C11 -> 6.04 | C24: ='Input Data'!D11 -> Elekta Pty Limited | D24: ='Input Data'!E11 -> Elekta Pty Limited | E24: ='Input Data'!F11 -> 267.9 | F24: ='Input Data'!G11 -> 45870 | G24: ='Input Data'!H11 -> 48426 | H24: ='Input Data'!I11 -> 7 | I24: ='Input Data'!V11 -> 5.7905544 | J24: ='Input Data'!J11 -> 954.5 | K24: ='Input Data'!X11 -> 955 | L24: ='Input Data'!Q11 -> 171546.75 | M24: ='Input Data'!L11 -> -98587.2 | N24: ='Input Data'!M11 -> 6957 | O24: ='Input Data'!N11 -> 4436.4 | P24: ='Input Data'!O11+'Input Data'!P11 -> 3030 | Q24: ='Input Data'!R11 -> 1 | R24: ='Input Data'!S11 -> FIXED (3.75%) | S24: =IFERROR('Input Data'!T11,"") -> 46600 | T24: ='Input Data'!U11 -> Semi-Gross | U24: ='Input Data'!Y11 -> -0.5 | V24: ='Input Data'!Z11 -> -0.00052356021 | W24: ='Input Data'!W11 -> 1551.2895 | X24: ='Input Data'!AB11 -> New lease 01/08/25. BG: $210,969. Abatement: $2,576 psm over term. Outgoings 2.95% base FY2025.
A25: ='Input Data'!B24 -> L11 | B25: ='Input Data'!C24 -> 11.02 | C25: ='Input Data'!D24 -> Haskoning Australia Pty Ltd | D25: ='Input Data'!E24 -> Haskoning Australia Pty Ltd | E25: ='Input Data'!F24 -> 548 | F25: ='Input Data'!G24 -> 46296 | G25: ='Input Data'!H24 -> 48487 | H25: ='Input Data'!I24 -> 6 | I25: ='Input Data'!V24 -> 5.9575633 | J25: ='Input Data'!J24 -> 1040 | K25: ='Input Data'!X24 -> 1040 | L25: ='Input Data'!Q24 -> 458074.67 | M25: ='Input Data'!L24 -> -111845.33 | N25: ='Input Data'!M24 -> 0 | O25: ='Input Data'!N24 -> 0 | P25: ='Input Data'!O24+'Input Data'!P24 -> 0 | Q25: ='Input Data'!R24 -> 0 | R25: ='Input Data'!S24 -> FIXED 3.5% | S25: =IFERROR('Input Data'!T24,"") -> 46661 | T25: ='Input Data'!Y24 -> 0 | U25: ='Input Data'!Z24 -> 0 | V25: ='Input Data'!W24 -> 3264.7447 | W25: ='Input Data'!AB24 -> Haskoning Australia Pty Ltd — new lease commencing 01/10/26, 6 yr term, $1,040 psm, fixed 3.5% review. Fitout contribution $750,400 (landlord funded). Outgoings/cleaning/car park TBC pending TS confirmation. Next review date estimated.
A26: ='Input Data'!B23 -> L11 | B26: ='Input Data'!C23 -> 11.01 | C26: ='Input Data'!D23 -> Luxasia | D26: ='Input Data'!E23 -> LUXASIA | E26: ='Input Data'!F23 -> 242.5 | F26: ='Input Data'!G23 -> 46296 | G26: ='Input Data'!H23 -> 48121 | H26: ='Input Data'!I23 -> 5 | I26: ='Input Data'!V23 -> 4.9555099 | J26: ='Input Data'!J23 -> 1060 | K26: ='Input Data'!X23 -> 1060 | L26: ='Input Data'!Q23 -> 266749.52 | M26: ='Input Data'!L23 -> -25705 | N26: ='Input Data'!M23 -> 9728.72 | O26: ='Input Data'!N23 -> 4015.8 | P26: ='Input Data'!O23+'Input Data'!P23 -> 21660 | Q26: ='Input Data'!R23 -> 2 | R26: ='Input Data'!S23 -> FIXED 3.75% | S26: =IFERROR('Input Data'!T23,"") -> 46661 | T26: ='Input Data'!U23 -> Semi-Gross | U26: ='Input Data'!Y23 -> 0 | V26: ='Input Data'!Z23 -> 0 | W26: ='Input Data'!W23 -> 1201.7112 | X26: ='Input Data'!AB23 -> Break at 3 years. Lease commenced 1/10/26, 5 yr term, $1,060 psm. Incentive: landlord fitout contribution $369,812.50 (see Fitout Costs register) + rent abatement totalling $192,787.50 over the term — Yr 1-3 $25,705 pa (reflected in Abatement PA), Yr 4-5 $57,836.25 pa. Abatement PA will need manual updating to -$57,836.25 from the Yr 4 anniversary (1/10/29).
A27: ='Input Data'!B20 -> L06 | B27: ='Input Data'!C20 -> 6.01 | C27: ='Input Data'!D20 -> Caldas Constructions Pty Ltd | D27: ='Input Data'!E20 -> Caldas Constructions Pty Ltd | E27: ='Input Data'!F20 -> 186.4 | F27: ='Input Data'!G20 -> 46204 | G27: ='Input Data'!H20 -> 48395 | H27: ='Input Data'!I20 -> 6 | I27: ='Input Data'!V20 -> 5.705681 | J27: ='Input Data'!J20 -> 920 | K27: ='Input Data'!X20 -> 0 | L27: ='Input Data'!Q20 -> -340767 | M27: ='Input Data'!L20 -> -512255 | N27: ='Input Data'!M20 -> 0 | O27: ='Input Data'!N20 -> 0 | P27: ='Input Data'!O20+'Input Data'!P20 -> 0 | Q27: ='Input Data'!R20 -> 0 | R27: ='Input Data'!S20 -> 0 | S27: =IFERROR('Input Data'!T20,"") -> 0 | T27: ='Input Data'!U20 -> 0 | U27: ='Input Data'!Y20 -> 920 | V27: ='Input Data'!Z20 -> 0 | W27: ='Input Data'!W20 -> 1063.5389 | X27: ='Input Data'!AB20 -> Caldas Constructions — new lease 01/07/26 (corrected from 30/06/26), 6 yr term, $920 psm. Prepaid rent held (no BG). Outgoings/cleaning/car park still TBC pending TS confirmation (still NIL on Sept26 TS). Tenant legal name corrected to "Caldas" (previously "Caladas").
A28: VACANT SUITES — 787 sqm available
A29: ='Input Data'!B21 -> L10 | B29: ='Input Data'!C21 -> 10.01 | C29: ='Input Data'!D21 -> VACANT | D29: ='Input Data'!E21 -> 0 | E29: ='Input Data'!F21 -> 438 | X29: ='Input Data'!AB21 -> 0
A30: ='Input Data'!B22 -> L10 | B30: ='Input Data'!C22 -> 10.02 | C30: ='Input Data'!D22 -> VACANT | D30: ='Input Data'!E22 -> 0 | E30: ='Input Data'!F22 -> 349 | X30: ='Input Data'!AB22 -> 0
A32: BUILDING TOTALS | E32: =SUM('Input Data'!F3:F24) -> 8940.9 | I32: =IFERROR(SUMPRODUCT(('Input Data'!H3:H24<>"")*'Input Data'!F3:F24*MAX(('Input Data'!H3:H24-TODAY())/365.25,0))/SUMPRODUCT(('Input Data'!H3:H24<>"")*'Input Data'!F3:F24),0) -> 5.9575633 | J32: =SUMPRODUCT(('Input Data'!H3:H24<>"")*'Input Data'!J3:J24*'Input Data'!F3:F24)/SUMPRODUCT(('Input Data'!H3:H24<>"")*'Input Data'!F3:F24) -> 978.84473 | L32: =SUM('Input Data'!Q3:Q24) -> 6606792.7

Sheet Make Good Obligations
A1: 1 ELIZABETH PLAZA, NORTH SYDNEY — MAKE GOOD OBLIGATIONS REGISTER | As at 30 September 2026
A2: Track make-good obligations, notice periods and estimated costs for each suite. Update when leases are signed or when condition changes.
B4: MAKE GOOD SUMMARY
B5: Leases with Make Good Obligation | E5: Total Estimated Cost ($) | H5: High Risk (expiring <12 mths) | K5: Make Good Notice Period
B6: =COUNTIF(G10:G32,"Yes") -> 10 | E6: =SUMIF(G10:G32,"Yes",H10:H32) -> 0 | H6: =COUNTIF(L10:L32,"Overdue")+COUNTIF(L10:L32,"Due < 6 Mths") -> 0 | K6: See per lease
B8: MAKE GOOD OBLIGATIONS — Per Lease (update from lease schedule & inspections)
B9: Floor | C9: Suite | D9: Tenant Name | E9: Lease Expiry | F9: Notice Period | G9: MG Obligation in Lease? | H9: Estimated Cost ($) | I9: Cost PSM ($) | J9: Last Inspected | K9: Condition Rating | L9: MG Status | M9: Action Required | N9: Notes / Scope of Works | P9: Further detail
B10: L03 | C10: 0301 | D10: =IFERROR(INDEX('Input Data'!D:D,MATCH("0301",'Input Data'!$A:$A,0)),"") -> Sydney Smiletree Pty Ltd | E10: =IFERROR(INDEX('Input Data'!H:H,MATCH("0301",'Input Data'!$A:$A,0)),"") -> 47118 | F10: NA | G10: Yes | I10: =IFERROR(H10/INDEX('Input Data'!F:F,MATCH("0301",'Input Data'!$A:$A,0)),"") -> 0 | K10: Not Inspected | L10: =IF(OR(E10="—",E10="N/A",E10="",F10="N/A"),"N/A",IF(NOT(ISNUMBER(E10)),"N/A",IF(E10<TODAY(),"Overdue",IF(E10<TODAY()+183,"Due < 6 Mths",IF(E10<TODAY()+365,"Due < 12 Mths","Not Due"))))) -> Not Due | M10: None | N10: Payment in Lieu $300 /sqm + GST ($32,310 + GST) | P10: Payment in Lieu $300 /sqm + GST ($32,310 + GST)
B11: L03 | C11: 0302 | D11: =IFERROR(INDEX('Input Data'!D:D,MATCH("0302",'Input Data'!$A:$A,0)),"") -> Fitness First Australia Pty Limited | E11: =IFERROR(INDEX('Input Data'!H:H,MATCH("0302",'Input Data'!$A:$A,0)),"") -> 48029 | F11: TBC | G11: TBC | I11: =IFERROR(H11/INDEX('Input Data'!F:F,MATCH("0302",'Input Data'!$A:$A,0)),"") -> 0 | K11: Not Inspected | L11: =IF(OR(E11="—",E11="N/A",E11="",F11="N/A"),"N/A",IF(NOT(ISNUMBER(E11)),"N/A",IF(E11<TODAY(),"Overdue",IF(E11<TODAY()+183,"Due < 6 Mths",IF(E11<TODAY()+365,"Due < 12 Mths","Not Due"))))) -> Not Due | M11: None | N11: Fitness First gross lease — no specific make-good clause captured in the tenancy schedule extract; confirm scope against executed lease.
B12: L04 | C12: 0401 | D12: =IFERROR(INDEX('Input Data'!D:D,MATCH("0401",'Input Data'!$A:$A,0)),"") -> Fitness First Australia Pty Limited | E12: =IFERROR(INDEX('Input Data'!H:H,MATCH("0401",'Input Data'!$A:$A,0)),"") -> 48029 | F12: TBC | G12: TBC | I12: =IFERROR(H12/INDEX('Input Data'!F:F,MATCH("0401",'Input Data'!$A:$A,0)),"") -> 0 | K12: Not Inspected | L12: =IF(OR(E12="—",E12="N/A",E12="",F12="N/A"),"N/A",IF(NOT(ISNUMBER(E12)),"N/A",IF(E12<TODAY(),"Overdue",IF(E12<TODAY()+183,"Due < 6 Mths",IF(E12<TODAY()+365,"Due < 12 Mths","Not Due"))))) -> Not Due | M12: None | N12: Fitness First gross lease — no specific make-good clause captured in the tenancy schedule extract; confirm scope against executed lease.
B13: L05 | C13: 0501 | D13: =IFERROR(INDEX('Input Data'!D:D,MATCH("0501",'Input Data'!$A:$A,0)),"") -> Fitness First Australia Pty Limited | E13: =IFERROR(INDEX('Input Data'!H:H,MATCH("0501",'Input Data'!$A:$A,0)),"") -> 48029 | F13: TBC | G13: TBC | I13: =IFERROR(H13/INDEX('Input Data'!F:F,MATCH("0501",'Input Data'!$A:$A,0)),"") -> 0 | K13: Not Inspected | L13: =IF(OR(E13="—",E13="N/A",E13="",F13="N/A"),"N/A",IF(NOT(ISNUMBER(E13)),"N/A",IF(E13<TODAY(),"Overdue",IF(E13<TODAY()+183,"Due < 6 Mths",IF(E13<TODAY()+365,"Due < 12 Mths","Not Due"))))) -> Not Due | M13: None | N13: Fitness First (North Sydney) gross lease — no specific make-good clause captured in the tenancy schedule extract; confirm scope against executed lease.
B14: L05 | C14: 0503 | D14: =IFERROR(INDEX('Input Data'!D:D,MATCH("0503",'Input Data'!$A:$A,0)),"") -> Asterx Pty Ltd | E14: =IFERROR(INDEX('Input Data'!H:H,MATCH("0503",'Input Data'!$A:$A,0)),"") -> 47299 | F14: TBC | G14: Yes | I14: =IFERROR(H14/INDEX('Input Data'!F:F,MATCH("0503",'Input Data'!$A:$A,0)),"") -> 0 | K14: Not Inspected | L14: =IF(OR(E14="—",E14="N/A",E14="",F14="N/A"),"N/A",IF(NOT(ISNUMBER(E14)),"N/A",IF(E14<TODAY(),"Overdue",IF(E14<TODAY()+183,"Due < 6 Mths",IF(E14<TODAY()+365,"Due < 12 Mths","Not Due"))))) -> Not Due | M14: None | N14: Clause 10 — tenant to make good any damage, remove tenant property and existing fit-out, and hand back the premises (including landlord-directed works) at expiry. | P14: Under Clause 10 the tenant must make good any damage existing in the premises and remove tenant property/fitout, unless the landlord directs otherwise.
B15: L05 | C15: 0504 | D15: =IFERROR(INDEX('Input Data'!D:D,MATCH("0504",'Input Data'!$A:$A,0)),"") -> Auctionsplus Pty Ltd | E15: =IFERROR(INDEX('Input Data'!H:H,MATCH("0504",'Input Data'!$A:$A,0)),"") -> 47177 | F15: TBC | G15: Yes | I15: =IFERROR(H15/INDEX('Input Data'!F:F,MATCH("0504",'Input Data'!$A:$A,0)),"") -> 0 | K15: Not Inspected | L15: =IF(OR(E15="—",E15="N/A",E15="",F15="N/A"),"N/A",IF(NOT(ISNUMBER(E15)),"N/A",IF(E15<TODAY(),"Overdue",IF(E15<TODAY()+183,"Due < 6 Mths",IF(E15<TODAY()+365,"Due < 12 Mths","Not Due"))))) -> Not Due | M15: None | N15: Clause 6.7(c) — tenant may elect to pay the Lessor $250/sqm + GST in lieu of undertaking make-good works. | P15: Payment in lieu of $250/sqm + GST (≈$103,375 ex GST based on current NLA).
B16: L06 | C16: 0601 | D16: =IFERROR(INDEX('Input Data'!D:D,MATCH("0601",'Input Data'!$A:$A,0)),"") -> Caldas Constructions Pty Ltd | E16: =IFERROR(INDEX('Input Data'!H:H,MATCH("0601",'Input Data'!$A:$A,0)),"") -> 48395 | F16: TBC | G16: Yes | I16: =IFERROR(H16/INDEX('Input Data'!F:F,MATCH("0601",'Input Data'!$A:$A,0)),"") -> 0 | K16: Not Inspected | L16: =IF(OR(E16="—",E16="N/A",E16="",F16="N/A"),"N/A",IF(NOT(ISNUMBER(E16)),"N/A",IF(E16<TODAY(),"Overdue",IF(E16<TODAY()+183,"Due < 6 Mths",IF(E16<TODAY()+365,"Due < 12 Mths","Not Due"))))) -> Not Due | M16: None | N16: Clause 10.2 (pg 53) — remove tenant property, reinstate alterations, restore ceiling & carpet tiles (fair wear & tear excepted), professionally steam-clean carpet, repaint. | P16: Full reinstatement clause — no fixed $/sqm payment-in-lieu rate specified; obtain make-good quote closer to expiry (30/06/2032).
B17: L06 | C17: 0602 | D17: =IFERROR(INDEX('Input Data'!D:D,MATCH("0602",'Input Data'!$A:$A,0)),"") -> Sungrow Australia Group | E17: =IFERROR(INDEX('Input Data'!H:H,MATCH("0602",'Input Data'!$A:$A,0)),"") -> 47375 | F17: TBC | G17: Yes | I17: =IFERROR(H17/INDEX('Input Data'!F:F,MATCH("0602",'Input Data'!$A:$A,0)),"") -> 0 | K17: Not Inspected | L17: =IF(OR(E17="—",E17="N/A",E17="",F17="N/A"),"N/A",IF(NOT(ISNUMBER(E17)),"N/A",IF(E17<TODAY(),"Overdue",IF(E17<TODAY()+183,"Due < 6 Mths",IF(E17<TODAY()+365,"Due < 12 Mths","Not Due"))))) -> Not Due | M17: None | N17: Make-good noted at $200/sqm against the lease summary (BG/incentive notes) — confirm exact clause reference against executed lease. | P17: Payment in lieu of $200/sqm + GST (≈$90,340 ex GST based on current NLA).
B18: L06 | C18: 0603 | D18: =IFERROR(INDEX('Input Data'!D:D,MATCH("0603",'Input Data'!$A:$A,0)),"") -> Keeping Company Pty Ltd | E18: =IFERROR(INDEX('Input Data'!H:H,MATCH("0603",'Input Data'!$A:$A,0)),"") -> 46538 | F18: TBC | G18: TBC | I18: =IFERROR(H18/INDEX('Input Data'!F:F,MATCH("0603",'Input Data'!$A:$A,0)),"") -> 0 | K18: Not Inspected | L18: =IF(OR(E18="—",E18="N/A",E18="",F18="N/A"),"N/A",IF(NOT(ISNUMBER(E18)),"N/A",IF(E18<TODAY(),"Overdue",IF(E18<TODAY()+183,"Due < 6 Mths",IF(E18<TODAY()+365,"Due < 12 Mths","Not Due"))))) -> Due < 12 Mths | M18: None | N18: Keeping Company — no specific make-good clause captured in the tenancy schedule extract; confirm scope against executed lease.
B19: L06 | C19: 0604 | D19: =IFERROR(INDEX('Input Data'!D:D,MATCH("0604",'Input Data'!$A:$A,0)),"") -> Elekta Pty Limited | E19: =IFERROR(INDEX('Input Data'!H:H,MATCH("0604",'Input Data'!$A:$A,0)),"") -> 48426 | F19: TBC | G19: TBC | I19: =IFERROR(H19/INDEX('Input Data'!F:F,MATCH("0604",'Input Data'!$A:$A,0)),"") -> 0 | K19: Not Inspected | L19: =IF(OR(E19="—",E19="N/A",E19="",F19="N/A"),"N/A",IF(NOT(ISNUMBER(E19)),"N/A",IF(E19<TODAY(),"Overdue",IF(E19<TODAY()+183,"Due < 6 Mths",IF(E19<TODAY()+365,"Due < 12 Mths","Not Due"))))) -> Not Due | M19: None | N19: Elekta — no specific make-good clause captured in the tenancy schedule extract; confirm scope against executed lease.
B20: L07 | C20: 0701 | D20: =IFERROR(INDEX('Input Data'!D:D,MATCH("0701",'Input Data'!$A:$A,0)),"") -> Sungrow Australia Group | E20: =IFERROR(INDEX('Input Data'!H:H,MATCH("0701",'Input Data'!$A:$A,0)),"") -> 47375 | F20: TBC | G20: Yes | I20: =IFERROR(H20/INDEX('Input Data'!F:F,MATCH("0701",'Input Data'!$A:$A,0)),"") -> 0 | K20: Not Inspected | L20: =IF(OR(E20="—",E20="N/A",E20="",F20="N/A"),"N/A",IF(NOT(ISNUMBER(E20)),"N/A",IF(E20<TODAY(),"Overdue",IF(E20<TODAY()+183,"Due < 6 Mths",IF(E20<TODAY()+365,"Due < 12 Mths","Not Due"))))) -> Not Due | M20: None | N20: Clause 6.7 — return suite to landlord in open-plan layout; recarpet worn areas, make good all damage, repaint walls (min. 2 coats), remove signage. Clause 6.8 — payment in lieu available at $200/sqm. | P20: Payment in lieu of $200/sqm + GST (≈$96,820 ex GST based on current NLA).
B21: L07 | C21: 0702 | D21: =IFERROR(INDEX('Input Data'!D:D,MATCH("0702",'Input Data'!$A:$A,0)),"") -> Sungrow Australia Group | E21: =IFERROR(INDEX('Input Data'!H:H,MATCH("0702",'Input Data'!$A:$A,0)),"") -> 47375 | F21: TBC | G21: Yes | I21: =IFERROR(H21/INDEX('Input Data'!F:F,MATCH("0702",'Input Data'!$A:$A,0)),"") -> 0 | K21: Not Inspected | L21: =IF(OR(E21="—",E21="N/A",E21="",F21="N/A"),"N/A",IF(NOT(ISNUMBER(E21)),"N/A",IF(E21<TODAY(),"Overdue",IF(E21<TODAY()+183,"Due < 6 Mths",IF(E21<TODAY()+365,"Due < 12 Mths","Not Due"))))) -> Not Due | M21: None | N21: Additional space under the same lease as Suite 0701 (001445) — same make-good terms (Clause 6.7/6.8) apply to this suite. | P21: Payment in lieu of $200/sqm + GST (≈$73,100 ex GST based on current NLA — same lease as 0701).
B22: L08 | C22: 0801 | D22: =IFERROR(INDEX('Input Data'!D:D,MATCH("0801",'Input Data'!$A:$A,0)),"") -> Vanderlande Industries Australia Pty Ltd | E22: =IFERROR(INDEX('Input Data'!H:H,MATCH("0801",'Input Data'!$A:$A,0)),"") -> 46934 | F22: TBC | G22: Yes | I22: =IFERROR(H22/INDEX('Input Data'!F:F,MATCH("0801",'Input Data'!$A:$A,0)),"") -> 0 | K22: Not Inspected | L22: =IF(OR(E22="—",E22="N/A",E22="",F22="N/A"),"N/A",IF(NOT(ISNUMBER(E22)),"N/A",IF(E22<TODAY(),"Overdue",IF(E22<TODAY()+183,"Due < 6 Mths",IF(E22<TODAY()+365,"Due < 12 Mths","Not Due"))))) -> Not Due | M22: None | N22: Clause 6.7 — full make-good back to open-plan layout (base build reinstatement). | P22: Full reinstatement clause — no fixed $/sqm payment-in-lieu rate specified; obtain make-good quote closer to expiry (30/06/2028).
B23: L08 | C23: 0802 | D23: Vanderlande Industries Australia Pty Ltd | E23: 30/06/2028 | F23: TBC | G23: Yes | I23: =IFERROR(H23/INDEX('Input Data'!F:F,MATCH("0802",'Input Data'!$A:$A,0)),"") | K23: Not Inspected | L23: =IF(OR(E23="—",E23="N/A",E23="",F23="N/A"),"N/A",IF(NOT(ISNUMBER(E23)),"N/A",IF(E23<TODAY(),"Overdue",IF(E23<TODAY()+183,"Due < 6 Mths",IF(E23<TODAY()+365,"Due < 12 Mths","Not Due"))))) -> N/A | M23: None | N23: Ancillary suite (0 sqm) under the same lease as Suite 0801 (001442) — same make-good obligation (Clause 6.7, full open-plan reinstatement) applies.
B24: L08 | C24: 0803 | D24: =IFERROR(INDEX('Input Data'!D:D,MATCH("0803",'Input Data'!$A:$A,0)),"") -> Can Too Foundation Limited | E24: =IFERROR(INDEX('Input Data'!H:H,MATCH("0803",'Input Data'!$A:$A,0)),"") -> 47787 | F24: TBC | G24: TBC | I24: =IFERROR(H24/INDEX('Input Data'!F:F,MATCH("0803",'Input Data'!$A:$A,0)),"") -> 0 | K24: Not Inspected | L24: =IF(OR(E24="—",E24="N/A",E24="",F24="N/A"),"N/A",IF(NOT(ISNUMBER(E24)),"N/A",IF(E24<TODAY(),"Overdue",IF(E24<TODAY()+183,"Due < 6 Mths",IF(E24<TODAY()+365,"Due < 12 Mths","Not Due"))))) -> Not Due | M24: None | N24: Can Too Foundation — no specific make-good clause captured in the tenancy schedule extract; confirm scope against executed lease.
B25: L09 | C25: 0901 | D25: =IFERROR(INDEX('Input Data'!D:D,MATCH("0901",'Input Data'!$A:$A,0)),"") -> Pitt & Sherry (Operations) Pty Ltd | E25: =IFERROR(INDEX('Input Data'!H:H,MATCH("0901",'Input Data'!$A:$A,0)),"") -> 46571 | F25: TBC | G25: Yes | I25: =IFERROR(H25/INDEX('Input Data'!F:F,MATCH("0901",'Input Data'!$A:$A,0)),"") -> 0 | K25: Not Inspected | L25: =IF(OR(E25="—",E25="N/A",E25="",F25="N/A"),"N/A",IF(NOT(ISNUMBER(E25)),"N/A",IF(E25<TODAY(),"Overdue",IF(E25<TODAY()+183,"Due < 6 Mths",IF(E25<TODAY()+365,"Due < 12 Mths","Not Due"))))) -> Due < 12 Mths | M25: None | N25: Clause 6.7 — return suite in open-plan layout, recarpet, make good all damage, repaint. Clause 6.8 — payment in lieu available at $175 + GST. | P25: Payment in lieu of $175/sqm + GST (≈$79,328 ex GST based on current NLA).
B26: L09 | C26: 0902 | D26: =IFERROR(INDEX('Input Data'!D:D,MATCH("0902",'Input Data'!$A:$A,0)),"") -> Smile Partners Australia | E26: =IFERROR(INDEX('Input Data'!H:H,MATCH("0902",'Input Data'!$A:$A,0)),"") -> 47483 | F26: TBC | G26: TBC | I26: =IFERROR(H26/INDEX('Input Data'!F:F,MATCH("0902",'Input Data'!$A:$A,0)),"") -> 0 | K26: Not Inspected | L26: =IF(OR(E26="—",E26="N/A",E26="",F26="N/A"),"N/A",IF(NOT(ISNUMBER(E26)),"N/A",IF(E26<TODAY(),"Overdue",IF(E26<TODAY()+183,"Due < 6 Mths",IF(E26<TODAY()+365,"Due < 12 Mths","Not Due"))))) -> Not Due | M26: None | N26: Smile Partners Australia — new lease (01/11/25); no specific make-good clause captured in the tenancy schedule extract; confirm scope against executed lease.
B27: L10 | C27: 1001 | D27: =IFERROR(INDEX('Input Data'!D:D,MATCH("1001",'Input Data'!$A:$A,0)),"") -> VACANT | E27: =IFERROR(INDEX('Input Data'!H:H,MATCH("1001",'Input Data'!$A:$A,0)),"") -> 0 | F27: N/A | G27: N/A | I27: =IFERROR(H27/INDEX('Input Data'!F:F,MATCH("1001",'Input Data'!$A:$A,0)),"") -> 0 | K27: Not Inspected | L27: =IF(OR(E27="—",E27="N/A",E27="",F27="N/A"),"N/A",IF(NOT(ISNUMBER(E27)),"N/A",IF(E27<TODAY(),"Overdue",IF(E27<TODAY()+183,"Due < 6 Mths",IF(E27<TODAY()+365,"Due < 12 Mths","Not Due"))))) -> N/A | M27: None | N27: Vacant suite — no current lease or make-good obligation.
B28: L10 | C28: 1002 | D28: =IFERROR(INDEX('Input Data'!D:D,MATCH("1002",'Input Data'!$A:$A,0)),"") -> VACANT | E28: =IFERROR(INDEX('Input Data'!H:H,MATCH("1002",'Input Data'!$A:$A,0)),"") -> 0 | F28: N/A | G28: N/A | I28: =IFERROR(H28/INDEX('Input Data'!F:F,MATCH("1002",'Input Data'!$A:$A,0)),"") -> 0 | K28: Not Inspected | L28: =IF(OR(E28="—",E28="N/A",E28="",F28="N/A"),"N/A",IF(NOT(ISNUMBER(E28)),"N/A",IF(E28<TODAY(),"Overdue",IF(E28<TODAY()+183,"Due < 6 Mths",IF(E28<TODAY()+365,"Due < 12 Mths","Not Due"))))) -> N/A | M28: None | N28: Vacant suite — no current lease or make-good obligation.
B29: L11 | C29: 1101 | D29: =IFERROR(INDEX('Input Data'!D:D,MATCH("1101",'Input Data'!$A:$A,0)),"") -> Luxasia | E29: =IFERROR(INDEX('Input Data'!H:H,MATCH("1101",'Input Data'!$A:$A,0)),"") -> 48121 | F29: TBC | G29: TBC | I29: =IFERROR(H29/INDEX('Input Data'!F:F,MATCH("1101",'Input Data'!$A:$A,0)),"") -> 0 | K29: Not Inspected | L29: =IF(OR(E29="—",E29="N/A",E29="",F29="N/A"),"N/A",IF(NOT(ISNUMBER(E29)),"N/A",IF(E29<TODAY(),"Overdue",IF(E29<TODAY()+183,"Due < 6 Mths",IF(E29<TODAY()+365,"Due < 12 Mths","Not Due"))))) -> Not Due | M29: None | N29: Luxasia — new lease commenced 01/10/2026; make-good clause not yet captured in the tenancy schedule extract; confirm scope against lease.
B30: L11 | C30: 1102 | D30: =IFERROR(INDEX('Input Data'!D:D,MATCH("1102",'Input Data'!$A:$A,0)),"") -> Haskoning Australia Pty Ltd | E30: =IFERROR(INDEX('Input Data'!H:H,MATCH("1102",'Input Data'!$A:$A,0)),"") -> 48487 | F30: TBC | G30: TBC | I30: =IFERROR(H30/INDEX('Input Data'!F:F,MATCH("1102",'Input Data'!$A:$A,0)),"") -> 0 | K30: Not Inspected | L30: =IF(OR(E30="—",E30="N/A",E30="",F30="N/A"),"N/A",IF(NOT(ISNUMBER(E30)),"N/A",IF(E30<TODAY(),"Overdue",IF(E30<TODAY()+183,"Due < 6 Mths",IF(E30<TODAY()+365,"Due < 12 Mths","Not Due"))))) -> Not Due | M30: None | N30: Haskoning Australia — new lease commencing 01/10/2026; make-good clause not yet captured in the tenancy schedule extract; confirm scope once lease is finalised.
B31: L12 | C31: 1201 | D31: =IFERROR(INDEX('Input Data'!D:D,MATCH("1201",'Input Data'!$A:$A,0)),"") -> Hulsbosch Design Pty Ltd | E31: =IFERROR(INDEX('Input Data'!H:H,MATCH("1201",'Input Data'!$A:$A,0)),"") -> 47787 | F31: TBC | G31: TBC | I31: =IFERROR(H31/INDEX('Input Data'!F:F,MATCH("1201",'Input Data'!$A:$A,0)),"") -> 0 | K31: Not Inspected | L31: =IF(OR(E31="—",E31="N/A",E31="",F31="N/A"),"N/A",IF(NOT(ISNUMBER(E31)),"N/A",IF(E31<TODAY(),"Overdue",IF(E31<TODAY()+183,"Due < 6 Mths",IF(E31<TODAY()+365,"Due < 12 Mths","Not Due"))))) -> Not Due | M31: None | N31: Hulsbosch Design — no specific make-good clause captured in the tenancy schedule extract; confirm scope against executed lease.
B32: L12 | C32: 1202 | D32: =IFERROR(INDEX('Input Data'!D:D,MATCH("1202",'Input Data'!$A:$A,0)),"") -> AEI Insurance Group Pty Ltd | E32: =IFERROR(INDEX('Input Data'!H:H,MATCH("1202",'Input Data'!$A:$A,0)),"") -> 47832 | F32: TBC | G32: TBC | I32: =IFERROR(H32/INDEX('Input Data'!F:F,MATCH("1202",'Input Data'!$A:$A,0)),"") -> 0 | K32: Not Inspected | L32: =IF(OR(E32="—",E32="N/A",E32="",F32="N/A"),"N/A",IF(NOT(ISNUMBER(E32)),"N/A",IF(E32<TODAY(),"Overdue",IF(E32<TODAY()+183,"Due < 6 Mths",IF(E32<TODAY()+365,"Due < 12 Mths","Not Due"))))) -> Not Due | M32: None | N32: Aei Insurance Group — no specific make-good clause captured in the tenancy schedule extract; confirm scope against executed lease.
B34: KEY | Amber cells = user input required | Status automatically set from expiry date
C35: LIGHT_RED (expired/overdue) | F35: LT_ORANGE (<6 mths) | I35: LT_AMBER (<12 mths) | L35: Blue/White (>12 mths)

Sheet Stack Plan
A1: 1 ELIZABETH PLAZA, NORTH SYDNEY — BUILDING STACK PLAN | As at 30/09/2026
A2: Blocks proportional to NLA | Colour = lease expiry year | Scale ≈ 360 sqm per column
B3: Floor | C3: NLA (sqm) | D3: ◄─────────────────────────────────── BUILDING STACK PLAN ───────────────────────────────────►
B5: Level 12 | C5: 787 | D5: =IFERROR(INDEX('Input Data'!D:D,MATCH("12.01",'Input Data'!C:C,0)),"—") -> Hulsbosch Design Pty Ltd | L5: =IFERROR(INDEX('Input Data'!D:D,MATCH("12.02",'Input Data'!C:C,0)),"—") -> AEI Insurance Group Pty Ltd
D6: =IFERROR("12.01 — "&INDEX('Input Data'!B:B,MATCH("12.01",'Input Data'!C:C,0)),"—") -> 12.01 — L12 | L6: =IFERROR("12.02 — "&INDEX('Input Data'!B:B,MATCH("12.02",'Input Data'!C:C,0)),"—") -> 12.02 — L12
D7: =IFERROR(TEXT(INDEX('Input Data'!F:F,MATCH("12.01",'Input Data'!C:C,0)),"#,##0.0")&" sqm","—") -> 251.0 sqm | L7: =IFERROR(TEXT(INDEX('Input Data'!F:F,MATCH("12.02",'Input Data'!C:C,0)),"#,##0.0")&" sqm","—") -> 536.0 sqm
D8: =IFERROR("Face $"&TEXT(INDEX('Input Data'!J:J,MATCH("12.01",'Input Data'!C:C,0)),"#,##0")&" | Net $"&TEXT(INDEX('Input Data'!Q:Q,MATCH("12.01",'Input Data'!C:C,0)),"#,##0 pa"),"—") -> Face $985 | Net $191,160 pa | L8: =IFERROR("Face $"&TEXT(INDEX('Input Data'!J:J,MATCH("12.02",'Input Data'!C:C,0)),"#,##0")&" | Net $"&TEXT(INDEX('Input Data'!Q:Q,MATCH("12.02",'Input Data'!C:C,0)),"#,##0 pa"),"—") -> Face $988 | Net $638,733 pa
D9: =IFERROR("Outg $"&TEXT(INDEX('Input Data'!M:M,MATCH("12.01",'Input Data'!C:C,0)),"#,##0")&" | Rev: "&INDEX('Input Data'!S:S,MATCH("12.01",'Input Data'!C:C,0)),"—") -> Outg $6,518 | Rev: FIXED 3.5% | L9: =IFERROR("Outg $"&TEXT(INDEX('Input Data'!M:M,MATCH("12.02",'Input Data'!C:C,0)),"#,##0")&" | Rev: "&INDEX('Input Data'!S:S,MATCH("12.02",'Input Data'!C:C,0)),"—") -> Outg $24,542 | Rev: FIXED 4%
D10: =IFERROR("Exp: "&TEXT(INDEX('Input Data'!H:H,MATCH("12.01",'Input Data'!C:C,0)),"MMM-YY")&" ("&TEXT(INDEX('Input Data'!V:V,MATCH("12.01",'Input Data'!C:C,0)),"0.0")&" yrs)","—") -> Exp: Oct-30 (4.0 yrs) | L10: =IFERROR("Exp: "&TEXT(INDEX('Input Data'!H:H,MATCH("12.02",'Input Data'!C:C,0)),"MMM-YY")&" ("&TEXT(INDEX('Input Data'!V:V,MATCH("12.02",'Input Data'!C:C,0)),"0.0")&" yrs)","—") -> Exp: Dec-30 (4.2 yrs)
D11: =IFERROR(TEXT(INDEX('Input Data'!V:V,MATCH("12.01",'Input Data'!C:C,0)),"0.0")&" yrs remaining","—") -> 4.0 yrs remaining | L11: =IFERROR(TEXT(INDEX('Input Data'!V:V,MATCH("12.02",'Input Data'!C:C,0)),"0.0")&" yrs remaining","—") -> 4.2 yrs remaining
B14: Level 11 | C14: 772 | D14: =IFERROR(INDEX('Input Data'!D:D,MATCH("11.01",'Input Data'!C:C,0)),"—") -> Luxasia | L14: =IFERROR(INDEX('Input Data'!D:D,MATCH("11.02",'Input Data'!C:C,0)),"—") -> Haskoning Australia Pty Ltd
D15: =IFERROR("11.01 — "&INDEX('Input Data'!B:B,MATCH("11.01",'Input Data'!C:C,0)),"—") -> 11.01 — L11 | L15: =IFERROR("11.02 — "&INDEX('Input Data'!B:B,MATCH("11.02",'Input Data'!C:C,0)),"—") -> 11.02 — L11
D16: =IFERROR(TEXT(INDEX('Input Data'!F:F,MATCH("11.01",'Input Data'!C:C,0)),"#,##0.0")&" sqm","—") -> 242.5 sqm | L16: =IFERROR(TEXT(INDEX('Input Data'!F:F,MATCH("11.02",'Input Data'!C:C,0)),"#,##0.0")&" sqm","—") -> 548.0 sqm
D17: =IFERROR(IF(INDEX('Input Data'!D:D,MATCH("11.01",'Input Data'!C:C,0))="VACANT","","Face $"&TEXT(INDEX('Input Data'!J:J,MATCH("11.01",'Input Data'!C:C,0)),"#,##0")&" | Net $"&TEXT(INDEX('Input Data'!Q:Q,MATCH("11.01",'Input Data'!C:C,0)),"#,##0 pa")),"—") -> Face $1,060 | Net $266,750 pa | L17: =IFERROR("Face $"&TEXT(INDEX('Input Data'!J:J,MATCH("11.02",'Input Data'!C:C,0)),"#,##0")&" | Net $"&TEXT(INDEX('Input Data'!Q:Q,MATCH("11.02",'Input Data'!C:C,0)),"#,##0 pa"),"—") -> Face $1,040 | Net $458,075 pa
D18: =IFERROR(IF(INDEX('Input Data'!D:D,MATCH("11.01",'Input Data'!C:C,0))="VACANT","","Outg $"&TEXT(INDEX('Input Data'!M:M,MATCH("11.01",'Input Data'!C:C,0)),"#,##0")&" | Rev: "&INDEX('Input Data'!S:S,MATCH("11.01",'Input Data'!C:C,0))),"—") -> Outg $9,729 | Rev: FIXED 3.75% | L18: =IFERROR("Outg $"&TEXT(INDEX('Input Data'!M:M,MATCH("11.02",'Input Data'!C:C,0)),"#,##0")&" | Rev: "&INDEX('Input Data'!S:S,MATCH("11.02",'Input Data'!C:C,0)),"—") -> Outg $0 | Rev: FIXED 3.5%
D19: =IFERROR(IF(INDEX('Input Data'!D:D,MATCH("11.01",'Input Data'!C:C,0))="VACANT","⬤ AVAILABLE NOW","Exp: "&TEXT(INDEX('Input Data'!H:H,MATCH("11.01",'Input Data'!C:C,0)),"MMM-YY")&" ("&TEXT(INDEX('Input Data'!V:V,MATCH("11.01",'Input Data'!C:C,0)),"0.0")&" yrs)"),"—") -> Exp: Sep-31 (5.0 yrs) | L19: =IFERROR("Exp: "&TEXT(INDEX('Input Data'!H:H,MATCH("11.02",'Input Data'!C:C,0)),"MMM-YY")&" ("&TEXT(INDEX('Input Data'!V:V,MATCH("11.02",'Input Data'!C:C,0)),"0.0")&" yrs)","—") -> Exp: Sep-32 (6.0 yrs)
D20: =IFERROR(IF(INDEX('Input Data'!D:D,MATCH("11.01",'Input Data'!C:C,0))="VACANT","",TEXT(INDEX('Input Data'!V:V,MATCH("11.01",'Input Data'!C:C,0)),"0.0")&" yrs remaining"),"—") -> 5.0 yrs remaining | L20: =IFERROR(TEXT(INDEX('Input Data'!V:V,MATCH("11.02",'Input Data'!C:C,0)),"0.0")&" yrs remaining","—") -> 6.0 yrs remaining
B23: Level 10 | C23: 787 | D23: VACANT | R23: VACANT
D24: 438 sqm | R24: 349 sqm
D29: ⬤ AVAILABLE NOW | R29: ⬤ AVAILABLE NOW
B32: Level 9 | C32: 797.8 | D32: =IFERROR(INDEX('Input Data'!D:D,MATCH("9.01",'Input Data'!C:C,0)),"—") -> Pitt & Sherry (Operations) Pty Ltd | R32: =IFERROR(INDEX('Input Data'!D:D,MATCH("9.02",'Input Data'!C:C,0)),"—") -> Smile Partners Australia
D33: =IFERROR("9.01 — "&INDEX('Input Data'!B:B,MATCH("9.01",'Input Data'!C:C,0)),"—") -> 9.01 — L09 | R33: =IFERROR("9.02 — "&INDEX('Input Data'!B:B,MATCH("9.02",'Input Data'!C:C,0)),"—") -> 9.02 — L09
D34: =IFERROR(TEXT(INDEX('Input Data'!F:F,MATCH("9.01",'Input Data'!C:C,0)),"#,##0.0")&" sqm","—") -> 453.3 sqm | R34: =IFERROR(TEXT(INDEX('Input Data'!F:F,MATCH("9.02",'Input Data'!C:C,0)),"#,##0.0")&" sqm","—") -> 344.5 sqm
D35: =IFERROR("Face $"&TEXT(INDEX('Input Data'!J:J,MATCH("9.01",'Input Data'!C:C,0)),"#,##0")&" | Net $"&TEXT(INDEX('Input Data'!Q:Q,MATCH("9.01",'Input Data'!C:C,0)),"#,##0 pa"),"—") -> Face $1,066 | Net $403,785 pa | R35: =IFERROR("Face $"&TEXT(INDEX('Input Data'!J:J,MATCH("9.02",'Input Data'!C:C,0)),"#,##0")&" | Net $"&TEXT(INDEX('Input Data'!Q:Q,MATCH("9.02",'Input Data'!C:C,0)),"#,##0 pa"),"—") -> Face $990 | Net $224,064 pa
D36: =IFERROR("Outg $"&TEXT(INDEX('Input Data'!M:M,MATCH("9.01",'Input Data'!C:C,0)),"#,##0")&" | Rev: "&INDEX('Input Data'!S:S,MATCH("9.01",'Input Data'!C:C,0)),"—") -> Outg $46,070 | Rev: FIXED 3.75% | R36: =IFERROR("Outg $"&TEXT(INDEX('Input Data'!M:M,MATCH("9.02",'Input Data'!C:C,0)),"#,##0")&" | Rev: "&INDEX('Input Data'!S:S,MATCH("9.02",'Input Data'!C:C,0)),"—") -> Outg $8,946 | Rev: FIXED 3.5%
D37: =IFERROR("Exp: "&TEXT(INDEX('Input Data'!H:H,MATCH("9.01",'Input Data'!C:C,0)),"MMM-YY")&" ("&TEXT(INDEX('Input Data'!V:V,MATCH("9.01",'Input Data'!C:C,0)),"0.0")&" yrs)","—") -> Exp: Jul-27 (0.7 yrs) | R37: =IFERROR("Exp: "&TEXT(INDEX('Input Data'!H:H,MATCH("9.02",'Input Data'!C:C,0)),"MMM-YY")&" ("&TEXT(INDEX('Input Data'!V:V,MATCH("9.02",'Input Data'!C:C,0)),"0.0")&" yrs)","—") -> Exp: Dec-29 (3.2 yrs)
D38: =IFERROR(TEXT(INDEX('Input Data'!V:V,MATCH("9.01",'Input Data'!C:C,0)),"0.0")&" yrs remaining","—") -> 0.7 yrs remaining | R38: =IFERROR(TEXT(INDEX('Input Data'!V:V,MATCH("9.02",'Input Data'!C:C,0)),"0.0")&" yrs remaining","—") -> 3.2 yrs remaining
B41: Level 8 | C41: 803 | D41: =IFERROR(INDEX('Input Data'!D:D,MATCH("8.01",'Input Data'!C:C,0)),"—") -> Vanderlande Industries Australia Pty Ltd | X41: =IFERROR(INDEX('Input Data'!D:D,MATCH("8.03",'Input Data'!C:C,0)),"—") -> Can Too Foundation Limited
D42: =IFERROR("8.01 — "&INDEX('Input Data'!B:B,MATCH("8.01",'Input Data'!C:C,0)),"—") -> 8.01 — L08 | X42: =IFERROR("8.03 — "&INDEX('Input Data'!B:B,MATCH("8.03",'Input Data'!C:C,0)),"—") -> 8.03 — L08
D43: =IFERROR(TEXT(INDEX('Input Data'!F:F,MATCH("8.01",'Input Data'!C:C,0)),"#,##0.0")&" sqm","—") -> 686.7 sqm | X43: =IFERROR(TEXT(INDEX('Input Data'!F:F,MATCH("8.03",'Input Data'!C:C,0)),"#,##0.0")&" sqm","—") -> 116.3 sqm
D44: =IFERROR("Face $"&TEXT(INDEX('Input Data'!J:J,MATCH("8.01",'Input Data'!C:C,0)),"#,##0")&" | Net $"&TEXT(INDEX('Input Data'!Q:Q,MATCH("8.01",'Input Data'!C:C,0)),"#,##0 pa"),"—") -> Face $1,029 | Net $577,102 pa | X44: =IFERROR("Face $"&TEXT(INDEX('Input Data'!J:J,MATCH("8.03",'Input Data'!C:C,0)),"#,##0")&" | Net $"&TEXT(INDEX('Input Data'!Q:Q,MATCH("8.03",'Input Data'!C:C,0)),"#,##0 pa"),"—") -> Face $1,027 | Net $76,043 pa
D45: =IFERROR("Outg $"&TEXT(INDEX('Input Data'!M:M,MATCH("8.01",'Input Data'!C:C,0)),"#,##0")&" | Rev: "&INDEX('Input Data'!S:S,MATCH("8.01",'Input Data'!C:C,0)),"—") -> Outg $78,860 | Rev: FIXED 4% | X45: =IFERROR("Outg $"&TEXT(INDEX('Input Data'!M:M,MATCH("8.03",'Input Data'!C:C,0)),"#,##0")&" | Rev: "&INDEX('Input Data'!S:S,MATCH("8.03",'Input Data'!C:C,0)),"—") -> Outg $3,020 | Rev: FIXED 3.75%
D46: =IFERROR("Exp: "&TEXT(INDEX('Input Data'!H:H,MATCH("8.01",'Input Data'!C:C,0)),"MMM-YY")&" ("&TEXT(INDEX('Input Data'!V:V,MATCH("8.01",'Input Data'!C:C,0)),"0.0")&" yrs)","—") -> Exp: Jun-28 (1.7 yrs) | X46: =IFERROR("Exp: "&TEXT(INDEX('Input Data'!H:H,MATCH("8.03",'Input Data'!C:C,0)),"MMM-YY")&" ("&TEXT(INDEX('Input Data'!V:V,MATCH("8.03",'Input Data'!C:C,0)),"0.0")&" yrs)","—") -> Exp: Oct-30 (4.0 yrs)
D47: =IFERROR(TEXT(INDEX('Input Data'!V:V,MATCH("8.01",'Input Data'!C:C,0)),"0.0")&" yrs remaining","—") -> 1.7 yrs remaining | X47: =IFERROR(TEXT(INDEX('Input Data'!V:V,MATCH("8.03",'Input Data'!C:C,0)),"0.0")&" yrs remaining","—") -> 4.0 yrs remaining
B50: Level 7 | C50: 849.6 | D50: =IFERROR(INDEX('Input Data'!D:D,MATCH("7.01",'Input Data'!C:C,0)),"—") -> Sungrow Australia Group | R50: =IFERROR(INDEX('Input Data'!D:D,MATCH("7.02",'Input Data'!C:C,0)),"—") -> Sungrow Australia Group
D51: =IFERROR("7.01 — "&INDEX('Input Data'!B:B,MATCH("7.01",'Input Data'!C:C,0)),"—") -> 7.01 — L07 | R51: =IFERROR("7.02 — "&INDEX('Input Data'!B:B,MATCH("7.02",'Input Data'!C:C,0)),"—") -> 7.02 — L07
D52: =IFERROR(TEXT(INDEX('Input Data'!F:F,MATCH("7.01",'Input Data'!C:C,0)),"#,##0.0")&" sqm","—") -> 484.1 sqm | R52: =IFERROR(TEXT(INDEX('Input Data'!F:F,MATCH("7.02",'Input Data'!C:C,0)),"#,##0.0")&" sqm","—") -> 365.5 sqm
D53: =IFERROR("Face $"&TEXT(INDEX('Input Data'!J:J,MATCH("7.01",'Input Data'!C:C,0)),"#,##0")&" | Net $"&TEXT(INDEX('Input Data'!Q:Q,MATCH("7.01",'Input Data'!C:C,0)),"#,##0 pa"),"—") -> Face $1,911 | Net $693,732 pa | R53: =IFERROR("Face $"&TEXT(INDEX('Input Data'!J:J,MATCH("7.02",'Input Data'!C:C,0)),"#,##0")&" | Net $"&TEXT(INDEX('Input Data'!Q:Q,MATCH("7.02",'Input Data'!C:C,0)),"#,##0 pa"),"—") -> Face $0 | Net $37,147 pa
D54: =IFERROR("Outg $"&TEXT(INDEX('Input Data'!M:M,MATCH("7.01",'Input Data'!C:C,0)),"#,##0")&" | Rev: "&INDEX('Input Data'!S:S,MATCH("7.01",'Input Data'!C:C,0)),"—") -> Outg $49,200 | Rev: FIXED 3.75% | R54: =IFERROR("Outg $"&TEXT(INDEX('Input Data'!M:M,MATCH("7.02",'Input Data'!C:C,0)),"#,##0")&" | Rev: "&INDEX('Input Data'!S:S,MATCH("7.02",'Input Data'!C:C,0)),"—") -> Outg $37,147 | Rev: FIXED 3.75%
D55: =IFERROR("Exp: "&TEXT(INDEX('Input Data'!H:H,MATCH("7.01",'Input Data'!C:C,0)),"MMM-YY")&" ("&TEXT(INDEX('Input Data'!V:V,MATCH("7.01",'Input Data'!C:C,0)),"0.0")&" yrs)","—") -> Exp: Sep-29 (2.9 yrs) | R55: =IFERROR("Exp: "&TEXT(INDEX('Input Data'!H:H,MATCH("7.02",'Input Data'!C:C,0)),"MMM-YY")&" ("&TEXT(INDEX('Input Data'!V:V,MATCH("7.02",'Input Data'!C:C,0)),"0.0")&" yrs)","—") -> Exp: Sep-29 (2.9 yrs)
D56: =IFERROR(TEXT(INDEX('Input Data'!V:V,MATCH("7.01",'Input Data'!C:C,0)),"0.0")&" yrs remaining","—") -> 2.9 yrs remaining | R56: =IFERROR(TEXT(INDEX('Input Data'!V:V,MATCH("7.02",'Input Data'!C:C,0)),"0.0")&" yrs remaining","—") -> 2.9 yrs remaining
B59: Level 6 | C59: 1095.4 | D59: =IFERROR(INDEX('Input Data'!D:D,MATCH("6.01",'Input Data'!C:C,0)),"—") -> Caldas Constructions Pty Ltd | I59: =IFERROR(INDEX('Input Data'!D:D,MATCH("6.02",'Input Data'!C:C,0)),"—") -> Sungrow Australia Group | R59: =IFERROR(INDEX('Input Data'!D:D,MATCH("6.03",'Input Data'!C:C,0)),"—") -> Keeping Company Pty Ltd | W59: =IFERROR(INDEX('Input Data'!D:D,MATCH("6.04",'Input Data'!C:C,0)),"—") -> Elekta Pty Limited
D60: =IFERROR("6.01 — "&INDEX('Input Data'!B:B,MATCH("6.01",'Input Data'!C:C,0)),"—") -> 6.01 — L06 | I60: =IFERROR("6.02 — "&INDEX('Input Data'!B:B,MATCH("6.02",'Input Data'!C:C,0)),"—") -> 6.02 — L06 | R60: =IFERROR("6.03 — "&INDEX('Input Data'!B:B,MATCH("6.03",'Input Data'!C:C,0)),"—") -> 6.03 — L06 | W60: =IFERROR("6.04 — "&INDEX('Input Data'!B:B,MATCH("6.04",'Input Data'!C:C,0)),"—") -> 6.04 — L06
D61: =IFERROR(TEXT(INDEX('Input Data'!F:F,MATCH("6.01",'Input Data'!C:C,0)),"#,##0.0")&" sqm","—") -> 186.4 sqm | I61: =IFERROR(TEXT(INDEX('Input Data'!F:F,MATCH("6.02",'Input Data'!C:C,0)),"#,##0.0")&" sqm","—") -> 451.7 sqm | R61: =IFERROR(TEXT(INDEX('Input Data'!F:F,MATCH("6.03",'Input Data'!C:C,0)),"#,##0.0")&" sqm","—") -> 189.4 sqm | W61: =IFERROR(TEXT(INDEX('Input Data'!F:F,MATCH("6.04",'Input Data'!C:C,0)),"#,##0.0")&" sqm","—") -> 267.9 sqm
D62: =IFERROR("Face $"&TEXT(INDEX('Input Data'!J:J,MATCH("6.01",'Input Data'!C:C,0)),"#,##0")&" | Net $"&TEXT(INDEX('Input Data'!Q:Q,MATCH("6.01",'Input Data'!C:C,0)),"#,##0 pa"),"—") -> Face $920 | Net $-340,767 pa | I62: =IFERROR("Face $"&TEXT(INDEX('Input Data'!J:J,MATCH("6.02",'Input Data'!C:C,0)),"#,##0")&" | Net $"&TEXT(INDEX('Input Data'!Q:Q,MATCH("6.02",'Input Data'!C:C,0)),"#,##0 pa"),"—") -> Face $955 | Net $283,260 pa | R62: =IFERROR("Face $"&TEXT(INDEX('Input Data'!J:J,MATCH("6.03",'Input Data'!C:C,0)),"#,##0")&" | Net $"&TEXT(INDEX('Input Data'!Q:Q,MATCH("6.03",'Input Data'!C:C,0)),"#,##0 pa"),"—") -> Face $1,056 | Net $219,057 pa | W62: =IFERROR("Face $"&TEXT(INDEX('Input Data'!J:J,MATCH("6.04",'Input Data'!C:C,0)),"#,##0")&" | Net $"&TEXT(INDEX('Input Data'!Q:Q,MATCH("6.04",'Input Data'!C:C,0)),"#,##0 pa"),"—") -> Face $955 | Net $171,547 pa
D63: =IFERROR("Outg $"&TEXT(INDEX('Input Data'!M:M,MATCH("6.01",'Input Data'!C:C,0)),"#,##0")&" | Rev: "&INDEX('Input Data'!S:S,MATCH("6.01",'Input Data'!C:C,0)),"—") -> Outg $0 | Rev: | I63: =IFERROR("Outg $"&TEXT(INDEX('Input Data'!M:M,MATCH("6.02",'Input Data'!C:C,0)),"#,##0")&" | Rev: "&INDEX('Input Data'!S:S,MATCH("6.02",'Input Data'!C:C,0)),"—") -> Outg $45,907 | Rev: FIXED 3.75% | R63: =IFERROR("Outg $"&TEXT(INDEX('Input Data'!M:M,MATCH("6.03",'Input Data'!C:C,0)),"#,##0")&" | Rev: "&INDEX('Input Data'!S:S,MATCH("6.03",'Input Data'!C:C,0)),"—") -> Outg $19,249 | Rev: FIXED 3.5% | W63: =IFERROR("Outg $"&TEXT(INDEX('Input Data'!M:M,MATCH("6.04",'Input Data'!C:C,0)),"#,##0")&" | Rev: "&INDEX('Input Data'!S:S,MATCH("6.04",'Input Data'!C:C,0)),"—") -> Outg $6,957 | Rev: FIXED (3.75%)
D64: =IFERROR("Exp: "&TEXT(INDEX('Input Data'!H:H,MATCH("6.01",'Input Data'!C:C,0)),"MMM-YY")&" ("&TEXT(INDEX('Input Data'!V:V,MATCH("6.01",'Input Data'!C:C,0)),"0.0")&" yrs)","—") -> Exp: Jun-32 (5.7 yrs) | I64: =IFERROR("Exp: "&TEXT(INDEX('Input Data'!H:H,MATCH("6.02",'Input Data'!C:C,0)),"MMM-YY")&" ("&TEXT(INDEX('Input Data'!V:V,MATCH("6.02",'Input Data'!C:C,0)),"0.0")&" yrs)","—") -> Exp: Sep-29 (2.9 yrs) | R64: =IFERROR("Exp: "&TEXT(INDEX('Input Data'!H:H,MATCH("6.03",'Input Data'!C:C,0)),"MMM-YY")&" ("&TEXT(INDEX('Input Data'!V:V,MATCH("6.03",'Input Data'!C:C,0)),"0.0")&" yrs)","—") -> Exp: May-27 (0.6 yrs) | W64: =IFERROR("Exp: "&TEXT(INDEX('Input Data'!H:H,MATCH("6.04",'Input Data'!C:C,0)),"MMM-YY")&" ("&TEXT(INDEX('Input Data'!V:V,MATCH("6.04",'Input Data'!C:C,0)),"0.0")&" yrs)","—") -> Exp: Jul-32 (5.8 yrs)
D65: =IFERROR(TEXT(INDEX('Input Data'!V:V,MATCH("6.01",'Input Data'!C:C,0)),"0.0")&" yrs remaining","—") -> 5.7 yrs remaining | I65: =IFERROR(TEXT(INDEX('Input Data'!V:V,MATCH("6.02",'Input Data'!C:C,0)),"0.0")&" yrs remaining","—") -> 2.9 yrs remaining | R65: =IFERROR(TEXT(INDEX('Input Data'!V:V,MATCH("6.03",'Input Data'!C:C,0)),"0.0")&" yrs remaining","—") -> 0.6 yrs remaining | W65: =IFERROR(TEXT(INDEX('Input Data'!V:V,MATCH("6.04",'Input Data'!C:C,0)),"0.0")&" yrs remaining","—") -> 5.8 yrs remaining
B68: Level 5 | C68: 1080.4 | D68: =IFERROR(INDEX('Input Data'!D:D,MATCH("5.01",'Input Data'!C:C,0)),"—") -> Fitness First Australia Pty Limited | N68: =IFERROR(INDEX('Input Data'!D:D,MATCH("5.03",'Input Data'!C:C,0)),"—") -> Asterx Pty Ltd | S68: =IFERROR(INDEX('Input Data'!D:D,MATCH("5.04",'Input Data'!C:C,0)),"—") -> Auctionsplus Pty Ltd
D69: =IFERROR("5.01 — "&INDEX('Input Data'!B:B,MATCH("5.01",'Input Data'!C:C,0)),"—") -> 5.01 — L05 | N69: =IFERROR("5.03 — "&INDEX('Input Data'!B:B,MATCH("5.03",'Input Data'!C:C,0)),"—") -> 5.03 — L05 | S69: =IFERROR("5.04 — "&INDEX('Input Data'!B:B,MATCH("5.04",'Input Data'!C:C,0)),"—") -> 5.04 — L05
D70: =IFERROR(TEXT(INDEX('Input Data'!F:F,MATCH("5.01",'Input Data'!C:C,0)),"#,##0.0")&" sqm","—") -> 437.1 sqm | N70: =IFERROR(TEXT(INDEX('Input Data'!F:F,MATCH("5.03",'Input Data'!C:C,0)),"#,##0.0")&" sqm","—") -> 229.8 sqm | S70: =IFERROR(TEXT(INDEX('Input Data'!F:F,MATCH("5.04",'Input Data'!C:C,0)),"#,##0.0")&" sqm","—") -> 413.5 sqm
D71: =IFERROR("Face $"&TEXT(INDEX('Input Data'!J:J,MATCH("5.01",'Input Data'!C:C,0)),"#,##0")&" | Net $"&TEXT(INDEX('Input Data'!Q:Q,MATCH("5.01",'Input Data'!C:C,0)),"#,##0 pa"),"—") -> Face $856 | Net $377,056 pa | N71: =IFERROR("Face $"&TEXT(INDEX('Input Data'!J:J,MATCH("5.03",'Input Data'!C:C,0)),"#,##0")&" | Net $"&TEXT(INDEX('Input Data'!Q:Q,MATCH("5.03",'Input Data'!C:C,0)),"#,##0 pa"),"—") -> Face $986 | Net $205,033 pa | S71: =IFERROR("Face $"&TEXT(INDEX('Input Data'!J:J,MATCH("5.04",'Input Data'!C:C,0)),"#,##0")&" | Net $"&TEXT(INDEX('Input Data'!Q:Q,MATCH("5.04",'Input Data'!C:C,0)),"#,##0 pa"),"—") -> Face $1,006 | Net $366,668 pa
D72: =IFERROR("Outg $"&TEXT(INDEX('Input Data'!M:M,MATCH("5.01",'Input Data'!C:C,0)),"#,##0")&" | Rev: "&INDEX('Input Data'!S:S,MATCH("5.01",'Input Data'!C:C,0)),"—") -> Outg $0 | Rev: FIXED 4% | N72: =IFERROR("Outg $"&TEXT(INDEX('Input Data'!M:M,MATCH("5.03",'Input Data'!C:C,0)),"#,##0")&" | Rev: "&INDEX('Input Data'!S:S,MATCH("5.03",'Input Data'!C:C,0)),"—") -> Outg $10,522 | Rev: FIXED 3.5% | S72: =IFERROR("Outg $"&TEXT(INDEX('Input Data'!M:M,MATCH("5.04",'Input Data'!C:C,0)),"#,##0")&" | Rev: "&INDEX('Input Data'!S:S,MATCH("5.04",'Input Data'!C:C,0)),"—") -> Outg $40,069 | Rev: FIXED 4%
D73: =IFERROR("Exp: "&TEXT(INDEX('Input Data'!H:H,MATCH("5.01",'Input Data'!C:C,0)),"MMM-YY")&" ("&TEXT(INDEX('Input Data'!V:V,MATCH("5.01",'Input Data'!C:C,0)),"0.0")&" yrs)","—") -> Exp: Jun-31 (4.7 yrs) | N73: =IFERROR("Exp: "&TEXT(INDEX('Input Data'!H:H,MATCH("5.03",'Input Data'!C:C,0)),"MMM-YY")&" ("&TEXT(INDEX('Input Data'!V:V,MATCH("5.03",'Input Data'!C:C,0)),"0.0")&" yrs)","—") -> Exp: Jun-29 (2.7 yrs) | S73: =IFERROR("Exp: "&TEXT(INDEX('Input Data'!H:H,MATCH("5.04",'Input Data'!C:C,0)),"MMM-YY")&" ("&TEXT(INDEX('Input Data'!V:V,MATCH("5.04",'Input Data'!C:C,0)),"0.0")&" yrs)","—") -> Exp: Feb-29 (2.4 yrs)
D74: =IFERROR(TEXT(INDEX('Input Data'!V:V,MATCH("5.01",'Input Data'!C:C,0)),"0.0")&" yrs remaining","—") -> 4.7 yrs remaining | N74: =IFERROR(TEXT(INDEX('Input Data'!V:V,MATCH("5.03",'Input Data'!C:C,0)),"0.0")&" yrs remaining","—") -> 2.7 yrs remaining | S74: =IFERROR(TEXT(INDEX('Input Data'!V:V,MATCH("5.04",'Input Data'!C:C,0)),"0.0")&" yrs remaining","—") -> 2.4 yrs remaining
B77: Level 4 | C77: 1047 | D77: =IFERROR(INDEX('Input Data'!D:D,MATCH("4.01",'Input Data'!C:C,0)),"—") -> Fitness First Australia Pty Limited
D78: =IFERROR("4.01 — "&INDEX('Input Data'!B:B,MATCH("4.01",'Input Data'!C:C,0)),"—") -> 4.01 — L04
D79: =IFERROR(TEXT(INDEX('Input Data'!F:F,MATCH("4.01",'Input Data'!C:C,0)),"#,##0.0")&" sqm","—") -> 1,047.0 sqm
D80: =IFERROR("Face $"&TEXT(INDEX('Input Data'!J:J,MATCH("4.01",'Input Data'!C:C,0)),"#,##0")&" | Net $"&TEXT(INDEX('Input Data'!Q:Q,MATCH("4.01",'Input Data'!C:C,0)),"#,##0 pa"),"—") -> Face $856 | Net $906,078 pa
D81: =IFERROR("Outg $"&TEXT(INDEX('Input Data'!M:M,MATCH("4.01",'Input Data'!C:C,0)),"#,##0")&" | Rev: "&INDEX('Input Data'!S:S,MATCH("4.01",'Input Data'!C:C,0)),"—") -> Outg $0 | Rev: FIXED 4%
D82: =IFERROR("Exp: "&TEXT(INDEX('Input Data'!H:H,MATCH("4.01",'Input Data'!C:C,0)),"MMM-YY")&" ("&TEXT(INDEX('Input Data'!V:V,MATCH("4.01",'Input Data'!C:C,0)),"0.0")&" yrs)","—") -> Exp: Jun-31 (4.7 yrs)
D83: =IFERROR(TEXT(INDEX('Input Data'!V:V,MATCH("4.01",'Input Data'!C:C,0)),"0.0")&" yrs remaining","—") -> 4.7 yrs remaining
B86: Level 3 | C86: 903.2 | D86: =IFERROR(INDEX('Input Data'!D:D,MATCH("3.01",'Input Data'!C:C,0)),"—") -> Sydney Smiletree Pty Ltd | I86: =IFERROR(INDEX('Input Data'!D:D,MATCH("3.02",'Input Data'!C:C,0)),"—") -> Fitness First Australia Pty Limited
D87: =IFERROR("3.01 — "&INDEX('Input Data'!B:B,MATCH("3.01",'Input Data'!C:C,0)),"—") -> 3.01 — L03 | I87: =IFERROR("3.02 — "&INDEX('Input Data'!B:B,MATCH("3.02",'Input Data'!C:C,0)),"—") -> 3.02 — L03
D88: =IFERROR(TEXT(INDEX('Input Data'!F:F,MATCH("3.01",'Input Data'!C:C,0)),"#,##0.0")&" sqm","—") -> 107.7 sqm | I88: =IFERROR(TEXT(INDEX('Input Data'!F:F,MATCH("3.02",'Input Data'!C:C,0)),"#,##0.0")&" sqm","—") -> 795.5 sqm
D89: =IFERROR("Face $"&TEXT(INDEX('Input Data'!J:J,MATCH("3.01",'Input Data'!C:C,0)),"#,##0")&" | Net $"&TEXT(INDEX('Input Data'!Q:Q,MATCH("3.01",'Input Data'!C:C,0)),"#,##0 pa"),"—") -> Face $1,396 | Net $171,561 pa | I89: =IFERROR("Face $"&TEXT(INDEX('Input Data'!J:J,MATCH("3.02",'Input Data'!C:C,0)),"#,##0")&" | Net $"&TEXT(INDEX('Input Data'!Q:Q,MATCH("3.02",'Input Data'!C:C,0)),"#,##0 pa"),"—") -> Face $856 | Net $680,709 pa
D90: =IFERROR("Outg $"&TEXT(INDEX('Input Data'!M:M,MATCH("3.01",'Input Data'!C:C,0)),"#,##0")&" | Rev: "&INDEX('Input Data'!S:S,MATCH("3.01",'Input Data'!C:C,0)),"—") -> Outg $9,156 | Rev: FIXED 4% | I90: =IFERROR("Outg $"&TEXT(INDEX('Input Data'!M:M,MATCH("3.02",'Input Data'!C:C,0)),"#,##0")&" | Rev: "&INDEX('Input Data'!S:S,MATCH("3.02",'Input Data'!C:C,0)),"—") -> Outg $0 | Rev: FIXED 4%
D91: =IFERROR("Exp: "&TEXT(INDEX('Input Data'!H:H,MATCH("3.01",'Input Data'!C:C,0)),"MMM-YY")&" ("&TEXT(INDEX('Input Data'!V:V,MATCH("3.01",'Input Data'!C:C,0)),"0.0")&" yrs)","—") -> Exp: Dec-28 (2.2 yrs) | I91: =IFERROR("Exp: "&TEXT(INDEX('Input Data'!H:H,MATCH("3.02",'Input Data'!C:C,0)),"MMM-YY")&" ("&TEXT(INDEX('Input Data'!V:V,MATCH("3.02",'Input Data'!C:C,0)),"0.0")&" yrs)","—") -> Exp: Jun-31 (4.7 yrs)
D92: =IFERROR(TEXT(INDEX('Input Data'!V:V,MATCH("3.01",'Input Data'!C:C,0)),"0.0")&" yrs remaining","—") -> 2.2 yrs remaining | I92: =IFERROR(TEXT(INDEX('Input Data'!V:V,MATCH("3.02",'Input Data'!C:C,0)),"0.0")&" yrs remaining","—") -> 4.7 yrs remaining
B95: Roof | C95: — | D95: Pipe Networks Pty Ltd (Vocus)
D96: ROOF — Roof
D97: —
D98: Face $— | Net $2,500 pa
D99: Outg $— | Rev: —
D100: Exp: Aug-27 (1.3 yrs)
D101: 1.3 yrs remaining
B106: LEGEND — Expiry Year Colour Code
D107: Expiring 2026 ⚠ | H107: 2027 | L107: 2028 | P107: 2029 | T107: 2030 | X107: 2031+ | AB107: Vacant
B109: PORTFOLIO SUMMARY | As at 30/09/2026 | Total NLA: 8,940.9 sqm | Occupied: 8,153.9 sqm (91.2%) | Vacant: 787.0 sqm (8.8%) | Gross Income PA: ~$8.0M

Sheet Leasing Activity
A1: 1 ELIZABETH PLAZA — LEASING ACTIVITY LOG | Since June 2024
A2: Date | B2: Tenant Name | C2: Type | D2: Suite | E2: NLA (sqm) | F2: Face PSM ($) | G2: Review | H2: Commencement | I2: Expiry | J2: Term | K2: Incentive % | L2: Fitout ($) | M2: Abatement ($) | N2: TR Fee ($) | O2: Notes
A3: 45962 | B3: Hulsbosch Design Pty Ltd | C3: New Lease | D3: 12.01 | E3: 251 | F3: 985 | G3: 0.035 | H3: 45962 | I3: 47787 | J3: 5 Years | K3: 0.37 | L3: 0 | M3: 66750.12 | N3: 0 | O3: Suite 12.01. BG: 6 mths.
A4: 45992 | B4: Smile Partners Australia | C4: New Lease | D4: 9.02 | E4: 344.5 | F4: 990.29 | G4: 0.035 | H4: 45992 | I4: 47483 | J4: 4.1 Years | K4: 0.4 | L4: 0 | M4: 137802.12 | N4: 0 | O4: Suite 9.02.
A5: 45870 | B5: Elekta Pty Limited | C5: New Lease | D5: 6.04 | E5: 267.9 | F5: 920 | H5: 45870 | I5: 48426 | J5: 7 Years | K5: 0.4 | L5: 0 | M5: 690110 | N5: 0 | O5: Suite 6.04. $2,576 psm abatement over 7 yr term. BG $210,969.
A6: 45809 | B6: Can Too Foundation Limited | C6: New Lease | D6: 8.03 | E6: 116.3 | F6: 990 | G6: 0.0375 | H6: 45809 | I6: 47787 | J6: 5.4 Years | K6: 0.42 | L6: 0 | M6: 48357.48 | N6: 0 | O6: Suite 8.03. BG: $74,934.
A7: 45762 | B7: Sungrow Australia Group | C7: New Lease | D7: 6.02 | E7: 451.7 | F7: 954.5 | G7: 0.0375 | H7: 45762 | I7: 47375 | J7: 4.4 Years | K7: 0.5 | L7: 0 | M7: 211718.64 | N7: 0 | O7: Suite 6.02. 50% incentive as abatement. BG $291,050.
A8: 45642 | B8: AEI Insurance Group Pty Ltd | C8: New Lease | D8: 12.02 | E8: 536 | F8: 988 | G8: 0.04 | H8: 45642 | I8: 47832 | J8: 6 Years | K8: 0.35 | L8: 762115 | M8: 51200.76 | N8: 0 | O8: Suite 12.02. Formerly Austbrokers. 10 car spaces. BG $440,704.
A9: 45352 | B9: Auctionsplus Pty Ltd | C9: New Lease | D9: 5.04 | E9: 413.5 | F9: 1005.89 | G9: 0.04 | H9: 45352 | I9: 47177 | J9: 5 Years | K9: 0.25 | L9: 672971.25 | M9: 104594.28 | N9: 0 | O9: Suite 5.04. Incentive as fitout + abatement. BG equiv $199k incl GST.
A10: 45444 | B10: Asterx Pty Ltd | C10: Renewal | D10: 5.03 | E10: 229.8 | F10: 877.01 | G10: 0.035 | H10: 45444 | I10: 47269 | J10: 5 Years | K10: 0 | L10: 0 | M10: 0 | N10: 0 | O10: Suite 5.03 (MediRecords). Continuation. BG $135,234.
A11: 45992 | B11: Caladas Constructions | C11: New Lease | D11: 6.01 | E11: 186.4 | F11: 920 | H11: 46204 | I11: 48395 | J11: 6 Years | K11: 46.5 | L11: 0 | M11: 512255 | N11: 0 | O11: PROSPECT — New lease commencing 01/07/26. Prepaid rent held.
A12: 45931 | B12: Haskoning Australia Pty Ltd | C12: New Lease | D12: 11.02 | E12: 536 | F12: 1040 | G12: 0.035 | H12: 46296 | I12: 49582 | J12: 6 Years | K12: 0.425 | L12: 750400 | M12: 671072 | N12: 0 | O12: PROSPECT — New lease commencing 01/10/26.
A16: LEASING ACTIVITY SUMMARY
A17: WALE by NLA (Current) | D17: =TEXT(Dashboard!E14,"0.0")&" years" -> 3.9 years
A18: Occupancy (Current) | D18: =TEXT('Input Data'!K26,"0.00%") -> 91.20%
A19: WALE by NLA (May 2025) | D19: 3.34 years
A20: Occupancy (May 2025) | D20: 76.9% | K20: r
A21: WALE by NLA (May 2024) | D21: 3.20 years
A22: Occupancy (May 2024) | D22: 68.1%
A23: Total NLA Leased (Since Jun 24) | D23: =TEXT(SUM(E3:E12),"#,##0")&" sqm leased/renewed" -> 3,333 sqm leased/renewed

Sheet Fitout Costs
A1: 1 ELIZABETH PLAZA — SPEC FITOUT & LANDLORD WORKS REGISTER | As at 30/04/2026
A2: Track approved and completed fitout works, spec fitouts and landlord contributions. All costs ex-GST unless noted.
B4: SPEC FITOUT SUMMARY
B5: Total Approved Budget | D5: Total Spent | F5: Avg Cost PSM | H5: Suites In Progress
B6: — | D6: — | F6: — | H6: —
B8: FITOUT DETAILS — Per Suite / Project
B9: Floor/Suite | C9: Description | D9: NLA (sqm) | E9: Date Approved | F9: Status | G9: Total Budget ($) | H9: Cost PSM ($) | I9: Fitout Allow ($) | J9: Net Cost ($) | K9: Contractor | L9: Date Complete | M9: Notes
B10: 9.01 | C10: Landlord fitout contribution / partials | D10: 453.3 | E10: 44746 | F10: Completed | G10: 64625.28 | H10: 186.24 | I10: 0 | J10: 64625.28 | L10: 2022 | M10: Fitout cost psm $186.24
B11: 10.01 | C11: Spec fitout — Level 10 (10.01) | D11: 349 | E11: 45292 | F11: Completed | G11: 86789.32 | H11: 248.68 | I11: 0 | J11: 86789.32 | L11: 2024 | M11: Spec fitted: Level 10 (completed 2025)
B12: 10.02 | C12: Spec fitout — Level 10 (10.02) | D12: 438 | E12: 45292 | F12: Completed | G12: 671825 | H12: 1547.98 | I12: 0 | J12: 671825 | L12: 2024 | M12: Full spec fitout incl MG 10.02. Lift lobby, electrical box etc.
B13: 6.01 | C13: Spec fitout — Level 6 (6.01) | D13: 186.4 | E13: 44562 | F13: Completed | G13: 170556 | H13: 915 | I13: 0 | J13: 170556 | L13: 2022 | M13: Fitout completed 2022. Rate: $915 psm
B14: 12.01 | C14: Spec fitout — Level 12 (12.01) | D14: 251 | E14: 44562 | F14: Completed | G14: 248030.67 | H14: 988.17 | I14: 0 | J14: 248030.67 | L14: 2023 | M14: Fitout completed. $988 psm
B15: 8.03 | C15: Spec fitout — Level 8 (8.03) | D15: 116.3 | E15: 45658 | F15: Completed | G15: 3023.8 | H15: 26 | I15: 0 | J15: 3023.8 | L15: 2025 | M15: Minor works $26 psm
B16: 11.01/11.02 | C16: Spec fitout — Level 11 | D16: 850.4 | E16: 45809 | F16: In Progress | G16: — | H16: — | I16: — | J16: — | L16: 2026 | M16: Spec fitted Level 11 — to be completed June 2026
B17: 9.02 | C17: Refurbishment — Suite 9.02 | D17: 344.5 | E17: 45658 | F17: Completed | G17: 64161 | H17: 186.24 | I17: 0 | J17: 64161 | L17: 2025 | M17: Refurb completed 2025. Rate $186.24 psm (power, blinds, works, vinyl, MG)
B18: 5.04 | C18: Fitout — Auctionsplus (5.04) | D18: 413.5 | E18: 45352 | F18: Completed | G18: — | H18: — | I18: 672971.25 | J18: — | L18: 2024 | M18: Landlord contribution $672,971 + GST. Tenant's fitout.
B19: 11.01 | C19: Fitout — Luxasia (11.01) | D19: 242.5 | E19: 46296 | F19: In Progress | G19: — | H19: — | I19: 369812.5 | J19: — | L19: 2026 | M19: Landlord contribution $369,812.50 + GST. Plus rent abatement $192,787.50 over term (Yr1-3 $25,705 pa, Yr4-5 $57,836.25 pa) tracked in Input Data tab.
B27: COST REFERENCE GUIDE — Typical Fitout Costs (ex-GST)
B28: Category | C28: Low psm | D28: Mid psm | E28: High psm | F28: Notes
B29: Partition offices + open plan | C29: $350 | D29: $550 | E29: $750 | F29: Demolition, new partitions, doors
B30: Carpet / floor coverings | C30: $65 | D30: $90 | E30: $130 | F30: Commercial carpet tiles
B31: Painting — full repaint | C31: $25 | D31: $40 | E31: $55 | F31: Per sqm NLA
B32: Lighting upgrade (LED) | C32: $40 | D32: $70 | E32: $110 | F32: Assume if >10 years old
B33: Kitchen / joinery | C33: $15,000 | D33: $25,000 | E33: $40,000 | F33: Per kitchen
B34: Full blank canvas spec | C34: $600 | D34: $900 | E34: $1,500 | F34: Complete stripped + fitted
B35: Cosmetic refresh only | C35: $100 | D35: $180 | E35: $260 | F35: Carpet + paint + lighting only

Sheet Leasing Fees
A1: 1 ELIZABETH PLAZA — LEASING FEES REGISTER | As at 30/09/2026
A2: Leasing fees based on NLA. 3-5yr: $15/sqm (single agency), $20/sqm (split). 5yr+: $20/sqm (single), $25/sqm (split). Car space fees negotiated separately.
B3: BUILDING VACANCY STATUS | As at 30/09/2026
B4: VACANCY | D4: 8.8% | E4: OCCUPANCY | G4: 91.2% | H4: TOTAL NLA | J4: 8,940.9 sqm | K4: VACANT NLA | M4: 787.0 sqm
B6: LEASING FEES — By Suite (Vacant)
B7: Suite | C7: NLA | D7: 3-5yr (Single) | E7: 5yr+ (Single) | F7: 3-5yr (Split) | G7: 5yr+ (Split) | H7: Fitout Spent ($) | I7: Asking PSM ($) | J7: Incentive % | K7: Car Spaces | L7: Comments
B9: 10.01 | C9: 349 | D9: 5235 | E9: 6980 | F9: 6980 | G9: 8725 | H9: 248.68 | I9: 990 | J9: — | K9: 2 | L9: Level 10 spec fitted
B10: 10.02 | C10: 438 | D10: 6570 | E10: 8760 | F10: 8760 | G10: 10950 | H10: 1547.98 | I10: 1000 | J10: 0.38 | K10: 3 | L10: Spec fitout complete. Full level 10
B12: TOTALS | D12: 787 | E12: =D9+D10 -> 11805 | F12: =E9+E10 -> 15740 | G12: =F9+F10 -> 15740 | H12: =G9+G10 -> 19675 | I12: =H9+H10 -> 1796.66
B14: AGENT INCENTIVE PROGRAMME | Current Conditions
B15: Condition: Executed lease + complying BG by required date. Introduction must be made on or after specified date. Not applicable to TRs. 3-5 year leases: $3,000 incentive (gift card) | 5+ year leases: $6,000 incentive (gift card) 1 tandem car space offered with Levys only. Incentives between $15k-$30k.

Sheet Rental Analysis
A1: 1 ELIZABETH PLAZA — RENTAL ANALYSIS | Deal Analyser Template
A2: Enter deal terms in the yellow input cells. All outputs calculate automatically. Use one copy per deal being analysed.
B4: BUILDING & SUITE OVERVIEW
B5: Building Net Lettable Area | C5: sqm | D5: 8940.9
B6: Suite Proportional Share | C6: % | D6: =D9/D5 -> 0.028073236
B8: LEASE TERMS — Input Fields (Yellow)
B9: Area | C9: sqm | D9: 251
B10: Lease Term Years | C10: # | D10: 5
B11: Gross Rent (Face) | C11: $ / sqm | D11: 985
B12: Gross Rent | C12: $ p.a. | D12: =D10*D9 -> 1255
B13: Lease Value (Face) | C13: $ | D13: =D11*D9 -> 247235
B15: INCENTIVE TERMS
B16: Rental Abatement % | C16: % | D16: 0.3
B17: Rental Abatement Value | C17: $ | D17: =D11*D16 -> 295.5
B18: Annual Abatement | C18: $ p.a. | D18: =D17/D9 -> 1.1772908
B19: Monthly Abatement | C19: $ | D19: =D18/12 -> 0.09810757
B20: Rent Free (Months) | C20: # | D20: 0
B21: Rent Free Value | C21: $ | D21: =D11/D9/12*D20 -> 0
B22: Landlord Contribution | C22: $ | D22: 248030.67
B24: OTHER COSTS & INCOME
B25: Rent Reviews | C25: % | D25: 0.035
B26: Cleaning | C26: $ / sqm | D26: 15.77
B27: Total Cleaning PA | C27: $ | D27: =D10*D26 -> 78.85
B28: Tandem Car Spaces | C28: # | D28: 0
B29: Cost per Tandem Space | C29: $ / space | D29: 1000
B30: Total Carparking | C30: $ | D30: =D28*D29 -> 0
B32: ANNUAL CASH FLOW (Years 1-5)
B33: Item | E33: Year 1 | F33: Year 2 | G33: Year 3 | H33: Year 4
B34: Rental Income | E34: =D11 -> 985 | F34: =E34*(1+D25) -> 1019.475 | G34: =F34*(1+D25) -> 1055.1566 | H34: =G34*(1+D25) -> 1092.0871
B35: Cleaning | E35: =D27 -> 78.85 | F35: =E35 -> 78.85 | G35: =F35 -> 78.85 | H35: =G35 -> 78.85
B36: Carparking | E36: =D30 -> 0 | F36: =E36 -> 0 | G36: =F36 -> 0 | H36: =G36 -> 0
B37: Incentive (Abatement) | E37: =IF(D20>0,-D11/D9/12*MIN(D20,12),IF(D16>0,-D18,0)) -> -1.1772908 | F37: =IF(D20>1,-D11/D9/12*MIN(D20-12,12),IF(D16>0,-D18,0)) -> -1.1772908 | G37: =0 -> 0 | H37: =0 -> 0
B38: NET TOTAL | E38: =SUM(E34:E37) -> 1062.6727 | F38: =SUM(F34:F37) -> 1097.1477 | G38: =SUM(G34:G37) -> 1134.0066 | H38: =SUM(H34:H37) -> 1170.9371
B40: BANK GUARANTEE
B41: BG Months | C41: # | D41: 6
B42: Rent | C42: $ | D42: =D9*(D10/12)*D41 -> 627.5
B43: Cleaning | C43: $ | D43: =D27/12*D41 -> 39.425
B44: Parking | C44: $ | D44: =D30/12*D41 -> 0
B45: Total BG (Ex GST) | C45: $ | D45: =SUM(D42:D44) -> 666.925
B46: GST | C46: $ | D46: =D45*0.1 -> 66.6925
B47: Total BG (Inc GST) | C47: $ | D47: =D45+D46 -> 733.6175
B49: EFFECTIVE RENT ANALYSIS
B50: Rent Year 1 | C50: $ | D50: =D34 -> 0
B51: Cleaning Year 1 | C51: $ | D51: =D35 -> 0
B52: Carparking Year 1 | C52: $ | D52: =D36 -> 0
B53: Abatement Year 1 | C53: $ | D53: =D37 -> 0
B54: Effective Rent Year 1 | C54: $ | D54: =SUM(D50:D53) -> 0
B55: Eff. Rent Year 1 PSQM | C55: $ | D55: =D54/D10 -> 0
B56: Eff. Rent Monthly Year 1 | C56: $ | D56: =D54/12 -> 0
B58: TOTAL INCENTIVE SUMMARY
B59: Total Abatement Value | C59: $ | D59: =D17 -> 295.5
B60: Total Rent Free Value | C60: $ | D60: =D21 -> 0
B61: Landlord Contribution | C61: $ | D61: =D22 -> 248030.67
B62: TOTAL INCENTIVES | C62: $ | D62: =SUM(D59:D61) -> 248326.17
B63: Total Incentive PSQM | C63: $ | D63: =D62/D10 -> 49665.234
B64: Incentive % of Lease Value | C64: % | D64: =D62/D13 -> 1.0044135
B66: LEGEND: Yellow cells = user input | White/Blue cells = formula outputs | Green cells = key results | Do not edit non-yellow cells
